{
  "type": "Feature",
  "properties": {
    "gn:admin1_code":"10.0",
    "gn:admin2_code":"0504",
    "gn:admin3_code":"0504193",
    "gn:asciiname":"Igaua",
    "gn:country_code":"TZ",
    "gn:dem":282,
    "gn:feature_class":"P",
    "gn:feature_code":"PPL",
    "gn:name":"Igaua",
    "gn:population":0,
    "gn:timezone":"Africa/Dar_es_Salaam",
    "iso:country":"TZ",
    "name:und_x_variant":[
        "Igawa",
        "Igaua"
    ],
    "wof:name":"Igaua",
    "wof:placetype":"locality"
},
  "geometry": {"coordinates":[36.11667,-8.88333],"type":"Point"}
}