{
  "type": "Feature",
  "properties": {
    "gn:admin1_code":"14.0",
    "gn:admin2_code":"1001",
    "gn:admin3_code":"1001201",
    "gn:asciiname":"Nandembo",
    "gn:country_code":"TZ",
    "gn:dem":555,
    "gn:feature_class":"P",
    "gn:feature_code":"PPL",
    "gn:name":"Nandembo",
    "gn:population":0,
    "gn:timezone":"Africa/Dar_es_Salaam",
    "iso:country":"TZ",
    "wof:name":"Nandembo",
    "wof:placetype":"locality"
},
  "geometry": {"coordinates":[37.28202,-10.98294],"type":"Point"}
}