{
  "type": "Feature",
  "properties": {
    "gn:admin1_code":"5.0",
    "gn:admin2_code":"1608",
    "gn:admin3_code":"1608021",
    "gn:asciiname":"Kibumba",
    "gn:country_code":"TZ",
    "gn:dem":1256,
    "gn:feature_class":"P",
    "gn:feature_code":"PPL",
    "gn:name":"Kibumba",
    "gn:population":0,
    "gn:timezone":"Africa/Dar_es_Salaam",
    "iso:country":"TZ",
    "wof:name":"Kibumba",
    "wof:placetype":"locality"
},
  "geometry": {"coordinates":[30.18333,-4.53333],"type":"Point"}
}