{
  "type": "Feature",
  "properties": {
    "gn:admin1_code":"23.0",
    "gn:admin2_code":"0701",
    "gn:admin3_code":"0701322",
    "gn:asciiname":"Kigomanunguru",
    "gn:country_code":"TZ",
    "gn:dem":89,
    "gn:feature_class":"P",
    "gn:feature_code":"PPL",
    "gn:name":"Kigomanunguru",
    "gn:population":0,
    "gn:timezone":"Africa/Dar_es_Salaam",
    "iso:country":"TZ",
    "wof:name":"Kigomanunguru",
    "wof:placetype":"locality"
},
  "geometry": {"coordinates":[39.16667,-6.76667],"type":"Point"}
}