{
  "type": "Feature",
  "properties": {
    "gn:admin1_code":"10.0",
    "gn:admin2_code":"0502",
    "gn:admin3_code":"0502031",
    "gn:asciiname":"Mvuha",
    "gn:country_code":"TZ",
    "gn:dem":129,
    "gn:feature_class":"P",
    "gn:feature_code":"PPL",
    "gn:name":"Mvuha",
    "gn:population":0,
    "gn:timezone":"Africa/Dar_es_Salaam",
    "iso:country":"TZ",
    "name:eng_x_preferred":[
        "Mvuha"
    ],
    "wof:name":"Mvuha",
    "wof:placetype":"locality"
},
  "geometry": {"coordinates":[37.8589,-7.19254],"type":"Point"}
}