{
  "type": "Feature",
  "properties": {
    "gn:admin1_code":"21.0",
    "gn:asciiname":"Kepwani",
    "gn:country_code":"TZ",
    "gn:dem":-9999,
    "gn:feature_class":"P",
    "gn:feature_code":"PPL",
    "gn:name":"Kepwani",
    "gn:population":0,
    "gn:timezone":"Africa/Dar_es_Salaam",
    "iso:country":"TZ",
    "wof:name":"Kepwani",
    "wof:placetype":"locality"
},
  "geometry": {"coordinates":[39.36667,-6.31667],"type":"Point"}
}