{
  "type": "Feature",
  "properties": {
    "gn:admin1_code":"12.0",
    "gn:admin2_code":"1907",
    "gn:admin3_code":"1907271",
    "gn:asciiname":"Fulo",
    "gn:country_code":"TZ",
    "gn:dem":1290,
    "gn:feature_class":"P",
    "gn:feature_code":"PPL",
    "gn:name":"Fulo",
    "gn:population":0,
    "gn:timezone":"Africa/Dar_es_Salaam",
    "iso:country":"TZ",
    "wof:name":"Fulo",
    "wof:placetype":"locality"
},
  "geometry": {"coordinates":[33.01667,-2.66667],"type":"Point"}
}