{
  "type": "Feature",
  "properties": {
    "gn:admin1_code":"3.0",
    "gn:admin2_code":"0102",
    "gn:admin3_code":"0102131",
    "gn:asciiname":"Mima",
    "gn:country_code":"TZ",
    "gn:dem":1028,
    "gn:feature_class":"P",
    "gn:feature_code":"PPL",
    "gn:name":"Mima",
    "gn:population":0,
    "gn:timezone":"Africa/Dar_es_Salaam",
    "iso:country":"TZ",
    "name:ita_x_preferred":[
        "Mima"
    ],
    "name:swa_x_preferred":[
        "Mima"
    ],
    "wof:name":"Mima",
    "wof:placetype":"locality"
},
  "geometry": {"coordinates":[36.13333,-6.53333],"type":"Point"}
}