{
  "type": "Feature",
  "properties": {
    "gn:admin1_code":"29.0",
    "gn:admin2_code":"2302",
    "gn:admin3_code":"2302013",
    "gn:asciiname":"Mtembwe",
    "gn:country_code":"TZ",
    "gn:dem":1450,
    "gn:feature_class":"P",
    "gn:feature_code":"PPL",
    "gn:name":"Mtembwe",
    "gn:population":0,
    "gn:timezone":"Africa/Dar_es_Salaam",
    "iso:country":"TZ",
    "wof:name":"Mtembwe",
    "wof:placetype":"locality"
},
  "geometry": {"coordinates":[30.65,-5.66667],"type":"Point"}
}