{
  "type": "Feature",
  "properties": {
    "gn:admin1_code":"9.0",
    "gn:admin2_code":"1201",
    "gn:admin3_code":"1201211",
    "gn:asciiname":"Igalele",
    "gn:country_code":"TZ",
    "gn:dem":1188,
    "gn:feature_class":"P",
    "gn:feature_code":"PPL",
    "gn:name":"Igalele",
    "gn:population":0,
    "gn:timezone":"Africa/Dar_es_Salaam",
    "iso:country":"TZ",
    "wof:name":"Igalele",
    "wof:placetype":"locality"
},
  "geometry": {"coordinates":[32.45,-7.81667],"type":"Point"}
}