{
  "type": "Feature",
  "properties": {
    "gn:admin1_code":"28.0",
    "gn:asciiname":"Nyanchenche",
    "gn:country_code":"TZ",
    "gn:dem":1178,
    "gn:feature_class":"P",
    "gn:feature_code":"PPL",
    "gn:name":"Nyanchenche",
    "gn:population":0,
    "gn:timezone":"Africa/Dar_es_Salaam",
    "iso:country":"TZ",
    "wof:name":"Nyanchenche",
    "wof:placetype":"locality"
},
  "geometry": {"coordinates":[32.64135,-2.82667],"type":"Point"}
}