{
  "type": "Feature",
  "properties": {
    "gn:gn_country":"TZ",
    "gn:gn_fcode":"PPLX",
    "gn:gn_pop":0,
    "iso:country":"TZ",
    "qs_pg:aaroncc":"TZ",
    "qs_pg:gn_country":"TZ",
    "qs_pg:gn_fcode":"PPLX",
    "qs_pg:gn_pop":0,
    "qs_pg:name":"Temeke",
    "qs_pg:name_adm0":"Tanzania",
    "qs_pg:name_adm1":"Dar es Salaam",
    "qs_pg:photos":75,
    "qs_pg:photos_1k":15,
    "qs_pg:photos_9k":1,
    "qs_pg:photos_9r":2,
    "qs_pg:photos_all":75,
    "qs_pg:photos_sr":2,
    "qs_pg:pop_sr":0,
    "qs_pg:qs_pg_placetype":"neighbourhood",
    "qs_pg:qs_pg_placetype_gp":"Suburb",
    "qs_pg:woe_adm0":23424973,
    "woe:adm0_id":23424973,
    "woe:name_adm0":"Tanzania",
    "woe:name_adm1":"Dar es Salaam",
    "woe:placetype":"Suburb",
    "wof:name":"Temeke",
    "wof:placetype":"neighbourhood"
},
  "geometry": {"coordinates":[39.25,-6.85],"type":"Point"}
}