{
  "type": "Feature",
  "properties": {
    "gn:admin1_code":"7.0",
    "gn:admin2_code":"0804",
    "gn:admin3_code":"0804031",
    "gn:asciiname":"Ngongowele",
    "gn:country_code":"TZ",
    "gn:dem":746,
    "gn:feature_class":"P",
    "gn:feature_code":"PPL",
    "gn:name":"Ngongowele",
    "gn:population":0,
    "gn:timezone":"Africa/Dar_es_Salaam",
    "iso:country":"TZ",
    "wof:name":"Ngongowele",
    "wof:placetype":"locality"
},
  "geometry": {"coordinates":[37.75,-10.05],"type":"Point"}
}