{
  "type": "Feature",
  "properties": {
    "gn:admin1_code":"5.0",
    "gn:admin2_code":"1605",
    "gn:admin3_code":"1605061",
    "gn:asciiname":"Ilagala",
    "gn:cc2":"TZ",
    "gn:country_code":"TZ",
    "gn:dem":778,
    "gn:feature_class":"P",
    "gn:feature_code":"PPL",
    "gn:name":"Ilagala",
    "gn:population":0,
    "gn:timezone":"Africa/Dar_es_Salaam",
    "iso:country":"TZ",
    "name:und_x_variant":[
        "Iragala",
        "Ilagala"
    ],
    "wof:name":"Ilagala",
    "wof:placetype":"locality"
},
  "geometry": {"coordinates":[29.83889000000001,-5.21083],"type":"Point"}
}