{
  "type": "Feature",
  "properties": {
    "gn:admin1_code":"9.0",
    "gn:admin2_code":"1207",
    "gn:admin3_code":"1207011",
    "gn:asciiname":"Mababila",
    "gn:country_code":"TZ",
    "gn:dem":1057,
    "gn:feature_class":"P",
    "gn:feature_code":"PPL",
    "gn:name":"Mababila",
    "gn:population":0,
    "gn:timezone":"Africa/Dar_es_Salaam",
    "iso:country":"TZ",
    "wof:name":"Mababila",
    "wof:placetype":"locality"
},
  "geometry": {"coordinates":[33.85,-8.63333],"type":"Point"}
}