{
  "type": "Feature",
  "properties": {
    "gn:admin1_code":"8.0",
    "gn:admin2_code":"2007",
    "gn:admin3_code":"2007131",
    "gn:asciiname":"Ikungu",
    "gn:country_code":"TZ",
    "gn:dem":1216,
    "gn:feature_class":"P",
    "gn:feature_code":"PPL",
    "gn:name":"Ikungu",
    "gn:population":0,
    "gn:timezone":"Africa/Dar_es_Salaam",
    "iso:country":"TZ",
    "wof:name":"Ikungu",
    "wof:placetype":"locality"
},
  "geometry": {"coordinates":[33.66667,-1.56667],"type":"Point"}
}