{
  "type": "Feature",
  "properties": {
    "gn:admin1_code":"5.0",
    "gn:admin2_code":"1606",
    "gn:admin3_code":"1606101",
    "gn:asciiname":"Buyonga",
    "gn:country_code":"TZ",
    "gn:dem":1145,
    "gn:feature_class":"P",
    "gn:feature_code":"PPL",
    "gn:name":"Buyonga",
    "gn:population":0,
    "gn:timezone":"Africa/Dar_es_Salaam",
    "iso:country":"TZ",
    "wof:name":"Buyonga",
    "wof:placetype":"locality"
},
  "geometry": {"coordinates":[29.85806,-4.62778],"type":"Point"}
}