{
  "type": "Feature",
  "properties": {
    "gn:admin1_code":"2.0",
    "gn:admin2_code":"0607",
    "gn:admin3_code":"0607112",
    "gn:asciiname":"Mbwawa",
    "gn:country_code":"TZ",
    "gn:dem":77,
    "gn:feature_class":"P",
    "gn:feature_code":"PPL",
    "gn:name":"Mbwawa",
    "gn:population":0,
    "gn:timezone":"Africa/Dar_es_Salaam",
    "iso:country":"TZ",
    "wof:name":"Mbwawa",
    "wof:placetype":"locality"
},
  "geometry": {"coordinates":[38.78333,-6.63333],"type":"Point"}
}