{
  "type": "Feature",
  "properties": {
    "gn:admin1_code":"5.0",
    "gn:admin2_code":"1602",
    "gn:admin3_code":"1602091",
    "gn:asciiname":"Murungu",
    "gn:country_code":"TZ",
    "gn:dem":1083,
    "gn:feature_class":"P",
    "gn:feature_code":"PPL",
    "gn:name":"Murungu",
    "gn:population":0,
    "gn:timezone":"Africa/Dar_es_Salaam",
    "iso:country":"TZ",
    "wof:name":"Murungu",
    "wof:placetype":"locality"
},
  "geometry": {"coordinates":[30.68333,-4.65],"type":"Point"}
}