{
  "type": "Feature",
  "properties": {
    "gn:admin1_code":"28.0",
    "gn:admin2_code":"2505",
    "gn:admin3_code":"2505213",
    "gn:asciiname":"Bwanga",
    "gn:country_code":"TZ",
    "gn:dem":1251,
    "gn:feature_class":"P",
    "gn:feature_code":"PPL",
    "gn:name":"Bwanga",
    "gn:population":0,
    "gn:timezone":"Africa/Dar_es_Salaam",
    "iso:country":"TZ",
    "wof:name":"Bwanga",
    "wof:placetype":"locality"
},
  "geometry": {"coordinates":[31.76361,-3.03222],"type":"Point"}
}