{
  "type": "Feature",
  "properties": {
    "gn:admin1_code":"4.0",
    "gn:admin2_code":"1102",
    "gn:admin3_code":"1102241",
    "gn:asciiname":"Mgunga",
    "gn:country_code":"TZ",
    "gn:dem":1779,
    "gn:feature_class":"P",
    "gn:feature_code":"PPL",
    "gn:name":"Mgunga",
    "gn:population":0,
    "gn:timezone":"Africa/Dar_es_Salaam",
    "iso:country":"TZ",
    "wof:name":"Mgunga",
    "wof:placetype":"locality"
},
  "geometry": {"coordinates":[35.75,-8.38333],"type":"Point"}
}