{
  "type": "Feature",
  "properties": {
    "gn:admin1_code":"13.0",
    "gn:admin2_code":"5401",
    "gn:admin3_code":"5401111",
    "gn:asciiname":"Mashugu",
    "gn:country_code":"TZ",
    "gn:dem":40,
    "gn:feature_class":"P",
    "gn:feature_code":"PPL",
    "gn:name":"Mashugu",
    "gn:population":0,
    "gn:timezone":"Africa/Dar_es_Salaam",
    "iso:country":"TZ",
    "wof:name":"Mashugu",
    "wof:placetype":"locality"
},
  "geometry": {"coordinates":[39.78333,-5.15],"type":"Point"}
}