{
  "type": "Feature",
  "properties": {
    "gn:admin1_code":"21.0",
    "gn:admin2_code":"5202",
    "gn:admin3_code":"5202051",
    "gn:asciiname":"Kuumbi",
    "gn:country_code":"TZ",
    "gn:dem":26,
    "gn:feature_class":"P",
    "gn:feature_code":"PPL",
    "gn:name":"Kuumbi",
    "gn:population":0,
    "gn:timezone":"Africa/Dar_es_Salaam",
    "iso:country":"TZ",
    "wof:name":"Kuumbi",
    "wof:placetype":"locality"
},
  "geometry": {"coordinates":[39.53333,-6.36667],"type":"Point"}
}