{
  "type": "Feature",
  "properties": {
    "gn:admin1_code":"2.0",
    "gn:admin2_code":"0606",
    "gn:admin3_code":"0606021",
    "gn:asciiname":"Tongani",
    "gn:country_code":"TZ",
    "gn:dem":7,
    "gn:feature_class":"P",
    "gn:feature_code":"PPL",
    "gn:name":"Tongani",
    "gn:population":0,
    "gn:timezone":"Africa/Dar_es_Salaam",
    "iso:country":"TZ",
    "name:eng_x_preferred":[
        "Tongani"
    ],
    "wof:name":"Tongani",
    "wof:placetype":"locality"
},
  "geometry": {"coordinates":[39.83276,-7.75712],"type":"Point"}
}