{
  "type": "Feature",
  "properties": {
    "gn:admin1_code":"12.0",
    "gn:admin2_code":"1902",
    "gn:admin3_code":"1902121",
    "gn:asciiname":"Bubinza",
    "gn:country_code":"TZ",
    "gn:dem":1154,
    "gn:feature_class":"P",
    "gn:feature_code":"PPL",
    "gn:name":"Bubinza",
    "gn:population":0,
    "gn:timezone":"Africa/Dar_es_Salaam",
    "iso:country":"TZ",
    "wof:name":"Bubinza",
    "wof:placetype":"locality"
},
  "geometry": {"coordinates":[33.48333,-2.53333],"type":"Point"}
}