{
  "type": "Feature",
  "properties": {
    "gn:admin1_code":"24.0",
    "gn:admin2_code":"1503",
    "gn:admin3_code":"1503101",
    "gn:asciiname":"Kizumbi",
    "gn:country_code":"TZ",
    "gn:dem":829,
    "gn:feature_class":"P",
    "gn:feature_code":"PPL",
    "gn:name":"Kizumbi",
    "gn:population":0,
    "gn:timezone":"Africa/Dar_es_Salaam",
    "iso:country":"TZ",
    "wof:name":"Kizumbi",
    "wof:placetype":"locality"
},
  "geometry": {"coordinates":[30.83333,-7.88333],"type":"Point"}
}