{
  "type": "Feature",
  "properties": {
    "gn:gn_country":"TZ",
    "gn:gn_fcode":"PPL",
    "gn:gn_pop":24648,
    "gn:population":24648,
    "iso:country":"TZ",
    "name:eng_x_preferred":[
        "Nyalikungu"
    ],
    "name:nld_x_preferred":[
        "Nyalikungu"
    ],
    "name:unk_x_variant":[
        "Nyarikungu"
    ],
    "qs_pg:aaroncc":"TZ",
    "qs_pg:gn_country":"TZ",
    "qs_pg:gn_fcode":"PPL",
    "qs_pg:gn_pop":24648,
    "qs_pg:name":"Nyalikungu",
    "qs_pg:photos_9r":0,
    "qs_pg:photos_sr":0,
    "qs_pg:pop_sr":7,
    "qs_pg:qs_pg_placetype":"locality",
    "wof:name":"Nyalikungu",
    "wof:placetype":"locality",
    "wof:population":24648
},
  "geometry": {"coordinates":[33.78333,-3.18333],"type":"Point"}
}