{
  "type": "Feature",
  "properties": {
    "gn:admin1_code":"23.0",
    "gn:admin2_code":"0701",
    "gn:admin3_code":"0701282",
    "gn:asciiname":"Luisi",
    "gn:country_code":"TZ",
    "gn:dem":100,
    "gn:feature_class":"P",
    "gn:feature_code":"PPL",
    "gn:name":"Luisi",
    "gn:population":0,
    "gn:timezone":"Africa/Dar_es_Salaam",
    "iso:country":"TZ",
    "wof:name":"Luisi",
    "wof:placetype":"locality"
},
  "geometry": {"coordinates":[39.13333,-6.76667],"type":"Point"}
}