{
  "type": "Feature",
  "properties": {
    "gn:admin1_code":"4.0",
    "gn:admin2_code":"1101",
    "gn:admin3_code":"1101131",
    "gn:asciiname":"Makutupa",
    "gn:country_code":"TZ",
    "gn:dem":941,
    "gn:feature_class":"P",
    "gn:feature_code":"PPL",
    "gn:name":"Makutupa",
    "gn:population":0,
    "gn:timezone":"Africa/Dar_es_Salaam",
    "iso:country":"TZ",
    "wof:name":"Makutupa",
    "wof:placetype":"locality"
},
  "geometry": {"coordinates":[35.06667,-7.48333],"type":"Point"}
}