{
  "type": "Feature",
  "properties": {
    "iso:country":"TZ",
    "name:ast_x_preferred":[
        "Matema"
    ],
    "name:deu_x_preferred":[
        "Matema"
    ],
    "name:ell_x_preferred":[
        "\u039c\u03b1\u03c4\u03ad\u03bc\u03b1"
    ],
    "name:eng_x_preferred":[
        "Matema"
    ],
    "name:fra_x_preferred":[
        "Matema"
    ],
    "name:ind_x_preferred":[
        "Matema"
    ],
    "name:ita_x_preferred":[
        "Matema"
    ],
    "name:nld_x_preferred":[
        "Matema"
    ],
    "name:swa_x_preferred":[
        "Matema"
    ],
    "qs:gn_pop":0,
    "qs:name":"Matema",
    "qs:name_adm0":"Tanzania",
    "qs:name_adm1":"Mbeya",
    "qs:photos":41,
    "qs:photos_1k":8,
    "qs:photos_9k":1,
    "qs:photos_9r":2,
    "qs:photos_all":41,
    "qs:photos_sr":2,
    "qs:placetype":"Town",
    "qs:pop_sr":"0",
    "qs:woe_adm0":23424973,
    "wd:wordcount":75,
    "wof:name":"Matema",
    "wof:placetype":"locality"
},
  "geometry": {"coordinates":[34.021945,-9.488852],"type":"Point"}
}