{
  "type": "Feature",
  "properties": {
    "iso:country":"TZ",
    "name:ell_x_preferred":[
        "\u039c\u03b1\u03bd\u03c5\u03cc\u03bd\u03b9"
    ],
    "name:vie_x_preferred":[
        "Manyoni"
    ],
    "ne:ADM0CAP":0.0,
    "ne:ADM0NAME":"Tanzania",
    "ne:ADM0_A3":"TZA",
    "ne:ADM1NAME":"Singida",
    "ne:ADMIN1_COD":0,
    "ne:CAPALT":0,
    "ne:CHANGED":4,
    "ne:CHECKME":0,
    "ne:COMPARE":0,
    "ne:DIFFASCII":0,
    "ne:DIFFNOTE":"Changed scale rank.",
    "ne:ELEVATION":0.0,
    "ne:FEATURECLA":"Populated place",
    "ne:GEONAMEID":-1,
    "ne:GN_POP":0,
    "ne:GTOPO30":0.0,
    "ne:ISO_A2":"TZ",
    "ne:LABELRANK":5,
    "ne:LATITUDE":-5.77961,
    "ne:LONGITUDE":34.90003,
    "ne:LS_MATCH":1,
    "ne:LS_NAME":"Manyoni",
    "ne:MAX_AREAKM":1.0,
    "ne:MAX_AREAMI":0.0,
    "ne:MAX_BBXMAX":34.908333,
    "ne:MAX_BBXMIN":34.9,
    "ne:MAX_BBYMAX":-5.783333,
    "ne:MAX_BBYMIN":-5.791667,
    "ne:MAX_NATSCA":10.0,
    "ne:MAX_PERKM":4.0,
    "ne:MAX_PERMI":2.0,
    "ne:MAX_POP10":310,
    "ne:MAX_POP20":0,
    "ne:MAX_POP300":0,
    "ne:MAX_POP310":0,
    "ne:MAX_POP50":0,
    "ne:MEAN_BBXC":34.904167,
    "ne:MEAN_BBYC":-5.7875,
    "ne:MEGACITY":0,
    "ne:MIN_AREAKM":1.0,
    "ne:MIN_AREAMI":0.0,
    "ne:MIN_BBXMAX":34.908333,
    "ne:MIN_BBXMIN":34.9,
    "ne:MIN_BBYMAX":-5.783333,
    "ne:MIN_BBYMIN":-5.791667,
    "ne:MIN_PERKM":4.0,
    "ne:MIN_PERMI":2.0,
    "ne:NAME":"Manyoni",
    "ne:NAMEASCII":"Manyoni",
    "ne:NAMEDIFF":0,
    "ne:NATSCALE":20,
    "ne:POP1950":0,
    "ne:POP1955":0,
    "ne:POP1960":0,
    "ne:POP1965":0,
    "ne:POP1970":0,
    "ne:POP1975":0,
    "ne:POP1980":0,
    "ne:POP1985":0,
    "ne:POP1990":0,
    "ne:POP1995":0,
    "ne:POP2000":0,
    "ne:POP2005":0,
    "ne:POP2010":0,
    "ne:POP2015":0,
    "ne:POP2020":0,
    "ne:POP2025":0,
    "ne:POP2050":0,
    "ne:POP_MAX":310,
    "ne:POP_MIN":310,
    "ne:POP_OTHER":0,
    "ne:RANK_MAX":2,
    "ne:RANK_MIN":2,
    "ne:SCALERANK":7,
    "ne:SOV0NAME":"United Republic of Tanzania",
    "ne:SOV_A3":"TZA",
    "ne:UN_FID":0,
    "ne:UN_LAT":0.0,
    "ne:UN_LONG":0.0,
    "ne:WORLDCITY":0,
    "ne:min_zoom":6.7,
    "wof:name":"Manyoni",
    "wof:placetype":"locality"
},
  "geometry": {"coordinates":[34.90002966181089,-5.77960976270197],"type":"Point"}
}