{
  "type": "Feature",
  "properties": {
    "gn:admin1_code":"21.0",
    "gn:admin2_code":"5202",
    "gn:admin3_code":"5202061",
    "gn:asciiname":"Ramla",
    "gn:country_code":"TZ",
    "gn:dem":30,
    "gn:feature_class":"P",
    "gn:feature_code":"PPL",
    "gn:name":"Ramla",
    "gn:population":0,
    "gn:timezone":"Africa/Dar_es_Salaam",
    "iso:country":"TZ",
    "name:afr_x_preferred":[
        "Ramla"
    ],
    "name:ara_x_preferred":[
        "\u0627\u0644\u0631\u0645\u0644\u0629"
    ],
    "name:aze_x_preferred":[
        "Ramla"
    ],
    "name:bos_x_preferred":[
        "Ramla"
    ],
    "name:bul_x_preferred":[
        "\u0420\u0430\u043c\u043b\u0430"
    ],
    "name:cat_x_preferred":[
        "Ramla"
    ],
    "name:ceb_x_preferred":[
        "Ramla"
    ],
    "name:ces_x_preferred":[
        "Ramla"
    ],
    "name:dan_x_preferred":[
        "Ramla"
    ],
    "name:deu_x_preferred":[
        "Ramla"
    ],
    "name:ell_x_preferred":[
        "\u03a1\u03ac\u03bc\u03bb\u03b1"
    ],
    "name:epo_x_preferred":[
        "Ramlo"
    ],
    "name:eus_x_preferred":[
        "Ramla"
    ],
    "name:fas_x_preferred":[
        "\u0631\u0645\u0644\u0647"
    ],
    "name:fin_x_preferred":[
        "Ramla"
    ],
    "name:fra_x_preferred":[
        "Ramla"
    ],
    "name:glv_x_preferred":[
        "Ramla"
    ],
    "name:heb_x_preferred":[
        "\u05e8\u05de\u05dc\u05d4"
    ],
    "name:ind_x_preferred":[
        "Ramla"
    ],
    "name:ita_x_preferred":[
        "Ramla"
    ],
    "name:jpn_x_preferred":[
        "\u30e9\u30e0\u30e9"
    ],
    "name:kal_x_preferred":[
        "Ramla"
    ],
    "name:kor_x_preferred":[
        "\ub77c\ubbc8\ub77c"
    ],
    "name:lad_x_preferred":[
        "Ramla"
    ],
    "name:lit_x_preferred":[
        "Ramla"
    ],
    "name:nah_x_preferred":[
        "Ramla"
    ],
    "name:nld_x_preferred":[
        "Ramla"
    ],
    "name:nno_x_preferred":[
        "Ramla"
    ],
    "name:nor_x_preferred":[
        "Ramla"
    ],
    "name:pol_x_preferred":[
        "Ramla"
    ],
    "name:por_x_preferred":[
        "Ramla"
    ],
    "name:ron_x_preferred":[
        "Ramla"
    ],
    "name:rus_x_preferred":[
        "\u0420\u0430\u043c\u043b\u0430"
    ],
    "name:sco_x_preferred":[
        "Ramla"
    ],
    "name:spa_x_preferred":[
        "Ramla"
    ],
    "name:srp_x_preferred":[
        "\u0420\u0430\u043c\u043b\u0430"
    ],
    "name:swe_x_preferred":[
        "Ramle"
    ],
    "name:tur_x_preferred":[
        "Ramla"
    ],
    "name:ukr_x_preferred":[
        "\u0420\u0430\u043c\u043b\u0430"
    ],
    "name:urd_x_preferred":[
        "\u0631\u0645\u0644\u06c1"
    ],
    "name:vie_x_preferred":[
        "Ramla"
    ],
    "name:war_x_preferred":[
        "Ramla"
    ],
    "name:yid_x_preferred":[
        "\u05e8\u05de\u05dc\u05d4"
    ],
    "name:zea_x_preferred":[
        "Ramla"
    ],
    "name:zho_x_preferred":[
        "\u62c9\u59c6\u62c9"
    ],
    "wof:name":"Ramla",
    "wof:placetype":"locality"
},
  "geometry": {"coordinates":[39.53333,-6.45],"type":"Point"}
}