{
  "type": "Feature",
  "properties": {
    "gn:admin1_code":"9.0",
    "gn:admin2_code":"1204",
    "gn:admin3_code":"1204043",
    "gn:asciiname":"Lugombo",
    "gn:country_code":"TZ",
    "gn:dem":1612,
    "gn:feature_class":"P",
    "gn:feature_code":"PPL",
    "gn:name":"Lugombo",
    "gn:population":0,
    "gn:timezone":"Africa/Dar_es_Salaam",
    "iso:country":"TZ",
    "wof:name":"Lugombo",
    "wof:placetype":"locality"
},
  "geometry": {"coordinates":[33.76667,-9.15],"type":"Point"}
}