{
  "type": "Feature",
  "properties": {
    "gn:admin1_code":"10.0",
    "gn:admin2_code":"0506",
    "gn:admin3_code":"0506161",
    "gn:asciiname":"Doma",
    "gn:country_code":"TZ",
    "gn:dem":507,
    "gn:feature_class":"P",
    "gn:feature_code":"PPL",
    "gn:name":"Doma",
    "gn:population":0,
    "gn:timezone":"Africa/Dar_es_Salaam",
    "iso:country":"TZ",
    "name:bar_x_preferred":[
        "Doma"
    ],
    "name:cat_x_preferred":[
        "Doma"
    ],
    "name:ceb_x_preferred":[
        "Doma"
    ],
    "name:deu_x_preferred":[
        "Doma"
    ],
    "name:eng_x_preferred":[
        "Doma"
    ],
    "name:fra_x_preferred":[
        "Doma"
    ],
    "name:ita_x_preferred":[
        "Doma"
    ],
    "name:oci_x_preferred":[
        "Doma"
    ],
    "name:rus_x_preferred":[
        "\u0414\u043e\u043c\u0430"
    ],
    "name:spa_x_preferred":[
        "Doma"
    ],
    "name:swe_x_preferred":[
        "Doma"
    ],
    "wof:name":"Doma",
    "wof:placetype":"locality"
},
  "geometry": {"coordinates":[37.24298,-7.0552],"type":"Point"}
}