{
  "type": "Feature",
  "properties": {
    "gn:admin1_code":"9.0",
    "gn:admin2_code":"1207",
    "gn:admin3_code":"1207011",
    "gn:asciiname":"Luhanga",
    "gn:country_code":"TZ",
    "gn:dem":1053,
    "gn:feature_class":"P",
    "gn:feature_code":"PPL",
    "gn:name":"Luhanga",
    "gn:population":0,
    "gn:timezone":"Africa/Dar_es_Salaam",
    "iso:country":"TZ",
    "wof:name":"Luhanga",
    "wof:placetype":"locality"
},
  "geometry": {"coordinates":[33.88333,-8.61667],"type":"Point"}
}