{
  "type": "Feature",
  "properties": {
    "gn:admin1_code":"12.0",
    "gn:asciiname":"Kishinda",
    "gn:country_code":"TZ",
    "gn:dem":1267,
    "gn:feature_class":"P",
    "gn:feature_code":"PPL",
    "gn:name":"Kishinda",
    "gn:population":0,
    "gn:timezone":"Africa/Dar_es_Salaam",
    "iso:country":"TZ",
    "wof:name":"Kishinda",
    "wof:placetype":"locality"
},
  "geometry": {"coordinates":[32.29469,-2.67063],"type":"Point"}
}