{
  "type": "Feature",
  "properties": {
    "gn:admin1_code":"11.0",
    "gn:admin2_code":"0902",
    "gn:admin3_code":"0902161",
    "gn:asciiname":"Chionga",
    "gn:country_code":"TZ",
    "gn:dem":639,
    "gn:feature_class":"P",
    "gn:feature_code":"PPL",
    "gn:name":"Chionga",
    "gn:population":0,
    "gn:timezone":"Africa/Dar_es_Salaam",
    "iso:country":"TZ",
    "wof:name":"Chionga",
    "wof:placetype":"locality"
},
  "geometry": {"coordinates":[39.33333,-10.56667],"type":"Point"}
}