{
  "type": "Feature",
  "properties": {
    "gn:admin1_code":"11.0",
    "gn:admin2_code":"0902",
    "gn:admin3_code":"0902213",
    "gn:asciiname":"Makongonda",
    "gn:country_code":"TZ",
    "gn:dem":410,
    "gn:feature_class":"P",
    "gn:feature_code":"PPL",
    "gn:name":"Makongonda",
    "gn:population":0,
    "gn:timezone":"Africa/Dar_es_Salaam",
    "iso:country":"TZ",
    "wof:name":"Makongonda",
    "wof:placetype":"locality"
},
  "geometry": {"coordinates":[39.28333,-10.98333],"type":"Point"}
}