{
  "type": "Feature",
  "properties": {
    "gn:admin1_code":"29.0",
    "gn:admin2_code":"2303",
    "gn:admin3_code":"2303171",
    "gn:asciiname":"Kasasinyata",
    "gn:country_code":"TZ",
    "gn:dem":919,
    "gn:feature_class":"P",
    "gn:feature_code":"PPL",
    "gn:name":"Kasasinyata",
    "gn:population":0,
    "gn:timezone":"Africa/Dar_es_Salaam",
    "iso:country":"TZ",
    "name:eng_x_preferred":[
        "Kasasinyata"
    ],
    "wof:name":"Kasasinyata",
    "wof:placetype":"locality"
},
  "geometry": {"coordinates":[31.09547,-6.94517],"type":"Point"}
}