{
  "type": "Feature",
  "properties": {
    "gn:admin1_code":"22.0",
    "gn:admin2_code":"5101",
    "gn:admin3_code":"5101221",
    "gn:asciiname":"Moga",
    "gn:country_code":"TZ",
    "gn:dem":64,
    "gn:feature_class":"P",
    "gn:feature_code":"PPL",
    "gn:name":"Moga",
    "gn:population":0,
    "gn:timezone":"Africa/Dar_es_Salaam",
    "iso:country":"TZ",
    "name:ceb_x_preferred":[
        "Moga"
    ],
    "name:deu_x_preferred":[
        "Moga"
    ],
    "name:nld_x_preferred":[
        "Moga"
    ],
    "name:pnb_x_preferred":[
        "\u0645\u0648\u06af\u0627"
    ],
    "name:rus_x_preferred":[
        "\u041c\u043e\u0433\u0430"
    ],
    "name:swe_x_preferred":[
        "Moga"
    ],
    "wof:name":"Moga",
    "wof:placetype":"locality"
},
  "geometry": {"coordinates":[39.28333,-5.91667],"type":"Point"}
}