{
  "type": "Feature",
  "properties": {
    "gn:admin1_code":"30.0",
    "gn:admin2_code":"2201",
    "gn:admin3_code":"2201091",
    "gn:asciiname":"Lisitu",
    "gn:country_code":"TZ",
    "gn:dem":2220,
    "gn:feature_class":"P",
    "gn:feature_code":"PPL",
    "gn:name":"Lisitu",
    "gn:population":0,
    "gn:timezone":"Africa/Dar_es_Salaam",
    "iso:country":"TZ",
    "name:und_x_variant":[
        "Lusitu",
        "Lisitu"
    ],
    "wof:name":"Lisitu",
    "wof:placetype":"locality"
},
  "geometry": {"coordinates":[34.65,-9.65],"type":"Point"}
}