{
  "type": "Feature",
  "properties": {
    "gn:gn_country":"TZ",
    "gn:gn_fcode":"PPL",
    "gn:gn_pop":15320,
    "gn:population":15320,
    "iso:country":"TZ",
    "qs_pg:aaroncc":"TZ",
    "qs_pg:gn_country":"TZ",
    "qs_pg:gn_fcode":"PPL",
    "qs_pg:gn_pop":15320,
    "qs_pg:name":"Mabama",
    "qs_pg:photos_9r":0,
    "qs_pg:photos_sr":0,
    "qs_pg:pop_sr":6,
    "qs_pg:qs_pg_placetype":"locality",
    "wof:name":"Mabama",
    "wof:placetype":"locality",
    "wof:population":15320
},
  "geometry": {"coordinates":[32.53333,-5.13333],"type":"Point"}
}