{
  "type": "Feature",
  "properties": {
    "gn:admin1_code":"14.0",
    "gn:admin2_code":"1002",
    "gn:admin3_code":"1002061",
    "gn:asciiname":"Mkurumusi",
    "gn:country_code":"TZ",
    "gn:dem":1033,
    "gn:feature_class":"P",
    "gn:feature_code":"PPL",
    "gn:name":"Mkurumusi",
    "gn:population":0,
    "gn:timezone":"Africa/Dar_es_Salaam",
    "iso:country":"TZ",
    "wof:name":"Mkurumusi",
    "wof:placetype":"locality"
},
  "geometry": {"coordinates":[35.55,-10.78333],"type":"Point"}
}