{
  "type": "Feature",
  "properties": {
    "gn:admin1_code":"20.0",
    "gn:asciiname":"Mchua",
    "gn:country_code":"TZ",
    "gn:dem":0,
    "gn:feature_class":"P",
    "gn:feature_code":"PPL",
    "gn:name":"Mchua",
    "gn:population":0,
    "gn:timezone":"Africa/Dar_es_Salaam",
    "iso:country":"TZ",
    "wof:name":"Mchua",
    "wof:placetype":"locality"
},
  "geometry": {"coordinates":[39.75,-5.25],"type":"Point"}
}