{
  "type": "Feature",
  "properties": {
    "gn:admin1_code":"29.0",
    "gn:admin2_code":"2302",
    "gn:admin3_code":"2302041",
    "gn:asciiname":"Simbo",
    "gn:country_code":"TZ",
    "gn:dem":1192,
    "gn:feature_class":"P",
    "gn:feature_code":"PPL",
    "gn:name":"Simbo",
    "gn:population":0,
    "gn:timezone":"Africa/Dar_es_Salaam",
    "iso:country":"TZ",
    "name:eng_x_preferred":[
        "Simbo"
    ],
    "wof:name":"Simbo",
    "wof:placetype":"locality"
},
  "geometry": {"coordinates":[30.69748,-6.34507],"type":"Point"}
}