{
  "type": "Feature",
  "properties": {
    "gn:admin1_code":"17.0",
    "gn:admin2_code":"1403",
    "gn:admin3_code":"1403131",
    "gn:asciiname":"Upuge",
    "gn:country_code":"TZ",
    "gn:dem":1244,
    "gn:feature_class":"P",
    "gn:feature_code":"PPL",
    "gn:name":"Upuge",
    "gn:population":0,
    "gn:timezone":"Africa/Dar_es_Salaam",
    "iso:country":"TZ",
    "wof:name":"Upuge",
    "wof:placetype":"locality"
},
  "geometry": {"coordinates":[33.01667,-4.88333],"type":"Point"}
}