{
  "type": "Feature",
  "properties": {
    "gn:admin1_code":"20.0",
    "gn:admin2_code":"5502",
    "gn:admin3_code":"5502081",
    "gn:asciiname":"Kigongoni",
    "gn:country_code":"TZ",
    "gn:dem":0,
    "gn:feature_class":"P",
    "gn:feature_code":"PPL",
    "gn:name":"Kigongoni",
    "gn:population":0,
    "gn:timezone":"Africa/Dar_es_Salaam",
    "iso:country":"TZ",
    "wof:name":"Kigongoni",
    "wof:placetype":"locality"
},
  "geometry": {"coordinates":[39.65,-5.46667],"type":"Point"}
}