{
  "type": "Feature",
  "properties": {
    "gn:admin1_code":"11.0",
    "gn:asciiname":"Hangambali",
    "gn:country_code":"TZ",
    "gn:dem":127,
    "gn:feature_class":"P",
    "gn:feature_code":"PPL",
    "gn:name":"Hangambali",
    "gn:population":0,
    "gn:timezone":"Africa/Dar_es_Salaam",
    "iso:country":"TZ",
    "wof:name":"Hangambali",
    "wof:placetype":"locality"
},
  "geometry": {"coordinates":[39.66667,-10.35],"type":"Point"}
}