{
  "type": "Feature",
  "properties": {
    "gn:admin1_code":"16.0",
    "gn:admin2_code":"1302",
    "gn:admin3_code":"1302091",
    "gn:asciiname":"Salimu",
    "gn:country_code":"TZ",
    "gn:dem":1504,
    "gn:feature_class":"P",
    "gn:feature_code":"PPL",
    "gn:name":"Salimu",
    "gn:population":0,
    "gn:timezone":"Africa/Dar_es_Salaam",
    "iso:country":"TZ",
    "wof:name":"Salimu",
    "wof:placetype":"locality"
},
  "geometry": {"coordinates":[35.18333,-4.85],"type":"Point"}
}