{
  "type": "Feature",
  "properties": {
    "gn:admin1_code":"20.0",
    "gn:admin2_code":"5502",
    "gn:admin3_code":"5502291",
    "gn:asciiname":"Kaole",
    "gn:country_code":"TZ",
    "gn:dem":28,
    "gn:feature_class":"P",
    "gn:feature_code":"PPL",
    "gn:name":"Kaole",
    "gn:population":0,
    "gn:timezone":"Africa/Dar_es_Salaam",
    "iso:country":"TZ",
    "name:fas_x_preferred":[
        "\u06a9\u0627\u0626\u0648\u0644\u0647"
    ],
    "name:ita_x_preferred":[
        "Kaole"
    ],
    "name:swa_x_preferred":[
        "Kaole"
    ],
    "name:zho_x_preferred":[
        "\u5361\u5967\u840a"
    ],
    "wof:name":"Kaole",
    "wof:placetype":"locality"
},
  "geometry": {"coordinates":[39.73333,-5.38333],"type":"Point"}
}