{
  "type": "Feature",
  "properties": {
    "gn:admin1_code":"24.0",
    "gn:admin2_code":"1504",
    "gn:admin3_code":"1504101",
    "gn:asciiname":"Nambogo",
    "gn:country_code":"TZ",
    "gn:dem":1892,
    "gn:feature_class":"P",
    "gn:feature_code":"PPL",
    "gn:name":"Nambogo",
    "gn:population":0,
    "gn:timezone":"Africa/Dar_es_Salaam",
    "iso:country":"TZ",
    "wof:name":"Nambogo",
    "wof:placetype":"locality"
},
  "geometry": {"coordinates":[31.66667,-8.06667],"type":"Point"}
}