{
  "type": "Feature",
  "properties": {
    "gn:admin1_code":"10.0",
    "gn:admin2_code":"0506",
    "gn:admin3_code":"0506101",
    "gn:asciiname":"Maguruwe",
    "gn:country_code":"TZ",
    "gn:dem":1684,
    "gn:feature_class":"P",
    "gn:feature_code":"PPL",
    "gn:name":"Maguruwe",
    "gn:population":0,
    "gn:timezone":"Africa/Dar_es_Salaam",
    "iso:country":"TZ",
    "name:eng_x_preferred":[
        "Maguruwe"
    ],
    "wof:name":"Maguruwe",
    "wof:placetype":"locality"
},
  "geometry": {"coordinates":[37.61595,-7.00909],"type":"Point"}
}