{
  "type": "Feature",
  "properties": {
    "gn:admin1_code":"13.0",
    "gn:admin2_code":"5401",
    "gn:admin3_code":"5401261",
    "gn:asciiname":"Machengwe",
    "gn:country_code":"TZ",
    "gn:dem":23,
    "gn:feature_class":"P",
    "gn:feature_code":"PPL",
    "gn:name":"Machengwe",
    "gn:population":0,
    "gn:timezone":"Africa/Dar_es_Salaam",
    "iso:country":"TZ",
    "wof:name":"Machengwe",
    "wof:placetype":"locality"
},
  "geometry": {"coordinates":[39.76667,-5.08333],"type":"Point"}
}