{
  "type": "Feature",
  "properties": {
    "gn:admin1_code":"18.0",
    "gn:admin2_code":"0402",
    "gn:admin3_code":"0402021",
    "gn:asciiname":"Maji Moto",
    "gn:country_code":"TZ",
    "gn:dem":439,
    "gn:feature_class":"P",
    "gn:feature_code":"PPL",
    "gn:name":"Maji Moto",
    "gn:population":0,
    "gn:timezone":"Africa/Dar_es_Salaam",
    "iso:country":"TZ",
    "wof:name":"Maji Moto",
    "wof:placetype":"locality"
},
  "geometry": {"coordinates":[38.68333,-4.85],"type":"Point"}
}