{
  "type": "Feature",
  "properties": {
    "gn:admin1_code":"8.0",
    "gn:asciiname":"Busagami",
    "gn:country_code":"TZ",
    "gn:dem":1158,
    "gn:feature_class":"P",
    "gn:feature_code":"PPL",
    "gn:name":"Busagami",
    "gn:population":0,
    "gn:timezone":"Africa/Dar_es_Salaam",
    "iso:country":"TZ",
    "wof:name":"Busagami",
    "wof:placetype":"locality"
},
  "geometry": {"coordinates":[32.95,-1.96667],"type":"Point"}
}