{
  "type": "Feature",
  "properties": {
    "gn:admin1_code":"12.0",
    "gn:admin2_code":"1907",
    "gn:admin3_code":"1907161",
    "gn:asciiname":"Lubiri",
    "gn:country_code":"TZ",
    "gn:dem":1139,
    "gn:feature_class":"P",
    "gn:feature_code":"PPL",
    "gn:name":"Lubiri",
    "gn:population":0,
    "gn:timezone":"Africa/Dar_es_Salaam",
    "iso:country":"TZ",
    "wof:name":"Lubiri",
    "wof:placetype":"locality"
},
  "geometry": {"coordinates":[32.78333,-3.05],"type":"Point"}
}