{
  "type": "Feature",
  "properties": {
    "gn:admin1_code":"2.0",
    "gn:admin2_code":"0604",
    "gn:admin3_code":"0604041",
    "gn:asciiname":"Mbezi",
    "gn:country_code":"TZ",
    "gn:dem":51,
    "gn:feature_class":"P",
    "gn:feature_code":"PPL",
    "gn:name":"Mbezi",
    "gn:population":0,
    "gn:timezone":"Africa/Dar_es_Salaam",
    "iso:country":"TZ",
    "name:eng_x_preferred":[
        "Mbezi"
    ],
    "name:ita_x_preferred":[
        "Mbezi"
    ],
    "name:swa_x_preferred":[
        "Mbezi"
    ],
    "wof:name":"Mbezi",
    "wof:placetype":"locality"
},
  "geometry": {"coordinates":[39.23502,-7.15752],"type":"Point"}
}