{
  "type": "Feature",
  "properties": {
    "gn:admin1_code":"18.0",
    "gn:admin2_code":"0404",
    "gn:admin3_code":"0404133",
    "gn:asciiname":"Bagamoyo",
    "gn:country_code":"TZ",
    "gn:dem":25,
    "gn:feature_class":"P",
    "gn:feature_code":"PPL",
    "gn:name":"Bagamoyo",
    "gn:population":0,
    "gn:timezone":"Africa/Dar_es_Salaam",
    "iso:country":"TZ",
    "name:ara_x_preferred":[
        "\u0628\u0627\u062c\u0627\u0645\u0648\u064a\u0648"
    ],
    "name:ast_x_preferred":[
        "Bagamoyo"
    ],
    "name:azb_x_preferred":[
        "\u0628\u0627\u0642\u0627\u0645\u0648\u06cc\u0648"
    ],
    "name:bul_x_preferred":[
        "\u0411\u0430\u0433\u0430\u043c\u043e\u0439\u043e"
    ],
    "name:ceb_x_preferred":[
        "Bagamoyo"
    ],
    "name:dan_x_preferred":[
        "Bagamoyo"
    ],
    "name:deu_x_preferred":[
        "Bagamoyo"
    ],
    "name:ell_x_preferred":[
        "\u039c\u03c0\u03b1\u03b3\u03ba\u03b1\u03bc\u03cc\u03b3\u03b9\u03bf"
    ],
    "name:fas_x_preferred":[
        "\u0628\u0627\u06af\u0627\u0645\u0648\u06cc\u0648"
    ],
    "name:fin_x_preferred":[
        "Bagamoyo"
    ],
    "name:fra_x_preferred":[
        "Bagamoyo"
    ],
    "name:glg_x_preferred":[
        "Bagamoyo"
    ],
    "name:ita_x_preferred":[
        "Bagamoyo"
    ],
    "name:jpn_x_preferred":[
        "\u30d0\u30ac\u30e2\u30e8"
    ],
    "name:kor_x_preferred":[
        "\ubc14\uac00\ubaa8\uc694"
    ],
    "name:nld_x_preferred":[
        "Bagamoyo"
    ],
    "name:nor_x_preferred":[
        "Bagamoyo"
    ],
    "name:pol_x_preferred":[
        "Bagamoyo"
    ],
    "name:por_x_preferred":[
        "Bagamoyo"
    ],
    "name:ron_x_preferred":[
        "Bagamoyo"
    ],
    "name:rus_x_preferred":[
        "\u0411\u0430\u0433\u0430\u043c\u043e\u0439\u043e"
    ],
    "name:spa_x_preferred":[
        "Bagamoyo"
    ],
    "name:swa_x_preferred":[
        "Bagamoyo"
    ],
    "name:swe_x_preferred":[
        "Bagamoyo"
    ],
    "name:tur_x_preferred":[
        "Bagamoyo"
    ],
    "name:ukr_x_preferred":[
        "\u0411\u0430\u0433\u0430\u043c\u043e\u0439\u043e"
    ],
    "name:urd_x_preferred":[
        "\u0628\u0627\u06af\u0627\u0645\u0648\u06cc\u0648"
    ],
    "name:zho_x_preferred":[
        "\u5df4\u52a0\u83ab\u7d04"
    ],
    "wof:name":"Bagamoyo",
    "wof:placetype":"locality"
},
  "geometry": {"coordinates":[39.08333,-5.11667],"type":"Point"}
}