{
  "type": "Feature",
  "properties": {
    "gn:admin1_code":"13.0",
    "gn:asciiname":"Mdimuni",
    "gn:country_code":"TZ",
    "gn:dem":-9999,
    "gn:feature_class":"P",
    "gn:feature_code":"PPL",
    "gn:name":"Mdimuni",
    "gn:population":0,
    "gn:timezone":"Africa/Dar_es_Salaam",
    "iso:country":"TZ",
    "wof:name":"Mdimuni",
    "wof:placetype":"locality"
},
  "geometry": {"coordinates":[39.68333,-4.96667],"type":"Point"}
}