{
  "type": "Feature",
  "properties": {
    "gn:admin1_code":"15.0",
    "gn:admin2_code":"1703",
    "gn:admin3_code":"1703261",
    "gn:asciiname":"Ihugi",
    "gn:country_code":"TZ",
    "gn:dem":1192,
    "gn:feature_class":"P",
    "gn:feature_code":"PPL",
    "gn:name":"Ihugi",
    "gn:population":0,
    "gn:timezone":"Africa/Dar_es_Salaam",
    "iso:country":"TZ",
    "wof:name":"Ihugi",
    "wof:placetype":"locality"
},
  "geometry": {"coordinates":[33.06667,-3.66667],"type":"Point"}
}