{
  "type": "Feature",
  "properties": {
    "gn:admin1_code":"14.0",
    "gn:admin2_code":"1004",
    "gn:admin3_code":"1004172",
    "gn:asciiname":"Lilambo",
    "gn:country_code":"TZ",
    "gn:dem":1041,
    "gn:feature_class":"P",
    "gn:feature_code":"PPL",
    "gn:name":"Lilambo",
    "gn:population":0,
    "gn:timezone":"Africa/Dar_es_Salaam",
    "iso:country":"TZ",
    "name:swa_x_preferred":[
        "Lilambo"
    ],
    "wof:name":"Lilambo",
    "wof:placetype":"locality"
},
  "geometry": {"coordinates":[35.55,-10.68333],"type":"Point"}
}