{
  "type": "Feature",
  "properties": {
    "gn:admin1_code":"28.0",
    "gn:admin2_code":"2505",
    "gn:admin3_code":"2505153",
    "gn:asciiname":"Diobahika",
    "gn:country_code":"TZ",
    "gn:dem":1190,
    "gn:feature_class":"P",
    "gn:feature_code":"PPL",
    "gn:name":"Diobahika",
    "gn:population":0,
    "gn:timezone":"Africa/Dar_es_Salaam",
    "iso:country":"TZ",
    "name:und_x_variant":[
        "Diabohika",
        "Diobahika"
    ],
    "wof:name":"Diobahika",
    "wof:placetype":"locality"
},
  "geometry": {"coordinates":[31.59972,-3.20472],"type":"Point"}
}