{
  "type": "Feature",
  "properties": {
    "gn:admin1_code":"2.0",
    "gn:asciiname":"Kiechuru",
    "gn:country_code":"TZ",
    "gn:dem":15,
    "gn:feature_class":"P",
    "gn:feature_code":"PPL",
    "gn:name":"Kiechuru",
    "gn:population":0,
    "gn:timezone":"Africa/Dar_es_Salaam",
    "iso:country":"TZ",
    "name:eng_x_preferred":[
        "Kiechuru"
    ],
    "name:eng_x_variant":[
        "Kiachuru"
    ],
    "wof:name":"Kiechuru",
    "wof:placetype":"locality"
},
  "geometry": {"coordinates":[39.39326,-8.0429],"type":"Point"}
}