{
  "type": "Feature",
  "properties": {
    "gn:admin1_code":"10.0",
    "gn:admin2_code":"0502",
    "gn:admin3_code":"0502231",
    "gn:asciiname":"Vikatala",
    "gn:country_code":"TZ",
    "gn:dem":391,
    "gn:feature_class":"P",
    "gn:feature_code":"PPL",
    "gn:name":"Vikatala",
    "gn:population":0,
    "gn:timezone":"Africa/Dar_es_Salaam",
    "iso:country":"TZ",
    "name:eng_x_preferred":[
        "Vikatala"
    ],
    "wof:name":"Vikatala",
    "wof:placetype":"locality"
},
  "geometry": {"coordinates":[37.81723,-7.12788],"type":"Point"}
}