{
  "type": "Feature",
  "properties": {
    "gn:admin1_code":"19.0",
    "gn:admin2_code":"1801",
    "gn:admin3_code":"1801161",
    "gn:asciiname":"Kabwera",
    "gn:country_code":"TZ",
    "gn:dem":1374,
    "gn:feature_class":"P",
    "gn:feature_code":"PPL",
    "gn:name":"Kabwera",
    "gn:population":0,
    "gn:timezone":"Africa/Dar_es_Salaam",
    "iso:country":"TZ",
    "wof:name":"Kabwera",
    "wof:placetype":"locality"
},
  "geometry": {"coordinates":[30.85,-1.68333],"type":"Point"}
}