{
  "type": "Feature",
  "properties": {
    "gn:admin1_code":"14.0",
    "gn:admin2_code":"1001",
    "gn:admin3_code":"1001291",
    "gn:asciiname":"Kipojora",
    "gn:country_code":"TZ",
    "gn:dem":561,
    "gn:feature_class":"P",
    "gn:feature_code":"PPL",
    "gn:name":"Kipojora",
    "gn:population":0,
    "gn:timezone":"Africa/Dar_es_Salaam",
    "iso:country":"TZ",
    "wof:name":"Kipojora",
    "wof:placetype":"locality"
},
  "geometry": {"coordinates":[37.08333,-10.68333],"type":"Point"}
}