{
  "type": "Feature",
  "properties": {
    "gn:admin1_code":"10.0",
    "gn:admin2_code":"0506",
    "gn:admin3_code":"0506151",
    "gn:asciiname":"Womba",
    "gn:country_code":"TZ",
    "gn:dem":1007,
    "gn:feature_class":"P",
    "gn:feature_code":"PPL",
    "gn:name":"Womba",
    "gn:population":0,
    "gn:timezone":"Africa/Dar_es_Salaam",
    "iso:country":"TZ",
    "name:eng_x_preferred":[
        "Womba"
    ],
    "wof:name":"Womba",
    "wof:placetype":"locality"
},
  "geometry": {"coordinates":[37.53559,-7.05364],"type":"Point"}
}