{
  "type": "Feature",
  "properties": {
    "gn:admin1_code":"8.0",
    "gn:admin2_code":"2002",
    "gn:admin3_code":"2002101",
    "gn:asciiname":"Kilima Fedha",
    "gn:country_code":"TZ",
    "gn:dem":1460,
    "gn:feature_class":"P",
    "gn:feature_code":"PPL",
    "gn:name":"Kilima Fedha",
    "gn:population":0,
    "gn:timezone":"Africa/Dar_es_Salaam",
    "iso:country":"TZ",
    "name:und_x_variant":[
        "Kilimafeza",
        "Kilima Fedha"
    ],
    "wof:name":"Kilima Fedha",
    "wof:placetype":"locality"
},
  "geometry": {"coordinates":[34.91667,-2.26667],"type":"Point"}
}