{
  "type": "Feature",
  "properties": {
    "gn:admin1_code":"3.0",
    "gn:admin2_code":"0102",
    "gn:admin3_code":"0102111",
    "gn:asciiname":"Kinyika",
    "gn:country_code":"TZ",
    "gn:dem":858,
    "gn:feature_class":"P",
    "gn:feature_code":"PPL",
    "gn:name":"Kinyika",
    "gn:population":0,
    "gn:timezone":"Africa/Dar_es_Salaam",
    "iso:country":"TZ",
    "name:und_x_variant":[
        "Chinyika",
        "Kinyika"
    ],
    "wof:name":"Kinyika",
    "wof:placetype":"locality"
},
  "geometry": {"coordinates":[36.15,-6.71667],"type":"Point"}
}