{
  "type": "Feature",
  "properties": {
    "gn:admin1_code":"18.0",
    "gn:admin2_code":"0408",
    "gn:admin3_code":"0408171",
    "gn:asciiname":"Mazola",
    "gn:country_code":"TZ",
    "gn:dem":59,
    "gn:feature_class":"P",
    "gn:feature_code":"PPL",
    "gn:name":"Mazola",
    "gn:population":0,
    "gn:timezone":"Africa/Dar_es_Salaam",
    "iso:country":"TZ",
    "wof:name":"Mazola",
    "wof:placetype":"locality"
},
  "geometry": {"coordinates":[39.06667,-4.86667],"type":"Point"}
}