{
  "type": "Feature",
  "properties": {
    "gn:admin1_code":"2.0",
    "gn:admin2_code":"0601",
    "gn:admin3_code":"0601011",
    "gn:asciiname":"Simbo",
    "gn:country_code":"TZ",
    "gn:dem":224,
    "gn:feature_class":"P",
    "gn:feature_code":"PPL",
    "gn:name":"Simbo",
    "gn:population":0,
    "gn:timezone":"Africa/Dar_es_Salaam",
    "iso:country":"TZ",
    "name:deu_x_preferred":[
        "Simbo"
    ],
    "name:fra_x_preferred":[
        "Simbo"
    ],
    "name:glg_x_preferred":[
        "Simbo"
    ],
    "name:hye_x_preferred":[
        "\u054d\u056b\u0574\u0562\u0578"
    ],
    "name:ita_x_preferred":[
        "Simbo"
    ],
    "name:nld_x_preferred":[
        "Simbo"
    ],
    "wof:name":"Simbo",
    "wof:placetype":"locality"
},
  "geometry": {"coordinates":[38.53333,-6.38333],"type":"Point"}
}