{
  "type": "Feature",
  "properties": {
    "gn:admin1_code":"2.0",
    "gn:admin2_code":"0601",
    "gn:admin3_code":"0601011",
    "gn:asciiname":"Simbo",
    "gn:country_code":"TZ",
    "gn:dem":224,
    "gn:feature_class":"P",
    "gn:feature_code":"PPL",
    "gn:name":"Simbo",
    "gn:population":0,
    "gn:timezone":"Africa/Dar_es_Salaam",
    "iso:country":"TZ",
    "wof:name":"Simbo",
    "wof:placetype":"locality"
},
  "geometry": {"coordinates":[38.53333,-6.38333],"type":"Point"}
}