{
  "type": "Feature",
  "properties": {
    "iso:country":"TZ",
    "name:deu_x_preferred":[
        "Usa River"
    ],
    "name:dut_x_preferred":[
        "Usa River"
    ],
    "name:eng_x_preferred":[
        "Usa River"
    ],
    "name:fas_x_preferred":[
        "\u06cc\u0648\u0627\u0633\u200c\u0627\u06cc \u0631\u06cc\u0648\u0631"
    ],
    "name:ger_x_preferred":[
        "Usa River"
    ],
    "name:gre_x_preferred":[
        "\u039f\u03cd\u03c3\u03b1 \u03a1\u03af\u03b2\u03b5\u03c1"
    ],
    "name:per_x_preferred":[
        "\u06cc\u0648\u0627\u0633\u200c\u0627\u06cc \u0631\u06cc\u0648\u0631"
    ],
    "name:ron_x_preferred":[
        "Usa River"
    ],
    "name:rum_x_preferred":[
        "Usa River"
    ],
    "name:swa_x_preferred":[
        "Usa River"
    ],
    "name:unk_x_variant":[
        "Usa"
    ],
    "qs:gn_country":"TZ",
    "qs:gn_fcode":"PPL",
    "qs:gn_pop":18726,
    "qs:name":"Usa River",
    "qs:name_adm0":"Tanzania",
    "qs:name_adm1":"Arusha",
    "qs:photos":106,
    "qs:photos_1k":21,
    "qs:photos_9k":1,
    "qs:photos_9r":3,
    "qs:photos_all":106,
    "qs:photos_sr":3,
    "qs:placetype":"Town",
    "qs:pop_sr":"6",
    "qs:woe_adm0":23424973,
    "wd:wordcount":192,
    "wof:name":"Usa River",
    "wof:placetype":"locality",
    "wof:population":18726
},
  "geometry": {"coordinates":[36.85,-3.36667],"type":"Point"}
}