{
  "type": "Feature",
  "properties": {
    "gn:admin1_code":"20.0",
    "gn:admin2_code":"5501",
    "gn:admin3_code":"5501121",
    "gn:asciiname":"Dongoni",
    "gn:country_code":"TZ",
    "gn:dem":7,
    "gn:feature_class":"P",
    "gn:feature_code":"PPL",
    "gn:name":"Dongoni",
    "gn:population":0,
    "gn:timezone":"Africa/Dar_es_Salaam",
    "iso:country":"TZ",
    "wof:name":"Dongoni",
    "wof:placetype":"locality"
},
  "geometry": {"coordinates":[39.73333,-5.25],"type":"Point"}
}