{
  "type": "Feature",
  "properties": {
    "gn:admin1_code":"3.0",
    "gn:admin2_code":"0104",
    "gn:admin3_code":"0104051",
    "gn:asciiname":"Chihunungu",
    "gn:country_code":"TZ",
    "gn:dem":1033,
    "gn:feature_class":"P",
    "gn:feature_code":"PPL",
    "gn:name":"Chihunungu",
    "gn:population":0,
    "gn:timezone":"Africa/Dar_es_Salaam",
    "iso:country":"TZ",
    "wof:name":"Chihunungu",
    "wof:placetype":"locality"
},
  "geometry": {"coordinates":[36.28333,-5.86667],"type":"Point"}
}