{
  "type": "Feature",
  "properties": {
    "gn:admin1_code":"5.0",
    "gn:admin2_code":"1602",
    "gn:admin3_code":"1602011",
    "gn:asciiname":"Kipanga",
    "gn:cc2":"TZ",
    "gn:country_code":"TZ",
    "gn:dem":1228,
    "gn:feature_class":"P",
    "gn:feature_code":"PPL",
    "gn:name":"Kipanga",
    "gn:population":0,
    "gn:timezone":"Africa/Dar_es_Salaam",
    "iso:country":"TZ",
    "name:und_x_variant":[
        "Kitanga",
        "Kipanga"
    ],
    "wof:name":"Kipanga",
    "wof:placetype":"locality"
},
  "geometry": {"coordinates":[30.33028,-3.86972],"type":"Point"}
}