{
  "type": "Feature",
  "properties": {
    "gn:admin1_code":"15.0",
    "gn:admin2_code":"1704",
    "gn:admin3_code":"1704151",
    "gn:asciiname":"Malugulu",
    "gn:country_code":"TZ",
    "gn:dem":1185,
    "gn:feature_class":"P",
    "gn:feature_code":"PPL",
    "gn:name":"Malugulu",
    "gn:population":0,
    "gn:timezone":"Africa/Dar_es_Salaam",
    "iso:country":"TZ",
    "name:und_x_variant":[
        "Malugulo",
        "Malugulu"
    ],
    "wof:name":"Malugulu",
    "wof:placetype":"locality"
},
  "geometry": {"coordinates":[32.98333,-3.81667],"type":"Point"}
}