{
  "type": "Feature",
  "properties": {
    "gn:admin1_code":"25.0",
    "gn:admin2_code":"5301",
    "gn:admin3_code":"5301201",
    "gn:asciiname":"Mkunguni Pwani",
    "gn:country_code":"TZ",
    "gn:dem":13,
    "gn:feature_class":"P",
    "gn:feature_code":"PPL",
    "gn:name":"Mkunguni Pwani",
    "gn:population":0,
    "gn:timezone":"Africa/Dar_es_Salaam",
    "iso:country":"TZ",
    "wof:name":"Mkunguni Pwani",
    "wof:placetype":"locality"
},
  "geometry": {"coordinates":[39.28333,-6.28333],"type":"Point"}
}