{
  "type": "Feature",
  "properties": {
    "gn:admin1_code":"17.0",
    "gn:admin2_code":"1405",
    "gn:admin3_code":"1405101",
    "gn:asciiname":"Ibulwa",
    "gn:country_code":"TZ",
    "gn:dem":1134,
    "gn:feature_class":"P",
    "gn:feature_code":"PPL",
    "gn:name":"Ibulwa",
    "gn:population":0,
    "gn:timezone":"Africa/Dar_es_Salaam",
    "iso:country":"TZ",
    "wof:name":"Ibulwa",
    "wof:placetype":"locality"
},
  "geometry": {"coordinates":[32.65,-5.21667],"type":"Point"}
}