{
  "type": "Feature",
  "properties": {
    "gn:admin1_code":"11.0",
    "gn:admin2_code":"0902",
    "gn:admin3_code":"0902091",
    "gn:asciiname":"Mjembe",
    "gn:country_code":"TZ",
    "gn:dem":548,
    "gn:feature_class":"P",
    "gn:feature_code":"PPL",
    "gn:name":"Mjembe",
    "gn:population":0,
    "gn:timezone":"Africa/Dar_es_Salaam",
    "iso:country":"TZ",
    "name:und_x_variant":[
        "Majembe",
        "Mjembe"
    ],
    "wof:name":"Mjembe",
    "wof:placetype":"locality"
},
  "geometry": {"coordinates":[39.13333,-10.71667],"type":"Point"}
}