{
  "type": "Feature",
  "properties": {
    "gn:admin1_code":"8.0",
    "gn:admin2_code":"2007",
    "gn:admin3_code":"2007071",
    "gn:asciiname":"Zanaki",
    "gn:country_code":"TZ",
    "gn:dem":1485,
    "gn:feature_class":"P",
    "gn:feature_code":"PPL",
    "gn:name":"Zanaki",
    "gn:population":0,
    "gn:timezone":"Africa/Dar_es_Salaam",
    "iso:country":"TZ",
    "name:und_x_variant":[
        "Muriaza",
        "Zanaki"
    ],
    "wof:name":"Zanaki",
    "wof:placetype":"locality"
},
  "geometry": {"coordinates":[33.98333,-1.71667],"type":"Point"}
}