{
  "type": "Feature",
  "properties": {
    "gn:admin1_code":"2.0",
    "gn:admin2_code":"0601",
    "gn:admin3_code":"0601153",
    "gn:asciiname":"Mbwewe",
    "gn:country_code":"TZ",
    "gn:dem":414,
    "gn:feature_class":"P",
    "gn:feature_code":"PPL",
    "gn:name":"Mbwewe",
    "gn:population":0,
    "gn:timezone":"Africa/Dar_es_Salaam",
    "iso:country":"TZ",
    "wof:name":"Mbwewe",
    "wof:placetype":"locality"
},
  "geometry": {"coordinates":[38.23333,-6.06667],"type":"Point"}
}