{
  "type": "Feature",
  "properties": {
    "gn:admin1_code":"9.0",
    "gn:admin2_code":"1203",
    "gn:admin3_code":"1203181",
    "gn:asciiname":"Njugilo",
    "gn:country_code":"TZ",
    "gn:dem":500,
    "gn:feature_class":"P",
    "gn:feature_code":"PPL",
    "gn:name":"Njugilo",
    "gn:population":0,
    "gn:timezone":"Africa/Dar_es_Salaam",
    "iso:country":"TZ",
    "name:und_x_variant":[
        "Njugiro",
        "Njugilo"
    ],
    "wof:name":"Njugilo",
    "wof:placetype":"locality"
},
  "geometry": {"coordinates":[33.81667,-9.48333],"type":"Point"}
}