{
  "type": "Feature",
  "properties": {
    "gn:admin1_code":"15.0",
    "gn:admin2_code":"1702",
    "gn:admin3_code":"1702101",
    "gn:asciiname":"Mango",
    "gn:country_code":"TZ",
    "gn:dem":1110,
    "gn:feature_class":"P",
    "gn:feature_code":"PPL",
    "gn:name":"Mango",
    "gn:population":0,
    "gn:timezone":"Africa/Dar_es_Salaam",
    "iso:country":"TZ",
    "wof:name":"Mango",
    "wof:placetype":"locality"
},
  "geometry": {"coordinates":[33.91667,-3.68333],"type":"Point"}
}