{
  "type": "Feature",
  "properties": {
    "gn:admin1_code":"3.0",
    "gn:admin2_code":"0102",
    "gn:admin3_code":"0102101",
    "gn:asciiname":"Rudi",
    "gn:country_code":"TZ",
    "gn:dem":742,
    "gn:feature_class":"P",
    "gn:feature_code":"PPL",
    "gn:name":"Rudi",
    "gn:population":0,
    "gn:timezone":"Africa/Dar_es_Salaam",
    "iso:country":"TZ",
    "name:eng_x_preferred":[
        "Rudi"
    ],
    "name:ita_x_preferred":[
        "Rudi"
    ],
    "name:swa_x_preferred":[
        "Rudi"
    ],
    "wof:name":"Rudi",
    "wof:placetype":"locality"
},
  "geometry": {"coordinates":[36.26667,-6.96667],"type":"Point"}
}