{
  "type": "Feature",
  "properties": {
    "gn:admin1_code":"10.0",
    "gn:admin2_code":"0502",
    "gn:admin3_code":"0502101",
    "gn:asciiname":"Sangasanga",
    "gn:country_code":"TZ",
    "gn:dem":419,
    "gn:feature_class":"P",
    "gn:feature_code":"PPL",
    "gn:name":"Sangasanga",
    "gn:population":0,
    "gn:timezone":"Africa/Dar_es_Salaam",
    "iso:country":"TZ",
    "wof:name":"Sangasanga",
    "wof:placetype":"locality"
},
  "geometry": {"coordinates":[37.81667,-6.66667],"type":"Point"}
}