{
  "type": "Feature",
  "properties": {
    "gn:admin1_code":"3.0",
    "gn:admin2_code":"0106",
    "gn:admin3_code":"0106061",
    "gn:asciiname":"Mundemu",
    "gn:country_code":"TZ",
    "gn:dem":1118,
    "gn:feature_class":"P",
    "gn:feature_code":"PPL",
    "gn:name":"Mundemu",
    "gn:population":0,
    "gn:timezone":"Africa/Dar_es_Salaam",
    "iso:country":"TZ",
    "wof:name":"Mundemu",
    "wof:placetype":"locality"
},
  "geometry": {"coordinates":[35.68333,-5.91667],"type":"Point"}
}