{
  "type": "Feature",
  "properties": {
    "gn:admin1_code":"15.0",
    "gn:admin2_code":"1704",
    "gn:admin3_code":"1704281",
    "gn:asciiname":"Ihapula",
    "gn:country_code":"TZ",
    "gn:dem":1289,
    "gn:feature_class":"P",
    "gn:feature_code":"PPL",
    "gn:name":"Ihapula",
    "gn:population":0,
    "gn:timezone":"Africa/Dar_es_Salaam",
    "iso:country":"TZ",
    "wof:name":"Ihapula",
    "wof:placetype":"locality"
},
  "geometry": {"coordinates":[32.26667,-3.88333],"type":"Point"}
}