{
  "type": "Feature",
  "properties": {
    "gn:admin1_code":"22.0",
    "gn:admin2_code":"5102",
    "gn:admin3_code":"5102071",
    "gn:asciiname":"Kidutani",
    "gn:country_code":"TZ",
    "gn:dem":52,
    "gn:feature_class":"P",
    "gn:feature_code":"PPL",
    "gn:name":"Kidutani",
    "gn:population":0,
    "gn:timezone":"Africa/Dar_es_Salaam",
    "iso:country":"TZ",
    "wof:name":"Kidutani",
    "wof:placetype":"locality"
},
  "geometry": {"coordinates":[39.23333,-6.03333],"type":"Point"}
}