{
  "type": "Feature",
  "properties": {
    "gn:admin1_code":"21.0",
    "gn:admin2_code":"5202",
    "gn:admin3_code":"5202111",
    "gn:asciiname":"Kijichi",
    "gn:country_code":"TZ",
    "gn:dem":38,
    "gn:feature_class":"P",
    "gn:feature_code":"PPL",
    "gn:name":"Kijichi",
    "gn:population":0,
    "gn:timezone":"Africa/Dar_es_Salaam",
    "iso:country":"TZ",
    "wof:name":"Kijichi",
    "wof:placetype":"locality"
},
  "geometry": {"coordinates":[39.46667,-6.36667],"type":"Point"}
}