{
  "type": "Feature",
  "properties": {
    "gn:admin1_code":"18.0",
    "gn:admin2_code":"0402",
    "gn:admin3_code":"0402161",
    "gn:asciiname":"Buiko",
    "gn:country_code":"TZ",
    "gn:dem":533,
    "gn:feature_class":"P",
    "gn:feature_code":"PPL",
    "gn:name":"Buiko",
    "gn:population":0,
    "gn:timezone":"Africa/Dar_es_Salaam",
    "iso:country":"TZ",
    "wof:name":"Buiko",
    "wof:placetype":"locality"
},
  "geometry": {"coordinates":[38.05,-4.65],"type":"Point"}
}