{
  "type": "Feature",
  "properties": {
    "gn:admin1_code":"4.0",
    "gn:admin2_code":"1104",
    "gn:admin3_code":"1104171",
    "gn:asciiname":"Mazombe",
    "gn:country_code":"TZ",
    "gn:dem":1429,
    "gn:feature_class":"P",
    "gn:feature_code":"PPL",
    "gn:name":"Mazombe",
    "gn:population":0,
    "gn:timezone":"Africa/Dar_es_Salaam",
    "iso:country":"TZ",
    "name:eng_x_preferred":[
        "Mazombe"
    ],
    "wof:name":"Mazombe",
    "wof:placetype":"locality"
},
  "geometry": {"coordinates":[36.01150999999999,-7.70694],"type":"Point"}
}