{
  "type": "Feature",
  "properties": {
    "gn:admin1_code":"27.0",
    "gn:admin2_code":"2101",
    "gn:admin3_code":"2101161",
    "gn:asciiname":"Madunga",
    "gn:country_code":"TZ",
    "gn:dem":2102,
    "gn:feature_class":"P",
    "gn:feature_code":"PPL",
    "gn:name":"Madunga",
    "gn:population":0,
    "gn:timezone":"Africa/Dar_es_Salaam",
    "iso:country":"TZ",
    "wof:name":"Madunga",
    "wof:placetype":"locality"
},
  "geometry": {"coordinates":[35.41667,-4.15],"type":"Point"}
}