{
  "type": "Feature",
  "properties": {
    "gn:admin1_code":"3.0",
    "gn:admin2_code":"0105",
    "gn:admin3_code":"0105291",
    "gn:asciiname":"Chihoni",
    "gn:country_code":"TZ",
    "gn:dem":1158,
    "gn:feature_class":"P",
    "gn:feature_code":"PPL",
    "gn:name":"Chihoni",
    "gn:population":0,
    "gn:timezone":"Africa/Dar_es_Salaam",
    "iso:country":"TZ",
    "wof:name":"Chihoni",
    "wof:placetype":"locality"
},
  "geometry": {"coordinates":[35.61667,-6.11667],"type":"Point"}
}