{
  "type": "Feature",
  "properties": {
    "gn:admin1_code":"4.0",
    "gn:admin2_code":"1104",
    "gn:admin3_code":"1104091",
    "gn:asciiname":"Kumwanzi",
    "gn:country_code":"TZ",
    "gn:dem":1787,
    "gn:feature_class":"P",
    "gn:feature_code":"PPL",
    "gn:name":"Kumwanzi",
    "gn:population":0,
    "gn:timezone":"Africa/Dar_es_Salaam",
    "iso:country":"TZ",
    "wof:name":"Kumwanzi",
    "wof:placetype":"locality"
},
  "geometry": {"coordinates":[35.68333,-8.06667],"type":"Point"}
}