{
  "type": "Feature",
  "properties": {
    "gn:country":"TZ",
    "gn:fcode":"ADM3",
    "gn:population":1060416,
    "iso:country":"TZ",
    "name:ita_x_preferred":[
        "Unguja Ukuu"
    ],
    "name:und_x_variant":[
        "Unguja Ukuu Kaebona"
    ],
    "qs_pg:aaroncc":"TZ",
    "qs_pg:gn_country":"TZ",
    "qs_pg:gn_fcode":"ADM3",
    "qs_pg:gn_pop":1060416,
    "qs_pg:name":"Unguja Ukuu",
    "qs_pg:photos_9r":0,
    "qs_pg:photos_sr":0,
    "qs_pg:pop_sr":12,
    "qs_pg:qs_pg_placetype":"localadmin",
    "wof:name":"Unguja Ukuu",
    "wof:placetype":"localadmin",
    "wof:population":1060416
},
  "geometry": {"coordinates":[39.36667,-6.28333],"type":"Point"}
}