{
  "type": "Feature",
  "properties": {
    "gn:admin1_code":"16.0",
    "gn:admin2_code":"1303",
    "gn:admin3_code":"1303271",
    "gn:asciiname":"Masima",
    "gn:country_code":"TZ",
    "gn:dem":1310,
    "gn:feature_class":"P",
    "gn:feature_code":"PPL",
    "gn:name":"Masima",
    "gn:population":0,
    "gn:timezone":"Africa/Dar_es_Salaam",
    "iso:country":"TZ",
    "wof:name":"Masima",
    "wof:placetype":"locality"
},
  "geometry": {"coordinates":[34.38333,-6.75],"type":"Point"}
}