{
  "type": "Feature",
  "properties": {
    "gn:admin1_code":"9.0",
    "gn:admin2_code":"1201",
    "gn:admin3_code":"1201031",
    "gn:asciiname":"Igoma",
    "gn:country_code":"TZ",
    "gn:dem":1419,
    "gn:feature_class":"P",
    "gn:feature_code":"PPL",
    "gn:name":"Igoma",
    "gn:population":0,
    "gn:timezone":"Africa/Dar_es_Salaam",
    "iso:country":"TZ",
    "wof:name":"Igoma",
    "wof:placetype":"locality"
},
  "geometry": {"coordinates":[33.33333,-7.85],"type":"Point"}
}