{
  "type": "Feature",
  "properties": {
    "gn:admin1_code":"16.0",
    "gn:admin2_code":"1303",
    "gn:admin3_code":"1303131",
    "gn:asciiname":"Isombeka",
    "gn:country_code":"TZ",
    "gn:dem":1160,
    "gn:feature_class":"P",
    "gn:feature_code":"PPL",
    "gn:name":"Isombeka",
    "gn:population":0,
    "gn:timezone":"Africa/Dar_es_Salaam",
    "iso:country":"TZ",
    "wof:name":"Isombeka",
    "wof:placetype":"locality"
},
  "geometry": {"coordinates":[34.96667,-6.26667],"type":"Point"}
}