{
  "type": "Feature",
  "properties": {
    "gn:admin1_code":"18.0",
    "gn:admin2_code":"0408",
    "gn:admin3_code":"0408041",
    "gn:asciiname":"Zingibaru",
    "gn:country_code":"TZ",
    "gn:dem":8,
    "gn:feature_class":"P",
    "gn:feature_code":"PPL",
    "gn:name":"Zingibaru",
    "gn:population":0,
    "gn:timezone":"Africa/Dar_es_Salaam",
    "iso:country":"TZ",
    "wof:name":"Zingibaru",
    "wof:placetype":"locality"
},
  "geometry": {"coordinates":[39.16667,-4.76667],"type":"Point"}
}