{
  "type": "Feature",
  "properties": {
    "gn:admin1_code":"3.0",
    "gn:admin2_code":"0102",
    "gn:admin3_code":"0102091",
    "gn:asciiname":"Fufuko",
    "gn:country_code":"TZ",
    "gn:dem":1964,
    "gn:feature_class":"P",
    "gn:feature_code":"PPL",
    "gn:name":"Fufuko",
    "gn:population":0,
    "gn:timezone":"Africa/Dar_es_Salaam",
    "iso:country":"TZ",
    "name:eng_x_preferred":[
        "Fufuko"
    ],
    "wof:name":"Fufuko",
    "wof:placetype":"locality"
},
  "geometry": {"coordinates":[36.4049,-7.19445],"type":"Point"}
}