{
  "type": "Feature",
  "properties": {
    "gn:country":"TZ",
    "gn:fcode":"PPL",
    "gn:population":13810,
    "iso:country":"TZ",
    "name:ceb_x_preferred":[
        "Kyaka"
    ],
    "name:deu_x_preferred":[
        "Kyaka"
    ],
    "name:eng_x_preferred":[
        "Kyaka"
    ],
    "name:fra_x_preferred":[
        "Kyaka"
    ],
    "name:ita_x_preferred":[
        "Kyaka"
    ],
    "name:ron_x_preferred":[
        "Kyaka"
    ],
    "name:swa_x_preferred":[
        "Kyaka"
    ],
    "qs:name":"Kyaka",
    "qs:photos_9r":0,
    "qs:photos_sr":0,
    "qs:pop_sr":"6",
    "wd:wordcount":39,
    "wof:name":"Kyaka",
    "wof:placetype":"locality",
    "wof:population":13810
},
  "geometry": {"coordinates":[31.42028,-1.25222],"type":"Point"}
}