{
  "type": "Feature",
  "properties": {
    "gn:admin1_code":"19.0",
    "gn:admin2_code":"1803",
    "gn:admin3_code":"1803351",
    "gn:asciiname":"Kashasha",
    "gn:country_code":"TZ",
    "gn:dem":1532,
    "gn:feature_class":"P",
    "gn:feature_code":"PPL",
    "gn:name":"Kashasha",
    "gn:population":0,
    "gn:timezone":"Africa/Dar_es_Salaam",
    "iso:country":"TZ",
    "name:swe_x_preferred":[
        "Kashasha"
    ],
    "wof:name":"Kashasha",
    "wof:placetype":"locality"
},
  "geometry": {"coordinates":[31.61583,-1.75778],"type":"Point"}
}