{
  "type": "Feature",
  "properties": {
    "gn:admin1_code":"25.0",
    "gn:admin2_code":"5301",
    "gn:admin3_code":"5301242",
    "gn:asciiname":"Kinuni",
    "gn:country_code":"TZ",
    "gn:dem":47,
    "gn:feature_class":"P",
    "gn:feature_code":"PPL",
    "gn:name":"Kinuni",
    "gn:population":0,
    "gn:timezone":"Africa/Dar_es_Salaam",
    "iso:country":"TZ",
    "wof:name":"Kinuni",
    "wof:placetype":"locality"
},
  "geometry": {"coordinates":[39.23333,-6.16667],"type":"Point"}
}