{
  "type": "Feature",
  "properties": {
    "gn:admin1_code":"13.0",
    "gn:admin2_code":"5402",
    "gn:admin3_code":"5402091",
    "gn:asciiname":"Kinazini",
    "gn:country_code":"TZ",
    "gn:dem":41,
    "gn:feature_class":"P",
    "gn:feature_code":"PPL",
    "gn:name":"Kinazini",
    "gn:population":0,
    "gn:timezone":"Africa/Dar_es_Salaam",
    "iso:country":"TZ",
    "wof:name":"Kinazini",
    "wof:placetype":"locality"
},
  "geometry": {"coordinates":[39.78333,-5.01667],"type":"Point"}
}