{
  "type": "Feature",
  "properties": {
    "gn:admin1_code":"29.0",
    "gn:asciiname":"Mhuba",
    "gn:country_code":"TZ",
    "gn:dem":1074,
    "gn:feature_class":"P",
    "gn:feature_code":"PPL",
    "gn:name":"Mhuba",
    "gn:population":0,
    "gn:timezone":"Africa/Dar_es_Salaam",
    "iso:country":"TZ",
    "wof:name":"Mhuba",
    "wof:placetype":"locality"
},
  "geometry": {"coordinates":[31.65,-5.81667],"type":"Point"}
}