{
  "type": "Feature",
  "properties": {
    "gn:admin1_code":"2.0",
    "gn:admin2_code":"0603",
    "gn:admin3_code":"0603081",
    "gn:asciiname":"Titu",
    "gn:country_code":"TZ",
    "gn:dem":181,
    "gn:feature_class":"P",
    "gn:feature_code":"PPL",
    "gn:name":"Titu",
    "gn:population":0,
    "gn:timezone":"Africa/Dar_es_Salaam",
    "iso:country":"TZ",
    "name:eng_x_preferred":[
        "Titu"
    ],
    "wof:name":"Titu",
    "wof:placetype":"locality"
},
  "geometry": {"coordinates":[38.70842,-7.39483],"type":"Point"}
}