{
  "type": "Feature",
  "properties": {
    "gn:admin1_code":"2.0",
    "gn:admin2_code":"0603",
    "gn:admin3_code":"0603081",
    "gn:asciiname":"Titu",
    "gn:country_code":"TZ",
    "gn:dem":181,
    "gn:feature_class":"P",
    "gn:feature_code":"PPL",
    "gn:name":"Titu",
    "gn:population":0,
    "gn:timezone":"Africa/Dar_es_Salaam",
    "iso:country":"TZ",
    "name:ceb_x_preferred":[
        "Ora\u0219 Titu"
    ],
    "name:deu_x_preferred":[
        "Titu"
    ],
    "name:eng_x_preferred":[
        "Titu"
    ],
    "name:fas_x_preferred":[
        "\u062a\u06cc\u062a\u0648"
    ],
    "name:fra_x_preferred":[
        "Titu"
    ],
    "name:hun_x_preferred":[
        "Titu"
    ],
    "name:ind_x_preferred":[
        "Titu"
    ],
    "name:ita_x_preferred":[
        "Titu"
    ],
    "name:lat_x_preferred":[
        "Titu"
    ],
    "name:min_x_preferred":[
        "Titu"
    ],
    "name:msa_x_preferred":[
        "Titu"
    ],
    "name:nld_x_preferred":[
        "Titu"
    ],
    "name:pol_x_preferred":[
        "Titu"
    ],
    "name:por_x_preferred":[
        "Titu"
    ],
    "name:ron_x_preferred":[
        "Titu"
    ],
    "name:rus_x_preferred":[
        "\u0422\u0438\u0442\u0443"
    ],
    "name:spa_x_preferred":[
        "Titu"
    ],
    "name:srp_x_preferred":[
        "\u041e\u043f\u0448\u0442\u0438\u043d\u0430 \u0422\u0438\u0442\u0443"
    ],
    "name:tgk_x_preferred":[
        "\u0422\u0438\u0442\u0443"
    ],
    "name:ukr_x_preferred":[
        "\u0422\u0456\u0442\u0443"
    ],
    "name:vie_x_preferred":[
        "Titu"
    ],
    "wof:name":"Titu",
    "wof:placetype":"locality"
},
  "geometry": {"coordinates":[38.70842,-7.39483],"type":"Point"}
}