{
  "type": "Feature",
  "properties": {
    "iso:country":"TZ",
    "name:dan_x_preferred":[
        "Vwawa"
    ],
    "name:deu_x_preferred":[
        "Vwawa"
    ],
    "name:eng_x_preferred":[
        "Vwawa"
    ],
    "name:fin_x_preferred":[
        "Vwawa"
    ],
    "name:fra_x_preferred":[
        "Vwawa"
    ],
    "name:jpn_x_preferred":[
        "\u30f4\u30ef\u30ef"
    ],
    "name:nld_x_preferred":[
        "Vwawa"
    ],
    "name:nno_x_preferred":[
        "Vwawa"
    ],
    "name:nob_x_preferred":[
        "Vwawa"
    ],
    "name:pol_x_preferred":[
        "Vwawa"
    ],
    "name:rus_x_preferred":[
        "\u0412\u0443\u0430\u0443\u0430"
    ],
    "name:swa_x_preferred":[
        "Vwawa"
    ],
    "name:swe_x_preferred":[
        "Vwawa"
    ],
    "name:und_x_variant":[
        "Vawa"
    ],
    "qs:gn_country":"TZ",
    "qs:gn_fcode":"PPL",
    "qs:gn_pop":40145,
    "qs:name":"Vwawa",
    "qs:name_adm0":"Tanzania",
    "qs:name_adm1":"Mbeya",
    "qs:photos":0,
    "qs:photos_1k":0,
    "qs:photos_9k":1,
    "qs:photos_9r":1,
    "qs:photos_all":5,
    "qs:photos_sr":0,
    "qs:placetype":"Town",
    "qs:pop_sr":"7",
    "qs:woe_adm0":23424973,
    "wd:wordcount":158,
    "wof:name":"Vwawa",
    "wof:placetype":"locality",
    "wof:population":40145
},
  "geometry": {"coordinates":[32.93333,-9.11667],"type":"Point"}
}