{
  "type": "Feature",
  "properties": {
    "gn:admin1_code":"14.0",
    "gn:admin2_code":"1002",
    "gn:admin3_code":"1002061",
    "gn:asciiname":"Namtui",
    "gn:country_code":"TZ",
    "gn:dem":1024,
    "gn:feature_class":"P",
    "gn:feature_code":"PPL",
    "gn:name":"Namtui",
    "gn:population":0,
    "gn:timezone":"Africa/Dar_es_Salaam",
    "iso:country":"TZ",
    "name:und_x_variant":[
        "Namatui",
        "Namtui"
    ],
    "wof:name":"Namtui",
    "wof:placetype":"locality"
},
  "geometry": {"coordinates":[35.45,-10.86667],"type":"Point"}
}