{
  "type": "Feature",
  "properties": {
    "gn:admin1_code":"29.0",
    "gn:admin2_code":"2302",
    "gn:admin3_code":"2302013",
    "gn:asciiname":"Msobwe",
    "gn:country_code":"TZ",
    "gn:dem":1365,
    "gn:feature_class":"P",
    "gn:feature_code":"PPL",
    "gn:name":"Msobwe",
    "gn:population":0,
    "gn:timezone":"Africa/Dar_es_Salaam",
    "iso:country":"TZ",
    "name:und_x_variant":[
        "Kasombwe",
        "Sombwe",
        "Msobwe"
    ],
    "wof:name":"Msobwe",
    "wof:placetype":"locality"
},
  "geometry": {"coordinates":[30.41667,-5.45],"type":"Point"}
}