{
  "type": "Feature",
  "properties": {
    "gn:admin1_code":"19.0",
    "gn:admin2_code":"1804",
    "gn:admin3_code":"1804033",
    "gn:asciiname":"Rubondo",
    "gn:country_code":"TZ",
    "gn:dem":1462,
    "gn:feature_class":"P",
    "gn:feature_code":"PPL",
    "gn:name":"Rubondo",
    "gn:population":0,
    "gn:timezone":"Africa/Dar_es_Salaam",
    "iso:country":"TZ",
    "wof:name":"Rubondo",
    "wof:placetype":"locality"
},
  "geometry": {"coordinates":[31.32444000000001,-2.66389],"type":"Point"}
}