{
  "type": "Feature",
  "properties": {
    "gn:admin1_code":"18.0",
    "gn:admin2_code":"0401",
    "gn:admin3_code":"0401371",
    "gn:asciiname":"Kwemiangwa",
    "gn:country_code":"TZ",
    "gn:dem":1426,
    "gn:feature_class":"P",
    "gn:feature_code":"PPL",
    "gn:name":"Kwemiangwa",
    "gn:population":0,
    "gn:timezone":"Africa/Dar_es_Salaam",
    "iso:country":"TZ",
    "wof:name":"Kwemiangwa",
    "wof:placetype":"locality"
},
  "geometry": {"coordinates":[38.31667,-4.58333],"type":"Point"}
}