{
  "type": "Feature",
  "properties": {
    "gn:admin1_code":"17.0",
    "gn:admin2_code":"1403",
    "gn:admin3_code":"1403091",
    "gn:asciiname":"Ibiri",
    "gn:country_code":"TZ",
    "gn:dem":1176,
    "gn:feature_class":"P",
    "gn:feature_code":"PPL",
    "gn:name":"Ibiri",
    "gn:population":0,
    "gn:timezone":"Africa/Dar_es_Salaam",
    "iso:country":"TZ",
    "wof:name":"Ibiri",
    "wof:placetype":"locality"
},
  "geometry": {"coordinates":[32.55,-4.93333],"type":"Point"}
}