{
  "type": "Feature",
  "properties": {
    "gn:admin1_code":"7.0",
    "gn:admin2_code":"0806",
    "gn:admin3_code":"0806132",
    "gn:asciiname":"Kitunda",
    "gn:country_code":"TZ",
    "gn:dem":101,
    "gn:feature_class":"P",
    "gn:feature_code":"PPL",
    "gn:name":"Kitunda",
    "gn:population":0,
    "gn:timezone":"Africa/Dar_es_Salaam",
    "iso:country":"TZ",
    "name:afr_x_preferred":[
        "Kitunda"
    ],
    "name:ita_x_preferred":[
        "Kitunda"
    ],
    "name:ron_x_preferred":[
        "Kitunda"
    ],
    "name:swa_x_preferred":[
        "Kitunda"
    ],
    "wof:name":"Kitunda",
    "wof:placetype":"locality"
},
  "geometry": {"coordinates":[39.76667,-10.01667],"type":"Point"}
}