{
  "type": "Feature",
  "properties": {
    "gn:admin1_code":"21.0",
    "gn:admin2_code":"5201",
    "gn:admin3_code":"5201391",
    "gn:asciiname":"Ndijani",
    "gn:country_code":"TZ",
    "gn:dem":37,
    "gn:feature_class":"P",
    "gn:feature_code":"PPL",
    "gn:name":"Ndijani",
    "gn:population":0,
    "gn:timezone":"Africa/Dar_es_Salaam",
    "iso:country":"TZ",
    "name:und_x_variant":[
        "Ndidyani",
        "Ndijani"
    ],
    "wof:name":"Ndijani",
    "wof:placetype":"locality"
},
  "geometry": {"coordinates":[39.35,-6.16667],"type":"Point"}
}