{
  "type": "Feature",
  "properties": {
    "gn:admin1_code":"3.0",
    "gn:admin2_code":"0105",
    "gn:admin3_code":"0105351",
    "gn:asciiname":"Chahwa",
    "gn:country_code":"TZ",
    "gn:dem":1038,
    "gn:feature_class":"P",
    "gn:feature_code":"PPL",
    "gn:name":"Chahwa",
    "gn:population":0,
    "gn:timezone":"Africa/Dar_es_Salaam",
    "iso:country":"TZ",
    "name:und_x_variant":[
        "Chawa",
        "Chahwa"
    ],
    "wof:name":"Chahwa",
    "wof:placetype":"locality"
},
  "geometry": {"coordinates":[35.98333,-6.05],"type":"Point"}
}