{
  "type": "Feature",
  "properties": {
    "gn:admin1_code":"17.0",
    "gn:admin2_code":"1403",
    "gn:admin3_code":"1403121",
    "gn:asciiname":"Ikongolo",
    "gn:country_code":"TZ",
    "gn:dem":1222,
    "gn:feature_class":"P",
    "gn:feature_code":"PPL",
    "gn:name":"Ikongolo",
    "gn:population":0,
    "gn:timezone":"Africa/Dar_es_Salaam",
    "iso:country":"TZ",
    "wof:name":"Ikongolo",
    "wof:placetype":"locality"
},
  "geometry": {"coordinates":[32.95,-4.88333],"type":"Point"}
}