{
  "type": "Feature",
  "properties": {
    "gn:admin1_code":"18.0",
    "gn:admin2_code":"0407",
    "gn:admin3_code":"0407141",
    "gn:asciiname":"Mkonde",
    "gn:country_code":"TZ",
    "gn:dem":829,
    "gn:feature_class":"P",
    "gn:feature_code":"PPL",
    "gn:name":"Mkonde",
    "gn:population":0,
    "gn:timezone":"Africa/Dar_es_Salaam",
    "iso:country":"TZ",
    "wof:name":"Mkonde",
    "wof:placetype":"locality"
},
  "geometry": {"coordinates":[37.73333,-5.43333],"type":"Point"}
}