{
  "type": "Feature",
  "properties": {
    "gn:admin1_code":"2.0",
    "gn:admin2_code":"0605",
    "gn:admin3_code":"0605161",
    "gn:asciiname":"Salale",
    "gn:country_code":"TZ",
    "gn:dem":18,
    "gn:feature_class":"P",
    "gn:feature_code":"PPL",
    "gn:name":"Salale",
    "gn:population":0,
    "gn:timezone":"Africa/Dar_es_Salaam",
    "iso:country":"TZ",
    "name:eng_x_preferred":[
        "Salale"
    ],
    "wof:name":"Salale",
    "wof:placetype":"locality"
},
  "geometry": {"coordinates":[39.35195,-7.84984],"type":"Point"}
}