{
  "type": "Feature",
  "properties": {
    "gn:admin1_code":"19.0",
    "gn:admin2_code":"1805",
    "gn:admin3_code":"1805121",
    "gn:asciiname":"Mu Kikomero",
    "gn:country_code":"TZ",
    "gn:dem":1645,
    "gn:feature_class":"P",
    "gn:feature_code":"PPL",
    "gn:name":"Mu Kikomero",
    "gn:population":0,
    "gn:timezone":"Africa/Dar_es_Salaam",
    "iso:country":"TZ",
    "wof:name":"Mu Kikomero",
    "wof:placetype":"locality"
},
  "geometry": {"coordinates":[30.53333,-2.51667],"type":"Point"}
}