{
  "type": "Feature",
  "properties": {
    "gn:admin1_code":"2.0",
    "gn:admin2_code":"0605",
    "gn:admin3_code":"0605061",
    "gn:asciiname":"Kipungira",
    "gn:country_code":"TZ",
    "gn:dem":55,
    "gn:feature_class":"P",
    "gn:feature_code":"PPL",
    "gn:name":"Kipungira",
    "gn:population":0,
    "gn:timezone":"Africa/Dar_es_Salaam",
    "iso:country":"TZ",
    "name:eng_x_preferred":[
        "Kipungira"
    ],
    "wof:name":"Kipungira",
    "wof:placetype":"locality"
},
  "geometry": {"coordinates":[38.51478,-7.83577],"type":"Point"}
}