{
  "type": "Feature",
  "properties": {
    "gn:admin1_code":"14.0",
    "gn:admin2_code":"1005",
    "gn:admin3_code":"1005031",
    "gn:asciiname":"Matimbuka",
    "gn:country_code":"TZ",
    "gn:dem":719,
    "gn:feature_class":"P",
    "gn:feature_code":"PPL",
    "gn:name":"Matimbuka",
    "gn:population":0,
    "gn:timezone":"Africa/Dar_es_Salaam",
    "iso:country":"TZ",
    "wof:name":"Matimbuka",
    "wof:placetype":"locality"
},
  "geometry": {"coordinates":[35.93333,-11.15],"type":"Point"}
}