{
  "type": "Feature",
  "properties": {
    "gn:admin1_code":"24.0",
    "gn:admin2_code":"1502",
    "gn:admin3_code":"1502041",
    "gn:asciiname":"Milepa",
    "gn:country_code":"TZ",
    "gn:dem":848,
    "gn:feature_class":"P",
    "gn:feature_code":"PPL",
    "gn:name":"Milepa",
    "gn:population":0,
    "gn:timezone":"Africa/Dar_es_Salaam",
    "iso:country":"TZ",
    "name:und_x_variant":[
        "Milapa",
        "Milepa"
    ],
    "wof:name":"Milepa",
    "wof:placetype":"locality"
},
  "geometry": {"coordinates":[31.93333,-8.06667],"type":"Point"}
}