{
  "type": "Feature",
  "properties": {
    "gn:admin1_code":"13.0",
    "gn:admin2_code":"5402",
    "gn:admin3_code":"5402061",
    "gn:asciiname":"Jondoli",
    "gn:country_code":"TZ",
    "gn:dem":39,
    "gn:feature_class":"P",
    "gn:feature_code":"PPL",
    "gn:name":"Jondoli",
    "gn:population":0,
    "gn:timezone":"Africa/Dar_es_Salaam",
    "iso:country":"TZ",
    "wof:name":"Jondoli",
    "wof:placetype":"locality"
},
  "geometry": {"coordinates":[39.76667,-4.98333],"type":"Point"}
}