{
  "type": "Feature",
  "properties": {
    "gn:admin1_code":"5.0",
    "gn:admin2_code":"1605",
    "gn:admin3_code":"1605021",
    "gn:asciiname":"Sitete",
    "gn:country_code":"TZ",
    "gn:dem":1625,
    "gn:feature_class":"P",
    "gn:feature_code":"PPL",
    "gn:name":"Sitete",
    "gn:population":0,
    "gn:timezone":"Africa/Dar_es_Salaam",
    "iso:country":"TZ",
    "name:eng_x_preferred":[
        "Sitete"
    ],
    "wof:name":"Sitete",
    "wof:placetype":"locality"
},
  "geometry": {"coordinates":[29.87252,-6.12629],"type":"Point"}
}