{
  "type": "Feature",
  "properties": {
    "gn:admin1_code":"22.0",
    "gn:admin2_code":"5102",
    "gn:admin3_code":"5102261",
    "gn:asciiname":"Kitope",
    "gn:country_code":"TZ",
    "gn:dem":67,
    "gn:feature_class":"P",
    "gn:feature_code":"PPL",
    "gn:name":"Kitope",
    "gn:population":0,
    "gn:timezone":"Africa/Dar_es_Salaam",
    "iso:country":"TZ",
    "name:und_x_variant":[
        "Kitope Village",
        "Kitope"
    ],
    "wof:name":"Kitope",
    "wof:placetype":"locality"
},
  "geometry": {"coordinates":[39.26667,-6.01667],"type":"Point"}
}