{
  "type": "Feature",
  "properties": {
    "gn:admin1_code":"5.0",
    "gn:admin2_code":"1605",
    "gn:admin3_code":"1605021",
    "gn:asciiname":"Konkwa",
    "gn:country_code":"TZ",
    "gn:dem":783,
    "gn:feature_class":"P",
    "gn:feature_code":"PPL",
    "gn:name":"Konkwa",
    "gn:population":0,
    "gn:timezone":"Africa/Dar_es_Salaam",
    "iso:country":"TZ",
    "name:eng_x_preferred":[
        "Konkwa"
    ],
    "wof:name":"Konkwa",
    "wof:placetype":"locality"
},
  "geometry": {"coordinates":[29.81804,-6.0061],"type":"Point"}
}