{
  "type": "Feature",
  "properties": {
    "gn:admin1_code":"18.0",
    "gn:admin2_code":"0404",
    "gn:admin3_code":"0404203",
    "gn:asciiname":"Kihongwe",
    "gn:country_code":"TZ",
    "gn:dem":6,
    "gn:feature_class":"P",
    "gn:feature_code":"PPL",
    "gn:name":"Kihongwe",
    "gn:population":0,
    "gn:timezone":"Africa/Dar_es_Salaam",
    "iso:country":"TZ",
    "wof:name":"Kihongwe",
    "wof:placetype":"locality"
},
  "geometry": {"coordinates":[39.08333,-5.05],"type":"Point"}
}