{
  "type": "Feature",
  "properties": {
    "gn:admin1_code":"6.0",
    "gn:admin2_code":"0303",
    "gn:admin3_code":"0303201",
    "gn:asciiname":"Vunta",
    "gn:country_code":"TZ",
    "gn:dem":1312,
    "gn:feature_class":"P",
    "gn:feature_code":"PPL",
    "gn:name":"Vunta",
    "gn:population":0,
    "gn:timezone":"Africa/Dar_es_Salaam",
    "iso:country":"TZ",
    "wof:name":"Vunta",
    "wof:placetype":"locality"
},
  "geometry": {"coordinates":[37.98333,-4.56667],"type":"Point"}
}