{
  "type": "Feature",
  "properties": {
    "gn:admin1_code":"4.0",
    "gn:admin2_code":"1104",
    "gn:admin3_code":"1104061",
    "gn:asciiname":"Tenguka",
    "gn:country_code":"TZ",
    "gn:dem":693,
    "gn:feature_class":"P",
    "gn:feature_code":"PPL",
    "gn:name":"Tenguka",
    "gn:population":0,
    "gn:timezone":"Africa/Dar_es_Salaam",
    "iso:country":"TZ",
    "name:eng_x_preferred":[
        "Tenguka"
    ],
    "wof:name":"Tenguka",
    "wof:placetype":"locality"
},
  "geometry": {"coordinates":[36.25943,-7.64693],"type":"Point"}
}