{
  "type": "Feature",
  "properties": {
    "gn:admin1_code":"18.0",
    "gn:admin2_code":"0407",
    "gn:admin3_code":"0407141",
    "gn:asciiname":"Mbali",
    "gn:country_code":"TZ",
    "gn:dem":752,
    "gn:feature_class":"P",
    "gn:feature_code":"PPL",
    "gn:name":"Mbali",
    "gn:population":0,
    "gn:timezone":"Africa/Dar_es_Salaam",
    "iso:country":"TZ",
    "name:ceb_x_preferred":[
        "Mbali"
    ],
    "name:deu_x_preferred":[
        "Mbali"
    ],
    "name:swe_x_preferred":[
        "Mbali"
    ],
    "wof:name":"Mbali",
    "wof:placetype":"locality"
},
  "geometry": {"coordinates":[37.68333,-5.48333],"type":"Point"}
}