{
  "type": "Feature",
  "properties": {
    "gn:admin1_code":"14.0",
    "gn:admin2_code":"1001",
    "gn:admin3_code":"1001161",
    "gn:asciiname":"Mnemba",
    "gn:country_code":"TZ",
    "gn:dem":655,
    "gn:feature_class":"P",
    "gn:feature_code":"PPL",
    "gn:name":"Mnemba",
    "gn:population":0,
    "gn:timezone":"Africa/Dar_es_Salaam",
    "iso:country":"TZ",
    "wof:name":"Mnemba",
    "wof:placetype":"locality"
},
  "geometry": {"coordinates":[36.95,-11.41667],"type":"Point"}
}