{
  "type": "Feature",
  "properties": {
    "gn:admin1_code":"13.0",
    "gn:asciiname":"Move",
    "gn:country_code":"TZ",
    "gn:dem":-9999,
    "gn:feature_class":"P",
    "gn:feature_code":"PPL",
    "gn:name":"Move",
    "gn:population":0,
    "gn:timezone":"Africa/Dar_es_Salaam",
    "iso:country":"TZ",
    "name:deu_x_preferred":[
        "Move"
    ],
    "name:fin_x_preferred":[
        "Move"
    ],
    "name:fra_x_preferred":[
        "Move"
    ],
    "name:ita_x_preferred":[
        "Move"
    ],
    "name:jpn_x_preferred":[
        "\u30e0\u30fc\u30d6"
    ],
    "name:nld_x_preferred":[
        "Move"
    ],
    "name:pol_x_preferred":[
        "Move"
    ],
    "name:por_x_preferred":[
        "Move"
    ],
    "name:rus_x_preferred":[
        "Move"
    ],
    "name:swe_x_preferred":[
        "Move"
    ],
    "name:zho_x_preferred":[
        "Move"
    ],
    "wof:name":"Move",
    "wof:placetype":"locality"
},
  "geometry": {"coordinates":[39.96667,-5.06667],"type":"Point"}
}