{
  "type": "Feature",
  "properties": {
    "gn:admin1_code":"2.0",
    "gn:admin2_code":"0603",
    "gn:admin3_code":"0603111",
    "gn:asciiname":"Gwata",
    "gn:country_code":"TZ",
    "gn:dem":56,
    "gn:feature_class":"P",
    "gn:feature_code":"PPL",
    "gn:name":"Gwata",
    "gn:population":0,
    "gn:timezone":"Africa/Dar_es_Salaam",
    "iso:country":"TZ",
    "name:eng_x_preferred":[
        "Gwata"
    ],
    "wof:name":"Gwata",
    "wof:placetype":"locality"
},
  "geometry": {"coordinates":[38.47066,-7.12256],"type":"Point"}
}