{
  "type": "Feature",
  "properties": {
    "gn:admin1_code":"9.0",
    "gn:admin2_code":"1201",
    "gn:admin3_code":"1201061",
    "gn:asciiname":"Matopotopo",
    "gn:country_code":"TZ",
    "gn:dem":1379,
    "gn:feature_class":"P",
    "gn:feature_code":"PPL",
    "gn:name":"Matopotopo",
    "gn:population":0,
    "gn:timezone":"Africa/Dar_es_Salaam",
    "iso:country":"TZ",
    "wof:name":"Matopotopo",
    "wof:placetype":"locality"
},
  "geometry": {"coordinates":[34.11667,-7.68333],"type":"Point"}
}