{
  "type": "Feature",
  "properties": {
    "gn:admin1_code":"4.0",
    "gn:admin2_code":"1101",
    "gn:admin3_code":"1101201",
    "gn:asciiname":"Isaka",
    "gn:country_code":"TZ",
    "gn:dem":1048,
    "gn:feature_class":"P",
    "gn:feature_code":"PPL",
    "gn:name":"Isaka",
    "gn:population":0,
    "gn:timezone":"Africa/Dar_es_Salaam",
    "iso:country":"TZ",
    "name:eng_x_preferred":[
        "Isaka"
    ],
    "name:ita_x_preferred":[
        "Isaka"
    ],
    "name:swa_x_preferred":[
        "Isaka"
    ],
    "wof:name":"Isaka",
    "wof:placetype":"locality"
},
  "geometry": {"coordinates":[36.13333,-7.26667],"type":"Point"}
}