{
  "type": "Feature",
  "properties": {
    "gn:admin1_code":"4.0",
    "gn:admin2_code":"1102",
    "gn:admin3_code":"1102231",
    "gn:asciiname":"Kibengu",
    "gn:country_code":"TZ",
    "gn:dem":1938,
    "gn:feature_class":"P",
    "gn:feature_code":"PPL",
    "gn:name":"Kibengu",
    "gn:population":0,
    "gn:timezone":"Africa/Dar_es_Salaam",
    "iso:country":"TZ",
    "wof:name":"Kibengu",
    "wof:placetype":"locality"
},
  "geometry": {"coordinates":[35.71667,-8.26667],"type":"Point"}
}