{
  "type": "Feature",
  "properties": {
    "gn:admin1_code":"7.0",
    "gn:admin2_code":"0801",
    "gn:admin3_code":"0801151",
    "gn:asciiname":"Roango",
    "gn:country_code":"TZ",
    "gn:dem":28,
    "gn:feature_class":"P",
    "gn:feature_code":"PPL",
    "gn:name":"Roango",
    "gn:population":0,
    "gn:timezone":"Africa/Dar_es_Salaam",
    "iso:country":"TZ",
    "name:und_x_variant":[
        "Loangwa",
        "Roango"
    ],
    "wof:name":"Roango",
    "wof:placetype":"locality"
},
  "geometry": {"coordinates":[39.61667,-9.25],"type":"Point"}
}