{
  "type": "Feature",
  "properties": {
    "gn:admin1_code":"5.0",
    "gn:admin2_code":"1605",
    "gn:admin3_code":"1605031",
    "gn:asciiname":"Kasela",
    "gn:country_code":"TZ",
    "gn:dem":1062,
    "gn:feature_class":"P",
    "gn:feature_code":"PPL",
    "gn:name":"Kasela",
    "gn:population":0,
    "gn:timezone":"Africa/Dar_es_Salaam",
    "iso:country":"TZ",
    "name:eng_x_preferred":[
        "Kasela"
    ],
    "wof:name":"Kasela",
    "wof:placetype":"locality"
},
  "geometry": {"coordinates":[30.18277,-6.32246],"type":"Point"}
}