{
  "type": "Feature",
  "properties": {
    "gn:admin1_code":"25.0",
    "gn:admin2_code":"5301",
    "gn:admin3_code":"5301023",
    "gn:asciiname":"Mtoni",
    "gn:country_code":"TZ",
    "gn:dem":16,
    "gn:feature_class":"P",
    "gn:feature_code":"PPL",
    "gn:name":"Mtoni",
    "gn:population":0,
    "gn:timezone":"Africa/Dar_es_Salaam",
    "iso:country":"TZ",
    "name:ceb_x_preferred":[
        "Mtoni"
    ],
    "name:swe_x_preferred":[
        "Mtoni"
    ],
    "name:und_x_variant":[
        "Mtoni Village"
    ],
    "wof:name":"Mtoni",
    "wof:placetype":"locality"
},
  "geometry": {"coordinates":[39.21667,-6.13333],"type":"Point"}
}