{
  "type": "Feature",
  "properties": {
    "gn:admin1_code":"18.0",
    "gn:admin2_code":"0408",
    "gn:admin3_code":"0408081",
    "gn:asciiname":"Gombero",
    "gn:country_code":"TZ",
    "gn:dem":125,
    "gn:feature_class":"P",
    "gn:feature_code":"PPL",
    "gn:name":"Gombero",
    "gn:population":0,
    "gn:timezone":"Africa/Dar_es_Salaam",
    "iso:country":"TZ",
    "name:und_x_variant":[
        "Gombelo",
        "Gombero"
    ],
    "wof:name":"Gombero",
    "wof:placetype":"locality"
},
  "geometry": {"coordinates":[38.95,-4.95],"type":"Point"}
}