{
  "type": "Feature",
  "properties": {
    "gn:admin1_code":"29.0",
    "gn:admin2_code":"2303",
    "gn:admin3_code":"2303111",
    "gn:asciiname":"Utendesia",
    "gn:country_code":"TZ",
    "gn:dem":1053,
    "gn:feature_class":"P",
    "gn:feature_code":"PPL",
    "gn:name":"Utendesia",
    "gn:population":0,
    "gn:timezone":"Africa/Dar_es_Salaam",
    "iso:country":"TZ",
    "name:eng_x_preferred":[
        "Utendesia"
    ],
    "wof:name":"Utendesia",
    "wof:placetype":"locality"
},
  "geometry": {"coordinates":[31.38995,-6.47004],"type":"Point"}
}