{
  "type": "Feature",
  "properties": {
    "gn:admin1_code":"2.0",
    "gn:admin2_code":"0601",
    "gn:admin3_code":"0601011",
    "gn:asciiname":"Masugulu",
    "gn:country_code":"TZ",
    "gn:dem":198,
    "gn:feature_class":"P",
    "gn:feature_code":"PPL",
    "gn:name":"Masugulu",
    "gn:population":0,
    "gn:timezone":"Africa/Dar_es_Salaam",
    "iso:country":"TZ",
    "wof:name":"Masugulu",
    "wof:placetype":"locality"
},
  "geometry": {"coordinates":[38.46667,-6.35],"type":"Point"}
}