{
  "type": "Feature",
  "properties": {
    "gn:admin1_code":"20.0",
    "gn:admin2_code":"5502",
    "gn:admin3_code":"5502012",
    "gn:asciiname":"Katomeni",
    "gn:country_code":"TZ",
    "gn:dem":51,
    "gn:feature_class":"P",
    "gn:feature_code":"PPL",
    "gn:name":"Katomeni",
    "gn:population":0,
    "gn:timezone":"Africa/Dar_es_Salaam",
    "iso:country":"TZ",
    "wof:name":"Katomeni",
    "wof:placetype":"locality"
},
  "geometry": {"coordinates":[39.65,-5.35],"type":"Point"}
}