{
  "type": "Feature",
  "properties": {
    "gn:admin1_code":"24.0",
    "gn:admin2_code":"1501",
    "gn:admin3_code":"1501141",
    "gn:asciiname":"Katete",
    "gn:country_code":"TZ",
    "gn:dem":1797,
    "gn:feature_class":"P",
    "gn:feature_code":"PPL",
    "gn:name":"Katete",
    "gn:population":0,
    "gn:timezone":"Africa/Dar_es_Salaam",
    "iso:country":"TZ",
    "name:bul_x_preferred":[
        "\u041a\u0430\u0442\u0435\u0442\u0435"
    ],
    "name:deu_x_preferred":[
        "Katete"
    ],
    "name:ita_x_preferred":[
        "Katete"
    ],
    "name:mrj_x_preferred":[
        "\u041a\u0430\u0442\u0435\u0442\u0435"
    ],
    "name:pol_x_preferred":[
        "Katete"
    ],
    "name:por_x_preferred":[
        "Katete"
    ],
    "name:ron_x_preferred":[
        "Katete"
    ],
    "name:spa_x_preferred":[
        "Katete"
    ],
    "name:zho_x_preferred":[
        "\u5361\u6cf0\u7279"
    ],
    "wof:name":"Katete",
    "wof:placetype":"locality"
},
  "geometry": {"coordinates":[31.53333,-8.63333],"type":"Point"}
}