{
  "type": "Feature",
  "properties": {
    "gn:admin1_code":"20.0",
    "gn:admin2_code":"5502",
    "gn:admin3_code":"5502071",
    "gn:asciiname":"Kilimani",
    "gn:country_code":"TZ",
    "gn:dem":18,
    "gn:feature_class":"P",
    "gn:feature_code":"PPL",
    "gn:name":"Kilimani",
    "gn:population":0,
    "gn:timezone":"Africa/Dar_es_Salaam",
    "iso:country":"TZ",
    "wof:name":"Kilimani",
    "wof:placetype":"locality"
},
  "geometry": {"coordinates":[39.65,-5.41667],"type":"Point"}
}