{
  "type": "Feature",
  "properties": {
    "gn:admin1_code":"5.0",
    "gn:admin2_code":"1602",
    "gn:admin3_code":"1602031",
    "gn:asciiname":"Kabuga",
    "gn:country_code":"TZ",
    "gn:dem":1234,
    "gn:feature_class":"P",
    "gn:feature_code":"PPL",
    "gn:name":"Kabuga",
    "gn:population":0,
    "gn:timezone":"Africa/Dar_es_Salaam",
    "iso:country":"TZ",
    "name:cat_x_preferred":[
        "Kabuga"
    ],
    "name:fra_x_preferred":[
        "Kabuga"
    ],
    "name:pol_x_preferred":[
        "Kabuga"
    ],
    "wof:name":"Kabuga",
    "wof:placetype":"locality"
},
  "geometry": {"coordinates":[30.46667,-4.10806],"type":"Point"}
}