{
  "type": "Feature",
  "properties": {
    "gn:admin1_code":"18.0",
    "gn:admin2_code":"0401",
    "gn:admin3_code":"0401053",
    "gn:asciiname":"Mwakwalei",
    "gn:country_code":"TZ",
    "gn:dem":1191,
    "gn:feature_class":"P",
    "gn:feature_code":"PPL",
    "gn:name":"Mwakwalei",
    "gn:population":0,
    "gn:timezone":"Africa/Dar_es_Salaam",
    "iso:country":"TZ",
    "wof:name":"Mwakwalei",
    "wof:placetype":"locality"
},
  "geometry": {"coordinates":[38.36667,-4.85],"type":"Point"}
}