{
  "type": "Feature",
  "properties": {
    "gn:admin1_code":"10.0",
    "gn:admin2_code":"0504",
    "gn:admin3_code":"0504141",
    "gn:asciiname":"Ilonga",
    "gn:country_code":"TZ",
    "gn:dem":404,
    "gn:feature_class":"P",
    "gn:feature_code":"PPL",
    "gn:name":"Ilonga",
    "gn:population":0,
    "gn:timezone":"Africa/Dar_es_Salaam",
    "iso:country":"TZ",
    "name:und_x_variant":[
        "Ikongo",
        "Ilonga"
    ],
    "wof:name":"Ilonga",
    "wof:placetype":"locality"
},
  "geometry": {"coordinates":[36.85,-9.06667],"type":"Point"}
}