{
  "type": "Feature",
  "properties": {
    "gn:admin1_code":"24.0",
    "gn:admin2_code":"1502",
    "gn:admin3_code":"1502023",
    "gn:asciiname":"Soda",
    "gn:country_code":"TZ",
    "gn:dem":801,
    "gn:feature_class":"P",
    "gn:feature_code":"PPL",
    "gn:name":"Soda",
    "gn:population":0,
    "gn:timezone":"Africa/Dar_es_Salaam",
    "iso:country":"TZ",
    "name:ara_x_preferred":[
        "\u0635\u0648\u062f\u0627"
    ],
    "name:ast_x_preferred":[
        "Soda"
    ],
    "name:aze_x_preferred":[
        "Soda"
    ],
    "name:bel_x_preferred":[
        "\u0421\u043e\u0434\u0430"
    ],
    "name:bul_x_preferred":[
        "\u0421\u043e\u0434\u0430"
    ],
    "name:ceb_x_preferred":[
        "Soda"
    ],
    "name:ces_x_preferred":[
        "Soda"
    ],
    "name:deu_x_preferred":[
        "Soda"
    ],
    "name:ell_x_preferred":[
        "\u03a3\u03cc\u03b4\u03b1"
    ],
    "name:fas_x_preferred":[
        "\u0633\u0648\u062f\u0627"
    ],
    "name:fra_x_preferred":[
        "Soda"
    ],
    "name:heb_x_preferred":[
        "\u05e1\u05d5\u05d3\u05d4"
    ],
    "name:ita_x_preferred":[
        "Soda"
    ],
    "name:jpn_x_preferred":[
        "\u30bd\u30fc\u30c0"
    ],
    "name:kaz_x_preferred":[
        "\u0421\u043e\u0434\u0430"
    ],
    "name:lat_x_preferred":[
        "Soda"
    ],
    "name:lav_x_preferred":[
        "Soda"
    ],
    "name:lit_x_preferred":[
        "Soda"
    ],
    "name:mya_x_preferred":[
        "\u1006\u102d\u102f\u1012\u102b"
    ],
    "name:nld_x_preferred":[
        "Soda"
    ],
    "name:nno_x_preferred":[
        "Soda"
    ],
    "name:nor_x_preferred":[
        "Soda"
    ],
    "name:oci_x_preferred":[
        "Soda"
    ],
    "name:pol_x_preferred":[
        "Soda"
    ],
    "name:por_x_preferred":[
        "Soda"
    ],
    "name:rus_x_preferred":[
        "\u0421\u043e\u0434\u0430"
    ],
    "name:spa_x_preferred":[
        "Soda"
    ],
    "name:swa_x_preferred":[
        "Soda"
    ],
    "name:swe_x_preferred":[
        "Soda"
    ],
    "name:tel_x_preferred":[
        "\u0c38\u0c4b\u0c21\u0c3e"
    ],
    "name:tur_x_preferred":[
        "Soda"
    ],
    "name:vie_x_preferred":[
        "Soda"
    ],
    "wof:name":"Soda",
    "wof:placetype":"locality"
},
  "geometry": {"coordinates":[31.55,-7.61667],"type":"Point"}
}