{
  "type": "Feature",
  "properties": {
    "gn:admin1_code":"24.0",
    "gn:admin2_code":"1502",
    "gn:admin3_code":"1502023",
    "gn:asciiname":"Soda",
    "gn:country_code":"TZ",
    "gn:dem":801,
    "gn:feature_class":"P",
    "gn:feature_code":"PPL",
    "gn:name":"Soda",
    "gn:population":0,
    "gn:timezone":"Africa/Dar_es_Salaam",
    "iso:country":"TZ",
    "wof:name":"Soda",
    "wof:placetype":"locality"
},
  "geometry": {"coordinates":[31.55,-7.61667],"type":"Point"}
}