{
  "type": "Feature",
  "properties": {
    "gn:admin1_code":"16.0",
    "gn:admin2_code":"1302",
    "gn:admin3_code":"1302181",
    "gn:asciiname":"Ikiwu",
    "gn:country_code":"TZ",
    "gn:dem":1586,
    "gn:feature_class":"P",
    "gn:feature_code":"PPL",
    "gn:name":"Ikiwu",
    "gn:population":0,
    "gn:timezone":"Africa/Dar_es_Salaam",
    "iso:country":"TZ",
    "wof:name":"Ikiwu",
    "wof:placetype":"locality"
},
  "geometry": {"coordinates":[34.79159,-4.61085],"type":"Point"}
}