{
  "type": "Feature",
  "properties": {
    "gn:admin1_code":"18.0",
    "gn:admin2_code":"0406",
    "gn:admin3_code":"0406181",
    "gn:asciiname":"Manga",
    "gn:country_code":"TZ",
    "gn:dem":354,
    "gn:feature_class":"P",
    "gn:feature_code":"PPL",
    "gn:name":"Manga",
    "gn:population":0,
    "gn:timezone":"Africa/Dar_es_Salaam",
    "iso:country":"TZ",
    "wof:name":"Manga",
    "wof:placetype":"locality"
},
  "geometry": {"coordinates":[38.23333,-5.91667],"type":"Point"}
}