{
  "type": "Feature",
  "properties": {
    "gn:admin1_code":"16.0",
    "gn:admin2_code":"1305",
    "gn:admin3_code":"1305051",
    "gn:asciiname":"Panja",
    "gn:country_code":"TZ",
    "gn:dem":1312,
    "gn:feature_class":"P",
    "gn:feature_code":"PPL",
    "gn:name":"Panja",
    "gn:population":0,
    "gn:timezone":"Africa/Dar_es_Salaam",
    "iso:country":"TZ",
    "wof:name":"Panja",
    "wof:placetype":"locality"
},
  "geometry": {"coordinates":[35.03333,-4.95],"type":"Point"}
}