{
  "type": "Feature",
  "properties": {
    "gn:admin1_code":"20.0",
    "gn:admin2_code":"5502",
    "gn:admin3_code":"5502201",
    "gn:asciiname":"Kichaka",
    "gn:country_code":"TZ",
    "gn:dem":26,
    "gn:feature_class":"P",
    "gn:feature_code":"PPL",
    "gn:name":"Kichaka",
    "gn:population":0,
    "gn:timezone":"Africa/Dar_es_Salaam",
    "iso:country":"TZ",
    "wof:name":"Kichaka",
    "wof:placetype":"locality"
},
  "geometry": {"coordinates":[39.76667,-5.36667],"type":"Point"}
}