{
  "type": "Feature",
  "properties": {
    "gn:admin1_code":"20.0",
    "gn:admin2_code":"5502",
    "gn:admin3_code":"5502201",
    "gn:asciiname":"Kichaka",
    "gn:country_code":"TZ",
    "gn:dem":26,
    "gn:feature_class":"P",
    "gn:feature_code":"PPL",
    "gn:name":"Kichaka",
    "gn:population":0,
    "gn:timezone":"Africa/Dar_es_Salaam",
    "iso:country":"TZ",
    "name:fra_x_preferred":[
        "Kichaka"
    ],
    "name:guj_x_preferred":[
        "\u0a95\u0abf\u0a82\u0a9a\u0a95"
    ],
    "name:hin_x_preferred":[
        "\u0915\u0940\u091a\u0915"
    ],
    "name:ind_x_preferred":[
        "Kicaka"
    ],
    "name:jav_x_preferred":[
        "Kicaka"
    ],
    "name:kan_x_preferred":[
        "\u0c95\u0cc0\u0c9a\u0c95"
    ],
    "name:mal_x_preferred":[
        "\u0d15\u0d40\u0d1a\u0d15\u0d7b"
    ],
    "name:mar_x_preferred":[
        "\u0915\u0940\u091a\u0915"
    ],
    "name:nep_x_preferred":[
        "\u0915\u0940\u091a\u0915"
    ],
    "name:pan_x_preferred":[
        "\u0a15\u0a40\u0a1a\u0a15"
    ],
    "name:rus_x_preferred":[
        "\u041a\u0438\u0447\u0430\u043a\u0430"
    ],
    "name:sun_x_preferred":[
        "Kicaka"
    ],
    "name:tam_x_preferred":[
        "\u0b95\u0bc0\u0b9a\u0b95\u0ba9\u0bcd"
    ],
    "name:tel_x_preferred":[
        "\u0c15\u0c40\u0c1a\u0c15\u0c41\u0c21\u0c41"
    ],
    "name:urd_x_preferred":[
        "\u06a9\u06cc\u0686\u06a9"
    ],
    "wof:name":"Kichaka",
    "wof:placetype":"locality"
},
  "geometry": {"coordinates":[39.76667,-5.36667],"type":"Point"}
}