{
  "type": "Feature",
  "properties": {
    "gn:admin1_code":"12.0",
    "gn:admin2_code":"1905",
    "gn:admin3_code":"1905292",
    "gn:asciiname":"Sengerema",
    "gn:country_code":"TZ",
    "gn:dem":1254,
    "gn:feature_class":"P",
    "gn:feature_code":"PPL",
    "gn:name":"Sengerema",
    "gn:population":0,
    "gn:timezone":"Africa/Dar_es_Salaam",
    "iso:country":"TZ",
    "wof:name":"Sengerema",
    "wof:placetype":"locality"
},
  "geometry": {"coordinates":[32.65,-2.66667],"type":"Point"}
}