{
  "type": "Feature",
  "properties": {
    "gn:admin1_code":"19.0",
    "gn:admin2_code":"1808",
    "gn:admin3_code":"1808141",
    "gn:asciiname":"Nyamweza",
    "gn:country_code":"TZ",
    "gn:dem":1425,
    "gn:feature_class":"P",
    "gn:feature_code":"PPL",
    "gn:name":"Nyamweza",
    "gn:population":0,
    "gn:timezone":"Africa/Dar_es_Salaam",
    "iso:country":"TZ",
    "wof:name":"Nyamweza",
    "wof:placetype":"locality"
},
  "geometry": {"coordinates":[30.92806,-1.47694],"type":"Point"}
}