{
  "type": "Feature",
  "properties": {
    "gn:admin1_code":"28.0",
    "gn:admin2_code":"2501",
    "gn:admin3_code":"2501021",
    "gn:asciiname":"Bugurura",
    "gn:country_code":"TZ",
    "gn:dem":1182,
    "gn:feature_class":"P",
    "gn:feature_code":"PPL",
    "gn:name":"Bugurura",
    "gn:population":0,
    "gn:timezone":"Africa/Dar_es_Salaam",
    "iso:country":"TZ",
    "name:und_x_variant":[
        "Ugurura",
        "Bugurura"
    ],
    "wof:name":"Bugurura",
    "wof:placetype":"locality"
},
  "geometry": {"coordinates":[32.15,-2.78333],"type":"Point"}
}