{
  "type": "Feature",
  "properties": {
    "gn:admin1_code":"4.0",
    "gn:admin2_code":"1101",
    "gn:admin3_code":"1101091",
    "gn:asciiname":"Ulete",
    "gn:country_code":"TZ",
    "gn:dem":1743,
    "gn:feature_class":"P",
    "gn:feature_code":"PPL",
    "gn:name":"Ulete",
    "gn:population":0,
    "gn:timezone":"Africa/Dar_es_Salaam",
    "iso:country":"TZ",
    "wof:name":"Ulete",
    "wof:placetype":"locality"
},
  "geometry": {"coordinates":[35.41667,-8.11667],"type":"Point"}
}