{
  "type": "Feature",
  "properties": {
    "gn:admin1_code":"2.0",
    "gn:admin2_code":"0605",
    "gn:admin3_code":"0605071",
    "gn:asciiname":"Mpanga",
    "gn:country_code":"TZ",
    "gn:dem":69,
    "gn:feature_class":"P",
    "gn:feature_code":"PPL",
    "gn:name":"Mpanga",
    "gn:population":0,
    "gn:timezone":"Africa/Dar_es_Salaam",
    "iso:country":"TZ",
    "name:eng_x_preferred":[
        "Mpanga"
    ],
    "wof:name":"Mpanga",
    "wof:placetype":"locality"
},
  "geometry": {"coordinates":[37.99628,-7.79002],"type":"Point"}
}