{
  "type": "Feature",
  "properties": {
    "gn:admin1_code":"15.0",
    "gn:admin2_code":"1703",
    "gn:admin3_code":"1703171",
    "gn:asciiname":"Nyida",
    "gn:country_code":"TZ",
    "gn:dem":1154,
    "gn:feature_class":"P",
    "gn:feature_code":"PPL",
    "gn:name":"Nyida",
    "gn:population":0,
    "gn:timezone":"Africa/Dar_es_Salaam",
    "iso:country":"TZ",
    "wof:name":"Nyida",
    "wof:placetype":"locality"
},
  "geometry": {"coordinates":[33.05,-3.91667],"type":"Point"}
}