{
  "type": "Feature",
  "properties": {
    "gn:admin1_code":"4.0",
    "gn:admin2_code":"1104",
    "gn:admin3_code":"1104191",
    "gn:asciiname":"Kimilawonga",
    "gn:country_code":"TZ",
    "gn:dem":1342,
    "gn:feature_class":"P",
    "gn:feature_code":"PPL",
    "gn:name":"Kimilawonga",
    "gn:population":0,
    "gn:timezone":"Africa/Dar_es_Salaam",
    "iso:country":"TZ",
    "name:eng_x_preferred":[
        "Kimilawonga"
    ],
    "wof:name":"Kimilawonga",
    "wof:placetype":"locality"
},
  "geometry": {"coordinates":[36.13333,-7.81667],"type":"Point"}
}