{
  "type": "Feature",
  "properties": {
    "gn:admin1_code":"18.0",
    "gn:admin2_code":"0408",
    "gn:admin3_code":"0408103",
    "gn:asciiname":"Mwele",
    "gn:country_code":"TZ",
    "gn:dem":223,
    "gn:feature_class":"P",
    "gn:feature_code":"PPL",
    "gn:name":"Mwele",
    "gn:population":0,
    "gn:timezone":"Africa/Dar_es_Salaam",
    "iso:country":"TZ",
    "name:ceb_x_preferred":[
        "Mwele"
    ],
    "name:swe_x_preferred":[
        "Mwele"
    ],
    "wof:name":"Mwele",
    "wof:placetype":"locality"
},
  "geometry": {"coordinates":[38.81667,-4.83333],"type":"Point"}
}