{
  "type": "Feature",
  "properties": {
    "gn:admin1_code":"14.0",
    "gn:admin2_code":"1001",
    "gn:admin3_code":"1001011",
    "gn:asciiname":"Mpelembe",
    "gn:country_code":"TZ",
    "gn:dem":788,
    "gn:feature_class":"P",
    "gn:feature_code":"PPL",
    "gn:name":"Mpelembe",
    "gn:population":0,
    "gn:timezone":"Africa/Dar_es_Salaam",
    "iso:country":"TZ",
    "wof:name":"Mpelembe",
    "wof:placetype":"locality"
},
  "geometry": {"coordinates":[36.81667,-10.63333],"type":"Point"}
}