{
  "type": "Feature",
  "properties": {
    "gn:admin1_code":"27.0",
    "gn:admin2_code":"2103",
    "gn:admin3_code":"2103282",
    "gn:asciiname":"Endagikot",
    "gn:country_code":"TZ",
    "gn:dem":1784,
    "gn:feature_class":"P",
    "gn:feature_code":"PPL",
    "gn:name":"Endagikot",
    "gn:population":0,
    "gn:timezone":"Africa/Dar_es_Salaam",
    "iso:country":"TZ",
    "wof:name":"Endagikot",
    "wof:placetype":"locality"
},
  "geometry": {"coordinates":[35.53333,-3.86667],"type":"Point"}
}