{
  "type": "Feature",
  "properties": {
    "gn:admin1_code":"9.0",
    "gn:admin2_code":"1201",
    "gn:admin3_code":"1201292",
    "gn:asciiname":"Mawoga",
    "gn:country_code":"TZ",
    "gn:dem":1107,
    "gn:feature_class":"P",
    "gn:feature_code":"PPL",
    "gn:name":"Mawoga",
    "gn:population":0,
    "gn:timezone":"Africa/Dar_es_Salaam",
    "iso:country":"TZ",
    "wof:name":"Mawoga",
    "wof:placetype":"locality"
},
  "geometry": {"coordinates":[33.08333,-8.38333],"type":"Point"}
}