{
  "type": "Feature",
  "properties": {
    "gn:admin1_code":"18.0",
    "gn:admin2_code":"0401",
    "gn:admin3_code":"0401431",
    "gn:asciiname":"Msasa",
    "gn:country_code":"TZ",
    "gn:dem":795,
    "gn:feature_class":"P",
    "gn:feature_code":"PPL",
    "gn:name":"Msasa",
    "gn:population":0,
    "gn:timezone":"Africa/Dar_es_Salaam",
    "iso:country":"TZ",
    "wof:name":"Msasa",
    "wof:placetype":"locality"
},
  "geometry": {"coordinates":[38.28333,-4.85],"type":"Point"}
}