{
  "type": "Feature",
  "properties": {
    "gn:admin1_code":"22.0",
    "gn:admin2_code":"5102",
    "gn:admin3_code":"5102191",
    "gn:asciiname":"Gulioni",
    "gn:country_code":"TZ",
    "gn:dem":23,
    "gn:feature_class":"P",
    "gn:feature_code":"PPL",
    "gn:name":"Gulioni",
    "gn:population":0,
    "gn:timezone":"Africa/Dar_es_Salaam",
    "iso:country":"TZ",
    "wof:name":"Gulioni",
    "wof:placetype":"locality"
},
  "geometry": {"coordinates":[39.36667,-5.98333],"type":"Point"}
}