{
  "type": "Feature",
  "properties": {
    "gn:country":"TZ",
    "gn:fcode":"PPL",
    "gn:pop":24895,
    "iso:country":"TZ",
    "name:bul_x_preferred":[
        "\u0418\u0433\u0443\u0440\u0443\u0441\u0438"
    ],
    "name:ceb_x_preferred":[
        "Igurusi"
    ],
    "name:eng_x_preferred":[
        "Igurusi"
    ],
    "name:ita_x_preferred":[
        "Igurusi"
    ],
    "name:nld_x_preferred":[
        "Igurusi"
    ],
    "name:swa_x_preferred":[
        "Igurusi"
    ],
    "name:unk_x_variant":[
        "Igurunzi"
    ],
    "qs:name":"Igurusi",
    "qs:photos_9r":0,
    "qs:photos_sr":0,
    "qs:pop_sr":"7",
    "wd:wordcount":67,
    "wof:name":"Igurusi",
    "wof:placetype":"locality",
    "wof:population":24895
},
  "geometry": {"coordinates":[33.85,-8.85],"type":"Point"}
}