{
  "type": "Feature",
  "properties": {
    "gn:admin1_code":"3.0",
    "gn:admin2_code":"0102",
    "gn:admin3_code":"0102191",
    "gn:asciiname":"Chibechwa Nguta",
    "gn:country_code":"TZ",
    "gn:dem":1406,
    "gn:feature_class":"P",
    "gn:feature_code":"PPL",
    "gn:name":"Chibechwa Nguta",
    "gn:population":0,
    "gn:timezone":"Africa/Dar_es_Salaam",
    "iso:country":"TZ",
    "name:und_x_variant":[
        "Chibwecha Nguta",
        "Chibechwa Nguta"
    ],
    "wof:name":"Chibechwa Nguta",
    "wof:placetype":"locality"
},
  "geometry": {"coordinates":[36.55,-6.36667],"type":"Point"}
}