{
  "type": "Feature",
  "properties": {
    "gn:admin1_code":"10.0",
    "gn:admin2_code":"0502",
    "gn:admin3_code":"0502291",
    "gn:asciiname":"Nkulukulu",
    "gn:country_code":"TZ",
    "gn:dem":290,
    "gn:feature_class":"P",
    "gn:feature_code":"PPL",
    "gn:name":"Nkulukulu",
    "gn:population":0,
    "gn:timezone":"Africa/Dar_es_Salaam",
    "iso:country":"TZ",
    "name:eng_x_preferred":[
        "Nkulukulu"
    ],
    "wof:name":"Nkulukulu",
    "wof:placetype":"locality"
},
  "geometry": {"coordinates":[37.80373,-7.18088],"type":"Point"}
}