{
  "type": "Feature",
  "properties": {
    "gn:admin1_code":"16.0",
    "gn:admin2_code":"1305",
    "gn:admin3_code":"1305101",
    "gn:asciiname":"Mangonyi",
    "gn:country_code":"TZ",
    "gn:dem":1403,
    "gn:feature_class":"P",
    "gn:feature_code":"PPL",
    "gn:name":"Mangonyi",
    "gn:population":0,
    "gn:timezone":"Africa/Dar_es_Salaam",
    "iso:country":"TZ",
    "name:swa_x_preferred":[
        "Mangonyi"
    ],
    "name:und_x_variant":[
        "Manoni",
        "Mangonyi"
    ],
    "wof:name":"Mangonyi",
    "wof:placetype":"locality"
},
  "geometry": {"coordinates":[34.91667,-5.23333],"type":"Point"}
}