{
  "type": "Feature",
  "properties": {
    "gn:admin1_code":"4.0",
    "gn:admin2_code":"1102",
    "gn:admin3_code":"1102121",
    "gn:asciiname":"Iberege",
    "gn:country_code":"TZ",
    "gn:dem":1488,
    "gn:feature_class":"P",
    "gn:feature_code":"PPL",
    "gn:name":"Iberege",
    "gn:population":0,
    "gn:timezone":"Africa/Dar_es_Salaam",
    "iso:country":"TZ",
    "wof:name":"Iberege",
    "wof:placetype":"locality"
},
  "geometry": {"coordinates":[34.73333,-8.51667],"type":"Point"}
}