{
  "type": "Feature",
  "properties": {
    "gn:admin1_code":"4.0",
    "gn:admin2_code":"1101",
    "gn:admin3_code":"1101131",
    "gn:asciiname":"Mugama",
    "gn:country_code":"TZ",
    "gn:dem":918,
    "gn:feature_class":"P",
    "gn:feature_code":"PPL",
    "gn:name":"Mugama",
    "gn:population":0,
    "gn:timezone":"Africa/Dar_es_Salaam",
    "iso:country":"TZ",
    "name:swa_x_preferred":[
        "Mgama"
    ],
    "name:und_x_variant":[
        "Mgama",
        "Mugama"
    ],
    "wof:name":"Mugama",
    "wof:placetype":"locality"
},
  "geometry": {"coordinates":[35.23333,-7.68333],"type":"Point"}
}