{
  "type": "Feature",
  "properties": {
    "gn:admin1_code":"29.0",
    "gn:admin2_code":"2302",
    "gn:admin3_code":"2302071",
    "gn:asciiname":"Kabogo",
    "gn:country_code":"TZ",
    "gn:dem":776,
    "gn:feature_class":"P",
    "gn:feature_code":"PPL",
    "gn:name":"Kabogo",
    "gn:population":0,
    "gn:timezone":"Africa/Dar_es_Salaam",
    "iso:country":"TZ",
    "name:eng_x_preferred":[
        "Kabogo"
    ],
    "name:eng_x_variant":[
        "Kobogo"
    ],
    "wof:name":"Kabogo",
    "wof:placetype":"locality"
},
  "geometry": {"coordinates":[30.35734,-6.68129],"type":"Point"}
}