{
  "type": "Feature",
  "properties": {
    "gn:admin1_code":"18.0",
    "gn:admin2_code":"0406",
    "gn:admin3_code":"0406041",
    "gn:asciiname":"Kwamsisi",
    "gn:country_code":"TZ",
    "gn:dem":227,
    "gn:feature_class":"P",
    "gn:feature_code":"PPL",
    "gn:name":"Kwamsisi",
    "gn:population":0,
    "gn:timezone":"Africa/Dar_es_Salaam",
    "iso:country":"TZ",
    "wof:name":"Kwamsisi",
    "wof:placetype":"locality"
},
  "geometry": {"coordinates":[38.56667,-5.85],"type":"Point"}
}