{
  "type": "Feature",
  "properties": {
    "iso:country":"TZ",
    "name:rus_x_preferred":[
        "\u041c\u0430\u0441\u0430\u0441\u0438"
    ],
    "name:unk_x_variant":[
        "Massassi"
    ],
    "ne:ADM0CAP":0.0,
    "ne:ADM0NAME":"Tanzania",
    "ne:ADM0_A3":"TZA",
    "ne:ADM1NAME":"Mtwara",
    "ne:ADMIN1_COD":0,
    "ne:CAPALT":0,
    "ne:CHANGED":0,
    "ne:CHECKME":0,
    "ne:COMPARE":0,
    "ne:DIFFASCII":0,
    "ne:ELEVATION":0.0,
    "ne:FEATURECLA":"Populated place",
    "ne:FEATURE_CL":"P",
    "ne:FEATURE_CO":"PPL",
    "ne:GEONAMEID":878058,
    "ne:GEONAMESNO":"Geonames ascii name + lat.d + long.d matching.",
    "ne:GN_ASCII":"Masasi",
    "ne:GN_POP":36032,
    "ne:GTOPO30":504.0,
    "ne:ISO_A2":"TZ",
    "ne:LABELRANK":5,
    "ne:LATITUDE":-10.729592,
    "ne:LONGITUDE":38.799947,
    "ne:LS_MATCH":1,
    "ne:LS_NAME":"Masasi",
    "ne:MAX_AREAKM":15.0,
    "ne:MAX_AREAMI":6.0,
    "ne:MAX_BBXMAX":38.825,
    "ne:MAX_BBXMIN":38.783333,
    "ne:MAX_BBYMAX":-10.708333,
    "ne:MAX_BBYMIN":-10.75,
    "ne:MAX_NATSCA":20.0,
    "ne:MAX_PERKM":20.0,
    "ne:MAX_PERMI":13.0,
    "ne:MAX_POP10":27067,
    "ne:MAX_POP20":27067,
    "ne:MAX_POP300":0,
    "ne:MAX_POP310":0,
    "ne:MAX_POP50":0,
    "ne:MEAN_BBXC":38.807407,
    "ne:MEAN_BBYC":-10.733333,
    "ne:MEGACITY":0,
    "ne:MIN_AREAKM":15.0,
    "ne:MIN_AREAMI":6.0,
    "ne:MIN_BBXMAX":38.825,
    "ne:MIN_BBXMIN":38.783333,
    "ne:MIN_BBYMAX":-10.708333,
    "ne:MIN_BBYMIN":-10.75,
    "ne:MIN_PERKM":20.0,
    "ne:MIN_PERMI":13.0,
    "ne:NAME":"Masasi",
    "ne:NAMEASCII":"Masasi",
    "ne:NAMEDIFF":0,
    "ne:NATSCALE":20,
    "ne:POP1950":0,
    "ne:POP1955":0,
    "ne:POP1960":0,
    "ne:POP1965":0,
    "ne:POP1970":0,
    "ne:POP1975":0,
    "ne:POP1980":0,
    "ne:POP1985":0,
    "ne:POP1990":0,
    "ne:POP1995":0,
    "ne:POP2000":0,
    "ne:POP2005":0,
    "ne:POP2010":0,
    "ne:POP2015":0,
    "ne:POP2020":0,
    "ne:POP2025":0,
    "ne:POP2050":0,
    "ne:POP_MAX":36032,
    "ne:POP_MIN":27067,
    "ne:POP_OTHER":0,
    "ne:RANK_MAX":7,
    "ne:RANK_MIN":7,
    "ne:SCALERANK":7,
    "ne:SOV0NAME":"United Republic of Tanzania",
    "ne:SOV_A3":"TZA",
    "ne:TIMEZONE":"Africa/Dar_es_Salaam",
    "ne:UN_FID":0,
    "ne:UN_LAT":0.0,
    "ne:UN_LONG":0.0,
    "ne:WORLDCITY":0,
    "qs:gn_country":"TZ",
    "qs:gn_fcode":"PPL",
    "qs:gn_pop":36032,
    "qs:name":"Masasi",
    "qs:name_adm0":"Tanzania",
    "qs:name_adm1":"Mtwara",
    "qs:photos":0,
    "qs:photos_1k":0,
    "qs:photos_9k":1,
    "qs:photos_9r":1,
    "qs:photos_all":7,
    "qs:photos_sr":0,
    "qs:placetype":"Town",
    "qs:pop_sr":"7",
    "qs:woe_adm0":23424973,
    "wof:name":"Masasi",
    "wof:placetype":"locality",
    "wof:population":36032
},
  "geometry": {"coordinates":[38.8,-10.71667],"type":"Point"}
}