{
  "type": "Feature",
  "properties": {
    "gn:admin1_code":"28.0",
    "gn:admin2_code":"2505",
    "gn:admin3_code":"2505171",
    "gn:asciiname":"Makurugusi",
    "gn:country_code":"TZ",
    "gn:dem":1150,
    "gn:feature_class":"P",
    "gn:feature_code":"PPL",
    "gn:name":"Makurugusi",
    "gn:population":0,
    "gn:timezone":"Africa/Dar_es_Salaam",
    "iso:country":"TZ",
    "wof:name":"Makurugusi",
    "wof:placetype":"locality"
},
  "geometry": {"coordinates":[31.74417,-2.91806],"type":"Point"}
}