{
  "type": "Feature",
  "properties": {
    "gn:admin1_code":"2.0",
    "gn:admin2_code":"0603",
    "gn:admin3_code":"0603051",
    "gn:asciiname":"Mkuhuni",
    "gn:country_code":"TZ",
    "gn:dem":296,
    "gn:feature_class":"P",
    "gn:feature_code":"PPL",
    "gn:name":"Mkuhuni",
    "gn:population":0,
    "gn:timezone":"Africa/Dar_es_Salaam",
    "iso:country":"TZ",
    "name:eng_x_preferred":[
        "Mkuhuni"
    ],
    "wof:name":"Mkuhuni",
    "wof:placetype":"locality"
},
  "geometry": {"coordinates":[38.79065,-7.13517],"type":"Point"}
}