{
  "type": "Feature",
  "properties": {
    "gn:gn_country":"TZ",
    "gn:gn_fcode":"PPL",
    "gn:gn_pop":10642,
    "gn:population":10642,
    "iso:country":"TZ",
    "qs_pg:aaroncc":"TZ",
    "qs_pg:gn_country":"TZ",
    "qs_pg:gn_fcode":"PPL",
    "qs_pg:gn_pop":10642,
    "qs_pg:name":"Matamba",
    "qs_pg:photos_9r":0,
    "qs_pg:photos_sr":0,
    "qs_pg:pop_sr":6,
    "qs_pg:qs_pg_placetype":"locality",
    "wof:name":"Matamba",
    "wof:placetype":"locality",
    "wof:population":10642
},
  "geometry": {"coordinates":[33.96667,-8.98333],"type":"Point"}
}