{
  "type": "Feature",
  "properties": {
    "gn:admin1_code":"20.0",
    "gn:admin2_code":"5502",
    "gn:admin3_code":"5502071",
    "gn:asciiname":"Chokocho",
    "gn:country_code":"TZ",
    "gn:dem":8,
    "gn:feature_class":"P",
    "gn:feature_code":"PPL",
    "gn:name":"Chokocho",
    "gn:population":0,
    "gn:timezone":"Africa/Dar_es_Salaam",
    "iso:country":"TZ",
    "name:por_x_preferred":[
        "Chococho"
    ],
    "wof:name":"Chokocho",
    "wof:placetype":"locality"
},
  "geometry": {"coordinates":[39.65,-5.43333],"type":"Point"}
}