{
  "type": "Feature",
  "properties": {
    "gn:admin1_code":"23.0",
    "gn:admin2_code":"0702",
    "gn:admin3_code":"0702182",
    "gn:asciiname":"Garden Avenue",
    "gn:country_code":"TZ",
    "gn:dem":12,
    "gn:feature_class":"P",
    "gn:feature_code":"PPL",
    "gn:name":"Garden Avenue",
    "gn:population":0,
    "gn:timezone":"Africa/Dar_es_Salaam",
    "iso:country":"TZ",
    "wof:name":"Garden Avenue",
    "wof:placetype":"locality"
},
  "geometry": {"coordinates":[39.28944,-6.81297],"type":"Point"}
}