{
  "type": "Feature",
  "properties": {
    "gn:admin1_code":"10.0",
    "gn:admin2_code":"0503",
    "gn:admin3_code":"0503171",
    "gn:asciiname":"Utengule",
    "gn:country_code":"TZ",
    "gn:dem":312,
    "gn:feature_class":"P",
    "gn:feature_code":"PPL",
    "gn:name":"Utengule",
    "gn:population":0,
    "gn:timezone":"Africa/Dar_es_Salaam",
    "iso:country":"TZ",
    "name:und_x_variant":[
        "Utenguli",
        "Utengule"
    ],
    "wof:name":"Utengule",
    "wof:placetype":"locality"
},
  "geometry": {"coordinates":[35.83333,-8.95],"type":"Point"}
}