{
  "type": "Feature",
  "properties": {
    "gn:admin1_code":"15.0",
    "gn:admin2_code":"1703",
    "gn:admin3_code":"1703011",
    "gn:asciiname":"Mhongwe",
    "gn:country_code":"TZ",
    "gn:dem":1208,
    "gn:feature_class":"P",
    "gn:feature_code":"PPL",
    "gn:name":"Mhongwe",
    "gn:population":0,
    "gn:timezone":"Africa/Dar_es_Salaam",
    "iso:country":"TZ",
    "wof:name":"Mhongwe",
    "wof:placetype":"locality"
},
  "geometry": {"coordinates":[33.11667,-3.71667],"type":"Point"}
}