{
  "type": "Feature",
  "properties": {
    "gn:admin1_code":"19.0",
    "gn:admin2_code":"1808",
    "gn:admin3_code":"1808161",
    "gn:asciiname":"Kitwechenkula",
    "gn:country_code":"TZ",
    "gn:dem":1314,
    "gn:feature_class":"P",
    "gn:feature_code":"PPL",
    "gn:name":"Kitwechenkula",
    "gn:population":0,
    "gn:timezone":"Africa/Dar_es_Salaam",
    "iso:country":"TZ",
    "wof:name":"Kitwechenkula",
    "wof:placetype":"locality"
},
  "geometry": {"coordinates":[30.8375,-1.46389],"type":"Point"}
}