{
  "type": "Feature",
  "properties": {
    "iso:country":"TZ",
    "name:swa_x_preferred":[
        "Kimamba 'A'"
    ],
    "qs:gn_country":"TZ",
    "qs:gn_fcode":"PPL",
    "qs:gn_pop":11235,
    "qs:name":"Kimamba",
    "qs:name_adm0":"Tanzania",
    "qs:name_adm1":"Morogoro",
    "qs:photos":0,
    "qs:photos_1k":0,
    "qs:photos_9k":0,
    "qs:photos_9r":0,
    "qs:photos_all":0,
    "qs:photos_sr":0,
    "qs:placetype":"Town",
    "qs:pop_sr":"6",
    "qs:woe_adm0":23424973,
    "wd:wordcount":60,
    "wof:name":"Kimamba",
    "wof:placetype":"locality",
    "wof:population":11235
},
  "geometry": {"coordinates":[37.13333,-6.78333],"type":"Point"}
}