{
  "type": "Feature",
  "properties": {
    "gn:admin1_code":"12.0",
    "gn:admin2_code":"1905",
    "gn:admin3_code":"1905281",
    "gn:asciiname":"Kaseni",
    "gn:country_code":"TZ",
    "gn:dem":1206,
    "gn:feature_class":"P",
    "gn:feature_code":"PPL",
    "gn:name":"Kaseni",
    "gn:population":0,
    "gn:timezone":"Africa/Dar_es_Salaam",
    "iso:country":"TZ",
    "name:pol_x_preferred":[
        "Kaseni"
    ],
    "wof:name":"Kaseni",
    "wof:placetype":"locality"
},
  "geometry": {"coordinates":[32.61667,-2.53333],"type":"Point"}
}