{
  "type": "Feature",
  "properties": {
    "gn:admin1_code":"18.0",
    "gn:admin2_code":"0404",
    "gn:admin3_code":"0404241",
    "gn:asciiname":"Mvuni",
    "gn:country_code":"TZ",
    "gn:dem":24,
    "gn:feature_class":"P",
    "gn:feature_code":"PPL",
    "gn:name":"Mvuni",
    "gn:population":0,
    "gn:timezone":"Africa/Dar_es_Salaam",
    "iso:country":"TZ",
    "name:und_x_variant":[
        "Myuni",
        "Mvuni"
    ],
    "wof:name":"Mvuni",
    "wof:placetype":"locality"
},
  "geometry": {"coordinates":[39.08333,-5.01667],"type":"Point"}
}