{
  "type": "Feature",
  "properties": {
    "gn:admin1_code":"14.0",
    "gn:admin2_code":"1001",
    "gn:admin3_code":"1001101",
    "gn:asciiname":"Masima",
    "gn:country_code":"TZ",
    "gn:dem":463,
    "gn:feature_class":"P",
    "gn:feature_code":"PPL",
    "gn:name":"Masima",
    "gn:population":0,
    "gn:timezone":"Africa/Dar_es_Salaam",
    "iso:country":"TZ",
    "wof:name":"Masima",
    "wof:placetype":"locality"
},
  "geometry": {"coordinates":[37.63333,-11.16667],"type":"Point"}
}