{
  "type": "Feature",
  "properties": {
    "gn:admin1_code":"26.0",
    "gn:admin2_code":"0205",
    "gn:admin3_code":"0205061",
    "gn:asciiname":"Olala",
    "gn:country_code":"TZ",
    "gn:dem":1307,
    "gn:feature_class":"P",
    "gn:feature_code":"PPL",
    "gn:name":"Olala",
    "gn:population":0,
    "gn:timezone":"Africa/Dar_es_Salaam",
    "iso:country":"TZ",
    "name:und_x_variant":[
        "Olalaa",
        "Olala"
    ],
    "wof:name":"Olala",
    "wof:placetype":"locality"
},
  "geometry": {"coordinates":[35.56667,-2.53333],"type":"Point"}
}