{
  "type": "Feature",
  "properties": {
    "gn:admin1_code":"7.0",
    "gn:admin2_code":"0804",
    "gn:admin3_code":"0804071",
    "gn:asciiname":"Mkangira",
    "gn:country_code":"TZ",
    "gn:dem":296,
    "gn:feature_class":"P",
    "gn:feature_code":"PPL",
    "gn:name":"Mkangira",
    "gn:population":0,
    "gn:timezone":"Africa/Dar_es_Salaam",
    "iso:country":"TZ",
    "wof:name":"Mkangira",
    "wof:placetype":"locality"
},
  "geometry": {"coordinates":[37.41667,-8.95],"type":"Point"}
}