{
  "type": "Feature",
  "properties": {
    "gn:admin1_code":"27.0",
    "gn:admin2_code":"2105",
    "gn:admin3_code":"2105101",
    "gn:asciiname":"Kiteto",
    "gn:country_code":"TZ",
    "gn:dem":1329,
    "gn:feature_class":"P",
    "gn:feature_code":"PPL",
    "gn:name":"Kiteto",
    "gn:population":0,
    "gn:timezone":"Africa/Dar_es_Salaam",
    "iso:country":"TZ",
    "wof:name":"Kiteto",
    "wof:placetype":"locality"
},
  "geometry": {"coordinates":[36.85,-5.86667],"type":"Point"}
}