{
  "type": "Feature",
  "properties": {
    "gn:admin1_code":"4.0",
    "gn:admin2_code":"1104",
    "gn:admin3_code":"1104081",
    "gn:asciiname":"Malambo",
    "gn:country_code":"TZ",
    "gn:dem":1904,
    "gn:feature_class":"P",
    "gn:feature_code":"PPL",
    "gn:name":"Malambo",
    "gn:population":0,
    "gn:timezone":"Africa/Dar_es_Salaam",
    "iso:country":"TZ",
    "name:ceb_x_preferred":[
        "Malambo"
    ],
    "name:deu_x_preferred":[
        "Malambo"
    ],
    "name:fra_x_preferred":[
        "Malambo"
    ],
    "name:ita_x_preferred":[
        "Malambo"
    ],
    "name:spa_x_preferred":[
        "Malambo"
    ],
    "name:swa_x_preferred":[
        "Malambo"
    ],
    "name:swe_x_preferred":[
        "Malambo"
    ],
    "name:vie_x_preferred":[
        "Malambo"
    ],
    "wof:name":"Malambo",
    "wof:placetype":"locality"
},
  "geometry": {"coordinates":[35.91667,-8.13333],"type":"Point"}
}