{
  "type": "Feature",
  "properties": {
    "gn:admin1_code":"3.0",
    "gn:admin2_code":"0102",
    "gn:admin3_code":"0102301",
    "gn:asciiname":"Kamba",
    "gn:country_code":"TZ",
    "gn:dem":1577,
    "gn:feature_class":"P",
    "gn:feature_code":"PPL",
    "gn:name":"Kamba",
    "gn:population":0,
    "gn:timezone":"Africa/Dar_es_Salaam",
    "iso:country":"TZ",
    "name:ceb_x_preferred":[
        "Kamba"
    ],
    "name:deu_x_preferred":[
        "Kamba"
    ],
    "name:eng_x_preferred":[
        "Kamba"
    ],
    "name:eng_x_variant":[
        "Kambakwe"
    ],
    "name:fra_x_preferred":[
        "Kamba"
    ],
    "name:nld_x_preferred":[
        "Kamba"
    ],
    "name:slv_x_preferred":[
        "Kamba"
    ],
    "name:swa_x_preferred":[
        "Kamba"
    ],
    "name:swe_x_preferred":[
        "Kamba"
    ],
    "wof:name":"Kamba",
    "wof:placetype":"locality"
},
  "geometry": {"coordinates":[36.45184,-7.23628],"type":"Point"}
}