{
  "type": "Feature",
  "properties": {
    "gn:admin1_code":"18.0",
    "gn:admin2_code":"0408",
    "gn:admin3_code":"0408201",
    "gn:asciiname":"Nami",
    "gn:country_code":"TZ",
    "gn:dem":13,
    "gn:feature_class":"P",
    "gn:feature_code":"PPL",
    "gn:name":"Nami",
    "gn:population":0,
    "gn:timezone":"Africa/Dar_es_Salaam",
    "iso:country":"TZ",
    "name:cat_x_preferred":[
        "Nami"
    ],
    "name:ceb_x_preferred":[
        "Nami"
    ],
    "name:ind_x_preferred":[
        "Nami"
    ],
    "name:kor_x_preferred":[
        "\ub098\ubbf8"
    ],
    "name:spa_x_preferred":[
        "Nami"
    ],
    "name:swe_x_preferred":[
        "Nami"
    ],
    "name:ukr_x_preferred":[
        "\u041d\u0430\u043c\u0456"
    ],
    "wof:name":"Nami",
    "wof:placetype":"locality"
},
  "geometry": {"coordinates":[39.16546,-4.73566],"type":"Point"}
}