{
  "type": "Feature",
  "properties": {
    "gn:admin1_code":"3.0",
    "gn:admin2_code":"0105",
    "gn:admin3_code":"0105311",
    "gn:asciiname":"Ntyuka",
    "gn:country_code":"TZ",
    "gn:dem":1235,
    "gn:feature_class":"P",
    "gn:feature_code":"PPL",
    "gn:name":"Ntyuka",
    "gn:population":0,
    "gn:timezone":"Africa/Dar_es_Salaam",
    "iso:country":"TZ",
    "name:ita_x_preferred":[
        "Ntyuka"
    ],
    "name:swa_x_preferred":[
        "Ntyuka"
    ],
    "wof:name":"Ntyuka",
    "wof:placetype":"locality"
},
  "geometry": {"coordinates":[35.75754000000001,-6.2229],"type":"Point"}
}