{
  "type": "Feature",
  "properties": {
    "gn:admin1_code":"20.0",
    "gn:admin2_code":"5502",
    "gn:admin3_code":"5502291",
    "gn:asciiname":"Kiaigoni",
    "gn:country_code":"TZ",
    "gn:dem":28,
    "gn:feature_class":"P",
    "gn:feature_code":"PPL",
    "gn:name":"Kiaigoni",
    "gn:population":0,
    "gn:timezone":"Africa/Dar_es_Salaam",
    "iso:country":"TZ",
    "wof:name":"Kiaigoni",
    "wof:placetype":"locality"
},
  "geometry": {"coordinates":[39.73333,-5.38333],"type":"Point"}
}