{
  "type": "Feature",
  "properties": {
    "gn:admin1_code":"2.0",
    "gn:admin2_code":"0605",
    "gn:admin3_code":"0605101",
    "gn:asciiname":"Mahege",
    "gn:country_code":"TZ",
    "gn:dem":125,
    "gn:feature_class":"P",
    "gn:feature_code":"PPL",
    "gn:name":"Mahege",
    "gn:population":0,
    "gn:timezone":"Africa/Dar_es_Salaam",
    "iso:country":"TZ",
    "name:eng_x_preferred":[
        "Mahege"
    ],
    "wof:name":"Mahege",
    "wof:placetype":"locality"
},
  "geometry": {"coordinates":[39.17112,-7.67791],"type":"Point"}
}