{
  "type": "Feature",
  "properties": {
    "gn:admin1_code":"19.0",
    "gn:admin2_code":"1807",
    "gn:admin3_code":"1807121",
    "gn:asciiname":"Ishozi",
    "gn:country_code":"TZ",
    "gn:dem":1282,
    "gn:feature_class":"P",
    "gn:feature_code":"PPL",
    "gn:name":"Ishozi",
    "gn:population":0,
    "gn:timezone":"Africa/Dar_es_Salaam",
    "iso:country":"TZ",
    "name:ita_x_preferred":[
        "Ishozi"
    ],
    "name:swa_x_preferred":[
        "Ishozi"
    ],
    "wof:name":"Ishozi",
    "wof:placetype":"locality"
},
  "geometry": {"coordinates":[31.76833,-1.16278],"type":"Point"}
}