{
  "type": "Feature",
  "properties": {
    "gn:admin1_code":"12.0",
    "gn:admin2_code":"1904",
    "gn:admin3_code":"1904221",
    "gn:asciiname":"Nyanhonge",
    "gn:country_code":"TZ",
    "gn:dem":1189,
    "gn:feature_class":"P",
    "gn:feature_code":"PPL",
    "gn:name":"Nyanhonge",
    "gn:population":0,
    "gn:timezone":"Africa/Dar_es_Salaam",
    "iso:country":"TZ",
    "name:und_x_variant":[
        "Nyanhanga",
        "Nyahonge"
    ],
    "wof:name":"Nyanhonge",
    "wof:placetype":"locality"
},
  "geometry": {"coordinates":[33.16667,-3.18333],"type":"Point"}
}