{
  "type": "Feature",
  "properties": {
    "gn:admin1_code":"2.0",
    "gn:admin2_code":"0605",
    "gn:admin3_code":"0605061",
    "gn:asciiname":"Nyamiriywili",
    "gn:country_code":"TZ",
    "gn:dem":47,
    "gn:feature_class":"P",
    "gn:feature_code":"PPL",
    "gn:name":"Nyamiriywili",
    "gn:population":0,
    "gn:timezone":"Africa/Dar_es_Salaam",
    "iso:country":"TZ",
    "name:eng_x_preferred":[
        "Nyamiriywili"
    ],
    "wof:name":"Nyamiriywili",
    "wof:placetype":"locality"
},
  "geometry": {"coordinates":[38.42004,-7.85011],"type":"Point"}
}