{
  "type": "Feature",
  "properties": {
    "gn:admin1_code":"6.0",
    "gn:admin2_code":"0303",
    "gn:admin3_code":"0303133",
    "gn:asciiname":"Gonja",
    "gn:country_code":"TZ",
    "gn:dem":553,
    "gn:feature_class":"P",
    "gn:feature_code":"PPL",
    "gn:name":"Gonja",
    "gn:population":0,
    "gn:timezone":"Africa/Dar_es_Salaam",
    "iso:country":"TZ",
    "wof:name":"Gonja",
    "wof:placetype":"locality"
},
  "geometry": {"coordinates":[38.05,-4.26667],"type":"Point"}
}