{
  "type": "Feature",
  "properties": {
    "gn:admin1_code":"2.0",
    "gn:admin2_code":"0601",
    "gn:admin3_code":"0601171",
    "gn:asciiname":"Rusako",
    "gn:country_code":"TZ",
    "gn:dem":75,
    "gn:feature_class":"P",
    "gn:feature_code":"PPL",
    "gn:name":"Rusako",
    "gn:population":0,
    "gn:timezone":"Africa/Dar_es_Salaam",
    "iso:country":"TZ",
    "name:und_x_variant":[
        "Ruseko",
        "Rusako"
    ],
    "wof:name":"Rusako",
    "wof:placetype":"locality"
},
  "geometry": {"coordinates":[38.66667,-6.45],"type":"Point"}
}