{
  "type": "Feature",
  "properties": {
    "gn:admin1_code":"19.0",
    "gn:admin2_code":"1808",
    "gn:admin3_code":"1808111",
    "gn:asciiname":"Nyakatuntu",
    "gn:country_code":"TZ",
    "gn:dem":1591,
    "gn:feature_class":"P",
    "gn:feature_code":"PPL",
    "gn:name":"Nyakatuntu",
    "gn:population":0,
    "gn:timezone":"Africa/Dar_es_Salaam",
    "iso:country":"TZ",
    "wof:name":"Nyakatuntu",
    "wof:placetype":"locality"
},
  "geometry": {"coordinates":[30.82917,-1.30722],"type":"Point"}
}