{
  "type": "Feature",
  "properties": {
    "gn:admin1_code":"18.0",
    "gn:admin2_code":"0408",
    "gn:admin3_code":"0408081",
    "gn:asciiname":"Mjengeni",
    "gn:country_code":"TZ",
    "gn:dem":118,
    "gn:feature_class":"P",
    "gn:feature_code":"PPL",
    "gn:name":"Mjengeni",
    "gn:population":0,
    "gn:timezone":"Africa/Dar_es_Salaam",
    "iso:country":"TZ",
    "name:und_x_variant":[
        "Mjengani",
        "Mjengeni"
    ],
    "wof:name":"Mjengeni",
    "wof:placetype":"locality"
},
  "geometry": {"coordinates":[38.98333,-4.96667],"type":"Point"}
}