{
  "type": "Feature",
  "properties": {
    "gn:admin1_code":"10.0",
    "gn:admin2_code":"0504",
    "gn:admin3_code":"0504181",
    "gn:asciiname":"Biro",
    "gn:country_code":"TZ",
    "gn:dem":279,
    "gn:feature_class":"P",
    "gn:feature_code":"PPL",
    "gn:name":"Biro",
    "gn:population":0,
    "gn:timezone":"Africa/Dar_es_Salaam",
    "iso:country":"TZ",
    "wof:name":"Biro",
    "wof:placetype":"locality"
},
  "geometry": {"coordinates":[36.05,-8.88333],"type":"Point"}
}