{
  "type": "Feature",
  "properties": {
    "gn:admin1_code":"3.0",
    "gn:admin2_code":"0104",
    "gn:admin3_code":"0104271",
    "gn:asciiname":"Chikuyu",
    "gn:country_code":"TZ",
    "gn:dem":982,
    "gn:feature_class":"P",
    "gn:feature_code":"PPL",
    "gn:name":"Chikuyu",
    "gn:population":0,
    "gn:timezone":"Africa/Dar_es_Salaam",
    "iso:country":"TZ",
    "name:ita_x_preferred":[
        "Chikuyu"
    ],
    "name:swa_x_preferred":[
        "Chikuyu"
    ],
    "wof:name":"Chikuyu",
    "wof:placetype":"locality"
},
  "geometry": {"coordinates":[35.21667,-6.95],"type":"Point"}
}