{
  "type": "Feature",
  "properties": {
    "gn:admin1_code":"18.0",
    "gn:admin2_code":"0406",
    "gn:admin3_code":"0406141",
    "gn:asciiname":"Msimkulu",
    "gn:country_code":"TZ",
    "gn:dem":413,
    "gn:feature_class":"P",
    "gn:feature_code":"PPL",
    "gn:name":"Msimkulu",
    "gn:population":0,
    "gn:timezone":"Africa/Dar_es_Salaam",
    "iso:country":"TZ",
    "wof:name":"Msimkulu",
    "wof:placetype":"locality"
},
  "geometry": {"coordinates":[38.31667,-5.28333],"type":"Point"}
}