{
  "type": "Feature",
  "properties": {
    "gn:admin1_code":"24.0",
    "gn:asciiname":"Tgarukiru",
    "gn:country_code":"TZ",
    "gn:dem":993,
    "gn:feature_class":"P",
    "gn:feature_code":"PPL",
    "gn:name":"Tgarukiru",
    "gn:population":0,
    "gn:timezone":"Africa/Dar_es_Salaam",
    "iso:country":"TZ",
    "wof:name":"Tgarukiru",
    "wof:placetype":"locality"
},
  "geometry": {"coordinates":[31.13333,-7.15],"type":"Point"}
}