{
  "type": "Feature",
  "properties": {
    "gn:admin1_code":"11.0",
    "gn:admin2_code":"0906",
    "gn:admin3_code":"0906111",
    "gn:asciiname":"Chungu",
    "gn:country_code":"TZ",
    "gn:dem":291,
    "gn:feature_class":"P",
    "gn:feature_code":"PPL",
    "gn:name":"Chungu",
    "gn:population":0,
    "gn:timezone":"Africa/Dar_es_Salaam",
    "iso:country":"TZ",
    "wof:name":"Chungu",
    "wof:placetype":"locality"
},
  "geometry": {"coordinates":[38.45,-11.16667],"type":"Point"}
}