{
  "type": "Feature",
  "properties": {
    "gn:admin1_code":"19.0",
    "gn:admin2_code":"1807",
    "gn:admin3_code":"1807151",
    "gn:asciiname":"Kitobo",
    "gn:country_code":"TZ",
    "gn:dem":1294,
    "gn:feature_class":"P",
    "gn:feature_code":"PPL",
    "gn:name":"Kitobo",
    "gn:population":0,
    "gn:timezone":"Africa/Dar_es_Salaam",
    "iso:country":"TZ",
    "wof:name":"Kitobo",
    "wof:placetype":"locality"
},
  "geometry": {"coordinates":[31.63333,-1.21667],"type":"Point"}
}