{
  "type": "Feature",
  "properties": {
    "gn:admin1_code":"2.0",
    "gn:admin2_code":"0605",
    "gn:admin3_code":"0605211",
    "gn:asciiname":"Nangulangwa",
    "gn:country_code":"TZ",
    "gn:dem":418,
    "gn:feature_class":"P",
    "gn:feature_code":"PPL",
    "gn:name":"Nangulangwa",
    "gn:population":0,
    "gn:timezone":"Africa/Dar_es_Salaam",
    "iso:country":"TZ",
    "wof:name":"Nangulangwa",
    "wof:placetype":"locality"
},
  "geometry": {"coordinates":[38.76667,-8.36667],"type":"Point"}
}