{
  "type": "Feature",
  "properties": {
    "gn:admin1_code":"21.0",
    "gn:admin2_code":"5201",
    "gn:admin3_code":"5201111",
    "gn:asciiname":"Mgani Haji",
    "gn:country_code":"TZ",
    "gn:dem":43,
    "gn:feature_class":"P",
    "gn:feature_code":"PPL",
    "gn:name":"Mgani Haji",
    "gn:population":0,
    "gn:timezone":"Africa/Dar_es_Salaam",
    "iso:country":"TZ",
    "wof:name":"Mgani Haji",
    "wof:placetype":"locality"
},
  "geometry": {"coordinates":[39.33333,-6.08333],"type":"Point"}
}