{
  "type": "Feature",
  "properties": {
    "gn:admin1_code":"19.0",
    "gn:admin2_code":"1807",
    "gn:admin3_code":"1807173",
    "gn:asciiname":"Bulifani",
    "gn:country_code":"TZ",
    "gn:dem":1154,
    "gn:feature_class":"P",
    "gn:feature_code":"PPL",
    "gn:name":"Bulifani",
    "gn:population":0,
    "gn:timezone":"Africa/Dar_es_Salaam",
    "iso:country":"TZ",
    "wof:name":"Bulifani",
    "wof:placetype":"locality"
},
  "geometry": {"coordinates":[31.47025,-1.25662],"type":"Point"}
}