{
  "type": "Feature",
  "properties": {
    "gn:admin1_code":"26.0",
    "gn:admin2_code":"0206",
    "gn:admin3_code":"0206031",
    "gn:asciiname":"Olturoto",
    "gn:country_code":"TZ",
    "gn:dem":1549,
    "gn:feature_class":"P",
    "gn:feature_code":"PPL",
    "gn:name":"Olturoto",
    "gn:population":0,
    "gn:timezone":"Africa/Dar_es_Salaam",
    "iso:country":"TZ",
    "wof:name":"Olturoto",
    "wof:placetype":"locality"
},
  "geometry": {"coordinates":[36.68333,-3.33333],"type":"Point"}
}