{
  "type": "Feature",
  "properties": {
    "gn:admin1_code":"16.0",
    "gn:admin2_code":"1305",
    "gn:admin3_code":"1305131",
    "gn:asciiname":"Matari",
    "gn:country_code":"TZ",
    "gn:dem":1517,
    "gn:feature_class":"P",
    "gn:feature_code":"PPL",
    "gn:name":"Matari",
    "gn:population":0,
    "gn:timezone":"Africa/Dar_es_Salaam",
    "iso:country":"TZ",
    "wof:name":"Matari",
    "wof:placetype":"locality"
},
  "geometry": {"coordinates":[34.85,-5.15],"type":"Point"}
}