{
  "type": "Feature",
  "properties": {
    "gn:admin1_code":"18.0",
    "gn:admin2_code":"0403",
    "gn:admin3_code":"0403261",
    "gn:asciiname":"Tongwe",
    "gn:country_code":"TZ",
    "gn:dem":260,
    "gn:feature_class":"P",
    "gn:feature_code":"PPL",
    "gn:name":"Tongwe",
    "gn:population":0,
    "gn:timezone":"Africa/Dar_es_Salaam",
    "iso:country":"TZ",
    "wof:name":"Tongwe",
    "wof:placetype":"locality"
},
  "geometry": {"coordinates":[38.71667,-5.11667],"type":"Point"}
}