{
  "type": "Feature",
  "properties": {
    "gn:admin1_code":"17.0",
    "gn:admin2_code":"1402",
    "gn:admin3_code":"1402181",
    "gn:asciiname":"Mwakinda",
    "gn:country_code":"TZ",
    "gn:dem":1224,
    "gn:feature_class":"P",
    "gn:feature_code":"PPL",
    "gn:name":"Mwakinda",
    "gn:population":0,
    "gn:timezone":"Africa/Dar_es_Salaam",
    "iso:country":"TZ",
    "wof:name":"Mwakinda",
    "wof:placetype":"locality"
},
  "geometry": {"coordinates":[33.45,-4.21667],"type":"Point"}
}