{
  "type": "Feature",
  "properties": {
    "gn:admin1_code":"18.0",
    "gn:admin2_code":"0401",
    "gn:admin3_code":"0401211",
    "gn:asciiname":"Kwemkuyu",
    "gn:country_code":"TZ",
    "gn:dem":402,
    "gn:feature_class":"P",
    "gn:feature_code":"PPL",
    "gn:name":"Kwemkuyu",
    "gn:population":0,
    "gn:timezone":"Africa/Dar_es_Salaam",
    "iso:country":"TZ",
    "wof:name":"Kwemkuyu",
    "wof:placetype":"locality"
},
  "geometry": {"coordinates":[38.38333,-4.51667],"type":"Point"}
}