{
  "type": "Feature",
  "properties": {
    "gn:admin1_code":"8.0",
    "gn:admin2_code":"2006",
    "gn:admin3_code":"2006111",
    "gn:asciiname":"Randa",
    "gn:country_code":"TZ",
    "gn:dem":1271,
    "gn:feature_class":"P",
    "gn:feature_code":"PPL",
    "gn:name":"Randa",
    "gn:population":0,
    "gn:timezone":"Africa/Dar_es_Salaam",
    "iso:country":"TZ",
    "name:cat_x_preferred":[
        "Randa"
    ],
    "name:ceb_x_preferred":[
        "Randa"
    ],
    "name:ces_x_preferred":[
        "Randa"
    ],
    "name:deu_x_preferred":[
        "Randa"
    ],
    "name:fra_x_preferred":[
        "Randa"
    ],
    "name:hun_x_preferred":[
        "Randa"
    ],
    "name:nor_x_preferred":[
        "Randa"
    ],
    "name:rus_x_preferred":[
        "\u0420\u0430\u043d\u0434\u0430"
    ],
    "name:spa_x_preferred":[
        "Randa"
    ],
    "name:swe_x_preferred":[
        "Randa"
    ],
    "name:und_x_variant":[
        "Ronda"
    ],
    "wof:name":"Randa",
    "wof:placetype":"locality"
},
  "geometry": {"coordinates":[34.15,-1.26667],"type":"Point"}
}