{
  "type": "Feature",
  "properties": {
    "gn:admin1_code":"11.0",
    "gn:admin2_code":"0901",
    "gn:admin3_code":"0901131",
    "gn:asciiname":"Naulendi",
    "gn:country_code":"TZ",
    "gn:dem":288,
    "gn:feature_class":"P",
    "gn:feature_code":"PPL",
    "gn:name":"Naulendi",
    "gn:population":0,
    "gn:timezone":"Africa/Dar_es_Salaam",
    "iso:country":"TZ",
    "wof:name":"Naulendi",
    "wof:placetype":"locality"
},
  "geometry": {"coordinates":[39.81667,-10.35],"type":"Point"}
}