{
  "type": "Feature",
  "properties": {
    "gn:admin1_code":"8.0",
    "gn:admin2_code":"2007",
    "gn:admin3_code":"2007051",
    "gn:asciiname":"Buhemba",
    "gn:country_code":"TZ",
    "gn:dem":1443,
    "gn:feature_class":"P",
    "gn:feature_code":"PPL",
    "gn:name":"Buhemba",
    "gn:population":0,
    "gn:timezone":"Africa/Dar_es_Salaam",
    "iso:country":"TZ",
    "wof:name":"Buhemba",
    "wof:placetype":"locality"
},
  "geometry": {"coordinates":[34.08333,-1.76667],"type":"Point"}
}