{
  "type": "Feature",
  "properties": {
    "gn:admin1_code":"18.0",
    "gn:admin2_code":"0407",
    "gn:admin3_code":"0407061",
    "gn:asciiname":"Masarakha",
    "gn:country_code":"TZ",
    "gn:dem":690,
    "gn:feature_class":"P",
    "gn:feature_code":"PPL",
    "gn:name":"Masarakha",
    "gn:population":0,
    "gn:timezone":"Africa/Dar_es_Salaam",
    "iso:country":"TZ",
    "wof:name":"Masarakha",
    "wof:placetype":"locality"
},
  "geometry": {"coordinates":[37.68333,-5.85],"type":"Point"}
}