{
  "type": "Feature",
  "properties": {
    "gn:admin1_code":"13.0",
    "gn:admin2_code":"5402",
    "gn:admin3_code":"5402083",
    "gn:asciiname":"Kichungwani",
    "gn:country_code":"TZ",
    "gn:dem":39,
    "gn:feature_class":"P",
    "gn:feature_code":"PPL",
    "gn:name":"Kichungwani",
    "gn:population":0,
    "gn:timezone":"Africa/Dar_es_Salaam",
    "iso:country":"TZ",
    "wof:name":"Kichungwani",
    "wof:placetype":"locality"
},
  "geometry": {"coordinates":[39.71667,-4.95],"type":"Point"}
}