{
  "type": "Feature",
  "properties": {
    "gn:admin1_code":"16.0",
    "gn:admin2_code":"1305",
    "gn:admin3_code":"1305121",
    "gn:asciiname":"Issuna",
    "gn:country_code":"TZ",
    "gn:dem":1411,
    "gn:feature_class":"P",
    "gn:feature_code":"PPL",
    "gn:name":"Issuna",
    "gn:population":0,
    "gn:timezone":"Africa/Dar_es_Salaam",
    "iso:country":"TZ",
    "name:ita_x_preferred":[
        "Issuna"
    ],
    "name:swa_x_preferred":[
        "Issuna"
    ],
    "name:und_x_variant":[
        "Suna",
        "Isuna"
    ],
    "wof:name":"Issuna",
    "wof:placetype":"locality"
},
  "geometry": {"coordinates":[34.76667,-5.38333],"type":"Point"}
}