{
  "type": "Feature",
  "properties": {
    "gn:admin1_code":"28.0",
    "gn:admin2_code":"2501",
    "gn:admin3_code":"2501021",
    "gn:asciiname":"Nyakasasa",
    "gn:country_code":"TZ",
    "gn:dem":1268,
    "gn:feature_class":"P",
    "gn:feature_code":"PPL",
    "gn:name":"Nyakasasa",
    "gn:population":0,
    "gn:timezone":"Africa/Dar_es_Salaam",
    "iso:country":"TZ",
    "wof:name":"Nyakasasa",
    "wof:placetype":"locality"
},
  "geometry": {"coordinates":[32.17154,-2.75012],"type":"Point"}
}