{
  "type": "Feature",
  "properties": {
    "gn:admin1_code":"20.0",
    "gn:admin2_code":"5502",
    "gn:admin3_code":"5502311",
    "gn:asciiname":"Sisimizini",
    "gn:country_code":"TZ",
    "gn:dem":30,
    "gn:feature_class":"P",
    "gn:feature_code":"PPL",
    "gn:name":"Sisimizini",
    "gn:population":0,
    "gn:timezone":"Africa/Dar_es_Salaam",
    "iso:country":"TZ",
    "wof:name":"Sisimizini",
    "wof:placetype":"locality"
},
  "geometry": {"coordinates":[39.71667,-5.33333],"type":"Point"}
}