{
  "type": "Feature",
  "properties": {
    "gn:admin1_code":"18.0",
    "gn:admin2_code":"0406",
    "gn:admin3_code":"0406021",
    "gn:asciiname":"Kwamnere",
    "gn:country_code":"TZ",
    "gn:dem":391,
    "gn:feature_class":"P",
    "gn:feature_code":"PPL",
    "gn:name":"Kwamnere",
    "gn:population":0,
    "gn:timezone":"Africa/Dar_es_Salaam",
    "iso:country":"TZ",
    "wof:name":"Kwamnere",
    "wof:placetype":"locality"
},
  "geometry": {"coordinates":[38.33333,-5.46667],"type":"Point"}
}