{
  "type": "Feature",
  "properties": {
    "gn:admin1_code":"17.0",
    "gn:admin2_code":"1406",
    "gn:admin3_code":"1406221",
    "gn:asciiname":"Igambia",
    "gn:country_code":"TZ",
    "gn:dem":1154,
    "gn:feature_class":"P",
    "gn:feature_code":"PPL",
    "gn:name":"Igambia",
    "gn:population":0,
    "gn:timezone":"Africa/Dar_es_Salaam",
    "iso:country":"TZ",
    "wof:name":"Igambia",
    "wof:placetype":"locality"
},
  "geometry": {"coordinates":[32.71667,-4.85],"type":"Point"}
}