{
  "type": "Feature",
  "properties": {
    "gn:admin1_code":"15.0",
    "gn:admin2_code":"1703",
    "gn:admin3_code":"1703111",
    "gn:asciiname":"Lyabukande",
    "gn:country_code":"TZ",
    "gn:dem":1175,
    "gn:feature_class":"P",
    "gn:feature_code":"PPL",
    "gn:name":"Lyabukande",
    "gn:population":0,
    "gn:timezone":"Africa/Dar_es_Salaam",
    "iso:country":"TZ",
    "wof:name":"Lyabukande",
    "wof:placetype":"locality"
},
  "geometry": {"coordinates":[32.93333,-3.56667],"type":"Point"}
}