{
  "type": "Feature",
  "properties": {
    "gn:admin1_code":"17.0",
    "gn:admin2_code":"1402",
    "gn:admin3_code":"1402231",
    "gn:asciiname":"Mapiringa",
    "gn:country_code":"TZ",
    "gn:dem":1197,
    "gn:feature_class":"P",
    "gn:feature_code":"PPL",
    "gn:name":"Mapiringa",
    "gn:population":0,
    "gn:timezone":"Africa/Dar_es_Salaam",
    "iso:country":"TZ",
    "wof:name":"Mapiringa",
    "wof:placetype":"locality"
},
  "geometry": {"coordinates":[33.53333,-4.81667],"type":"Point"}
}