{
  "type": "Feature",
  "properties": {
    "gn:admin1_code":"5.0",
    "gn:admin2_code":"1607",
    "gn:admin3_code":"1607081",
    "gn:asciiname":"Kizuvu",
    "gn:cc2":"TZ",
    "gn:country_code":"TZ",
    "gn:dem":1352,
    "gn:feature_class":"P",
    "gn:feature_code":"PPL",
    "gn:name":"Kizuvu",
    "gn:population":0,
    "gn:timezone":"Africa/Dar_es_Salaam",
    "iso:country":"TZ",
    "name:und_x_variant":[
        "Kizivu",
        "Kizuvu"
    ],
    "wof:name":"Kizuvu",
    "wof:placetype":"locality"
},
  "geometry": {"coordinates":[30.82667,-3.46222],"type":"Point"}
}