{
  "type": "Feature",
  "properties": {
    "gn:admin1_code":"7.0",
    "gn:admin2_code":"0804",
    "gn:admin3_code":"0804131",
    "gn:asciiname":"Poyos",
    "gn:country_code":"TZ",
    "gn:dem":651,
    "gn:feature_class":"P",
    "gn:feature_code":"PPL",
    "gn:name":"Poyos",
    "gn:population":0,
    "gn:timezone":"Africa/Dar_es_Salaam",
    "iso:country":"TZ",
    "wof:name":"Poyos",
    "wof:placetype":"locality"
},
  "geometry": {"coordinates":[37.05,-10.15],"type":"Point"}
}