{
  "type": "Feature",
  "properties": {
    "gn:admin1_code":"31.0",
    "gn:admin2_code":"2402",
    "gn:admin3_code":"2402071",
    "gn:asciiname":"Ngano",
    "gn:country_code":"TZ",
    "gn:dem":1366,
    "gn:feature_class":"P",
    "gn:feature_code":"PPL",
    "gn:name":"Ngano",
    "gn:population":0,
    "gn:timezone":"Africa/Dar_es_Salaam",
    "iso:country":"TZ",
    "wof:name":"Ngano",
    "wof:placetype":"locality"
},
  "geometry": {"coordinates":[34.21667,-2.95],"type":"Point"}
}