{
  "type": "Feature",
  "properties": {
    "gn:admin1_code":"9.0",
    "gn:admin2_code":"1202",
    "gn:admin3_code":"1202141",
    "gn:asciiname":"Mole",
    "gn:country_code":"TZ",
    "gn:dem":1928,
    "gn:feature_class":"P",
    "gn:feature_code":"PPL",
    "gn:name":"Mole",
    "gn:population":0,
    "gn:timezone":"Africa/Dar_es_Salaam",
    "iso:country":"TZ",
    "name:ceb_x_preferred":[
        "Mole"
    ],
    "name:deu_x_preferred":[
        "Mole"
    ],
    "name:ell_x_preferred":[
        "Mole"
    ],
    "name:fin_x_preferred":[
        "Myyr\u00e4"
    ],
    "name:fra_x_preferred":[
        "Mole"
    ],
    "name:ita_x_preferred":[
        "Mole"
    ],
    "name:jpn_x_preferred":[
        "\u3082\u3050\u3089"
    ],
    "name:nld_x_preferred":[
        "Mole"
    ],
    "name:nor_x_preferred":[
        "Mole"
    ],
    "name:pol_x_preferred":[
        "Mole"
    ],
    "name:por_x_preferred":[
        "Mole"
    ],
    "name:spa_x_preferred":[
        "Mole"
    ],
    "name:swe_x_preferred":[
        "Mole"
    ],
    "wof:name":"Mole",
    "wof:placetype":"locality"
},
  "geometry": {"coordinates":[33.43333,-9.06667],"type":"Point"}
}