{
  "type": "Feature",
  "properties": {
    "gn:admin1_code":"9.0",
    "gn:admin2_code":"1202",
    "gn:admin3_code":"1202141",
    "gn:asciiname":"Mole",
    "gn:country_code":"TZ",
    "gn:dem":1928,
    "gn:feature_class":"P",
    "gn:feature_code":"PPL",
    "gn:name":"Mole",
    "gn:population":0,
    "gn:timezone":"Africa/Dar_es_Salaam",
    "iso:country":"TZ",
    "wof:name":"Mole",
    "wof:placetype":"locality"
},
  "geometry": {"coordinates":[33.43333,-9.06667],"type":"Point"}
}