{
  "type": "Feature",
  "properties": {
    "gn:admin1_code":"23.0",
    "gn:admin2_code":"0702",
    "gn:admin3_code":"0702092",
    "gn:asciiname":"Banana",
    "gn:country_code":"TZ",
    "gn:dem":62,
    "gn:feature_class":"P",
    "gn:feature_code":"PPL",
    "gn:name":"Banana",
    "gn:population":0,
    "gn:timezone":"Africa/Dar_es_Salaam",
    "iso:country":"TZ",
    "wof:name":"Banana",
    "wof:placetype":"locality"
},
  "geometry": {"coordinates":[39.18941,-6.87163],"type":"Point"}
}