{
  "type": "Feature",
  "properties": {
    "gn:admin1_code":"25.0",
    "gn:admin2_code":"5301",
    "gn:admin3_code":"5301093",
    "gn:asciiname":"Dunkuki",
    "gn:country_code":"TZ",
    "gn:dem":71,
    "gn:feature_class":"P",
    "gn:feature_code":"PPL",
    "gn:name":"Dunkuki",
    "gn:population":0,
    "gn:timezone":"Africa/Dar_es_Salaam",
    "iso:country":"TZ",
    "name:und_x_variant":[
        "Dunduki",
        "Dunkuki"
    ],
    "wof:name":"Dunkuki",
    "wof:placetype":"locality"
},
  "geometry": {"coordinates":[39.25,-6.11667],"type":"Point"}
}