{
  "type": "Feature",
  "properties": {
    "gn:admin1_code":"30.0",
    "gn:admin2_code":"2203",
    "gn:admin3_code":"2203051",
    "gn:asciiname":"Ukwama",
    "gn:country_code":"TZ",
    "gn:dem":2131,
    "gn:feature_class":"P",
    "gn:feature_code":"PPL",
    "gn:name":"Ukwama",
    "gn:population":0,
    "gn:timezone":"Africa/Dar_es_Salaam",
    "iso:country":"TZ",
    "wof:name":"Ukwama",
    "wof:placetype":"locality"
},
  "geometry": {"coordinates":[34.21667,-9.45],"type":"Point"}
}