{
  "type": "Feature",
  "properties": {
    "gn:admin1_code":"17.0",
    "gn:admin2_code":"1407",
    "gn:admin3_code":"1407021",
    "gn:asciiname":"Ussenye",
    "gn:country_code":"TZ",
    "gn:dem":1072,
    "gn:feature_class":"P",
    "gn:feature_code":"PPL",
    "gn:name":"Ussenye",
    "gn:population":0,
    "gn:timezone":"Africa/Dar_es_Salaam",
    "iso:country":"TZ",
    "wof:name":"Ussenye",
    "wof:placetype":"locality"
},
  "geometry": {"coordinates":[31.55,-5.36667],"type":"Point"}
}