{
  "type": "Feature",
  "properties": {
    "gn:admin1_code":"18.0",
    "gn:admin2_code":"0404",
    "gn:admin3_code":"0404211",
    "gn:asciiname":"Ntengeza",
    "gn:country_code":"TZ",
    "gn:dem":62,
    "gn:feature_class":"P",
    "gn:feature_code":"PPL",
    "gn:name":"Ntengeza",
    "gn:population":0,
    "gn:timezone":"Africa/Dar_es_Salaam",
    "iso:country":"TZ",
    "wof:name":"Ntengeza",
    "wof:placetype":"locality"
},
  "geometry": {"coordinates":[39.03333,-5.01667],"type":"Point"}
}