{
  "type": "Feature",
  "properties": {
    "gn:admin1_code":"3.0",
    "gn:admin2_code":"0101",
    "gn:admin3_code":"0101221",
    "gn:asciiname":"Kipungu",
    "gn:country_code":"TZ",
    "gn:dem":1344,
    "gn:feature_class":"P",
    "gn:feature_code":"PPL",
    "gn:name":"Kipungu",
    "gn:population":0,
    "gn:timezone":"Africa/Dar_es_Salaam",
    "iso:country":"TZ",
    "wof:name":"Kipungu",
    "wof:placetype":"locality"
},
  "geometry": {"coordinates":[35.58333,-5.03333],"type":"Point"}
}