{
  "type": "Feature",
  "properties": {
    "gn:admin1_code":"10.0",
    "gn:admin2_code":"0503",
    "gn:admin3_code":"0503141",
    "gn:asciiname":"Chita",
    "gn:country_code":"TZ",
    "gn:dem":309,
    "gn:feature_class":"P",
    "gn:feature_code":"PPL",
    "gn:name":"Chita",
    "gn:population":0,
    "gn:timezone":"Africa/Dar_es_Salaam",
    "iso:country":"TZ",
    "wof:name":"Chita",
    "wof:placetype":"locality"
},
  "geometry": {"coordinates":[35.93333,-8.51667],"type":"Point"}
}