{
  "type": "Feature",
  "properties": {
    "gn:admin1_code":"19.0",
    "gn:admin2_code":"1808",
    "gn:admin3_code":"1808071",
    "gn:asciiname":"Kigorogoro",
    "gn:country_code":"TZ",
    "gn:dem":1714,
    "gn:feature_class":"P",
    "gn:feature_code":"PPL",
    "gn:name":"Kigorogoro",
    "gn:population":0,
    "gn:timezone":"Africa/Dar_es_Salaam",
    "iso:country":"TZ",
    "wof:name":"Kigorogoro",
    "wof:placetype":"locality"
},
  "geometry": {"coordinates":[30.83111,-1.11861],"type":"Point"}
}