{
  "type": "Feature",
  "properties": {
    "gn:admin1_code":"30.0",
    "gn:admin2_code":"2205",
    "gn:admin3_code":"2205241",
    "gn:asciiname":"Kimato",
    "gn:country_code":"TZ",
    "gn:dem":593,
    "gn:feature_class":"P",
    "gn:feature_code":"PPL",
    "gn:name":"Kimato",
    "gn:population":0,
    "gn:timezone":"Africa/Dar_es_Salaam",
    "iso:country":"TZ",
    "wof:name":"Kimato",
    "wof:placetype":"locality"
},
  "geometry": {"coordinates":[34.46667,-9.95],"type":"Point"}
}