{
  "type": "Feature",
  "properties": {
    "gn:admin1_code":"7.0",
    "gn:admin2_code":"0801",
    "gn:admin3_code":"0801131",
    "gn:asciiname":"Kiswere",
    "gn:country_code":"TZ",
    "gn:dem":8,
    "gn:feature_class":"P",
    "gn:feature_code":"PPL",
    "gn:name":"Kiswere",
    "gn:population":0,
    "gn:timezone":"Africa/Dar_es_Salaam",
    "iso:country":"TZ",
    "wof:name":"Kiswere",
    "wof:placetype":"locality"
},
  "geometry": {"coordinates":[39.55713,-9.42883],"type":"Point"}
}