{
  "type": "Feature",
  "properties": {
    "gn:admin1_code":"2.0",
    "gn:admin2_code":"0601",
    "gn:admin3_code":"0601161",
    "gn:asciiname":"Kibindu",
    "gn:country_code":"TZ",
    "gn:dem":453,
    "gn:feature_class":"P",
    "gn:feature_code":"PPL",
    "gn:name":"Kibindu",
    "gn:population":0,
    "gn:timezone":"Africa/Dar_es_Salaam",
    "iso:country":"TZ",
    "wof:name":"Kibindu",
    "wof:placetype":"locality"
},
  "geometry": {"coordinates":[37.88333,-5.93333],"type":"Point"}
}