{
  "type": "Feature",
  "properties": {
    "gn:admin1_code":"24.0",
    "gn:admin2_code":"1503",
    "gn:admin3_code":"1503051",
    "gn:asciiname":"Lusembwa",
    "gn:country_code":"TZ",
    "gn:dem":1965,
    "gn:feature_class":"P",
    "gn:feature_code":"PPL",
    "gn:name":"Lusembwa",
    "gn:population":0,
    "gn:timezone":"Africa/Dar_es_Salaam",
    "iso:country":"TZ",
    "wof:name":"Lusembwa",
    "wof:placetype":"locality"
},
  "geometry": {"coordinates":[31.36667000000001,-7.81667],"type":"Point"}
}