{
  "type": "Feature",
  "properties": {
    "gn:admin1_code":"18.0",
    "gn:admin2_code":"0402",
    "gn:admin3_code":"0402171",
    "gn:asciiname":"Mgila",
    "gn:country_code":"TZ",
    "gn:dem":483,
    "gn:feature_class":"P",
    "gn:feature_code":"PPL",
    "gn:name":"Mgila",
    "gn:population":0,
    "gn:timezone":"Africa/Dar_es_Salaam",
    "iso:country":"TZ",
    "wof:name":"Mgila",
    "wof:placetype":"locality"
},
  "geometry": {"coordinates":[38.48333,-5.01667],"type":"Point"}
}