{
  "type": "Feature",
  "properties": {
    "gn:admin1_code":"17.0",
    "gn:admin2_code":"1405",
    "gn:admin3_code":"1405091",
    "gn:asciiname":"Kilumbi",
    "gn:country_code":"TZ",
    "gn:dem":1453,
    "gn:feature_class":"P",
    "gn:feature_code":"PPL",
    "gn:name":"Kilumbi",
    "gn:population":0,
    "gn:timezone":"Africa/Dar_es_Salaam",
    "iso:country":"TZ",
    "wof:name":"Kilumbi",
    "wof:placetype":"locality"
},
  "geometry": {"coordinates":[33.85,-6.28333],"type":"Point"}
}