{
  "type": "Feature",
  "properties": {
    "gn:admin1_code":"8.0",
    "gn:asciiname":"Busiri",
    "gn:country_code":"TZ",
    "gn:dem":1152,
    "gn:feature_class":"P",
    "gn:feature_code":"PPL",
    "gn:name":"Busiri",
    "gn:population":0,
    "gn:timezone":"Africa/Dar_es_Salaam",
    "iso:country":"TZ",
    "wof:name":"Busiri",
    "wof:placetype":"locality"
},
  "geometry": {"coordinates":[32.91667,-2.08333],"type":"Point"}
}