{
  "type": "Feature",
  "properties": {
    "gn:admin1_code":"19.0",
    "gn:admin2_code":"1801",
    "gn:admin3_code":"1801181",
    "gn:asciiname":"Nyabuyonza",
    "gn:cc2":"TZ",
    "gn:country_code":"TZ",
    "gn:dem":1518,
    "gn:feature_class":"P",
    "gn:feature_code":"PPL",
    "gn:name":"Nyabuyonza",
    "gn:population":0,
    "gn:timezone":"Africa/Dar_es_Salaam",
    "iso:country":"TZ",
    "name:und_x_variant":[
        "Nyabiyonza",
        "Nyabuyonza"
    ],
    "wof:name":"Nyabuyonza",
    "wof:placetype":"locality"
},
  "geometry": {"coordinates":[30.98694,-1.70056],"type":"Point"}
}