{
  "type": "Feature",
  "properties": {
    "gn:admin1_code":"5.0",
    "gn:admin2_code":"1603",
    "gn:admin3_code":"1603031",
    "gn:asciiname":"Bugamba",
    "gn:country_code":"TZ",
    "gn:dem":881,
    "gn:feature_class":"P",
    "gn:feature_code":"PPL",
    "gn:name":"Bugamba",
    "gn:population":0,
    "gn:timezone":"Africa/Dar_es_Salaam",
    "iso:country":"TZ",
    "wof:name":"Bugamba",
    "wof:placetype":"locality"
},
  "geometry": {"coordinates":[29.65,-4.56667],"type":"Point"}
}