{
  "type": "Feature",
  "properties": {
    "gn:admin1_code":"19.0",
    "gn:admin2_code":"1803",
    "gn:admin3_code":"1803011",
    "gn:asciiname":"Muhutwe",
    "gn:country_code":"TZ",
    "gn:dem":1326,
    "gn:feature_class":"P",
    "gn:feature_code":"PPL",
    "gn:name":"Muhutwe",
    "gn:population":0,
    "gn:timezone":"Africa/Dar_es_Salaam",
    "iso:country":"TZ",
    "wof:name":"Muhutwe",
    "wof:placetype":"locality"
},
  "geometry": {"coordinates":[31.70167,-1.56444],"type":"Point"}
}