{
  "type": "Feature",
  "properties": {
    "gn:admin1_code":"18.0",
    "gn:admin2_code":"0403",
    "gn:admin3_code":"0403161",
    "gn:asciiname":"Mruwazi",
    "gn:country_code":"TZ",
    "gn:dem":233,
    "gn:feature_class":"P",
    "gn:feature_code":"PPL",
    "gn:name":"Mruwazi",
    "gn:population":0,
    "gn:timezone":"Africa/Dar_es_Salaam",
    "iso:country":"TZ",
    "wof:name":"Mruwazi",
    "wof:placetype":"locality"
},
  "geometry": {"coordinates":[38.65,-5.25],"type":"Point"}
}