{
  "type": "Feature",
  "properties": {
    "gn:admin1_code":"10.0",
    "gn:admin2_code":"0501",
    "gn:admin3_code":"0501341",
    "gn:asciiname":"Mauzi",
    "gn:country_code":"TZ",
    "gn:dem":448,
    "gn:feature_class":"P",
    "gn:feature_code":"PPL",
    "gn:name":"Mauzi",
    "gn:population":0,
    "gn:timezone":"Africa/Dar_es_Salaam",
    "iso:country":"TZ",
    "wof:name":"Mauzi",
    "wof:placetype":"locality"
},
  "geometry": {"coordinates":[37.11667,-6.85],"type":"Point"}
}