{
  "type": "Feature",
  "properties": {
    "gn:admin1_code":"19.0",
    "gn:admin2_code":"1805",
    "gn:admin3_code":"1805201",
    "gn:asciiname":"Kasherazi",
    "gn:country_code":"TZ",
    "gn:dem":1651,
    "gn:feature_class":"P",
    "gn:feature_code":"PPL",
    "gn:name":"Kasherazi",
    "gn:population":0,
    "gn:timezone":"Africa/Dar_es_Salaam",
    "iso:country":"TZ",
    "wof:name":"Kasherazi",
    "wof:placetype":"locality"
},
  "geometry": {"coordinates":[30.80278,-2.51694],"type":"Point"}
}