{
  "type": "Feature",
  "properties": {
    "iso:country":"TZ",
    "name:dut_x_preferred":[
        "Ikungi"
    ],
    "name:eng_x_preferred":[
        "Ikungi"
    ],
    "name:gre_x_preferred":[
        "\u0399\u03ba\u03bf\u03cd\u03bd\u03b3\u03ba\u03b9"
    ],
    "name:swa_x_preferred":[
        "Ikungi"
    ],
    "qs:gn_country":"TZ",
    "qs:gn_fcode":"PPL",
    "qs:gn_pop":19692,
    "qs:name":"Ikungi",
    "qs:name_adm0":"Tanzania",
    "qs:name_adm1":"Singida",
    "qs:photos":0,
    "qs:photos_1k":0,
    "qs:photos_9k":0,
    "qs:photos_9r":0,
    "qs:photos_all":0,
    "qs:photos_sr":0,
    "qs:placetype":"Town",
    "qs:pop_sr":"6",
    "qs:woe_adm0":23424973,
    "wd:wordcount":130,
    "wof:name":"Ikungi",
    "wof:placetype":"locality",
    "wof:population":19692
},
  "geometry": {"coordinates":[34.76667,-5.13333],"type":"Point"}
}