{
  "type": "Feature",
  "properties": {
    "gn:admin1_code":"18.0",
    "gn:admin2_code":"0401",
    "gn:admin3_code":"0401131",
    "gn:asciiname":"Shembekeza",
    "gn:country_code":"TZ",
    "gn:dem":1449,
    "gn:feature_class":"P",
    "gn:feature_code":"PPL",
    "gn:name":"Shembekeza",
    "gn:population":0,
    "gn:timezone":"Africa/Dar_es_Salaam",
    "iso:country":"TZ",
    "wof:name":"Shembekeza",
    "wof:placetype":"locality"
},
  "geometry": {"coordinates":[38.53333,-4.85],"type":"Point"}
}