{
  "type": "Feature",
  "properties": {
    "gn:admin1_code":"9.0",
    "gn:admin2_code":"1207",
    "gn:admin3_code":"1207023",
    "gn:asciiname":"Mahango",
    "gn:country_code":"TZ",
    "gn:dem":1068,
    "gn:feature_class":"P",
    "gn:feature_code":"PPL",
    "gn:name":"Mahango",
    "gn:population":0,
    "gn:timezone":"Africa/Dar_es_Salaam",
    "iso:country":"TZ",
    "wof:name":"Mahango",
    "wof:placetype":"locality"
},
  "geometry": {"coordinates":[34.81941,-8.20342],"type":"Point"}
}