{
  "type": "Feature",
  "properties": {
    "gn:admin1_code":"11.0",
    "gn:admin2_code":"0902",
    "gn:admin3_code":"0902221",
    "gn:asciiname":"Nambunga",
    "gn:country_code":"TZ",
    "gn:dem":660,
    "gn:feature_class":"P",
    "gn:feature_code":"PPL",
    "gn:name":"Nambunga",
    "gn:population":0,
    "gn:timezone":"Africa/Dar_es_Salaam",
    "iso:country":"TZ",
    "name:und_x_variant":[
        "Namkunga",
        "Nambunga"
    ],
    "wof:name":"Nambunga",
    "wof:placetype":"locality"
},
  "geometry": {"coordinates":[39.26667,-10.86667],"type":"Point"}
}