{
  "type": "Feature",
  "properties": {
    "gn:admin1_code":"3.0",
    "gn:admin2_code":"0102",
    "gn:admin3_code":"0102301",
    "gn:asciiname":"Dodoma",
    "gn:country_code":"TZ",
    "gn:dem":562,
    "gn:feature_class":"P",
    "gn:feature_code":"PPL",
    "gn:name":"Dodoma",
    "gn:population":0,
    "gn:timezone":"Africa/Dar_es_Salaam",
    "iso:country":"TZ",
    "name:eng_x_preferred":[
        "Dodoma"
    ],
    "wof:name":"Dodoma",
    "wof:placetype":"locality"
},
  "geometry": {"coordinates":[36.34038,-7.29067],"type":"Point"}
}