{
  "type": "Feature",
  "properties": {
    "gn:admin1_code":"10.0",
    "gn:admin2_code":"0502",
    "gn:admin3_code":"0502171",
    "gn:asciiname":"Semakwede",
    "gn:country_code":"TZ",
    "gn:dem":405,
    "gn:feature_class":"P",
    "gn:feature_code":"PPL",
    "gn:name":"Semakwede",
    "gn:population":0,
    "gn:timezone":"Africa/Dar_es_Salaam",
    "iso:country":"TZ",
    "wof:name":"Semakwede",
    "wof:placetype":"locality"
},
  "geometry": {"coordinates":[37.91667,-6.78333],"type":"Point"}
}