{
  "type": "Feature",
  "properties": {
    "gn:admin1_code":"18.0",
    "gn:admin2_code":"0402",
    "gn:admin3_code":"0402181",
    "gn:asciiname":"Mali",
    "gn:country_code":"TZ",
    "gn:dem":1299,
    "gn:feature_class":"P",
    "gn:feature_code":"PPL",
    "gn:name":"Mali",
    "gn:population":0,
    "gn:timezone":"Africa/Dar_es_Salaam",
    "iso:country":"TZ",
    "wof:name":"Mali",
    "wof:placetype":"locality"
},
  "geometry": {"coordinates":[38.46667,-4.98333],"type":"Point"}
}