{
  "type": "Feature",
  "properties": {
    "gn:admin1_code":"18.0",
    "gn:asciiname":"Ushongo",
    "gn:country_code":"TZ",
    "gn:dem":9,
    "gn:feature_class":"P",
    "gn:feature_code":"PPL",
    "gn:name":"Ushongo",
    "gn:population":0,
    "gn:timezone":"Africa/Dar_es_Salaam",
    "iso:country":"TZ",
    "name:und_x_variant":[
        "Ushongu",
        "Ushongo Mabaoni"
    ],
    "wof:name":"Ushongo",
    "wof:placetype":"locality"
},
  "geometry": {"coordinates":[38.9741,-5.52684],"type":"Point"}
}