{
  "type": "Feature",
  "properties": {
    "gn:admin1_code":"19.0",
    "gn:admin2_code":"1801",
    "gn:admin3_code":"1801111",
    "gn:asciiname":"Nyaishozii",
    "gn:cc2":"TZ",
    "gn:country_code":"TZ",
    "gn:dem":1435,
    "gn:feature_class":"P",
    "gn:feature_code":"PPL",
    "gn:name":"Nyaishozii",
    "gn:population":0,
    "gn:timezone":"Africa/Dar_es_Salaam",
    "iso:country":"TZ",
    "name:und_x_variant":[
        "Nyaishozi",
        "Nyaishozii"
    ],
    "wof:name":"Nyaishozii",
    "wof:placetype":"locality"
},
  "geometry": {"coordinates":[31.11389,-1.73306],"type":"Point"}
}