{
  "type": "Feature",
  "properties": {
    "gn:admin1_code":"10.0",
    "gn:admin2_code":"0506",
    "gn:admin3_code":"0506131",
    "gn:asciiname":"Nduguto",
    "gn:country_code":"TZ",
    "gn:dem":1641,
    "gn:feature_class":"P",
    "gn:feature_code":"PPL",
    "gn:name":"Nduguto",
    "gn:population":0,
    "gn:timezone":"Africa/Dar_es_Salaam",
    "iso:country":"TZ",
    "name:eng_x_preferred":[
        "Nduguto"
    ],
    "wof:name":"Nduguto",
    "wof:placetype":"locality"
},
  "geometry": {"coordinates":[37.57758,-7.07918],"type":"Point"}
}