{
  "type": "Feature",
  "properties": {
    "gn:admin1_code":"5.0",
    "gn:admin2_code":"1605",
    "gn:admin3_code":"1605021",
    "gn:asciiname":"Katumbi",
    "gn:country_code":"TZ",
    "gn:dem":790,
    "gn:feature_class":"P",
    "gn:feature_code":"PPL",
    "gn:name":"Katumbi",
    "gn:population":0,
    "gn:timezone":"Africa/Dar_es_Salaam",
    "iso:country":"TZ",
    "name:eng_x_preferred":[
        "Katumbi"
    ],
    "wof:name":"Katumbi",
    "wof:placetype":"locality"
},
  "geometry": {"coordinates":[29.78261,-6.01023],"type":"Point"}
}