{
  "type": "Feature",
  "properties": {
    "gn:admin1_code":"9.0",
    "gn:admin2_code":"1201",
    "gn:admin3_code":"1201021",
    "gn:asciiname":"Kipampa",
    "gn:country_code":"TZ",
    "gn:dem":1473,
    "gn:feature_class":"P",
    "gn:feature_code":"PPL",
    "gn:name":"Kipampa",
    "gn:population":0,
    "gn:timezone":"Africa/Dar_es_Salaam",
    "iso:country":"TZ",
    "wof:name":"Kipampa",
    "wof:placetype":"locality"
},
  "geometry": {"coordinates":[33.75,-7.46667],"type":"Point"}
}