{
  "type": "Feature",
  "properties": {
    "gn:admin1_code":"10.0",
    "gn:admin2_code":"0501",
    "gn:admin3_code":"0501181",
    "gn:asciiname":"Mbamba",
    "gn:country_code":"TZ",
    "gn:dem":520,
    "gn:feature_class":"P",
    "gn:feature_code":"PPL",
    "gn:name":"Mbamba",
    "gn:population":0,
    "gn:timezone":"Africa/Dar_es_Salaam",
    "iso:country":"TZ",
    "name:eng_x_preferred":[
        "Mbamba"
    ],
    "name:eng_x_variant":[
        "Mhanha"
    ],
    "wof:name":"Mbamba",
    "wof:placetype":"locality"
},
  "geometry": {"coordinates":[37.03502,-7.11199],"type":"Point"}
}