{
  "type": "Feature",
  "properties": {
    "gn:admin1_code":"18.0",
    "gn:admin2_code":"0403",
    "gn:admin3_code":"0403141",
    "gn:asciiname":"Dar es Salaam",
    "gn:country_code":"TZ",
    "gn:dem":217,
    "gn:feature_class":"P",
    "gn:feature_code":"PPL",
    "gn:name":"Dar es Salaam",
    "gn:population":0,
    "gn:timezone":"Africa/Dar_es_Salaam",
    "iso:country":"TZ",
    "wof:name":"Dar es Salaam",
    "wof:placetype":"locality"
},
  "geometry": {"coordinates":[38.83333,-5.25],"type":"Point"}
}