{
  "type": "Feature",
  "properties": {
    "gn:admin1_code":"16.0",
    "gn:admin2_code":"1306",
    "gn:admin3_code":"1306113",
    "gn:asciiname":"Tumuli",
    "gn:country_code":"TZ",
    "gn:dem":1466,
    "gn:feature_class":"P",
    "gn:feature_code":"PPL",
    "gn:name":"Tumuli",
    "gn:population":0,
    "gn:timezone":"Africa/Dar_es_Salaam",
    "iso:country":"TZ",
    "wof:name":"Tumuli",
    "wof:placetype":"locality"
},
  "geometry": {"coordinates":[34.55,-4.55],"type":"Point"}
}