{
  "type": "Feature",
  "properties": {
    "gn:admin1_code":"13.0",
    "gn:asciiname":"Mambomsije",
    "gn:country_code":"TZ",
    "gn:dem":42,
    "gn:feature_class":"P",
    "gn:feature_code":"PPL",
    "gn:name":"Mambomsije",
    "gn:population":0,
    "gn:timezone":"Africa/Dar_es_Salaam",
    "iso:country":"TZ",
    "wof:name":"Mambomsije",
    "wof:placetype":"locality"
},
  "geometry": {"coordinates":[39.76667,-5.16667],"type":"Point"}
}