{
  "type": "Feature",
  "properties": {
    "gn:admin1_code":"24.0",
    "gn:admin2_code":"1501",
    "gn:admin3_code":"1501151",
    "gn:asciiname":"Kasote",
    "gn:country_code":"TZ",
    "gn:dem":1480,
    "gn:feature_class":"P",
    "gn:feature_code":"PPL",
    "gn:name":"Kasote",
    "gn:population":0,
    "gn:timezone":"Africa/Dar_es_Salaam",
    "iso:country":"TZ",
    "name:und_x_variant":[
        "Kasoti",
        "Kasote"
    ],
    "wof:name":"Kasote",
    "wof:placetype":"locality"
},
  "geometry": {"coordinates":[31.25,-8.41667],"type":"Point"}
}