{
  "type": "Feature",
  "properties": {
    "gn:admin1_code":"9.0",
    "gn:admin2_code":"1201",
    "gn:admin3_code":"1201201",
    "gn:asciiname":"Manda",
    "gn:country_code":"TZ",
    "gn:dem":809,
    "gn:feature_class":"P",
    "gn:feature_code":"PPL",
    "gn:name":"Manda",
    "gn:population":0,
    "gn:timezone":"Africa/Dar_es_Salaam",
    "iso:country":"TZ",
    "wof:name":"Manda",
    "wof:placetype":"locality"
},
  "geometry": {"coordinates":[32.43333,-7.96667],"type":"Point"}
}