{
  "type": "Feature",
  "properties": {
    "gn:admin1_code":"9.0",
    "gn:admin2_code":"1207",
    "gn:admin3_code":"1207151",
    "gn:asciiname":"Isunura",
    "gn:country_code":"TZ",
    "gn:dem":1064,
    "gn:feature_class":"P",
    "gn:feature_code":"PPL",
    "gn:name":"Isunura",
    "gn:population":0,
    "gn:timezone":"Africa/Dar_es_Salaam",
    "iso:country":"TZ",
    "wof:name":"Isunura",
    "wof:placetype":"locality"
},
  "geometry": {"coordinates":[34.41667,-8.61667],"type":"Point"}
}