{
  "type": "Feature",
  "properties": {
    "gn:country":"TZ",
    "gn:fcode":"PPL",
    "gn:population":13548,
    "iso:country":"TZ",
    "qs:name":"Mahuta",
    "qs:photos_9r":0,
    "qs:photos_sr":0,
    "qs:pop_sr":"6",
    "wof:name":"Mahuta",
    "wof:placetype":"locality",
    "wof:population":13548
},
  "geometry": {"coordinates":[39.45,-10.86667],"type":"Point"}
}