{
  "type": "Feature",
  "properties": {
    "gn:admin1_code":"10.0",
    "gn:admin2_code":"0502",
    "gn:admin3_code":"0502121",
    "gn:asciiname":"Kissio",
    "gn:country_code":"TZ",
    "gn:dem":137,
    "gn:feature_class":"P",
    "gn:feature_code":"PPL",
    "gn:name":"Kissio",
    "gn:population":0,
    "gn:timezone":"Africa/Dar_es_Salaam",
    "iso:country":"TZ",
    "name:eng_x_preferred":[
        "Kissio"
    ],
    "wof:name":"Kissio",
    "wof:placetype":"locality"
},
  "geometry": {"coordinates":[38.25,-6.96667],"type":"Point"}
}