{
  "type": "Feature",
  "properties": {
    "gn:admin1_code":"5.0",
    "gn:admin2_code":"1605",
    "gn:admin3_code":"1605041",
    "gn:asciiname":"Mgondozi",
    "gn:country_code":"TZ",
    "gn:dem":874,
    "gn:feature_class":"P",
    "gn:feature_code":"PPL",
    "gn:name":"Mgondozi",
    "gn:population":0,
    "gn:timezone":"Africa/Dar_es_Salaam",
    "iso:country":"TZ",
    "name:und_x_variant":[
        "Mgondosi",
        "Mgondozi"
    ],
    "wof:name":"Mgondozi",
    "wof:placetype":"locality"
},
  "geometry": {"coordinates":[29.95,-5.76667],"type":"Point"}
}