{
  "type": "Feature",
  "properties": {
    "gn:admin1_code":"6.0",
    "gn:admin2_code":"0303",
    "gn:admin3_code":"0303083",
    "gn:asciiname":"Mkanyeni",
    "gn:country_code":"TZ",
    "gn:dem":839,
    "gn:feature_class":"P",
    "gn:feature_code":"PPL",
    "gn:name":"Mkanyeni",
    "gn:population":0,
    "gn:timezone":"Africa/Dar_es_Salaam",
    "iso:country":"TZ",
    "wof:name":"Mkanyeni",
    "wof:placetype":"locality"
},
  "geometry": {"coordinates":[37.85,-4.25],"type":"Point"}
}