{
  "type": "Feature",
  "properties": {
    "gn:admin1_code":"11.0",
    "gn:admin2_code":"9072685",
    "gn:asciiname":"Nandembo",
    "gn:country_code":"TZ",
    "gn:dem":487,
    "gn:feature_class":"P",
    "gn:feature_code":"PPL",
    "gn:name":"Nandembo",
    "gn:population":0,
    "gn:timezone":"Africa/Dar_es_Salaam",
    "iso:country":"TZ",
    "wof:name":"Nandembo",
    "wof:placetype":"locality"
},
  "geometry": {"coordinates":[38.91667,-8.46667],"type":"Point"}
}