{
  "type": "Feature",
  "properties": {
    "gn:admin1_code":"5.0",
    "gn:admin2_code":"1605",
    "gn:admin3_code":"1605121",
    "gn:asciiname":"Kigurwe",
    "gn:country_code":"TZ",
    "gn:dem":1062,
    "gn:feature_class":"P",
    "gn:feature_code":"PPL",
    "gn:name":"Kigurwe",
    "gn:population":0,
    "gn:timezone":"Africa/Dar_es_Salaam",
    "iso:country":"TZ",
    "wof:name":"Kigurwe",
    "wof:placetype":"locality"
},
  "geometry": {"coordinates":[31.08333,-4.96667],"type":"Point"}
}