{
  "type": "Feature",
  "properties": {
    "gn:admin1_code":"7.0",
    "gn:admin2_code":"0804",
    "gn:admin3_code":"0804101",
    "gn:asciiname":"Mihumo Chini",
    "gn:country_code":"TZ",
    "gn:dem":329,
    "gn:feature_class":"P",
    "gn:feature_code":"PPL",
    "gn:name":"Mihumo Chini",
    "gn:population":0,
    "gn:timezone":"Africa/Dar_es_Salaam",
    "iso:country":"TZ",
    "wof:name":"Mihumo Chini",
    "wof:placetype":"locality"
},
  "geometry": {"coordinates":[38.33333,-9.96667],"type":"Point"}
}