{
  "type": "Feature",
  "properties": {
    "gn:admin1_code":"5.0",
    "gn:asciiname":"Luelampulla",
    "gn:country_code":"TZ",
    "gn:dem":781,
    "gn:feature_class":"P",
    "gn:feature_code":"PPL",
    "gn:name":"Luelampulla",
    "gn:population":0,
    "gn:timezone":"Africa/Dar_es_Salaam",
    "iso:country":"TZ",
    "name:eng_x_preferred":[
        "Luelampulla"
    ],
    "wof:name":"Luelampulla",
    "wof:placetype":"locality"
},
  "geometry": {"coordinates":[29.86812,-6.42042],"type":"Point"}
}