{
  "type": "Feature",
  "properties": {
    "gn:admin1_code":"22.0",
    "gn:asciiname":"Bumbwi Malindi",
    "gn:country_code":"TZ",
    "gn:dem":61,
    "gn:feature_class":"P",
    "gn:feature_code":"PPL",
    "gn:name":"Bumbwi Malindi",
    "gn:population":0,
    "gn:timezone":"Africa/Dar_es_Salaam",
    "iso:country":"TZ",
    "wof:name":"Bumbwi Malindi",
    "wof:placetype":"locality"
},
  "geometry": {"coordinates":[39.28333,-6.05],"type":"Point"}
}