{
  "type": "Feature",
  "properties": {
    "gn:admin1_code":"28.0",
    "gn:admin2_code":"2502",
    "gn:admin3_code":"2502101",
    "gn:asciiname":"Ikondo",
    "gn:country_code":"TZ",
    "gn:dem":1210,
    "gn:feature_class":"P",
    "gn:feature_code":"PPL",
    "gn:name":"Ikondo",
    "gn:population":0,
    "gn:timezone":"Africa/Dar_es_Salaam",
    "iso:country":"TZ",
    "wof:name":"Ikondo",
    "wof:placetype":"locality"
},
  "geometry": {"coordinates":[32.55,-3.13333],"type":"Point"}
}