{
  "type": "Feature",
  "properties": {
    "gn:admin1_code":"13.0",
    "gn:admin2_code":"5401",
    "gn:admin3_code":"5401101",
    "gn:asciiname":"Makongeni",
    "gn:country_code":"TZ",
    "gn:dem":33,
    "gn:feature_class":"P",
    "gn:feature_code":"PPL",
    "gn:name":"Makongeni",
    "gn:population":0,
    "gn:timezone":"Africa/Dar_es_Salaam",
    "iso:country":"TZ",
    "wof:name":"Makongeni",
    "wof:placetype":"locality"
},
  "geometry": {"coordinates":[39.76667,-5.11667],"type":"Point"}
}