{
  "type": "Feature",
  "properties": {
    "iso:country":"TZ",
    "qs:gn_country":"TZ",
    "qs:gn_fcode":"PPL",
    "qs:gn_pop":20937,
    "qs:name":"Basotu",
    "qs:name_adm0":"Tanzania",
    "qs:name_adm1":"Manyara",
    "qs:photos":0,
    "qs:photos_1k":0,
    "qs:photos_9k":1,
    "qs:photos_9r":1,
    "qs:photos_all":6,
    "qs:photos_sr":0,
    "qs:placetype":"Town",
    "qs:pop_sr":"7",
    "qs:woe_adm0":23424973,
    "wof:name":"Basotu",
    "wof:placetype":"locality",
    "wof:population":20937
},
  "geometry": {"coordinates":[35.08333,-4.36667],"type":"Point"}
}