{
  "type": "Feature",
  "properties": {
    "gn:admin1_code":"5.0",
    "gn:asciiname":"Mwamgongo",
    "gn:country_code":"TZ",
    "gn:dem":767,
    "gn:feature_class":"P",
    "gn:feature_code":"PPL",
    "gn:name":"Mwamgongo",
    "gn:population":0,
    "gn:timezone":"Africa/Dar_es_Salaam",
    "iso:country":"TZ",
    "name:und_x_variant":[
        "Nyangongo",
        "Mwamgongo"
    ],
    "wof:name":"Mwamgongo",
    "wof:placetype":"locality"
},
  "geometry": {"coordinates":[29.58333,-4.66667],"type":"Point"}
}