{
  "type": "Feature",
  "properties": {
    "gn:gn_country":"TZ",
    "gn:gn_fcode":"PPL",
    "gn:gn_pop":11122,
    "gn:population":11122,
    "iso:country":"TZ",
    "qs_pg:aaroncc":"TZ",
    "qs_pg:gn_country":"TZ",
    "qs_pg:gn_fcode":"PPL",
    "qs_pg:gn_pop":11122,
    "qs_pg:name":"Mtimbira",
    "qs_pg:photos_9r":0,
    "qs_pg:photos_sr":0,
    "qs_pg:pop_sr":6,
    "qs_pg:qs_pg_placetype":"locality",
    "wof:name":"Mtimbira",
    "wof:placetype":"locality",
    "wof:population":11122
},
  "geometry": {"coordinates":[36.35,-8.78333],"type":"Point"}
}