{
  "type": "Feature",
  "properties": {
    "gn:admin1_code":"7.0",
    "gn:admin2_code":"0801",
    "gn:admin3_code":"0801183",
    "gn:asciiname":"Lingaula",
    "gn:country_code":"TZ",
    "gn:dem":47,
    "gn:feature_class":"P",
    "gn:feature_code":"PPL",
    "gn:name":"Lingaula",
    "gn:population":0,
    "gn:timezone":"Africa/Dar_es_Salaam",
    "iso:country":"TZ",
    "name:eng_x_preferred":[
        "Lingaula"
    ],
    "name:eng_x_variant":[
        "Lingaura"
    ],
    "wof:name":"Lingaula",
    "wof:placetype":"locality"
},
  "geometry": {"coordinates":[39.32514000000001,-8.89249],"type":"Point"}
}