{
  "type": "Feature",
  "properties": {
    "iso:country":"TZ",
    "name:ell_x_preferred":[
        "\u039d\u03b6\u03ad\u03b3\u03ba\u03b1"
    ],
    "ne:ADM0CAP":0.0,
    "ne:ADM0NAME":"Tanzania",
    "ne:ADM0_A3":"TZA",
    "ne:ADM1NAME":"Tabora",
    "ne:ADMIN1_COD":0,
    "ne:CAPALT":0,
    "ne:CHANGED":0,
    "ne:CHECKME":0,
    "ne:COMPARE":0,
    "ne:DIFFASCII":0,
    "ne:ELEVATION":0.0,
    "ne:FEATURECLA":"Populated place",
    "ne:FEATURE_CL":"P",
    "ne:FEATURE_CO":"PPL",
    "ne:GEONAMEID":150930,
    "ne:GEONAMESNO":"Geonames ascii name + lat.d + long.d matching.",
    "ne:GN_ASCII":"Nzega",
    "ne:GN_POP":26584,
    "ne:GTOPO30":1210.0,
    "ne:ISO_A2":"TZ",
    "ne:LABELRANK":5,
    "ne:LATITUDE":-4.209628,
    "ne:LONGITUDE":33.180031,
    "ne:LS_MATCH":1,
    "ne:LS_NAME":"Nzega",
    "ne:MAX_AREAKM":6.0,
    "ne:MAX_AREAMI":2.0,
    "ne:MAX_BBXMAX":33.208333,
    "ne:MAX_BBXMIN":33.175,
    "ne:MAX_BBYMAX":-4.208333,
    "ne:MAX_BBYMIN":-4.241667,
    "ne:MAX_NATSCA":20.0,
    "ne:MAX_PERKM":15.0,
    "ne:MAX_PERMI":9.0,
    "ne:MAX_POP10":10066,
    "ne:MAX_POP20":10066,
    "ne:MAX_POP300":0,
    "ne:MAX_POP310":0,
    "ne:MAX_POP50":0,
    "ne:MEAN_BBXC":33.194643,
    "ne:MEAN_BBYC":-4.223214,
    "ne:MEGACITY":0,
    "ne:MIN_AREAKM":6.0,
    "ne:MIN_AREAMI":2.0,
    "ne:MIN_BBXMAX":33.208333,
    "ne:MIN_BBXMIN":33.175,
    "ne:MIN_BBYMAX":-4.208333,
    "ne:MIN_BBYMIN":-4.241667,
    "ne:MIN_PERKM":15.0,
    "ne:MIN_PERMI":9.0,
    "ne:NAME":"Nzega",
    "ne:NAMEASCII":"Nzega",
    "ne:NAMEDIFF":0,
    "ne:NATSCALE":20,
    "ne:POP1950":0,
    "ne:POP1955":0,
    "ne:POP1960":0,
    "ne:POP1965":0,
    "ne:POP1970":0,
    "ne:POP1975":0,
    "ne:POP1980":0,
    "ne:POP1985":0,
    "ne:POP1990":0,
    "ne:POP1995":0,
    "ne:POP2000":0,
    "ne:POP2005":0,
    "ne:POP2010":0,
    "ne:POP2015":0,
    "ne:POP2020":0,
    "ne:POP2025":0,
    "ne:POP2050":0,
    "ne:POP_MAX":26584,
    "ne:POP_MIN":10066,
    "ne:POP_OTHER":0,
    "ne:RANK_MAX":7,
    "ne:RANK_MIN":6,
    "ne:SCALERANK":7,
    "ne:SOV0NAME":"United Republic of Tanzania",
    "ne:SOV_A3":"TZA",
    "ne:TIMEZONE":"Africa/Dar_es_Salaam",
    "ne:UN_FID":0,
    "ne:UN_LAT":0.0,
    "ne:UN_LONG":0.0,
    "ne:WORLDCITY":0,
    "qs:gn_country":"TZ",
    "qs:gn_fcode":"PPL",
    "qs:gn_pop":26584,
    "qs:name":"Nzega",
    "qs:name_adm0":"Tanzania",
    "qs:name_adm1":"Tabora",
    "qs:photos":0,
    "qs:photos_1k":0,
    "qs:photos_9k":1,
    "qs:photos_9r":1,
    "qs:photos_all":19,
    "qs:photos_sr":0,
    "qs:placetype":"Town",
    "qs:pop_sr":"7",
    "qs:woe_adm0":23424973,
    "wd:wordcount":68,
    "wof:name":"Nzega",
    "wof:placetype":"locality",
    "wof:population":26584
},
  "geometry": {"coordinates":[33.18333,-4.21667],"type":"Point"}
}