{
  "type": "Feature",
  "properties": {
    "gn:admin1_code":"5.0",
    "gn:admin2_code":"1602",
    "gn:admin3_code":"1602081",
    "gn:asciiname":"Muhanga",
    "gn:country_code":"TZ",
    "gn:dem":1194,
    "gn:feature_class":"P",
    "gn:feature_code":"PPL",
    "gn:name":"Muhanga",
    "gn:population":0,
    "gn:timezone":"Africa/Dar_es_Salaam",
    "iso:country":"TZ",
    "name:afr_x_preferred":[
        "Gitarama"
    ],
    "name:cat_x_preferred":[
        "Muhanga"
    ],
    "name:ceb_x_preferred":[
        "Gitarama"
    ],
    "name:dan_x_preferred":[
        "Gitarama"
    ],
    "name:deu_x_preferred":[
        "Gitarama"
    ],
    "name:ell_x_preferred":[
        "\u0393\u03ba\u03b9\u03c4\u03b1\u03c1\u03ac\u03bc\u03b1"
    ],
    "name:est_x_preferred":[
        "Gitarama"
    ],
    "name:eus_x_preferred":[
        "Gitarama"
    ],
    "name:fra_x_preferred":[
        "Muhanga"
    ],
    "name:grn_x_preferred":[
        "Muhanga"
    ],
    "name:heb_x_preferred":[
        "\u05de\u05d5\u05d7\u05e0\u05d2\u05d4"
    ],
    "name:hrv_x_preferred":[
        "Gitarama"
    ],
    "name:ile_x_preferred":[
        "Gitarama"
    ],
    "name:jpn_x_preferred":[
        "\u30ae\u30bf\u30e9\u30de"
    ],
    "name:kat_x_preferred":[
        "\u10d2\u10d8\u10e2\u10d0\u10e0\u10d0\u10db\u10d0"
    ],
    "name:kor_x_preferred":[
        "\uae30\ud0c0\ub77c\ub9c8"
    ],
    "name:lav_x_preferred":[
        "Gitarama"
    ],
    "name:lit_x_preferred":[
        "Muhanga"
    ],
    "name:mrj_x_preferred":[
        "\u0413\u0438\u0442\u0430\u0440\u0430\u043c\u0430"
    ],
    "name:nld_x_preferred":[
        "Gitarama"
    ],
    "name:pol_x_preferred":[
        "Gitarama"
    ],
    "name:por_x_preferred":[
        "Gitarama"
    ],
    "name:rus_x_preferred":[
        "\u041c\u0443\u0445\u0430\u043d\u0433\u0430"
    ],
    "name:spa_x_preferred":[
        "Gitarama"
    ],
    "name:srp_x_preferred":[
        "\u0413\u0438\u0442\u0430\u0440\u0430\u043c\u0430"
    ],
    "name:swe_x_preferred":[
        "Gitarama"
    ],
    "name:tur_x_preferred":[
        "Gitarama"
    ],
    "name:urd_x_preferred":[
        "\u062c\u06cc\u0679\u0627\u0631\u0627\u0645\u0627"
    ],
    "name:zho_x_preferred":[
        "\u5409\u5854\u62c9\u99ac"
    ],
    "wof:name":"Muhanga",
    "wof:placetype":"locality"
},
  "geometry": {"coordinates":[30.38056,-4.51528],"type":"Point"}
}