{
  "type": "Feature",
  "properties": {
    "gn:admin1_code":"5.0",
    "gn:admin2_code":"1602",
    "gn:admin3_code":"1602081",
    "gn:asciiname":"Muhanga",
    "gn:country_code":"TZ",
    "gn:dem":1194,
    "gn:feature_class":"P",
    "gn:feature_code":"PPL",
    "gn:name":"Muhanga",
    "gn:population":0,
    "gn:timezone":"Africa/Dar_es_Salaam",
    "iso:country":"TZ",
    "wof:name":"Muhanga",
    "wof:placetype":"locality"
},
  "geometry": {"coordinates":[30.38056,-4.51528],"type":"Point"}
}