{
  "type": "Feature",
  "properties": {
    "gn:country":"TZ",
    "gn:fcode":"PPL",
    "gn:population":10291,
    "iso:country":"TZ",
    "name:und_x_variant":[
        "Makuugu"
    ],
    "qs_pg:aaroncc":"TZ",
    "qs_pg:gn_country":"TZ",
    "qs_pg:gn_fcode":"PPL",
    "qs_pg:gn_pop":10291,
    "qs_pg:name":"Makungu",
    "qs_pg:photos_9r":0,
    "qs_pg:photos_sr":0,
    "qs_pg:pop_sr":6,
    "qs_pg:qs_pg_placetype":"locality",
    "wof:name":"Makungu",
    "wof:placetype":"locality",
    "wof:population":10291
},
  "geometry": {"coordinates":[35.28333,-8.73333],"type":"Point"}
}