{
  "type": "Feature",
  "properties": {
    "gn:admin1_code":"31.0",
    "gn:admin2_code":"2404",
    "gn:admin3_code":"2404031",
    "gn:asciiname":"Mwamtumai",
    "gn:country_code":"TZ",
    "gn:dem":1326,
    "gn:feature_class":"P",
    "gn:feature_code":"PPL",
    "gn:name":"Mwamtumai",
    "gn:population":0,
    "gn:timezone":"Africa/Dar_es_Salaam",
    "iso:country":"TZ",
    "wof:name":"Mwamtumai",
    "wof:placetype":"locality"
},
  "geometry": {"coordinates":[34.0744,-3.12027],"type":"Point"}
}