{
  "type": "Feature",
  "properties": {
    "gn:admin1_code":"17.0",
    "gn:admin2_code":"1407",
    "gn:admin3_code":"1407121",
    "gn:asciiname":"Ntimbi",
    "gn:country_code":"TZ",
    "gn:dem":1104,
    "gn:feature_class":"P",
    "gn:feature_code":"PPL",
    "gn:name":"Ntimbi",
    "gn:population":0,
    "gn:timezone":"Africa/Dar_es_Salaam",
    "iso:country":"TZ",
    "wof:name":"Ntimbi",
    "wof:placetype":"locality"
},
  "geometry": {"coordinates":[31.95,-4.51667],"type":"Point"}
}