{
  "type": "Feature",
  "properties": {
    "gn:admin1_code":"20.0",
    "gn:asciiname":"Mitondooni",
    "gn:country_code":"TZ",
    "gn:dem":1,
    "gn:feature_class":"P",
    "gn:feature_code":"PPL",
    "gn:name":"Mitondooni",
    "gn:population":0,
    "gn:timezone":"Africa/Dar_es_Salaam",
    "iso:country":"TZ",
    "wof:name":"Mitondooni",
    "wof:placetype":"locality"
},
  "geometry": {"coordinates":[39.65,-5.45],"type":"Point"}
}