{
  "type": "Feature",
  "properties": {
    "gn:admin1_code":"18.0",
    "gn:admin2_code":"0401",
    "gn:admin3_code":"0401181",
    "gn:asciiname":"Hakidevu",
    "gn:country_code":"TZ",
    "gn:dem":1868,
    "gn:feature_class":"P",
    "gn:feature_code":"PPL",
    "gn:name":"Hakidevu",
    "gn:population":0,
    "gn:timezone":"Africa/Dar_es_Salaam",
    "iso:country":"TZ",
    "wof:name":"Hakidevu",
    "wof:placetype":"locality"
},
  "geometry": {"coordinates":[38.21667,-4.55],"type":"Point"}
}