{
  "type": "Feature",
  "properties": {
    "gn:admin1_code":"10.0",
    "gn:admin2_code":"0506",
    "gn:admin3_code":"0506013",
    "gn:asciiname":"Mvomero",
    "gn:country_code":"TZ",
    "gn:dem":420,
    "gn:feature_class":"P",
    "gn:feature_code":"PPL",
    "gn:name":"Mvomero",
    "gn:population":0,
    "gn:timezone":"Africa/Dar_es_Salaam",
    "iso:country":"TZ",
    "wof:name":"Mvomero",
    "wof:placetype":"locality"
},
  "geometry": {"coordinates":[37.41667,-6.33333],"type":"Point"}
}