{
  "type": "Feature",
  "properties": {
    "gn:admin1_code":"18.0",
    "gn:admin2_code":"0403",
    "gn:admin3_code":"0403221",
    "gn:asciiname":"Kazita",
    "gn:country_code":"TZ",
    "gn:dem":863,
    "gn:feature_class":"P",
    "gn:feature_code":"PPL",
    "gn:name":"Kazita",
    "gn:population":0,
    "gn:timezone":"Africa/Dar_es_Salaam",
    "iso:country":"TZ",
    "wof:name":"Kazita",
    "wof:placetype":"locality"
},
  "geometry": {"coordinates":[38.61667,-5.01667],"type":"Point"}
}