{
  "type": "Feature",
  "properties": {
    "gn:admin1_code":"23.0",
    "gn:asciiname":"Mjimwema",
    "gn:country_code":"TZ",
    "gn:dem":1,
    "gn:feature_class":"P",
    "gn:feature_code":"PPL",
    "gn:name":"Mjimwema",
    "gn:population":0,
    "gn:timezone":"Africa/Dar_es_Salaam",
    "iso:country":"TZ",
    "wof:name":"Mjimwema",
    "wof:placetype":"locality"
},
  "geometry": {"coordinates":[39.36667,-6.85],"type":"Point"}
}