{
  "type": "Feature",
  "properties": {
    "gn:admin1_code":"12.0",
    "gn:admin2_code":"1905",
    "gn:admin3_code":"1905031",
    "gn:asciiname":"Arogongo",
    "gn:country_code":"TZ",
    "gn:dem":1143,
    "gn:feature_class":"P",
    "gn:feature_code":"PPL",
    "gn:name":"Arogongo",
    "gn:population":0,
    "gn:timezone":"Africa/Dar_es_Salaam",
    "iso:country":"TZ",
    "wof:name":"Arogongo",
    "wof:placetype":"locality"
},
  "geometry": {"coordinates":[32.63333,-2.46667],"type":"Point"}
}