{
  "type": "Feature",
  "properties": {
    "gn:admin1_code":"24.0",
    "gn:admin2_code":"1503",
    "gn:admin3_code":"1503151",
    "gn:asciiname":"Kisua",
    "gn:country_code":"TZ",
    "gn:dem":1823,
    "gn:feature_class":"P",
    "gn:feature_code":"PPL",
    "gn:name":"Kisua",
    "gn:population":0,
    "gn:timezone":"Africa/Dar_es_Salaam",
    "iso:country":"TZ",
    "wof:name":"Kisua",
    "wof:placetype":"locality"
},
  "geometry": {"coordinates":[31.43333,-7.61667],"type":"Point"}
}