{
  "type": "Feature",
  "properties": {
    "gn:admin1_code":"19.0",
    "gn:admin2_code":"1807",
    "gn:admin3_code":"1807131",
    "gn:asciiname":"Gera",
    "gn:country_code":"TZ",
    "gn:dem":1278,
    "gn:feature_class":"P",
    "gn:feature_code":"PPL",
    "gn:name":"Gera",
    "gn:population":0,
    "gn:timezone":"Africa/Dar_es_Salaam",
    "iso:country":"TZ",
    "wof:name":"Gera",
    "wof:placetype":"locality"
},
  "geometry": {"coordinates":[31.75028,-1.24722],"type":"Point"}
}