{
  "type": "Feature",
  "properties": {
    "gn:admin1_code":"10.0",
    "gn:admin2_code":"0506",
    "gn:admin3_code":"0506151",
    "gn:asciiname":"Mlali",
    "gn:country_code":"TZ",
    "gn:dem":566,
    "gn:feature_class":"P",
    "gn:feature_code":"PPL",
    "gn:name":"Mlali",
    "gn:population":0,
    "gn:timezone":"Africa/Dar_es_Salaam",
    "iso:country":"TZ",
    "name:ceb_x_preferred":[
        "Mlali"
    ],
    "name:ita_x_preferred":[
        "Mlali"
    ],
    "name:swa_x_preferred":[
        "Mlali"
    ],
    "name:und_x_variant":[
        "Melela",
        "Mlali"
    ],
    "wof:name":"Mlali",
    "wof:placetype":"locality"
},
  "geometry": {"coordinates":[37.53333,-6.95],"type":"Point"}
}