{
  "type": "Feature",
  "properties": {
    "gn:admin1_code":"2.0",
    "gn:admin2_code":"0601",
    "gn:admin3_code":"0601053",
    "gn:asciiname":"Nunge",
    "gn:country_code":"TZ",
    "gn:dem":7,
    "gn:feature_class":"P",
    "gn:feature_code":"PPL",
    "gn:name":"Nunge",
    "gn:population":0,
    "gn:timezone":"Africa/Dar_es_Salaam",
    "iso:country":"TZ",
    "name:deu_x_preferred":[
        "Nunge"
    ],
    "name:und_x_variant":[
        "Nungwe"
    ],
    "wof:name":"Nunge",
    "wof:placetype":"locality"
},
  "geometry": {"coordinates":[38.86667,-6.38333],"type":"Point"}
}