{
  "type": "Feature",
  "properties": {
    "gn:admin1_code":"3.0",
    "gn:admin2_code":"0101",
    "gn:admin3_code":"0101241",
    "gn:asciiname":"Kolo",
    "gn:country_code":"TZ",
    "gn:dem":1505,
    "gn:feature_class":"P",
    "gn:feature_code":"PPL",
    "gn:name":"Kolo",
    "gn:population":0,
    "gn:timezone":"Africa/Dar_es_Salaam",
    "iso:country":"TZ",
    "name:ita_x_preferred":[
        "Kolo"
    ],
    "name:swa_x_preferred":[
        "Kolo"
    ],
    "name:und_x_variant":[
        "Kola",
        "Kolo"
    ],
    "wof:name":"Kolo",
    "wof:placetype":"locality"
},
  "geometry": {"coordinates":[35.83333,-4.73333],"type":"Point"}
}