{
  "type": "Feature",
  "properties": {
    "gn:admin1_code":"19.0",
    "gn:admin2_code":"1808",
    "gn:admin3_code":"1808011",
    "gn:asciiname":"Rwazi",
    "gn:country_code":"TZ",
    "gn:dem":1395,
    "gn:feature_class":"P",
    "gn:feature_code":"PPL",
    "gn:name":"Rwazi",
    "gn:population":0,
    "gn:timezone":"Africa/Dar_es_Salaam",
    "iso:country":"TZ",
    "wof:name":"Rwazi",
    "wof:placetype":"locality"
},
  "geometry": {"coordinates":[30.71667,-1.33333],"type":"Point"}
}