{
  "type": "Feature",
  "properties": {
    "gn:admin1_code":"10.0",
    "gn:admin2_code":"0502",
    "gn:admin3_code":"0502031",
    "gn:asciiname":"Kimero",
    "gn:country_code":"TZ",
    "gn:dem":134,
    "gn:feature_class":"P",
    "gn:feature_code":"PPL",
    "gn:name":"Kimero",
    "gn:population":0,
    "gn:timezone":"Africa/Dar_es_Salaam",
    "iso:country":"TZ",
    "name:eng_x_preferred":[
        "Kimero"
    ],
    "wof:name":"Kimero",
    "wof:placetype":"locality"
},
  "geometry": {"coordinates":[37.87879,-7.20113],"type":"Point"}
}