{
  "type": "Feature",
  "properties": {
    "gn:admin1_code":"19.0",
    "gn:admin2_code":"1808",
    "gn:admin3_code":"1808071",
    "gn:asciiname":"Kibare",
    "gn:country_code":"TZ",
    "gn:dem":1676,
    "gn:feature_class":"P",
    "gn:feature_code":"PPL",
    "gn:name":"Kibare",
    "gn:population":0,
    "gn:timezone":"Africa/Dar_es_Salaam",
    "iso:country":"TZ",
    "wof:name":"Kibare",
    "wof:placetype":"locality"
},
  "geometry": {"coordinates":[30.82167,-1.075],"type":"Point"}
}