{
  "type": "Feature",
  "properties": {
    "gn:admin1_code":"2.0",
    "gn:admin2_code":"0605",
    "gn:admin3_code":"0605181",
    "gn:asciiname":"Pombwe",
    "gn:country_code":"TZ",
    "gn:dem":9,
    "gn:feature_class":"P",
    "gn:feature_code":"PPL",
    "gn:name":"Pombwe",
    "gn:population":0,
    "gn:timezone":"Africa/Dar_es_Salaam",
    "iso:country":"TZ",
    "name:eng_x_preferred":[
        "Pombwe"
    ],
    "wof:name":"Pombwe",
    "wof:placetype":"locality"
},
  "geometry": {"coordinates":[39.3361,-8.26799],"type":"Point"}
}