{
  "type": "Feature",
  "properties": {
    "gn:admin1_code":"16.0",
    "gn:admin2_code":"1305",
    "gn:admin3_code":"1305101",
    "gn:asciiname":"Nduma",
    "gn:country_code":"TZ",
    "gn:dem":1384,
    "gn:feature_class":"P",
    "gn:feature_code":"PPL",
    "gn:name":"Nduma",
    "gn:population":0,
    "gn:timezone":"Africa/Dar_es_Salaam",
    "iso:country":"TZ",
    "wof:name":"Nduma",
    "wof:placetype":"locality"
},
  "geometry": {"coordinates":[34.93333,-5.38333],"type":"Point"}
}