{
  "type": "Feature",
  "properties": {
    "gn:admin1_code":"12.0",
    "gn:admin2_code":"1904",
    "gn:admin3_code":"1904081",
    "gn:asciiname":"Mwawuchuma",
    "gn:country_code":"TZ",
    "gn:dem":1218,
    "gn:feature_class":"P",
    "gn:feature_code":"PPL",
    "gn:name":"Mwawuchuma",
    "gn:population":0,
    "gn:timezone":"Africa/Dar_es_Salaam",
    "iso:country":"TZ",
    "wof:name":"Mwawuchuma",
    "wof:placetype":"locality"
},
  "geometry": {"coordinates":[33.53333,-2.76667],"type":"Point"}
}