{
  "type": "Feature",
  "properties": {
    "gn:admin1_code":"11.0",
    "gn:admin2_code":"0902",
    "gn:admin3_code":"0902101",
    "gn:asciiname":"Luchemi",
    "gn:country_code":"TZ",
    "gn:dem":782,
    "gn:feature_class":"P",
    "gn:feature_code":"PPL",
    "gn:name":"Luchemi",
    "gn:population":0,
    "gn:timezone":"Africa/Dar_es_Salaam",
    "iso:country":"TZ",
    "wof:name":"Luchemi",
    "wof:placetype":"locality"
},
  "geometry": {"coordinates":[39.11667,-10.61667],"type":"Point"}
}