{
  "type": "Feature",
  "properties": {
    "gn:admin1_code":"11.0",
    "gn:admin2_code":"0904",
    "gn:admin3_code":"0904031",
    "gn:asciiname":"Michenjele",
    "gn:country_code":"TZ",
    "gn:dem":176,
    "gn:feature_class":"P",
    "gn:feature_code":"PPL",
    "gn:name":"Michenjele",
    "gn:population":0,
    "gn:timezone":"Africa/Dar_es_Salaam",
    "iso:country":"TZ",
    "name:und_x_variant":[
        "Michinjele",
        "Michenjele"
    ],
    "wof:name":"Michenjele",
    "wof:placetype":"locality"
},
  "geometry": {"coordinates":[39.88333,-10.78333],"type":"Point"}
}