{
  "type": "Feature",
  "properties": {
    "gn:admin1_code":"19.0",
    "gn:admin2_code":"1801",
    "gn:admin3_code":"1801031",
    "gn:asciiname":"Kishoju",
    "gn:country_code":"TZ",
    "gn:dem":1256,
    "gn:feature_class":"P",
    "gn:feature_code":"PPL",
    "gn:name":"Kishoju",
    "gn:population":0,
    "gn:timezone":"Africa/Dar_es_Salaam",
    "iso:country":"TZ",
    "name:und_x_variant":[
        "Kishoyu",
        "Kishoju"
    ],
    "wof:name":"Kishoju",
    "wof:placetype":"locality"
},
  "geometry": {"coordinates":[31.18333,-1.46667],"type":"Point"}
}