{
  "type": "Feature",
  "properties": {
    "gn:admin1_code":"10.0",
    "gn:admin2_code":"0506",
    "gn:admin3_code":"0506151",
    "gn:asciiname":"Lusungi",
    "gn:country_code":"TZ",
    "gn:dem":1034,
    "gn:feature_class":"P",
    "gn:feature_code":"PPL",
    "gn:name":"Lusungi",
    "gn:population":0,
    "gn:timezone":"Africa/Dar_es_Salaam",
    "iso:country":"TZ",
    "wof:name":"Lusungi",
    "wof:placetype":"locality"
},
  "geometry": {"coordinates":[37.51667,-7.06667],"type":"Point"}
}