{
  "type": "Feature",
  "properties": {
    "gn:admin1_code":"17.0",
    "gn:admin2_code":"1401",
    "gn:admin3_code":"1401131",
    "gn:asciiname":"Ndugutu",
    "gn:country_code":"TZ",
    "gn:dem":1207,
    "gn:feature_class":"P",
    "gn:feature_code":"PPL",
    "gn:name":"Ndugutu",
    "gn:population":0,
    "gn:timezone":"Africa/Dar_es_Salaam",
    "iso:country":"TZ",
    "wof:name":"Ndugutu",
    "wof:placetype":"locality"
},
  "geometry": {"coordinates":[33.35,-4.21667],"type":"Point"}
}