{
  "type": "Feature",
  "properties": {
    "gn:admin1_code":"28.0",
    "gn:admin2_code":"2501",
    "gn:admin3_code":"2501221",
    "gn:asciiname":"Nyawizu",
    "gn:country_code":"TZ",
    "gn:dem":1279,
    "gn:feature_class":"P",
    "gn:feature_code":"PPL",
    "gn:name":"Nyawizu",
    "gn:population":0,
    "gn:timezone":"Africa/Dar_es_Salaam",
    "iso:country":"TZ",
    "name:und_x_variant":[
        "Nyawizo",
        "Nyawizu"
    ],
    "wof:name":"Nyawizu",
    "wof:placetype":"locality"
},
  "geometry": {"coordinates":[32.36667,-3.26667],"type":"Point"}
}