{
  "type": "Feature",
  "properties": {
    "gn:admin1_code":"9.0",
    "gn:admin2_code":"1206",
    "gn:admin3_code":"1206153",
    "gn:asciiname":"Tabora",
    "gn:country_code":"TZ",
    "gn:dem":1547,
    "gn:feature_class":"P",
    "gn:feature_code":"PPL",
    "gn:name":"Tabora",
    "gn:population":0,
    "gn:timezone":"Africa/Dar_es_Salaam",
    "iso:country":"TZ",
    "wof:name":"Tabora",
    "wof:placetype":"locality"
},
  "geometry": {"coordinates":[32.95,-9.03333],"type":"Point"}
}