{
  "type": "Feature",
  "properties": {
    "gn:admin1_code":"22.0",
    "gn:admin2_code":"5102",
    "gn:admin3_code":"5102121",
    "gn:asciiname":"Paiama",
    "gn:country_code":"TZ",
    "gn:dem":80,
    "gn:feature_class":"P",
    "gn:feature_code":"PPL",
    "gn:name":"Paiama",
    "gn:population":0,
    "gn:timezone":"Africa/Dar_es_Salaam",
    "iso:country":"TZ",
    "wof:name":"Paiama",
    "wof:placetype":"locality"
},
  "geometry": {"coordinates":[39.25,-5.93333],"type":"Point"}
}