{
  "type": "Feature",
  "properties": {
    "gn:admin1_code":"19.0",
    "gn:admin2_code":"1808",
    "gn:admin3_code":"1808101",
    "gn:asciiname":"Kimuli",
    "gn:country_code":"TZ",
    "gn:dem":1781,
    "gn:feature_class":"P",
    "gn:feature_code":"PPL",
    "gn:name":"Kimuli",
    "gn:population":0,
    "gn:timezone":"Africa/Dar_es_Salaam",
    "iso:country":"TZ",
    "wof:name":"Kimuli",
    "wof:placetype":"locality"
},
  "geometry": {"coordinates":[30.85861,-1.29056],"type":"Point"}
}