{
  "type": "Feature",
  "properties": {
    "gn:admin1_code":"18.0",
    "gn:admin2_code":"0401",
    "gn:admin3_code":"0401131",
    "gn:asciiname":"Kalange",
    "gn:country_code":"TZ",
    "gn:dem":1538,
    "gn:feature_class":"P",
    "gn:feature_code":"PPL",
    "gn:name":"Kalange",
    "gn:population":0,
    "gn:timezone":"Africa/Dar_es_Salaam",
    "iso:country":"TZ",
    "wof:name":"Kalange",
    "wof:placetype":"locality"
},
  "geometry": {"coordinates":[38.53333,-4.81667],"type":"Point"}
}