{
  "type": "Feature",
  "properties": {
    "gn:admin1_code":"18.0",
    "gn:asciiname":"Tangata",
    "gn:country_code":"TZ",
    "gn:dem":3,
    "gn:feature_class":"P",
    "gn:feature_code":"PPL",
    "gn:name":"Tangata",
    "gn:population":0,
    "gn:timezone":"Africa/Dar_es_Salaam",
    "iso:country":"TZ",
    "name:und_x_variant":[
        "Mtangata",
        "Tangata"
    ],
    "wof:name":"Tangata",
    "wof:placetype":"locality"
},
  "geometry": {"coordinates":[39.06667,-5.21667],"type":"Point"}
}