{
  "type": "Feature",
  "properties": {
    "gn:admin1_code":"8.0",
    "gn:admin2_code":"2002",
    "gn:admin3_code":"2002101",
    "gn:asciiname":"Nyabogati",
    "gn:country_code":"TZ",
    "gn:dem":1505,
    "gn:feature_class":"P",
    "gn:feature_code":"PPL",
    "gn:name":"Nyabogati",
    "gn:population":0,
    "gn:timezone":"Africa/Dar_es_Salaam",
    "iso:country":"TZ",
    "wof:name":"Nyabogati",
    "wof:placetype":"locality"
},
  "geometry": {"coordinates":[34.96667,-2.31667],"type":"Point"}
}