{
  "type": "Feature",
  "properties": {
    "iso:country":"TZ",
    "name:fra_x_preferred":[
        "Katogo"
    ],
    "name:msa_x_preferred":[
        "Katogo"
    ],
    "qs:gn_country":"TZ",
    "qs:gn_fcode":"PPL",
    "qs:gn_pop":11925,
    "qs:name":"Katoro",
    "qs:name_adm0":"Tanzania",
    "qs:name_adm1":"Kagera",
    "qs:photos":0,
    "qs:photos_1k":0,
    "qs:photos_9k":0,
    "qs:photos_9r":0,
    "qs:photos_all":0,
    "qs:photos_sr":0,
    "qs:placetype":"Town",
    "qs:pop_sr":"6",
    "qs:woe_adm0":23424973,
    "wd:wordcount":94,
    "wof:name":"Katoro",
    "wof:placetype":"locality",
    "wof:population":11925
},
  "geometry": {"coordinates":[31.50028,-1.39972],"type":"Point"}
}