{
  "type": "Feature",
  "properties": {
    "gn:admin1_code":"16.0",
    "gn:admin2_code":"1303",
    "gn:admin3_code":"1303291",
    "gn:asciiname":"Msalalo",
    "gn:country_code":"TZ",
    "gn:dem":1399,
    "gn:feature_class":"P",
    "gn:feature_code":"PPL",
    "gn:name":"Msalalo",
    "gn:population":0,
    "gn:timezone":"Africa/Dar_es_Salaam",
    "iso:country":"TZ",
    "wof:name":"Msalalo",
    "wof:placetype":"locality"
},
  "geometry": {"coordinates":[34.35,-5.93333],"type":"Point"}
}