{
  "type": "Feature",
  "properties": {
    "gn:admin1_code":"30.0",
    "gn:admin2_code":"2202",
    "gn:admin3_code":"2202131",
    "gn:asciiname":"Isome",
    "gn:country_code":"TZ",
    "gn:dem":2396,
    "gn:feature_class":"P",
    "gn:feature_code":"PPL",
    "gn:name":"Isome",
    "gn:population":0,
    "gn:timezone":"Africa/Dar_es_Salaam",
    "iso:country":"TZ",
    "wof:name":"Isome",
    "wof:placetype":"locality"
},
  "geometry": {"coordinates":[34.48333,-9.43333],"type":"Point"}
}