{
  "type": "Feature",
  "properties": {
    "gn:admin1_code":"19.0",
    "gn:admin2_code":"1802",
    "gn:admin3_code":"1802031",
    "gn:asciiname":"Kaagya",
    "gn:cc2":"TZ",
    "gn:country_code":"TZ",
    "gn:dem":1257,
    "gn:feature_class":"P",
    "gn:feature_code":"PPL",
    "gn:name":"Kaagya",
    "gn:population":0,
    "gn:timezone":"Africa/Dar_es_Salaam",
    "iso:country":"TZ",
    "name:und_x_variant":[
        "Kagya",
        "Kaagya"
    ],
    "wof:name":"Kaagya",
    "wof:placetype":"locality"
},
  "geometry": {"coordinates":[31.85861,-1.175],"type":"Point"}
}