{
  "type": "Feature",
  "properties": {
    "gn:admin1_code":"18.0",
    "gn:admin2_code":"0401",
    "gn:admin3_code":"0401383",
    "gn:asciiname":"Kiboma",
    "gn:country_code":"TZ",
    "gn:dem":1331,
    "gn:feature_class":"P",
    "gn:feature_code":"PPL",
    "gn:name":"Kiboma",
    "gn:population":0,
    "gn:timezone":"Africa/Dar_es_Salaam",
    "iso:country":"TZ",
    "wof:name":"Kiboma",
    "wof:placetype":"locality"
},
  "geometry": {"coordinates":[38.35,-4.58333],"type":"Point"}
}