{
  "type": "Feature",
  "properties": {
    "gn:admin1_code":"4.0",
    "gn:admin2_code":"1104",
    "gn:admin3_code":"1104183",
    "gn:asciiname":"Isere",
    "gn:country_code":"TZ",
    "gn:dem":1390,
    "gn:feature_class":"P",
    "gn:feature_code":"PPL",
    "gn:name":"Isere",
    "gn:population":0,
    "gn:timezone":"Africa/Dar_es_Salaam",
    "iso:country":"TZ",
    "name:eng_x_preferred":[
        "Isere"
    ],
    "wof:name":"Isere",
    "wof:placetype":"locality"
},
  "geometry": {"coordinates":[36.0304,-7.66721],"type":"Point"}
}