{
  "type": "Feature",
  "properties": {
    "gn:admin1_code":"30.0",
    "gn:asciiname":"Igawilo",
    "gn:country_code":"TZ",
    "gn:dem":1272,
    "gn:feature_class":"P",
    "gn:feature_code":"PPL",
    "gn:name":"Igawilo",
    "gn:population":0,
    "gn:timezone":"Africa/Dar_es_Salaam",
    "iso:country":"TZ",
    "name:ita_x_preferred":[
        "Igawilo"
    ],
    "name:swa_x_preferred":[
        "Igawilo"
    ],
    "wof:name":"Igawilo",
    "wof:placetype":"locality"
},
  "geometry": {"coordinates":[34.66667,-8.61667],"type":"Point"}
}