{
  "type": "Feature",
  "properties": {
    "gn:admin1_code":"2.0",
    "gn:admin2_code":"0605",
    "gn:admin3_code":"0605151",
    "gn:asciiname":"Pemba",
    "gn:country_code":"TZ",
    "gn:dem":6,
    "gn:feature_class":"P",
    "gn:feature_code":"PPLL",
    "gn:name":"Pemba",
    "gn:population":0,
    "gn:timezone":"Africa/Dar_es_Salaam",
    "iso:country":"TZ",
    "name:cat_x_preferred":[
        "Pemba"
    ],
    "name:ceb_x_preferred":[
        "Pemba"
    ],
    "name:ces_x_preferred":[
        "Pemba"
    ],
    "name:dan_x_preferred":[
        "Pemba"
    ],
    "name:deu_x_preferred":[
        "Pemba"
    ],
    "name:ell_x_preferred":[
        "\u03a0\u03ad\u03bc\u03c0\u03b1"
    ],
    "name:epo_x_preferred":[
        "Pemba"
    ],
    "name:eus_x_preferred":[
        "Pemba"
    ],
    "name:fin_x_preferred":[
        "Pemba"
    ],
    "name:fra_x_preferred":[
        "Pemba"
    ],
    "name:ita_x_preferred":[
        "Pemba"
    ],
    "name:jpn_x_preferred":[
        "\u30da\u30f3\u30d0"
    ],
    "name:nld_x_preferred":[
        "Pemba"
    ],
    "name:nor_x_preferred":[
        "Pemba"
    ],
    "name:pol_x_preferred":[
        "Pemba"
    ],
    "name:rus_x_preferred":[
        "\u041f\u0435\u043c\u0431\u0430"
    ],
    "name:spa_x_preferred":[
        "Pemba"
    ],
    "name:swa_x_preferred":[
        "Pemba"
    ],
    "name:swe_x_preferred":[
        "Pemba"
    ],
    "name:tur_x_preferred":[
        "Pemba"
    ],
    "name:ukr_x_preferred":[
        "\u041f\u0435\u043c\u0431\u0430"
    ],
    "wof:name":"Pemba",
    "wof:placetype":"locality"
},
  "geometry": {"coordinates":[39.23934000000001,-7.80495],"type":"Point"}
}