{
  "type": "Feature",
  "properties": {
    "gn:admin1_code":"5.0",
    "gn:admin2_code":"1605",
    "gn:admin3_code":"1605111",
    "gn:asciiname":"Mfumo",
    "gn:country_code":"TZ",
    "gn:dem":1058,
    "gn:feature_class":"P",
    "gn:feature_code":"PPL",
    "gn:name":"Mfumo",
    "gn:population":0,
    "gn:timezone":"Africa/Dar_es_Salaam",
    "iso:country":"TZ",
    "wof:name":"Mfumo",
    "wof:placetype":"locality"
},
  "geometry": {"coordinates":[30.98333,-4.98333],"type":"Point"}
}