{
  "type": "Feature",
  "properties": {
    "gn:admin1_code":"18.0",
    "gn:admin2_code":"0406",
    "gn:admin3_code":"0406161",
    "gn:asciiname":"Kwedichele",
    "gn:country_code":"TZ",
    "gn:dem":286,
    "gn:feature_class":"P",
    "gn:feature_code":"PPL",
    "gn:name":"Kwedichele",
    "gn:population":0,
    "gn:timezone":"Africa/Dar_es_Salaam",
    "iso:country":"TZ",
    "name:und_x_variant":[
        "Kwadicheri",
        "Kwedichele"
    ],
    "wof:name":"Kwedichele",
    "wof:placetype":"locality"
},
  "geometry": {"coordinates":[38.56667,-5.66667],"type":"Point"}
}