{
  "type": "Feature",
  "properties": {
    "gn:admin1_code":"10.0",
    "gn:admin2_code":"0506",
    "gn:admin3_code":"0506131",
    "gn:asciiname":"Kisomo",
    "gn:country_code":"TZ",
    "gn:dem":1710,
    "gn:feature_class":"P",
    "gn:feature_code":"PPL",
    "gn:name":"Kisomo",
    "gn:population":0,
    "gn:timezone":"Africa/Dar_es_Salaam",
    "iso:country":"TZ",
    "wof:name":"Kisomo",
    "wof:placetype":"locality"
},
  "geometry": {"coordinates":[37.58333,-7.08333],"type":"Point"}
}