{
  "type": "Feature",
  "properties": {
    "gn:admin1_code":"5.0",
    "gn:admin2_code":"1605",
    "gn:admin3_code":"1605021",
    "gn:asciiname":"Itwalele",
    "gn:country_code":"TZ",
    "gn:dem":1022,
    "gn:feature_class":"P",
    "gn:feature_code":"PPL",
    "gn:name":"Itwalele",
    "gn:population":0,
    "gn:timezone":"Africa/Dar_es_Salaam",
    "iso:country":"TZ",
    "name:eng_x_preferred":[
        "Itwalele"
    ],
    "wof:name":"Itwalele",
    "wof:placetype":"locality"
},
  "geometry": {"coordinates":[29.95169000000001,-6.35385],"type":"Point"}
}