{
  "type": "Feature",
  "properties": {
    "gn:admin1_code":"13.0",
    "gn:admin2_code":"5401",
    "gn:admin3_code":"5401322",
    "gn:asciiname":"Mwangala",
    "gn:country_code":"TZ",
    "gn:dem":23,
    "gn:feature_class":"P",
    "gn:feature_code":"PPL",
    "gn:name":"Mwangala",
    "gn:population":0,
    "gn:timezone":"Africa/Dar_es_Salaam",
    "iso:country":"TZ",
    "wof:name":"Mwangala",
    "wof:placetype":"locality"
},
  "geometry": {"coordinates":[39.73333,-5.06667],"type":"Point"}
}