{
  "type": "Feature",
  "properties": {
    "gn:admin1_code":"22.0",
    "gn:admin2_code":"5101",
    "gn:admin3_code":"5101171",
    "gn:asciiname":"Kongeni",
    "gn:country_code":"TZ",
    "gn:dem":47,
    "gn:feature_class":"P",
    "gn:feature_code":"PPL",
    "gn:name":"Kongeni",
    "gn:population":0,
    "gn:timezone":"Africa/Dar_es_Salaam",
    "iso:country":"TZ",
    "name:und_x_variant":[
        "Kilina Kongeni",
        "Kongeni"
    ],
    "wof:name":"Kongeni",
    "wof:placetype":"locality"
},
  "geometry": {"coordinates":[39.33333,-5.88333],"type":"Point"}
}