{
  "type": "Feature",
  "properties": {
    "gn:admin1_code":"21.0",
    "gn:admin2_code":"5201",
    "gn:admin3_code":"5201161",
    "gn:asciiname":"Umbuji",
    "gn:country_code":"TZ",
    "gn:dem":42,
    "gn:feature_class":"P",
    "gn:feature_code":"PPL",
    "gn:name":"Umbuji",
    "gn:population":0,
    "gn:timezone":"Africa/Dar_es_Salaam",
    "iso:country":"TZ",
    "name:und_x_variant":[
        "Umbuyi",
        "Umbuji"
    ],
    "wof:name":"Umbuji",
    "wof:placetype":"locality"
},
  "geometry": {"coordinates":[39.36667,-6.11667],"type":"Point"}
}