{
  "type": "Feature",
  "properties": {
    "gn:admin1_code":"10.0",
    "gn:admin2_code":"0504",
    "gn:admin3_code":"0504211",
    "gn:asciiname":"Kotakota",
    "gn:country_code":"TZ",
    "gn:dem":266,
    "gn:feature_class":"P",
    "gn:feature_code":"PPL",
    "gn:name":"Kotakota",
    "gn:population":0,
    "gn:timezone":"Africa/Dar_es_Salaam",
    "iso:country":"TZ",
    "wof:name":"Kotakota",
    "wof:placetype":"locality"
},
  "geometry": {"coordinates":[36.21667,-8.68333],"type":"Point"}
}