{
  "type": "Feature",
  "properties": {
    "gn:admin1_code":"8.0",
    "gn:admin2_code":"2004",
    "gn:admin3_code":"2004101",
    "gn:asciiname":"Guta",
    "gn:country_code":"TZ",
    "gn:dem":1153,
    "gn:feature_class":"P",
    "gn:feature_code":"PPL",
    "gn:name":"Guta",
    "gn:population":0,
    "gn:timezone":"Africa/Dar_es_Salaam",
    "iso:country":"TZ",
    "name:bul_x_preferred":[
        "\u0413\u0443\u0442\u0430"
    ],
    "name:ceb_x_preferred":[
        "Guta"
    ],
    "name:deu_x_preferred":[
        "Guta"
    ],
    "name:ita_x_preferred":[
        "Guta"
    ],
    "name:lav_x_preferred":[
        "Guta"
    ],
    "name:rus_x_preferred":[
        "\u0413\u0443\u0442\u0430"
    ],
    "name:slk_x_preferred":[
        "Guta"
    ],
    "name:spa_x_preferred":[
        "Guta"
    ],
    "wof:name":"Guta",
    "wof:placetype":"locality"
},
  "geometry": {"coordinates":[33.71667,-2.08333],"type":"Point"}
}