{
  "type": "Feature",
  "properties": {
    "gn:admin1_code":"22.0",
    "gn:asciiname":"Kichwele",
    "gn:country_code":"TZ",
    "gn:dem":56,
    "gn:feature_class":"P",
    "gn:feature_code":"PPL",
    "gn:name":"Kichwele",
    "gn:population":0,
    "gn:timezone":"Africa/Dar_es_Salaam",
    "iso:country":"TZ",
    "wof:name":"Kichwele",
    "wof:placetype":"locality"
},
  "geometry": {"coordinates":[39.26667,-6.03333],"type":"Point"}
}