{
  "type": "Feature",
  "properties": {
    "gn:admin1_code":"18.0",
    "gn:admin2_code":"0402",
    "gn:admin3_code":"0402021",
    "gn:asciiname":"Bombo",
    "gn:country_code":"TZ",
    "gn:dem":439,
    "gn:feature_class":"P",
    "gn:feature_code":"PPL",
    "gn:name":"Bombo",
    "gn:population":0,
    "gn:timezone":"Africa/Dar_es_Salaam",
    "iso:country":"TZ",
    "name:ben_x_preferred":[
        "\u09ac\u09cb\u09ae\u09cd\u09ac\u09cb"
    ],
    "name:ceb_x_preferred":[
        "Bombo"
    ],
    "name:deu_x_preferred":[
        "Bombo"
    ],
    "name:ell_x_preferred":[
        "\u039c\u03c0\u03cc\u03bc\u03c0\u03bf"
    ],
    "name:fas_x_preferred":[
        "\u0628\u0645\u0628\u0648"
    ],
    "name:fra_x_preferred":[
        "Bombo"
    ],
    "name:heb_x_preferred":[
        "\u05d1\u05d5\u05de\u05d1\u05d5"
    ],
    "name:hin_x_preferred":[
        "\u092c\u0949\u092e\u094d\u092c\u094b"
    ],
    "name:hun_x_preferred":[
        "Bombo"
    ],
    "name:ind_x_preferred":[
        "Bombo"
    ],
    "name:ita_x_preferred":[
        "Bombo"
    ],
    "name:kor_x_preferred":[
        "\ubd04\ubcf4"
    ],
    "name:lug_x_preferred":[
        "Bombo"
    ],
    "name:nld_x_preferred":[
        "Bombo"
    ],
    "name:pol_x_preferred":[
        "Bombo"
    ],
    "name:spa_x_preferred":[
        "Bombo"
    ],
    "name:swe_x_preferred":[
        "Bombo"
    ],
    "name:tur_x_preferred":[
        "Bombo"
    ],
    "name:ukr_x_preferred":[
        "\u0411\u043e\u043c\u0431\u043e"
    ],
    "name:vie_x_preferred":[
        "Bombo"
    ],
    "name:zho_cn_x_preferred":[
        "\u90a6\u535a"
    ],
    "name:zho_tw_x_preferred":[
        "\u90a6\u535a"
    ],
    "wof:name":"Bombo",
    "wof:placetype":"locality"
},
  "geometry": {"coordinates":[38.68333,-4.85],"type":"Point"}
}