{
  "type": "Feature",
  "properties": {
    "gn:admin1_code":"2.0",
    "gn:admin2_code":"0606",
    "gn:admin3_code":"0606061",
    "gn:asciiname":"Kitemondo",
    "gn:country_code":"TZ",
    "gn:dem":19,
    "gn:feature_class":"P",
    "gn:feature_code":"PPL",
    "gn:name":"Kitemondo",
    "gn:population":0,
    "gn:timezone":"Africa/Dar_es_Salaam",
    "iso:country":"TZ",
    "name:eng_x_preferred":[
        "Kitemondo"
    ],
    "wof:name":"Kitemondo",
    "wof:placetype":"locality"
},
  "geometry": {"coordinates":[39.6849,-7.92591],"type":"Point"}
}