{
  "type": "Feature",
  "properties": {
    "gn:admin1_code":"18.0",
    "gn:admin2_code":"0404",
    "gn:admin3_code":"0404151",
    "gn:asciiname":"Katipeni",
    "gn:country_code":"TZ",
    "gn:dem":60,
    "gn:feature_class":"P",
    "gn:feature_code":"PPL",
    "gn:name":"Katipeni",
    "gn:population":0,
    "gn:timezone":"Africa/Dar_es_Salaam",
    "iso:country":"TZ",
    "name:und_x_variant":[
        "Katopeni",
        "Katipeni"
    ],
    "wof:name":"Katipeni",
    "wof:placetype":"locality"
},
  "geometry": {"coordinates":[39.05,-5.18333],"type":"Point"}
}