{
  "type": "Feature",
  "properties": {
    "gn:admin1_code":"21.0",
    "gn:admin2_code":"5201",
    "gn:admin3_code":"5201201",
    "gn:asciiname":"Panga Pemba",
    "gn:country_code":"TZ",
    "gn:dem":22,
    "gn:feature_class":"P",
    "gn:feature_code":"PPL",
    "gn:name":"Panga Pemba",
    "gn:population":0,
    "gn:timezone":"Africa/Dar_es_Salaam",
    "iso:country":"TZ",
    "wof:name":"Panga Pemba",
    "wof:placetype":"locality"
},
  "geometry": {"coordinates":[39.36667,-6.18333],"type":"Point"}
}