{
  "type": "Feature",
  "properties": {
    "gn:admin1_code":"29.0",
    "gn:asciiname":"Tumba",
    "gn:country_code":"TZ",
    "gn:dem":801,
    "gn:feature_class":"P",
    "gn:feature_code":"PPL",
    "gn:name":"Tumba",
    "gn:population":0,
    "gn:timezone":"Africa/Dar_es_Salaam",
    "iso:country":"TZ",
    "name:ceb_x_preferred":[
        "Tumba"
    ],
    "name:ces_x_preferred":[
        "Tumba"
    ],
    "name:deu_x_preferred":[
        "Tumba"
    ],
    "name:fin_x_preferred":[
        "Tumba"
    ],
    "name:fra_x_preferred":[
        "Tumba"
    ],
    "name:hrv_x_preferred":[
        "Tumba"
    ],
    "name:ita_x_preferred":[
        "Tumba"
    ],
    "name:lat_x_preferred":[
        "Tumba"
    ],
    "name:lav_x_preferred":[
        "Tumba"
    ],
    "name:nld_x_preferred":[
        "Tumba"
    ],
    "name:pol_x_preferred":[
        "Tumba"
    ],
    "name:slk_x_preferred":[
        "Tumba"
    ],
    "name:swe_x_preferred":[
        "Tumba"
    ],
    "wof:name":"Tumba",
    "wof:placetype":"locality"
},
  "geometry": {"coordinates":[31.66667,-7.51667],"type":"Point"}
}