{
  "type": "Feature",
  "properties": {
    "gn:admin1_code":"5.0",
    "gn:admin2_code":"1602",
    "gn:admin3_code":"1602091",
    "gn:asciiname":"Bugigero",
    "gn:country_code":"TZ",
    "gn:dem":1148,
    "gn:feature_class":"P",
    "gn:feature_code":"PPL",
    "gn:name":"Bugigero",
    "gn:population":0,
    "gn:timezone":"Africa/Dar_es_Salaam",
    "iso:country":"TZ",
    "wof:name":"Bugigero",
    "wof:placetype":"locality"
},
  "geometry": {"coordinates":[30.49556,-4.35306],"type":"Point"}
}