{
  "type": "Feature",
  "properties": {
    "gn:admin1_code":"8.0",
    "gn:admin2_code":"2003",
    "gn:admin3_code":"2003081",
    "gn:asciiname":"Mrangi",
    "gn:country_code":"TZ",
    "gn:dem":1134,
    "gn:feature_class":"P",
    "gn:feature_code":"PPL",
    "gn:name":"Mrangi",
    "gn:population":0,
    "gn:timezone":"Africa/Dar_es_Salaam",
    "iso:country":"TZ",
    "wof:name":"Mrangi",
    "wof:placetype":"locality"
},
  "geometry": {"coordinates":[33.51667,-1.83333],"type":"Point"}
}