{
  "type": "Feature",
  "properties": {
    "gn:admin1_code":"31.0",
    "gn:admin2_code":"2404",
    "gn:admin3_code":"2404131",
    "gn:asciiname":"Likenejo",
    "gn:country_code":"TZ",
    "gn:dem":1210,
    "gn:feature_class":"P",
    "gn:feature_code":"PPL",
    "gn:name":"Likenejo",
    "gn:population":0,
    "gn:timezone":"Africa/Dar_es_Salaam",
    "iso:country":"TZ",
    "wof:name":"Likenejo",
    "wof:placetype":"locality"
},
  "geometry": {"coordinates":[33.65,-3.36667],"type":"Point"}
}