{
  "type": "Feature",
  "properties": {
    "gn:admin1_code":"17.0",
    "gn:admin2_code":"1401",
    "gn:admin3_code":"1401211",
    "gn:asciiname":"Mingire",
    "gn:country_code":"TZ",
    "gn:dem":1203,
    "gn:feature_class":"P",
    "gn:feature_code":"PPL",
    "gn:name":"Mingire",
    "gn:population":0,
    "gn:timezone":"Africa/Dar_es_Salaam",
    "iso:country":"TZ",
    "wof:name":"Mingire",
    "wof:placetype":"locality"
},
  "geometry": {"coordinates":[33.03333,-4.35],"type":"Point"}
}