{
  "type": "Feature",
  "properties": {
    "gn:admin1_code":"5.0",
    "gn:admin2_code":"1608",
    "gn:admin3_code":"1608091",
    "gn:asciiname":"Heru Juu",
    "gn:country_code":"TZ",
    "gn:dem":1607,
    "gn:feature_class":"P",
    "gn:feature_code":"PPL",
    "gn:name":"Heru Juu",
    "gn:population":0,
    "gn:timezone":"Africa/Dar_es_Salaam",
    "iso:country":"TZ",
    "wof:name":"Heru Juu",
    "wof:placetype":"locality"
},
  "geometry": {"coordinates":[30.06167,-4.5325],"type":"Point"}
}