{
  "type": "Feature",
  "properties": {
    "gn:admin1_code":"10.0",
    "gn:asciiname":"Boma ya Lindi",
    "gn:country_code":"TZ",
    "gn:dem":586,
    "gn:feature_class":"P",
    "gn:feature_code":"PPL",
    "gn:name":"Boma ya Lindi",
    "gn:population":0,
    "gn:timezone":"Africa/Dar_es_Salaam",
    "iso:country":"TZ",
    "wof:name":"Boma ya Lindi",
    "wof:placetype":"locality"
},
  "geometry": {"coordinates":[35.66667,-9.26667],"type":"Point"}
}