{
  "type": "Feature",
  "properties": {
    "gn:admin1_code":"23.0",
    "gn:admin2_code":"0703",
    "gn:admin3_code":"0703142",
    "gn:asciiname":"Mtoni",
    "gn:country_code":"TZ",
    "gn:dem":34,
    "gn:feature_class":"P",
    "gn:feature_code":"PPL",
    "gn:name":"Mtoni",
    "gn:population":0,
    "gn:timezone":"Africa/Dar_es_Salaam",
    "iso:country":"TZ",
    "name:ceb_x_preferred":[
        "Mtoni"
    ],
    "name:swe_x_preferred":[
        "Mtoni"
    ],
    "wof:name":"Mtoni",
    "wof:placetype":"locality"
},
  "geometry": {"coordinates":[39.26667,-6.86667],"type":"Point"}
}