{
  "type": "Feature",
  "properties": {
    "gn:admin1_code":"18.0",
    "gn:admin2_code":"0401",
    "gn:admin3_code":"0401141",
    "gn:asciiname":"Baga",
    "gn:country_code":"TZ",
    "gn:dem":1476,
    "gn:feature_class":"P",
    "gn:feature_code":"PPL",
    "gn:name":"Baga",
    "gn:population":0,
    "gn:timezone":"Africa/Dar_es_Salaam",
    "iso:country":"TZ",
    "name:ceb_x_preferred":[
        "Baga"
    ],
    "name:deu_x_preferred":[
        "Baga"
    ],
    "name:eus_x_preferred":[
        "Baga"
    ],
    "name:fao_x_preferred":[
        "Baga"
    ],
    "name:fra_x_preferred":[
        "Baga"
    ],
    "name:hye_x_preferred":[
        "\u0532\u0561\u0563\u0561"
    ],
    "name:ita_x_preferred":[
        "Baga"
    ],
    "name:kat_x_preferred":[
        "\u10d1\u10d0\u10d2\u10d0"
    ],
    "name:nld_x_preferred":[
        "Baga"
    ],
    "name:por_x_preferred":[
        "Baga"
    ],
    "name:rus_x_preferred":[
        "\u0411\u0430\u0433\u0430"
    ],
    "name:swe_x_preferred":[
        "Baga"
    ],
    "name:tgl_x_preferred":[
        "Baga"
    ],
    "name:ukr_x_preferred":[
        "\u0411\u0430\u0433\u0430"
    ],
    "wof:name":"Baga",
    "wof:placetype":"locality"
},
  "geometry": {"coordinates":[38.41667,-4.78333],"type":"Point"}
}