{
  "type": "Feature",
  "properties": {
    "gn:admin1_code":"19.0",
    "gn:admin2_code":"1801",
    "gn:admin3_code":"1801073",
    "gn:asciiname":"Nyakasana",
    "gn:country_code":"TZ",
    "gn:dem":1633,
    "gn:feature_class":"P",
    "gn:feature_code":"PPL",
    "gn:name":"Nyakasana",
    "gn:population":0,
    "gn:timezone":"Africa/Dar_es_Salaam",
    "iso:country":"TZ",
    "wof:name":"Nyakasana",
    "wof:placetype":"locality"
},
  "geometry": {"coordinates":[31.14778,-1.58194],"type":"Point"}
}