{
  "type": "Feature",
  "properties": {
    "gn:admin1_code":"8.0",
    "gn:asciiname":"Bukondo",
    "gn:country_code":"TZ",
    "gn:dem":1134,
    "gn:feature_class":"P",
    "gn:feature_code":"PPL",
    "gn:name":"Bukondo",
    "gn:population":0,
    "gn:timezone":"Africa/Dar_es_Salaam",
    "iso:country":"TZ",
    "wof:name":"Bukondo",
    "wof:placetype":"locality"
},
  "geometry": {"coordinates":[33.03333,-2.11667],"type":"Point"}
}