{
  "type": "Feature",
  "properties": {
    "gn:admin1_code":"26.0",
    "gn:admin2_code":"0207",
    "gn:admin3_code":"0207141",
    "gn:asciiname":"Sinya",
    "gn:country_code":"TZ",
    "gn:dem":1135,
    "gn:feature_class":"P",
    "gn:feature_code":"PPL",
    "gn:name":"Sinya",
    "gn:population":0,
    "gn:timezone":"Africa/Dar_es_Salaam",
    "iso:country":"TZ",
    "wof:name":"Sinya",
    "wof:placetype":"locality"
},
  "geometry": {"coordinates":[37.03333,-2.78333],"type":"Point"}
}