{
  "type": "Feature",
  "properties": {
    "gn:admin1_code":"3.0",
    "gn:admin2_code":"0106",
    "gn:admin3_code":"0106171",
    "gn:asciiname":"Mapanga",
    "gn:country_code":"TZ",
    "gn:dem":1055,
    "gn:feature_class":"P",
    "gn:feature_code":"PPL",
    "gn:name":"Mapanga",
    "gn:population":0,
    "gn:timezone":"Africa/Dar_es_Salaam",
    "iso:country":"TZ",
    "wof:name":"Mapanga",
    "wof:placetype":"locality"
},
  "geometry": {"coordinates":[35.55,-6.33333],"type":"Point"}
}