{
  "type": "Feature",
  "properties": {
    "gn:admin1_code":"12.0",
    "gn:admin2_code":"1902",
    "gn:admin3_code":"1902013",
    "gn:asciiname":"Kisesa",
    "gn:country_code":"TZ",
    "gn:dem":1306,
    "gn:feature_class":"P",
    "gn:feature_code":"PPL",
    "gn:name":"Kisesa",
    "gn:population":0,
    "gn:timezone":"Africa/Dar_es_Salaam",
    "iso:country":"TZ",
    "name:und_x_variant":[
        "Kissessa",
        "Kisesi",
        "Kisesa",
        "Kisessa"
    ],
    "wof:name":"Kisesa",
    "wof:placetype":"locality"
},
  "geometry": {"coordinates":[33.03333,-2.55],"type":"Point"}
}