{
  "type": "Feature",
  "properties": {
    "gn:admin1_code":"19.0",
    "gn:admin2_code":"1802",
    "gn:admin3_code":"1802011",
    "gn:asciiname":"Rubafu",
    "gn:cc2":"TZ",
    "gn:country_code":"TZ",
    "gn:dem":1200,
    "gn:feature_class":"P",
    "gn:feature_code":"PPL",
    "gn:name":"Rubafu",
    "gn:population":0,
    "gn:timezone":"Africa/Dar_es_Salaam",
    "iso:country":"TZ",
    "name:und_x_variant":[
        "Duwafu",
        "Rubafu"
    ],
    "wof:name":"Rubafu",
    "wof:placetype":"locality"
},
  "geometry": {"coordinates":[31.83222,-1.05056],"type":"Point"}
}