{
  "type": "Feature",
  "properties": {
    "gn:admin1_code":"18.0",
    "gn:admin2_code":"0408",
    "gn:admin3_code":"0408081",
    "gn:asciiname":"Yirihini",
    "gn:country_code":"TZ",
    "gn:dem":133,
    "gn:feature_class":"P",
    "gn:feature_code":"PPL",
    "gn:name":"Yirihini",
    "gn:population":0,
    "gn:timezone":"Africa/Dar_es_Salaam",
    "iso:country":"TZ",
    "name:und_x_variant":[
        "Yarahini",
        "Yirihini"
    ],
    "wof:name":"Yirihini",
    "wof:placetype":"locality"
},
  "geometry": {"coordinates":[38.91667,-4.95],"type":"Point"}
}