{
  "type": "Feature",
  "properties": {
    "gn:admin1_code":"19.0",
    "gn:admin2_code":"1804",
    "gn:admin3_code":"1804151",
    "gn:asciiname":"Kahafe",
    "gn:country_code":"TZ",
    "gn:dem":1333,
    "gn:feature_class":"P",
    "gn:feature_code":"PPL",
    "gn:name":"Kahafe",
    "gn:population":0,
    "gn:timezone":"Africa/Dar_es_Salaam",
    "iso:country":"TZ",
    "wof:name":"Kahafe",
    "wof:placetype":"locality"
},
  "geometry": {"coordinates":[31.16667,-3.06667],"type":"Point"}
}