{
  "type": "Feature",
  "properties": {
    "gn:admin1_code":"16.0",
    "gn:admin2_code":"1305",
    "gn:admin3_code":"1305241",
    "gn:asciiname":"Ndaiheya",
    "gn:country_code":"TZ",
    "gn:dem":1535,
    "gn:feature_class":"P",
    "gn:feature_code":"PPL",
    "gn:name":"Ndaiheya",
    "gn:population":0,
    "gn:timezone":"Africa/Dar_es_Salaam",
    "iso:country":"TZ",
    "wof:name":"Ndaiheya",
    "wof:placetype":"locality"
},
  "geometry": {"coordinates":[34.58333,-4.81667],"type":"Point"}
}