{
  "type": "Feature",
  "properties": {
    "gn:admin1_code":"14.0",
    "gn:admin2_code":"1001",
    "gn:admin3_code":"1001121",
    "gn:asciiname":"Chinunje",
    "gn:country_code":"TZ",
    "gn:dem":476,
    "gn:feature_class":"P",
    "gn:feature_code":"PPL",
    "gn:name":"Chinunje",
    "gn:population":0,
    "gn:timezone":"Africa/Dar_es_Salaam",
    "iso:country":"TZ",
    "wof:name":"Chinunje",
    "wof:placetype":"locality"
},
  "geometry": {"coordinates":[37.31667,-11.31667],"type":"Point"}
}