{
  "type": "Feature",
  "properties": {
    "gn:admin1_code":"4.0",
    "gn:admin2_code":"1102",
    "gn:admin3_code":"1102031",
    "gn:asciiname":"Kibau",
    "gn:country_code":"TZ",
    "gn:dem":1949,
    "gn:feature_class":"P",
    "gn:feature_code":"PPL",
    "gn:name":"Kibau",
    "gn:population":0,
    "gn:timezone":"Africa/Dar_es_Salaam",
    "iso:country":"TZ",
    "wof:name":"Kibau",
    "wof:placetype":"locality"
},
  "geometry": {"coordinates":[35.28333,-8.58333],"type":"Point"}
}