{
  "type": "Feature",
  "properties": {
    "gn:admin1_code":"30.0",
    "gn:admin2_code":"2201",
    "gn:admin3_code":"2201091",
    "gn:asciiname":"Lugenge/Madobole",
    "gn:country_code":"TZ",
    "gn:dem":2204,
    "gn:feature_class":"P",
    "gn:feature_code":"PPL",
    "gn:name":"Lugenge/Madobole",
    "gn:population":0,
    "gn:timezone":"Africa/Dar_es_Salaam",
    "iso:country":"TZ",
    "wof:name":"Lugenge/Madobole",
    "wof:placetype":"locality"
},
  "geometry": {"coordinates":[34.64315,-9.55149],"type":"Point"}
}