{
  "type": "Feature",
  "properties": {
    "gn:admin1_code":"6.0",
    "gn:admin2_code":"0305",
    "gn:admin3_code":"0305083",
    "gn:asciiname":"Kware",
    "gn:country_code":"TZ",
    "gn:dem":1017,
    "gn:feature_class":"P",
    "gn:feature_code":"PPL",
    "gn:name":"Kware",
    "gn:population":0,
    "gn:timezone":"Africa/Dar_es_Salaam",
    "iso:country":"TZ",
    "name:fra_x_preferred":[
        "Kware"
    ],
    "name:hau_x_preferred":[
        "Kware"
    ],
    "name:ita_x_preferred":[
        "Kware"
    ],
    "name:por_x_preferred":[
        "Kware"
    ],
    "name:spa_x_preferred":[
        "Kware"
    ],
    "wof:name":"Kware",
    "wof:placetype":"locality"
},
  "geometry": {"coordinates":[37.15,-3.28333],"type":"Point"}
}