{
  "type": "Feature",
  "properties": {
    "gn:admin1_code":"6.0",
    "gn:admin2_code":"0303",
    "gn:admin3_code":"0303233",
    "gn:asciiname":"Makanya",
    "gn:country_code":"TZ",
    "gn:dem":718,
    "gn:feature_class":"P",
    "gn:feature_code":"PPL",
    "gn:name":"Makanya",
    "gn:population":0,
    "gn:timezone":"Africa/Dar_es_Salaam",
    "iso:country":"TZ",
    "name:und_x_variant":[
        "Makania",
        "Makanya"
    ],
    "wof:name":"Makanya",
    "wof:placetype":"locality"
},
  "geometry": {"coordinates":[37.85,-4.33333],"type":"Point"}
}