{
  "type": "Feature",
  "properties": {
    "gn:admin1_code":"20.0",
    "gn:admin2_code":"5502",
    "gn:admin3_code":"5502133",
    "gn:asciiname":"Kisiwani",
    "gn:country_code":"TZ",
    "gn:dem":61,
    "gn:feature_class":"P",
    "gn:feature_code":"PPL",
    "gn:name":"Kisiwani",
    "gn:population":0,
    "gn:timezone":"Africa/Dar_es_Salaam",
    "iso:country":"TZ",
    "name:und_x_variant":[
        "Kieiwani",
        "Kisiwani"
    ],
    "wof:name":"Kisiwani",
    "wof:placetype":"locality"
},
  "geometry": {"coordinates":[39.68333,-5.38333],"type":"Point"}
}