{
  "type": "Feature",
  "properties": {
    "gn:admin1_code":"19.0",
    "gn:admin2_code":"1801",
    "gn:admin3_code":"1801161",
    "gn:asciiname":"Burangare",
    "gn:country_code":"TZ",
    "gn:dem":1286,
    "gn:feature_class":"P",
    "gn:feature_code":"PPL",
    "gn:name":"Burangare",
    "gn:population":0,
    "gn:timezone":"Africa/Dar_es_Salaam",
    "iso:country":"TZ",
    "name:und_x_variant":[
        "Buragara",
        "Burangare"
    ],
    "wof:name":"Burangare",
    "wof:placetype":"locality"
},
  "geometry": {"coordinates":[30.83333,-1.73333],"type":"Point"}
}