{
  "type": "Feature",
  "properties": {
    "gn:admin1_code":"14.0",
    "gn:asciiname":"Mkiri",
    "gn:country_code":"TZ",
    "gn:dem":476,
    "gn:feature_class":"P",
    "gn:feature_code":"PPL",
    "gn:name":"Mkiri",
    "gn:population":0,
    "gn:timezone":"Africa/Dar_es_Salaam",
    "iso:country":"TZ",
    "wof:name":"Mkiri",
    "wof:placetype":"locality"
},
  "geometry": {"coordinates":[34.66667,-10.85],"type":"Point"}
}