{
  "type": "Feature",
  "properties": {
    "gn:admin1_code":"5.0",
    "gn:admin2_code":"1606",
    "gn:admin3_code":"1606031",
    "gn:asciiname":"Nyabasenga",
    "gn:country_code":"TZ",
    "gn:dem":1331,
    "gn:feature_class":"P",
    "gn:feature_code":"PPL",
    "gn:name":"Nyabasenga",
    "gn:population":0,
    "gn:timezone":"Africa/Dar_es_Salaam",
    "iso:country":"TZ",
    "wof:name":"Nyabasenga",
    "wof:placetype":"locality"
},
  "geometry": {"coordinates":[30.05361,-4.3275],"type":"Point"}
}