{
  "type": "Feature",
  "properties": {
    "gn:admin1_code":"10.0",
    "gn:admin2_code":"0504",
    "gn:admin3_code":"0504071",
    "gn:asciiname":"Kitonga",
    "gn:country_code":"TZ",
    "gn:dem":1024,
    "gn:feature_class":"P",
    "gn:feature_code":"PPL",
    "gn:name":"Kitonga",
    "gn:population":0,
    "gn:timezone":"Africa/Dar_es_Salaam",
    "iso:country":"TZ",
    "wof:name":"Kitonga",
    "wof:placetype":"locality"
},
  "geometry": {"coordinates":[36.68333,-8.73333],"type":"Point"}
}