{
  "type": "Feature",
  "properties": {
    "gn:admin1_code":"18.0",
    "gn:admin2_code":"0402",
    "gn:admin3_code":"0402191",
    "gn:asciiname":"Kwaluma",
    "gn:country_code":"TZ",
    "gn:dem":444,
    "gn:feature_class":"P",
    "gn:feature_code":"PPL",
    "gn:name":"Kwaluma",
    "gn:population":0,
    "gn:timezone":"Africa/Dar_es_Salaam",
    "iso:country":"TZ",
    "wof:name":"Kwaluma",
    "wof:placetype":"locality"
},
  "geometry": {"coordinates":[38.25,-5.11667],"type":"Point"}
}