{
  "type": "Feature",
  "properties": {
    "gn:admin1_code":"11.0",
    "gn:admin2_code":"0907",
    "gn:admin3_code":"0907013",
    "gn:asciiname":"Ngaga",
    "gn:country_code":"TZ",
    "gn:dem":388,
    "gn:feature_class":"P",
    "gn:feature_code":"PPL",
    "gn:name":"Ngaga",
    "gn:population":0,
    "gn:timezone":"Africa/Dar_es_Salaam",
    "iso:country":"TZ",
    "name:und_x_variant":[
        "Nagaga",
        "Ngaga"
    ],
    "wof:name":"Ngaga",
    "wof:placetype":"locality"
},
  "geometry": {"coordinates":[38.75,-10.75],"type":"Point"}
}