{
  "type": "Feature",
  "properties": {
    "iso:country":"TZ",
    "qs:gn_country":"TZ",
    "qs:gn_fcode":"PPL",
    "qs:gn_pop":14080,
    "qs:name":"Dunda",
    "qs:name_adm0":"Tanzania",
    "qs:name_adm1":"Mbeya",
    "qs:photos":0,
    "qs:photos_1k":0,
    "qs:photos_9k":0,
    "qs:photos_9r":0,
    "qs:photos_all":0,
    "qs:photos_sr":0,
    "qs:placetype":"Town",
    "qs:pop_sr":"6",
    "qs:woe_adm0":23424973,
    "wof:name":"Dunda",
    "wof:placetype":"locality",
    "wof:population":14080
},
  "geometry": {"coordinates":[34.25,-8.11667],"type":"Point"}
}