{
  "type": "Feature",
  "properties": {
    "gn:admin1_code":"23.0",
    "gn:admin2_code":"0703",
    "gn:admin3_code":"0703232",
    "gn:asciiname":"Mpakani",
    "gn:country_code":"TZ",
    "gn:dem":5,
    "gn:feature_class":"P",
    "gn:feature_code":"PPL",
    "gn:name":"Mpakani",
    "gn:population":0,
    "gn:timezone":"Africa/Dar_es_Salaam",
    "iso:country":"TZ",
    "name:eng_x_preferred":[
        "Mpakani"
    ],
    "wof:name":"Mpakani",
    "wof:placetype":"locality"
},
  "geometry": {"coordinates":[39.51095,-7.16005],"type":"Point"}
}