{
  "type": "Feature",
  "properties": {
    "gn:admin1_code":"2.0",
    "gn:admin2_code":"0605",
    "gn:admin3_code":"0605071",
    "gn:asciiname":"Mroka",
    "gn:country_code":"TZ",
    "gn:dem":64,
    "gn:feature_class":"P",
    "gn:feature_code":"PPL",
    "gn:name":"Mroka",
    "gn:population":0,
    "gn:timezone":"Africa/Dar_es_Salaam",
    "iso:country":"TZ",
    "name:eng_x_preferred":[
        "Mroka"
    ],
    "wof:name":"Mroka",
    "wof:placetype":"locality"
},
  "geometry": {"coordinates":[38.24603,-7.77278],"type":"Point"}
}