{
  "type": "Feature",
  "properties": {
    "gn:admin1_code":"7.0",
    "gn:admin2_code":"0801",
    "gn:admin3_code":"0801061",
    "gn:asciiname":"Pondo",
    "gn:country_code":"TZ",
    "gn:dem":245,
    "gn:feature_class":"P",
    "gn:feature_code":"PPL",
    "gn:name":"Pondo",
    "gn:population":0,
    "gn:timezone":"Africa/Dar_es_Salaam",
    "iso:country":"TZ",
    "name:eng_x_preferred":[
        "Pondo"
    ],
    "name:swe_x_preferred":[
        "Pondo"
    ],
    "wof:name":"Pondo",
    "wof:placetype":"locality"
},
  "geometry": {"coordinates":[38.95,-8.58333],"type":"Point"}
}