{
  "type": "Feature",
  "properties": {
    "gn:admin1_code":"5.0",
    "gn:admin2_code":"1605",
    "gn:admin3_code":"1605031",
    "gn:asciiname":"Itindakusya",
    "gn:country_code":"TZ",
    "gn:dem":1216,
    "gn:feature_class":"P",
    "gn:feature_code":"PPL",
    "gn:name":"Itindakusya",
    "gn:population":0,
    "gn:timezone":"Africa/Dar_es_Salaam",
    "iso:country":"TZ",
    "name:eng_x_preferred":[
        "Itindakusya"
    ],
    "name:eng_x_variant":[
        "Itindakusia"
    ],
    "wof:name":"Itindakusya",
    "wof:placetype":"locality"
},
  "geometry": {"coordinates":[30.16366,-6.13417],"type":"Point"}
}