{
  "type": "Feature",
  "properties": {
    "gn:admin1_code":"8.0",
    "gn:admin2_code":"2003",
    "gn:admin3_code":"2003131",
    "gn:asciiname":"Suguti",
    "gn:country_code":"TZ",
    "gn:dem":1203,
    "gn:feature_class":"P",
    "gn:feature_code":"PPL",
    "gn:name":"Suguti",
    "gn:population":0,
    "gn:timezone":"Africa/Dar_es_Salaam",
    "iso:country":"TZ",
    "wof:name":"Suguti",
    "wof:placetype":"locality"
},
  "geometry": {"coordinates":[33.65,-1.73333],"type":"Point"}
}