{
  "type": "Feature",
  "properties": {
    "gn:admin1_code":"20.0",
    "gn:admin2_code":"5501",
    "gn:admin3_code":"5501251",
    "gn:asciiname":"Kibokoni",
    "gn:country_code":"TZ",
    "gn:dem":14,
    "gn:feature_class":"P",
    "gn:feature_code":"PPL",
    "gn:name":"Kibokoni",
    "gn:population":0,
    "gn:timezone":"Africa/Dar_es_Salaam",
    "iso:country":"TZ",
    "name:und_x_variant":[
        "Kibohoni",
        "Kibokoni"
    ],
    "wof:name":"Kibokoni",
    "wof:placetype":"locality"
},
  "geometry": {"coordinates":[39.83333,-5.25],"type":"Point"}
}