{
  "type": "Feature",
  "properties": {
    "gn:admin1_code":"19.0",
    "gn:admin2_code":"1804",
    "gn:admin3_code":"1804011",
    "gn:asciiname":"Nyamizi",
    "gn:country_code":"TZ",
    "gn:dem":1370,
    "gn:feature_class":"P",
    "gn:feature_code":"PPL",
    "gn:name":"Nyamizi",
    "gn:population":0,
    "gn:timezone":"Africa/Dar_es_Salaam",
    "iso:country":"TZ",
    "wof:name":"Nyamizi",
    "wof:placetype":"locality"
},
  "geometry": {"coordinates":[31.05222,-2.83056],"type":"Point"}
}