{
  "type": "Feature",
  "properties": {
    "gn:admin1_code":"5.0",
    "gn:admin2_code":"1601",
    "gn:admin3_code":"1601131",
    "gn:asciiname":"Kwitaba",
    "gn:country_code":"TZ",
    "gn:dem":1397,
    "gn:feature_class":"P",
    "gn:feature_code":"PPL",
    "gn:name":"Kwitaba",
    "gn:population":0,
    "gn:timezone":"Africa/Dar_es_Salaam",
    "iso:country":"TZ",
    "wof:name":"Kwitaba",
    "wof:placetype":"locality"
},
  "geometry": {"coordinates":[30.63333,-3.63333],"type":"Point"}
}