{
  "type": "Feature",
  "properties": {
    "gn:admin1_code":"14.0",
    "gn:admin2_code":"1005",
    "gn:admin3_code":"1005181",
    "gn:asciiname":"Mchomolo",
    "gn:country_code":"TZ",
    "gn:dem":936,
    "gn:feature_class":"P",
    "gn:feature_code":"PPL",
    "gn:name":"Mchomolo",
    "gn:population":0,
    "gn:timezone":"Africa/Dar_es_Salaam",
    "iso:country":"TZ",
    "wof:name":"Mchomolo",
    "wof:placetype":"locality"
},
  "geometry": {"coordinates":[36.31667,-10.56667],"type":"Point"}
}