{
  "type": "Feature",
  "properties": {
    "gn:admin1_code":"6.0",
    "gn:admin2_code":"0305",
    "gn:admin3_code":"0305083",
    "gn:asciiname":"Bondeni Boloti",
    "gn:country_code":"TZ",
    "gn:dem":1080,
    "gn:feature_class":"P",
    "gn:feature_code":"PPL",
    "gn:name":"Bondeni Boloti",
    "gn:population":0,
    "gn:timezone":"Africa/Dar_es_Salaam",
    "iso:country":"TZ",
    "name:und_x_variant":[
        "Baloti",
        "Bondeni Boloti"
    ],
    "wof:name":"Bondeni Boloti",
    "wof:placetype":"locality"
},
  "geometry": {"coordinates":[37.11667,-3.25],"type":"Point"}
}