{
  "type": "Feature",
  "properties": {
    "gn:admin1_code":"5.0",
    "gn:admin2_code":"1603",
    "gn:admin3_code":"1603101",
    "gn:asciiname":"Remba",
    "gn:country_code":"TZ",
    "gn:dem":857,
    "gn:feature_class":"P",
    "gn:feature_code":"PPL",
    "gn:name":"Remba",
    "gn:population":0,
    "gn:timezone":"Africa/Dar_es_Salaam",
    "iso:country":"TZ",
    "wof:name":"Remba",
    "wof:placetype":"locality"
},
  "geometry": {"coordinates":[29.61917,-4.83694],"type":"Point"}
}