{
  "type": "Feature",
  "properties": {
    "gn:admin1_code":"8.0",
    "gn:admin2_code":"2007",
    "gn:admin3_code":"2007121",
    "gn:asciiname":"Buruma",
    "gn:country_code":"TZ",
    "gn:dem":1259,
    "gn:feature_class":"P",
    "gn:feature_code":"PPL",
    "gn:name":"Buruma",
    "gn:population":0,
    "gn:timezone":"Africa/Dar_es_Salaam",
    "iso:country":"TZ",
    "name:deu_x_preferred":[
        "Buruma"
    ],
    "wof:name":"Buruma",
    "wof:placetype":"locality"
},
  "geometry": {"coordinates":[33.81667,-1.65],"type":"Point"}
}