{
  "type": "Feature",
  "properties": {
    "gn:gn_country":"TZ",
    "gn:gn_fcode":"PPL",
    "gn:gn_pop":35953,
    "gn:population":35953,
    "iso:country":"TZ",
    "name:eng_x_preferred":[
        "Kidodi"
    ],
    "qs_pg:aaroncc":"TZ",
    "qs_pg:gn_country":"TZ",
    "qs_pg:gn_fcode":"PPL",
    "qs_pg:gn_pop":35953,
    "qs_pg:name":"Kidodi",
    "qs_pg:photos_9r":0,
    "qs_pg:photos_sr":0,
    "qs_pg:pop_sr":7,
    "qs_pg:qs_pg_placetype":"locality",
    "wof:name":"Kidodi",
    "wof:placetype":"locality",
    "wof:population":35953
},
  "geometry": {"coordinates":[37.00438,-7.60361],"type":"Point"}
}