{
  "type": "Feature",
  "properties": {
    "gn:admin1_code":"18.0",
    "gn:admin2_code":"0405",
    "gn:admin3_code":"0405071",
    "gn:asciiname":"Ushongo Mtoni",
    "gn:country_code":"TZ",
    "gn:dem":9,
    "gn:feature_class":"P",
    "gn:feature_code":"PPL",
    "gn:name":"Ushongo Mtoni",
    "gn:population":0,
    "gn:timezone":"Africa/Dar_es_Salaam",
    "iso:country":"TZ",
    "name:und_x_variant":[
        "Ushongo Mtani",
        "Ushongo Mtoni"
    ],
    "wof:name":"Ushongo Mtoni",
    "wof:placetype":"locality"
},
  "geometry": {"coordinates":[38.96667,-5.51667],"type":"Point"}
}