{
  "type": "Feature",
  "properties": {
    "gn:admin1_code":"26.0",
    "gn:admin2_code":"0201",
    "gn:admin3_code":"0201071",
    "gn:asciiname":"Nangungu",
    "gn:country_code":"TZ",
    "gn:dem":1370,
    "gn:feature_class":"P",
    "gn:feature_code":"PPL",
    "gn:name":"Nangungu",
    "gn:population":0,
    "gn:timezone":"Africa/Dar_es_Salaam",
    "iso:country":"TZ",
    "wof:name":"Nangungu",
    "wof:placetype":"locality"
},
  "geometry": {"coordinates":[36.45722,-3.35078],"type":"Point"}
}