{
  "type": "Feature",
  "properties": {
    "gn:admin1_code":"6.0",
    "gn:admin2_code":"0302",
    "gn:admin3_code":"0302191",
    "gn:asciiname":"Taroha",
    "gn:country_code":"TZ",
    "gn:dem":709,
    "gn:feature_class":"P",
    "gn:feature_code":"PPL",
    "gn:name":"Taroha",
    "gn:population":0,
    "gn:timezone":"Africa/Dar_es_Salaam",
    "iso:country":"TZ",
    "wof:name":"Taroha",
    "wof:placetype":"locality"
},
  "geometry": {"coordinates":[37.76667,-3.68333],"type":"Point"}
}