{
  "type": "Feature",
  "properties": {
    "gn:admin1_code":"27.0",
    "gn:admin2_code":"2101",
    "gn:admin3_code":"2101141",
    "gn:asciiname":"Ufana",
    "gn:country_code":"TZ",
    "gn:dem":1877,
    "gn:feature_class":"P",
    "gn:feature_code":"PPL",
    "gn:name":"Ufana",
    "gn:population":0,
    "gn:timezone":"Africa/Dar_es_Salaam",
    "iso:country":"TZ",
    "name:swa_x_preferred":[
        "Ufana"
    ],
    "wof:name":"Ufana",
    "wof:placetype":"locality"
},
  "geometry": {"coordinates":[35.35,-4.25],"type":"Point"}
}