{
  "type": "Feature",
  "properties": {
    "gn:country":"TZ",
    "gn:fcode":"PPL",
    "gn:population":2607,
    "iso:country":"TZ",
    "name:eng_x_preferred":[
        "Ilembo"
    ],
    "name:ita_x_preferred":[
        "Ilembo"
    ],
    "name:swa_x_preferred":[
        "Ilembo"
    ],
    "qs:name":"Ilembo",
    "qs:photos_9r":0,
    "qs:photos_sr":0,
    "qs:pop_sr":"4",
    "wd:wordcount":51,
    "wof:name":"Ilembo",
    "wof:placetype":"locality",
    "wof:population":2607
},
  "geometry": {"coordinates":[33.38333,-9.25],"type":"Point"}
}