{
  "type": "Feature",
  "properties": {
    "gn:admin1_code":"24.0",
    "gn:admin2_code":"1503",
    "gn:admin3_code":"1503172",
    "gn:asciiname":"Kisensegere",
    "gn:country_code":"TZ",
    "gn:dem":1203,
    "gn:feature_class":"P",
    "gn:feature_code":"PPL",
    "gn:name":"Kisensegere",
    "gn:population":0,
    "gn:timezone":"Africa/Dar_es_Salaam",
    "iso:country":"TZ",
    "wof:name":"Kisensegere",
    "wof:placetype":"locality"
},
  "geometry": {"coordinates":[30.88333,-7.45],"type":"Point"}
}