{
  "type": "Feature",
  "properties": {
    "gn:admin1_code":"2.0",
    "gn:admin2_code":"0604",
    "gn:admin3_code":"0604171",
    "gn:asciiname":"Minangu",
    "gn:country_code":"TZ",
    "gn:dem":64,
    "gn:feature_class":"P",
    "gn:feature_code":"PPL",
    "gn:name":"Minangu",
    "gn:population":0,
    "gn:timezone":"Africa/Dar_es_Salaam",
    "iso:country":"TZ",
    "name:eng_x_preferred":[
        "Minangu"
    ],
    "wof:name":"Minangu",
    "wof:placetype":"locality"
},
  "geometry": {"coordinates":[39.14643,-7.34832],"type":"Point"}
}