{
  "type": "Feature",
  "properties": {
    "gn:admin1_code":"10.0",
    "gn:admin2_code":"0506",
    "gn:admin3_code":"0506013",
    "gn:asciiname":"Mkundi",
    "gn:country_code":"TZ",
    "gn:dem":457,
    "gn:feature_class":"P",
    "gn:feature_code":"PPL",
    "gn:name":"Mkundi",
    "gn:population":0,
    "gn:timezone":"Africa/Dar_es_Salaam",
    "iso:country":"TZ",
    "name:und_x_variant":[
        "Makuya",
        "Mkundi"
    ],
    "wof:name":"Mkundi",
    "wof:placetype":"locality"
},
  "geometry": {"coordinates":[37.38333,-6.31667],"type":"Point"}
}