{
  "type": "Feature",
  "properties": {
    "gn:admin1_code":"13.0",
    "gn:admin2_code":"5402",
    "gn:admin3_code":"5402171",
    "gn:asciiname":"Ngonwe",
    "gn:country_code":"TZ",
    "gn:dem":52,
    "gn:feature_class":"P",
    "gn:feature_code":"PPL",
    "gn:name":"Ngonwe",
    "gn:population":0,
    "gn:timezone":"Africa/Dar_es_Salaam",
    "iso:country":"TZ",
    "wof:name":"Ngonwe",
    "wof:placetype":"locality"
},
  "geometry": {"coordinates":[39.75,-4.98333],"type":"Point"}
}