{
  "type": "Feature",
  "properties": {
    "gn:country":"TZ",
    "gn:fcode":"PPL",
    "gn:pop":22069,
    "iso:country":"TZ",
    "qs:name":"Rulenge",
    "qs:photos_9r":0,
    "qs:photos_sr":0,
    "qs:pop_sr":"7",
    "wof:name":"Rulenge",
    "wof:placetype":"locality",
    "wof:population":22069
},
  "geometry": {"coordinates":[30.6325,-2.7175],"type":"Point"}
}