{
  "type": "Feature",
  "properties": {
    "gn:admin1_code":"8.0",
    "gn:admin2_code":"2001",
    "gn:admin3_code":"2001171",
    "gn:asciiname":"Gamasara",
    "gn:country_code":"TZ",
    "gn:dem":1319,
    "gn:feature_class":"P",
    "gn:feature_code":"PPL",
    "gn:name":"Gamasara",
    "gn:population":0,
    "gn:timezone":"Africa/Dar_es_Salaam",
    "iso:country":"TZ",
    "wof:name":"Gamasara",
    "wof:placetype":"locality"
},
  "geometry": {"coordinates":[34.33333,-1.33333],"type":"Point"}
}