{
  "type": "Feature",
  "properties": {
    "gn:admin1_code":"2.0",
    "gn:admin2_code":"0605",
    "gn:admin3_code":"0605061",
    "gn:asciiname":"Kilimani",
    "gn:country_code":"TZ",
    "gn:dem":42,
    "gn:feature_class":"P",
    "gn:feature_code":"PPL",
    "gn:name":"Kilimani",
    "gn:population":0,
    "gn:timezone":"Africa/Dar_es_Salaam",
    "iso:country":"TZ",
    "name:eng_x_preferred":[
        "Kilimani"
    ],
    "wof:name":"Kilimani",
    "wof:placetype":"locality"
},
  "geometry": {"coordinates":[38.68407,-7.90164],"type":"Point"}
}