{
  "type": "Feature",
  "properties": {
    "gn:admin1_code":"6.0",
    "gn:admin2_code":"0302",
    "gn:admin3_code":"0302191",
    "gn:asciiname":"Makanalika",
    "gn:country_code":"TZ",
    "gn:dem":742,
    "gn:feature_class":"P",
    "gn:feature_code":"PPL",
    "gn:name":"Makanalika",
    "gn:population":0,
    "gn:timezone":"Africa/Dar_es_Salaam",
    "iso:country":"TZ",
    "wof:name":"Makanalika",
    "wof:placetype":"locality"
},
  "geometry": {"coordinates":[37.71667,-3.68333],"type":"Point"}
}