{
  "type": "Feature",
  "properties": {
    "gn:admin1_code":"18.0",
    "gn:admin2_code":"0402",
    "gn:admin3_code":"0402041",
    "gn:asciiname":"Kerenge",
    "gn:country_code":"TZ",
    "gn:dem":310,
    "gn:feature_class":"P",
    "gn:feature_code":"PPL",
    "gn:name":"Kerenge",
    "gn:population":0,
    "gn:timezone":"Africa/Dar_es_Salaam",
    "iso:country":"TZ",
    "wof:name":"Kerenge",
    "wof:placetype":"locality"
},
  "geometry": {"coordinates":[38.55,-5.03333],"type":"Point"}
}