{
  "type": "Feature",
  "properties": {
    "gn:gn_country":"TZ",
    "gn:gn_fcode":"PPL",
    "gn:gn_pop":24817,
    "gn:population":24817,
    "iso:country":"TZ",
    "qs_pg:aaroncc":"TZ",
    "qs_pg:gn_country":"TZ",
    "qs_pg:gn_fcode":"PPL",
    "qs_pg:gn_pop":24817,
    "qs_pg:name":"Chimala",
    "qs_pg:photos_9r":0,
    "qs_pg:photos_sr":0,
    "qs_pg:pop_sr":7,
    "qs_pg:qs_pg_placetype":"locality",
    "wof:name":"Chimala",
    "wof:placetype":"locality",
    "wof:population":24817
},
  "geometry": {"coordinates":[34.01667,-8.85],"type":"Point"}
}