{
  "type": "Feature",
  "properties": {
    "gn:admin1_code":"19.0",
    "gn:admin2_code":"1803",
    "gn:admin3_code":"1803123",
    "gn:asciiname":"Rubungo",
    "gn:country_code":"TZ",
    "gn:dem":1273,
    "gn:feature_class":"P",
    "gn:feature_code":"PPL",
    "gn:name":"Rubungo",
    "gn:population":0,
    "gn:timezone":"Africa/Dar_es_Salaam",
    "iso:country":"TZ",
    "wof:name":"Rubungo",
    "wof:placetype":"locality"
},
  "geometry": {"coordinates":[31.64944,-1.85],"type":"Point"}
}