{
  "type": "Feature",
  "properties": {
    "gn:country":"TZ",
    "gn:fcode":"PPL",
    "gn:population":34780,
    "iso:country":"TZ",
    "name:ara_x_preferred":[
        "\u0648\u0644\u0627\u064a\u0629 \u0645\u0628\u0648\u063a\u0648\u064a"
    ],
    "name:ceb_x_preferred":[
        "Mbogwe"
    ],
    "name:deu_x_preferred":[
        "Mbogwe"
    ],
    "name:eng_x_preferred":[
        "Mbogwe District"
    ],
    "name:nob_x_preferred":[
        "Mbongwe"
    ],
    "name:spa_x_preferred":[
        "Mbogwe"
    ],
    "name:swa_x_preferred":[
        "Nguruka"
    ],
    "name:zul_x_preferred":[
        "Mbogwe District"
    ],
    "qs:name":"Masumbwe",
    "qs:photos_9r":0,
    "qs:photos_sr":0,
    "qs:pop_sr":"7",
    "wd:wordcount":158,
    "wof:name":"Masumbwe",
    "wof:placetype":"locality",
    "wof:population":34780
},
  "geometry": {"coordinates":[32.18333,-3.63333],"type":"Point"}
}