{
  "type": "Feature",
  "properties": {
    "gn:country":"TZ",
    "gn:fcode":"PPL",
    "gn:pop":34780,
    "iso:country":"TZ",
    "qs:name":"Masumbwe",
    "qs:photos_9r":0,
    "qs:photos_sr":0,
    "qs:pop_sr":"7",
    "wd:wordcount":158,
    "wof:name":"Masumbwe",
    "wof:placetype":"locality",
    "wof:population":34780
},
  "geometry": {"coordinates":[32.18333,-3.63333],"type":"Point"}
}