{
  "type": "Feature",
  "properties": {
    "gn:admin1_code":"7.0",
    "gn:admin2_code":"0801",
    "gn:admin3_code":"0801081",
    "gn:asciiname":"Ndende",
    "gn:country_code":"TZ",
    "gn:dem":100,
    "gn:feature_class":"P",
    "gn:feature_code":"PPL",
    "gn:name":"Ndende",
    "gn:population":0,
    "gn:timezone":"Africa/Dar_es_Salaam",
    "iso:country":"TZ",
    "name:ceb_x_preferred":[
        "Ndende"
    ],
    "name:deu_x_preferred":[
        "Ndende"
    ],
    "name:eng_x_preferred":[
        "Ndende"
    ],
    "name:fra_x_preferred":[
        "Ndende"
    ],
    "name:swe_x_preferred":[
        "Ndende"
    ],
    "wof:name":"Ndende",
    "wof:placetype":"locality"
},
  "geometry": {"coordinates":[38.96667,-8.73333],"type":"Point"}
}