{
  "type": "Feature",
  "properties": {
    "gn:admin1_code":"7.0",
    "gn:admin2_code":"0801",
    "gn:admin3_code":"0801081",
    "gn:asciiname":"Ndende",
    "gn:country_code":"TZ",
    "gn:dem":100,
    "gn:feature_class":"P",
    "gn:feature_code":"PPL",
    "gn:name":"Ndende",
    "gn:population":0,
    "gn:timezone":"Africa/Dar_es_Salaam",
    "iso:country":"TZ",
    "name:ara_x_preferred":[
        "\u0646\u062f\u064a\u0646\u062f\u064a"
    ],
    "name:ben_x_preferred":[
        "\u098f\u09a8\u09cd\u09a6\u09c7\u09a8\u09cd\u09a6\u09c7"
    ],
    "name:ceb_x_preferred":[
        "Ndende"
    ],
    "name:deu_x_preferred":[
        "Ndende"
    ],
    "name:ell_x_preferred":[
        "\u039d\u03c4\u03ad\u03bd\u03c4\u03b5"
    ],
    "name:eng_x_preferred":[
        "Ndende"
    ],
    "name:fas_x_preferred":[
        "\u0627\u0646\u062f\u0646\u062f\u0647"
    ],
    "name:fra_x_preferred":[
        "Ndende"
    ],
    "name:heb_x_preferred":[
        "\u05e0\u05d3\u05e0\u05d3\u05d4"
    ],
    "name:hin_x_preferred":[
        "\u090f\u0902\u0921\u0947\u0902\u0921\u0947"
    ],
    "name:hun_x_preferred":[
        "Ndende"
    ],
    "name:ind_x_preferred":[
        "Ndende"
    ],
    "name:kor_x_preferred":[
        "\uc740\ub374\ub370"
    ],
    "name:por_x_preferred":[
        "Ndend\u00e9"
    ],
    "name:swe_x_preferred":[
        "Ndende"
    ],
    "name:tur_x_preferred":[
        "Ndende"
    ],
    "name:ukr_x_preferred":[
        "\u041d\u0434\u0435\u043d\u0434\u0435"
    ],
    "name:urd_x_preferred":[
        "\u0627\u0646\u0688\u06cc\u0646\u062f\u06d2"
    ],
    "name:vie_x_preferred":[
        "Ndende"
    ],
    "wof:name":"Ndende",
    "wof:placetype":"locality"
},
  "geometry": {"coordinates":[38.96667,-8.73333],"type":"Point"}
}