{
  "type": "Feature",
  "properties": {
    "gn:admin1_code":"15.0",
    "gn:admin2_code":"1702",
    "gn:admin3_code":"1702201",
    "gn:asciiname":"Ipeja",
    "gn:country_code":"TZ",
    "gn:dem":1119,
    "gn:feature_class":"P",
    "gn:feature_code":"PPL",
    "gn:name":"Ipeja",
    "gn:population":0,
    "gn:timezone":"Africa/Dar_es_Salaam",
    "iso:country":"TZ",
    "wof:name":"Ipeja",
    "wof:placetype":"locality"
},
  "geometry": {"coordinates":[33.48333,-3.71667],"type":"Point"}
}