{
  "type": "Feature",
  "properties": {
    "gn:admin1_code":"4.0",
    "gn:admin2_code":"1104",
    "gn:admin3_code":"1104161",
    "gn:asciiname":"Kidodi",
    "gn:country_code":"TZ",
    "gn:dem":2001,
    "gn:feature_class":"P",
    "gn:feature_code":"PPL",
    "gn:name":"Kidodi",
    "gn:population":0,
    "gn:timezone":"Africa/Dar_es_Salaam",
    "iso:country":"TZ",
    "name:eng_x_preferred":[
        "Kidodi"
    ],
    "wof:name":"Kidodi",
    "wof:placetype":"locality"
},
  "geometry": {"coordinates":[35.91667,-7.91667],"type":"Point"}
}