{
  "type": "Feature",
  "properties": {
    "gn:admin1_code":"18.0",
    "gn:admin2_code":"0405",
    "gn:admin3_code":"0405101",
    "gn:asciiname":"Mwera",
    "gn:country_code":"TZ",
    "gn:dem":44,
    "gn:feature_class":"P",
    "gn:feature_code":"PPL",
    "gn:name":"Mwera",
    "gn:population":0,
    "gn:timezone":"Africa/Dar_es_Salaam",
    "iso:country":"TZ",
    "name:ceb_x_preferred":[
        "Mwera"
    ],
    "name:fra_x_preferred":[
        "Mwera"
    ],
    "name:swa_x_preferred":[
        "Mwera"
    ],
    "name:swe_x_preferred":[
        "Mwera"
    ],
    "wof:name":"Mwera",
    "wof:placetype":"locality"
},
  "geometry": {"coordinates":[38.93333,-5.53333],"type":"Point"}
}