{
  "type": "Feature",
  "properties": {
    "gn:admin1_code":"18.0",
    "gn:admin2_code":"0402",
    "gn:admin3_code":"0402191",
    "gn:asciiname":"Pulumbu",
    "gn:country_code":"TZ",
    "gn:dem":462,
    "gn:feature_class":"P",
    "gn:feature_code":"PPL",
    "gn:name":"Pulumbu",
    "gn:population":0,
    "gn:timezone":"Africa/Dar_es_Salaam",
    "iso:country":"TZ",
    "wof:name":"Pulumbu",
    "wof:placetype":"locality"
},
  "geometry": {"coordinates":[38.21667,-5.08333],"type":"Point"}
}