{
  "type": "Feature",
  "properties": {
    "gn:admin1_code":"19.0",
    "gn:admin2_code":"1801",
    "gn:admin3_code":"1801171",
    "gn:asciiname":"Kafuro",
    "gn:country_code":"TZ",
    "gn:dem":1367,
    "gn:feature_class":"P",
    "gn:feature_code":"PPL",
    "gn:name":"Kafuro",
    "gn:population":0,
    "gn:timezone":"Africa/Dar_es_Salaam",
    "iso:country":"TZ",
    "wof:name":"Kafuro",
    "wof:placetype":"locality"
},
  "geometry": {"coordinates":[31.00083,-1.73528],"type":"Point"}
}