{
  "type": "Feature",
  "properties": {
    "gn:admin1_code":"9.0",
    "gn:admin2_code":"1202",
    "gn:admin3_code":"1202121",
    "gn:asciiname":"Idugumbi",
    "gn:country_code":"TZ",
    "gn:dem":932,
    "gn:feature_class":"P",
    "gn:feature_code":"PPL",
    "gn:name":"Idugumbi",
    "gn:population":0,
    "gn:timezone":"Africa/Dar_es_Salaam",
    "iso:country":"TZ",
    "wof:name":"Idugumbi",
    "wof:placetype":"locality"
},
  "geometry": {"coordinates":[33.06667,-8.73333],"type":"Point"}
}