{
  "type": "Feature",
  "properties": {
    "gn:admin1_code":"19.0",
    "gn:admin2_code":"1805",
    "gn:admin3_code":"1805093",
    "gn:asciiname":"Ibugo",
    "gn:country_code":"TZ",
    "gn:dem":1475,
    "gn:feature_class":"P",
    "gn:feature_code":"PPL",
    "gn:name":"Ibugo",
    "gn:population":0,
    "gn:timezone":"Africa/Dar_es_Salaam",
    "iso:country":"TZ",
    "wof:name":"Ibugo",
    "wof:placetype":"locality"
},
  "geometry": {"coordinates":[30.46944,-2.66611],"type":"Point"}
}