{
  "type": "Feature",
  "properties": {
    "gn:admin1_code":"18.0",
    "gn:admin2_code":"0402",
    "gn:admin3_code":"0402201",
    "gn:asciiname":"Bombo",
    "gn:country_code":"TZ",
    "gn:dem":951,
    "gn:feature_class":"P",
    "gn:feature_code":"PPL",
    "gn:name":"Bombo",
    "gn:population":0,
    "gn:timezone":"Africa/Dar_es_Salaam",
    "iso:country":"TZ",
    "name:ceb_x_preferred":[
        "Bombo"
    ],
    "name:fra_x_preferred":[
        "Bombo"
    ],
    "name:ita_x_preferred":[
        "Bombo"
    ],
    "name:lug_x_preferred":[
        "Bombo"
    ],
    "name:nld_x_preferred":[
        "Bombo"
    ],
    "name:pol_x_preferred":[
        "Bombo"
    ],
    "name:spa_x_preferred":[
        "Bombo"
    ],
    "name:swe_x_preferred":[
        "Bombo"
    ],
    "wof:name":"Bombo",
    "wof:placetype":"locality"
},
  "geometry": {"coordinates":[38.16667,-4.91667],"type":"Point"}
}