{
  "type": "Feature",
  "properties": {
    "gn:admin1_code":"19.0",
    "gn:admin2_code":"1802",
    "gn:admin3_code":"1802071",
    "gn:asciiname":"Karabagaine",
    "gn:country_code":"TZ",
    "gn:dem":1285,
    "gn:feature_class":"P",
    "gn:feature_code":"PPL",
    "gn:name":"Karabagaine",
    "gn:population":0,
    "gn:timezone":"Africa/Dar_es_Salaam",
    "iso:country":"TZ",
    "wof:name":"Karabagaine",
    "wof:placetype":"locality"
},
  "geometry": {"coordinates":[31.75,-1.31667],"type":"Point"}
}