{
  "type": "Feature",
  "properties": {
    "gn:admin1_code":"22.0",
    "gn:admin2_code":"5102",
    "gn:admin3_code":"5102061",
    "gn:asciiname":"Nyanjani",
    "gn:country_code":"TZ",
    "gn:dem":2,
    "gn:feature_class":"P",
    "gn:feature_code":"PPL",
    "gn:name":"Nyanjani",
    "gn:population":0,
    "gn:timezone":"Africa/Dar_es_Salaam",
    "iso:country":"TZ",
    "name:und_x_variant":[
        "Myanjani",
        "Nyanjani"
    ],
    "wof:name":"Nyanjani",
    "wof:placetype":"locality"
},
  "geometry": {"coordinates":[39.21667,-5.91667],"type":"Point"}
}