{
  "type": "Feature",
  "properties": {
    "gn:admin1_code":"27.0",
    "gn:admin2_code":"2104",
    "gn:admin3_code":"2104121",
    "gn:asciiname":"Remiti",
    "gn:country_code":"TZ",
    "gn:dem":615,
    "gn:feature_class":"P",
    "gn:feature_code":"PPL",
    "gn:name":"Remiti",
    "gn:population":0,
    "gn:timezone":"Africa/Dar_es_Salaam",
    "iso:country":"TZ",
    "name:und_x_variant":[
        "Ruvu Remiti",
        "Remiti"
    ],
    "wof:name":"Remiti",
    "wof:placetype":"locality"
},
  "geometry": {"coordinates":[37.68333,-4.55],"type":"Point"}
}