{
  "type": "Feature",
  "properties": {
    "gn:admin1_code":"2.0",
    "gn:admin2_code":"0606",
    "gn:admin3_code":"0606081",
    "gn:asciiname":"Mwakuni",
    "gn:country_code":"TZ",
    "gn:dem":12,
    "gn:feature_class":"P",
    "gn:feature_code":"PPL",
    "gn:name":"Mwakuni",
    "gn:population":0,
    "gn:timezone":"Africa/Dar_es_Salaam",
    "iso:country":"TZ",
    "name:eng_x_preferred":[
        "Mwakuni"
    ],
    "wof:name":"Mwakuni",
    "wof:placetype":"locality"
},
  "geometry": {"coordinates":[39.75888,-7.86557],"type":"Point"}
}