{
  "type": "Feature",
  "properties": {
    "iso:country":"TZ",
    "name:eng_x_preferred":[
        "Utendo"
    ],
    "qs:gn_country":"TZ",
    "qs:gn_fcode":"PPL",
    "qs:gn_pop":0,
    "qs:name":"Utende",
    "qs:name_adm0":"Tanzania",
    "qs:name_adm1":"Pwani",
    "qs:photos":388,
    "qs:photos_1k":79,
    "qs:photos_9k":2,
    "qs:photos_9r":5,
    "qs:photos_all":388,
    "qs:photos_sr":6,
    "qs:placetype":"Town",
    "qs:pop_sr":"0",
    "qs:woe_adm0":23424973,
    "wof:name":"Utende",
    "wof:placetype":"locality"
},
  "geometry": {"coordinates":[39.73461,-7.96814],"type":"Point"}
}