{
  "type": "Feature",
  "properties": {
    "gn:admin1_code":"2.0",
    "gn:admin2_code":"0601",
    "gn:admin3_code":"0601041",
    "gn:asciiname":"Mkange",
    "gn:country_code":"TZ",
    "gn:dem":281,
    "gn:feature_class":"P",
    "gn:feature_code":"PPL",
    "gn:name":"Mkange",
    "gn:population":0,
    "gn:timezone":"Africa/Dar_es_Salaam",
    "iso:country":"TZ",
    "wof:name":"Mkange",
    "wof:placetype":"locality"
},
  "geometry": {"coordinates":[38.55,-6.06667],"type":"Point"}
}