{
  "type": "Feature",
  "properties": {
    "gn:admin1_code":"7.0",
    "gn:admin2_code":"0801",
    "gn:admin3_code":"0801141",
    "gn:asciiname":"Kiwawa",
    "gn:country_code":"TZ",
    "gn:dem":130,
    "gn:feature_class":"P",
    "gn:feature_code":"PPL",
    "gn:name":"Kiwawa",
    "gn:population":0,
    "gn:timezone":"Africa/Dar_es_Salaam",
    "iso:country":"TZ",
    "wof:name":"Kiwawa",
    "wof:placetype":"locality"
},
  "geometry": {"coordinates":[39.35,-9.16667],"type":"Point"}
}