{
  "type": "Feature",
  "properties": {
    "gn:admin1_code":"3.0",
    "gn:admin2_code":"0105",
    "gn:admin3_code":"0105322",
    "gn:asciiname":"Ilindi",
    "gn:country_code":"TZ",
    "gn:dem":1107,
    "gn:feature_class":"P",
    "gn:feature_code":"PPL",
    "gn:name":"Ilindi",
    "gn:population":0,
    "gn:timezone":"Africa/Dar_es_Salaam",
    "iso:country":"TZ",
    "wof:name":"Ilindi",
    "wof:placetype":"locality"
},
  "geometry": {"coordinates":[35.56667,-6.01667],"type":"Point"}
}