{
  "type": "Feature",
  "properties": {
    "gn:admin1_code":"13.0",
    "gn:asciiname":"Mabaoni",
    "gn:country_code":"TZ",
    "gn:dem":2,
    "gn:feature_class":"P",
    "gn:feature_code":"PPL",
    "gn:name":"Mabaoni",
    "gn:population":0,
    "gn:timezone":"Africa/Dar_es_Salaam",
    "iso:country":"TZ",
    "wof:name":"Mabaoni",
    "wof:placetype":"locality"
},
  "geometry": {"coordinates":[39.63333,-5.08333],"type":"Point"}
}