{
  "type": "Feature",
  "properties": {
    "gn:admin1_code":"5.0",
    "gn:admin2_code":"1605",
    "gn:admin3_code":"1605021",
    "gn:asciiname":"Muhela",
    "gn:country_code":"TZ",
    "gn:dem":1579,
    "gn:feature_class":"P",
    "gn:feature_code":"PPL",
    "gn:name":"Muhela",
    "gn:population":0,
    "gn:timezone":"Africa/Dar_es_Salaam",
    "iso:country":"TZ",
    "name:eng_x_preferred":[
        "Muhela"
    ],
    "wof:name":"Muhela",
    "wof:placetype":"locality"
},
  "geometry": {"coordinates":[29.7728,-6.21065],"type":"Point"}
}