{
  "type": "Feature",
  "properties": {
    "gn:admin1_code":"18.0",
    "gn:admin2_code":"0410",
    "gn:admin3_code":"0410072",
    "gn:asciiname":"Rudiga",
    "gn:country_code":"TZ",
    "gn:dem":649,
    "gn:feature_class":"P",
    "gn:feature_code":"PPL",
    "gn:name":"Rudiga",
    "gn:population":0,
    "gn:timezone":"Africa/Dar_es_Salaam",
    "iso:country":"TZ",
    "wof:name":"Rudiga",
    "wof:placetype":"locality"
},
  "geometry": {"coordinates":[38.01667,-5.46667],"type":"Point"}
}