{
  "type": "Feature",
  "properties": {
    "gn:admin1_code":"28.0",
    "gn:admin2_code":"2501",
    "gn:admin3_code":"2501321",
    "gn:asciiname":"Chankurongo",
    "gn:country_code":"TZ",
    "gn:dem":1152,
    "gn:feature_class":"P",
    "gn:feature_code":"PPL",
    "gn:name":"Chankurongo",
    "gn:population":0,
    "gn:timezone":"Africa/Dar_es_Salaam",
    "iso:country":"TZ",
    "wof:name":"Chankurongo",
    "wof:placetype":"locality"
},
  "geometry": {"coordinates":[31.96667,-2.75],"type":"Point"}
}