{
  "type": "Feature",
  "properties": {
    "gn:admin1_code":"28.0",
    "gn:admin2_code":"2501",
    "gn:admin3_code":"2501053",
    "gn:asciiname":"Mhalamba",
    "gn:country_code":"TZ",
    "gn:dem":1150,
    "gn:feature_class":"P",
    "gn:feature_code":"PPL",
    "gn:name":"Mhalamba",
    "gn:population":0,
    "gn:timezone":"Africa/Dar_es_Salaam",
    "iso:country":"TZ",
    "wof:name":"Mhalamba",
    "wof:placetype":"locality"
},
  "geometry": {"coordinates":[32.00991,-2.5812],"type":"Point"}
}