{
  "type": "Feature",
  "properties": {
    "gn:admin1_code":"20.0",
    "gn:admin2_code":"5501",
    "gn:admin3_code":"5501091",
    "gn:asciiname":"Misooni",
    "gn:country_code":"TZ",
    "gn:dem":36,
    "gn:feature_class":"P",
    "gn:feature_code":"PPL",
    "gn:name":"Misooni",
    "gn:population":0,
    "gn:timezone":"Africa/Dar_es_Salaam",
    "iso:country":"TZ",
    "wof:name":"Misooni",
    "wof:placetype":"locality"
},
  "geometry": {"coordinates":[39.75,-5.26667],"type":"Point"}
}