{
  "type": "Feature",
  "properties": {
    "gn:admin1_code":"25.0",
    "gn:admin2_code":"5301",
    "gn:admin3_code":"5301353",
    "gn:asciiname":"Maungani Kidutani",
    "gn:country_code":"TZ",
    "gn:dem":23,
    "gn:feature_class":"P",
    "gn:feature_code":"PPL",
    "gn:name":"Maungani Kidutani",
    "gn:population":0,
    "gn:timezone":"Africa/Dar_es_Salaam",
    "iso:country":"TZ",
    "wof:name":"Maungani Kidutani",
    "wof:placetype":"locality"
},
  "geometry": {"coordinates":[39.23535,-6.21531],"type":"Point"}
}