{
  "type": "Feature",
  "properties": {
    "gn:admin1_code":"21.0",
    "gn:admin2_code":"5202",
    "gn:admin3_code":"5202211",
    "gn:asciiname":"Bwejuu",
    "gn:country_code":"TZ",
    "gn:dem":10,
    "gn:feature_class":"P",
    "gn:feature_code":"PPL",
    "gn:name":"Bwejuu",
    "gn:population":0,
    "gn:timezone":"Africa/Dar_es_Salaam",
    "iso:country":"TZ",
    "name:eng_x_preferred":[
        "Bwejuu"
    ],
    "name:eng_x_variant":[
        "Bweju"
    ],
    "name:und_x_variant":[
        "Boyja"
    ],
    "wof:name":"Bwejuu",
    "wof:placetype":"locality"
},
  "geometry": {"coordinates":[39.53333,-6.23333],"type":"Point"}
}