{
  "type": "Feature",
  "properties": {
    "gn:admin1_code":"18.0",
    "gn:admin2_code":"0407",
    "gn:admin3_code":"0407011",
    "gn:asciiname":"Lulago",
    "gn:country_code":"TZ",
    "gn:dem":1155,
    "gn:feature_class":"P",
    "gn:feature_code":"PPL",
    "gn:name":"Lulago",
    "gn:population":0,
    "gn:timezone":"Africa/Dar_es_Salaam",
    "iso:country":"TZ",
    "wof:name":"Lulago",
    "wof:placetype":"locality"
},
  "geometry": {"coordinates":[37.46667,-5.61667],"type":"Point"}
}