{
  "type": "Feature",
  "properties": {
    "gn:admin1_code":"8.0",
    "gn:admin2_code":"2006",
    "gn:admin3_code":"2006131",
    "gn:asciiname":"Bugire",
    "gn:country_code":"TZ",
    "gn:dem":1364,
    "gn:feature_class":"P",
    "gn:feature_code":"PPL",
    "gn:name":"Bugire",
    "gn:population":0,
    "gn:timezone":"Africa/Dar_es_Salaam",
    "iso:country":"TZ",
    "wof:name":"Bugire",
    "wof:placetype":"locality"
},
  "geometry": {"coordinates":[34.28333,-1.15],"type":"Point"}
}