{
  "type": "Feature",
  "properties": {
    "gn:admin1_code":"8.0",
    "gn:admin2_code":"2004",
    "gn:admin3_code":"2004201",
    "gn:asciiname":"Bitaraguru",
    "gn:country_code":"TZ",
    "gn:dem":1249,
    "gn:feature_class":"P",
    "gn:feature_code":"PPL",
    "gn:name":"Bitaraguru",
    "gn:population":0,
    "gn:timezone":"Africa/Dar_es_Salaam",
    "iso:country":"TZ",
    "name:und_x_variant":[
        "Kungombe",
        "Bituruguru",
        "Bitaraguru"
    ],
    "wof:name":"Bitaraguru",
    "wof:placetype":"locality"
},
  "geometry": {"coordinates":[33.85,-1.95],"type":"Point"}
}