{
  "type": "Feature",
  "properties": {
    "gn:admin1_code":"4.0",
    "gn:admin2_code":"1104",
    "gn:admin3_code":"1104051",
    "gn:asciiname":"Ifua",
    "gn:country_code":"TZ",
    "gn:dem":1376,
    "gn:feature_class":"P",
    "gn:feature_code":"PPL",
    "gn:name":"Ifua",
    "gn:population":0,
    "gn:timezone":"Africa/Dar_es_Salaam",
    "iso:country":"TZ",
    "name:eng_x_preferred":[
        "Ifua"
    ],
    "wof:name":"Ifua",
    "wof:placetype":"locality"
},
  "geometry": {"coordinates":[36.38141,-7.71931],"type":"Point"}
}