{
  "type": "Feature",
  "properties": {
    "gn:admin1_code":"5.0",
    "gn:admin2_code":"1601",
    "gn:admin3_code":"1601051",
    "gn:asciiname":"Nyangwe",
    "gn:country_code":"TZ",
    "gn:dem":1140,
    "gn:feature_class":"P",
    "gn:feature_code":"PPL",
    "gn:name":"Nyangwe",
    "gn:population":0,
    "gn:timezone":"Africa/Dar_es_Salaam",
    "iso:country":"TZ",
    "name:cat_x_preferred":[
        "Nyangwe"
    ],
    "name:fra_x_preferred":[
        "Nyangwe"
    ],
    "name:kon_x_preferred":[
        "Nyangwe"
    ],
    "name:nld_x_preferred":[
        "Nyangwe"
    ],
    "name:spa_x_preferred":[
        "Nyangwe"
    ],
    "name:swe_x_preferred":[
        "Nyangwe"
    ],
    "wof:name":"Nyangwe",
    "wof:placetype":"locality"
},
  "geometry": {"coordinates":[30.77472,-4.17083],"type":"Point"}
}