{
  "type": "Feature",
  "properties": {
    "gn:admin1_code":"21.0",
    "gn:asciiname":"Kuwani",
    "gn:country_code":"TZ",
    "gn:dem":-9999,
    "gn:feature_class":"P",
    "gn:feature_code":"PPL",
    "gn:name":"Kuwani",
    "gn:population":0,
    "gn:timezone":"Africa/Dar_es_Salaam",
    "iso:country":"TZ",
    "wof:name":"Kuwani",
    "wof:placetype":"locality"
},
  "geometry": {"coordinates":[39.41667,-6.35],"type":"Point"}
}