{
  "type": "Feature",
  "properties": {
    "gn:country":"TZ",
    "gn:fcode":"PPL",
    "gn:population":22551,
    "iso:country":"TZ",
    "name:ceb_x_preferred":[
        "Maswa District"
    ],
    "name:deu_x_preferred":[
        "Maswa"
    ],
    "name:ell_x_preferred":[
        "\u03a0\u03b5\u03c1\u03b9\u03bf\u03c7\u03ae \u039c\u03ac\u03c3\u03bf\u03c5\u03b1"
    ],
    "name:eng_x_preferred":[
        "Maswa District"
    ],
    "name:rgn_x_preferred":[
        "Ndungu"
    ],
    "name:swa_x_preferred":[
        "Maswa"
    ],
    "name:vie_x_preferred":[
        "Maswa"
    ],
    "name:zul_x_preferred":[
        "Maswa District"
    ],
    "qs:name":"Lalago",
    "qs:photos_9r":0,
    "qs:photos_sr":0,
    "qs:pop_sr":"7",
    "wd:wordcount":171,
    "wof:name":"Lalago",
    "wof:placetype":"locality",
    "wof:population":22551
},
  "geometry": {"coordinates":[33.95,-3.45],"type":"Point"}
}