{
  "type": "Feature",
  "properties": {
    "gn:admin1_code":"5.0",
    "gn:admin2_code":"1602",
    "gn:admin3_code":"1602021",
    "gn:asciiname":"Sabigoma",
    "gn:country_code":"TZ",
    "gn:dem":1252,
    "gn:feature_class":"P",
    "gn:feature_code":"PPL",
    "gn:name":"Sabigoma",
    "gn:population":0,
    "gn:timezone":"Africa/Dar_es_Salaam",
    "iso:country":"TZ",
    "wof:name":"Sabigoma",
    "wof:placetype":"locality"
},
  "geometry": {"coordinates":[30.29,-4.02417],"type":"Point"}
}