{
  "type": "Feature",
  "properties": {
    "gn:admin1_code":"21.0",
    "gn:admin2_code":"5202",
    "gn:admin3_code":"5202111",
    "gn:asciiname":"Mau",
    "gn:country_code":"TZ",
    "gn:dem":16,
    "gn:feature_class":"P",
    "gn:feature_code":"PPL",
    "gn:name":"Mau",
    "gn:population":0,
    "gn:timezone":"Africa/Dar_es_Salaam",
    "iso:country":"TZ",
    "wof:name":"Mau",
    "wof:placetype":"locality"
},
  "geometry": {"coordinates":[39.45,-6.36667],"type":"Point"}
}