{
  "type": "Feature",
  "properties": {
    "gn:admin1_code":"20.0",
    "gn:admin2_code":"5501",
    "gn:admin3_code":"5501013",
    "gn:asciiname":"Mchekeni",
    "gn:country_code":"TZ",
    "gn:dem":20,
    "gn:feature_class":"P",
    "gn:feature_code":"PPL",
    "gn:name":"Mchekeni",
    "gn:population":0,
    "gn:timezone":"Africa/Dar_es_Salaam",
    "iso:country":"TZ",
    "wof:name":"Mchekeni",
    "wof:placetype":"locality"
},
  "geometry": {"coordinates":[39.76667,-5.26667],"type":"Point"}
}