{
  "type": "Feature",
  "properties": {
    "gn:admin1_code":"6.0",
    "gn:admin2_code":"0302",
    "gn:admin3_code":"0302163",
    "gn:asciiname":"Masinde",
    "gn:country_code":"TZ",
    "gn:dem":684,
    "gn:feature_class":"P",
    "gn:feature_code":"PPL",
    "gn:name":"Masinde",
    "gn:population":0,
    "gn:timezone":"Africa/Dar_es_Salaam",
    "iso:country":"TZ",
    "wof:name":"Masinde",
    "wof:placetype":"locality"
},
  "geometry": {"coordinates":[37.43333,-3.65],"type":"Point"}
}