{
  "type": "Feature",
  "properties": {
    "gn:admin1_code":"4.0",
    "gn:admin2_code":"1104",
    "gn:admin3_code":"1104201",
    "gn:asciiname":"Ibaka",
    "gn:country_code":"TZ",
    "gn:dem":1023,
    "gn:feature_class":"P",
    "gn:feature_code":"PPL",
    "gn:name":"Ibaka",
    "gn:population":0,
    "gn:timezone":"Africa/Dar_es_Salaam",
    "iso:country":"TZ",
    "name:eng_x_preferred":[
        "Ibaka"
    ],
    "wof:name":"Ibaka",
    "wof:placetype":"locality"
},
  "geometry": {"coordinates":[36.15602,-7.30325],"type":"Point"}
}