{
  "type": "Feature",
  "properties": {
    "gn:admin1_code":"18.0",
    "gn:admin2_code":"0407",
    "gn:admin3_code":"0407181",
    "gn:asciiname":"Tamota",
    "gn:country_code":"TZ",
    "gn:dem":750,
    "gn:feature_class":"P",
    "gn:feature_code":"PPL",
    "gn:name":"Tamota",
    "gn:population":0,
    "gn:timezone":"Africa/Dar_es_Salaam",
    "iso:country":"TZ",
    "wof:name":"Tamota",
    "wof:placetype":"locality"
},
  "geometry": {"coordinates":[37.55,-5.58333],"type":"Point"}
}