{
  "type": "Feature",
  "properties": {
    "gn:admin1_code":"10.0",
    "gn:admin2_code":"0506",
    "gn:admin3_code":"0506071",
    "gn:asciiname":"Msangazi",
    "gn:country_code":"TZ",
    "gn:dem":1155,
    "gn:feature_class":"P",
    "gn:feature_code":"PPL",
    "gn:name":"Msangazi",
    "gn:population":0,
    "gn:timezone":"Africa/Dar_es_Salaam",
    "iso:country":"TZ",
    "wof:name":"Msangazi",
    "wof:placetype":"locality"
},
  "geometry": {"coordinates":[37.58333,-6.08333],"type":"Point"}
}