{
  "type": "Feature",
  "properties": {
    "gn:admin1_code":"18.0",
    "gn:admin2_code":"0410",
    "gn:admin3_code":"0410082",
    "gn:asciiname":"Gombero",
    "gn:country_code":"TZ",
    "gn:dem":719,
    "gn:feature_class":"P",
    "gn:feature_code":"PPL",
    "gn:name":"Gombero",
    "gn:population":0,
    "gn:timezone":"Africa/Dar_es_Salaam",
    "iso:country":"TZ",
    "wof:name":"Gombero",
    "wof:placetype":"locality"
},
  "geometry": {"coordinates":[37.81667,-5.55],"type":"Point"}
}