{
  "type": "Feature",
  "properties": {
    "gn:admin1_code":"19.0",
    "gn:admin2_code":"1804",
    "gn:admin3_code":"1804061",
    "gn:asciiname":"Nyamahanga",
    "gn:country_code":"TZ",
    "gn:dem":1401,
    "gn:feature_class":"P",
    "gn:feature_code":"PPL",
    "gn:name":"Nyamahanga",
    "gn:population":0,
    "gn:timezone":"Africa/Dar_es_Salaam",
    "iso:country":"TZ",
    "wof:name":"Nyamahanga",
    "wof:placetype":"locality"
},
  "geometry": {"coordinates":[31.33194,-2.69861],"type":"Point"}
}