{
  "type": "Feature",
  "properties": {
    "gn:admin1_code":"6.0",
    "gn:admin2_code":"0304",
    "gn:admin3_code":"0304111",
    "gn:asciiname":"Komakya",
    "gn:country_code":"TZ",
    "gn:dem":1206,
    "gn:feature_class":"P",
    "gn:feature_code":"PPL",
    "gn:name":"Komakya",
    "gn:population":0,
    "gn:timezone":"Africa/Dar_es_Salaam",
    "iso:country":"TZ",
    "wof:name":"Komakya",
    "wof:placetype":"locality"
},
  "geometry": {"coordinates":[37.43333,-3.31667],"type":"Point"}
}