{
  "type": "Feature",
  "properties": {
    "iso:country":"TZ",
    "name:ceb_x_preferred":[
        "Ngorongoro"
    ],
    "name:eng_x_preferred":[
        "Ngorongoro"
    ],
    "name:fas_x_preferred":[
        "\u0627\u0646\u06af\u0648\u0631\u0648\u0646\u06af\u0648\u0631\u0648"
    ],
    "name:ita_x_preferred":[
        "Ngorongoro"
    ],
    "name:nld_x_preferred":[
        "Ngorongoro"
    ],
    "name:swa_x_preferred":[
        "Ngorongoro"
    ],
    "ne:ADM0CAP":0.0,
    "ne:ADM0NAME":"Tanzania",
    "ne:ADM0_A3":"TZA",
    "ne:ADM1NAME":"Arusha",
    "ne:ADMIN1_COD":0,
    "ne:CAPALT":0,
    "ne:CHANGED":4,
    "ne:CHECKME":0,
    "ne:COMPARE":0,
    "ne:DIFFASCII":0,
    "ne:DIFFNOTE":"Population from GeoNames.",
    "ne:ELEVATION":0.0,
    "ne:FEATURECLA":"Populated place",
    "ne:FEATURE_CL":"P",
    "ne:FEATURE_CO":"PPL",
    "ne:GEONAMEID":151610,
    "ne:GEONAMESNO":"Geonames ascii name + lat.d + long.d matching.",
    "ne:GN_ASCII":"Ngorongoro",
    "ne:GN_POP":10836,
    "ne:GTOPO30":2225.0,
    "ne:ISO_A2":"TZ",
    "ne:LABELRANK":5,
    "ne:LATITUDE":-3.249583,
    "ne:LONGITUDE":35.519992,
    "ne:LS_MATCH":0,
    "ne:LS_NAME":"Ngorongoro",
    "ne:MAX_AREAKM":0.0,
    "ne:MAX_AREAMI":0.0,
    "ne:MAX_BBXMAX":0.0,
    "ne:MAX_BBXMIN":0.0,
    "ne:MAX_BBYMAX":0.0,
    "ne:MAX_BBYMIN":0.0,
    "ne:MAX_NATSCA":0.0,
    "ne:MAX_PERKM":0.0,
    "ne:MAX_PERMI":0.0,
    "ne:MAX_POP10":0,
    "ne:MAX_POP20":0,
    "ne:MAX_POP300":0,
    "ne:MAX_POP310":0,
    "ne:MAX_POP50":0,
    "ne:MEAN_BBXC":0.0,
    "ne:MEAN_BBYC":0.0,
    "ne:MEGACITY":0,
    "ne:MIN_AREAKM":0.0,
    "ne:MIN_AREAMI":0.0,
    "ne:MIN_BBXMAX":0.0,
    "ne:MIN_BBXMIN":0.0,
    "ne:MIN_BBYMAX":0.0,
    "ne:MIN_BBYMIN":0.0,
    "ne:MIN_PERKM":0.0,
    "ne:MIN_PERMI":0.0,
    "ne:NAME":"Ngorongoro",
    "ne:NAMEASCII":"Ngorongoro",
    "ne:NAMEDIFF":0,
    "ne:NATSCALE":20,
    "ne:POP1950":0,
    "ne:POP1955":0,
    "ne:POP1960":0,
    "ne:POP1965":0,
    "ne:POP1970":0,
    "ne:POP1975":0,
    "ne:POP1980":0,
    "ne:POP1985":0,
    "ne:POP1990":0,
    "ne:POP1995":0,
    "ne:POP2000":0,
    "ne:POP2005":0,
    "ne:POP2010":0,
    "ne:POP2015":0,
    "ne:POP2020":0,
    "ne:POP2025":0,
    "ne:POP2050":0,
    "ne:POP_MAX":10836,
    "ne:POP_MIN":10836,
    "ne:POP_OTHER":0,
    "ne:RANK_MAX":6,
    "ne:RANK_MIN":6,
    "ne:SCALERANK":7,
    "ne:SOV0NAME":"United Republic of Tanzania",
    "ne:SOV_A3":"TZA",
    "ne:TIMEZONE":"Africa/Dar_es_Salaam",
    "ne:UN_FID":0,
    "ne:UN_LAT":0.0,
    "ne:UN_LONG":0.0,
    "ne:WORLDCITY":0,
    "qs:gn_country":"TZ",
    "qs:gn_fcode":"PPL",
    "qs:gn_pop":10836,
    "qs:name":"Ngorongoro",
    "qs:name_adm0":"Tanzania",
    "qs:name_adm1":"Arusha",
    "qs:photos":1975,
    "qs:photos_1k":400,
    "qs:photos_9k":9,
    "qs:photos_9r":9,
    "qs:photos_all":1975,
    "qs:photos_sr":15,
    "qs:placetype":"Town",
    "qs:pop_sr":"6",
    "qs:woe_adm0":23424973,
    "wof:name":"Ngorongoro",
    "wof:placetype":"locality",
    "wof:population":10836
},
  "geometry": {"coordinates":[35.48747,-3.23973],"type":"Point"}
}