{
  "type": "Feature",
  "properties": {
    "gn:admin1_code":"2.0",
    "gn:admin2_code":"0606",
    "gn:admin3_code":"0606071",
    "gn:asciiname":"Chole",
    "gn:country_code":"TZ",
    "gn:dem":5,
    "gn:feature_class":"P",
    "gn:feature_code":"PPL",
    "gn:name":"Chole",
    "gn:population":0,
    "gn:timezone":"Africa/Dar_es_Salaam",
    "iso:country":"TZ",
    "name:eng_x_preferred":[
        "Chole"
    ],
    "wof:name":"Chole",
    "wof:placetype":"locality"
},
  "geometry": {"coordinates":[39.76667,-7.98333],"type":"Point"}
}