{
  "type": "Feature",
  "properties": {
    "gn:admin1_code":"24.0",
    "gn:admin2_code":"1503",
    "gn:admin3_code":"1503013",
    "gn:asciiname":"Utinta",
    "gn:country_code":"TZ",
    "gn:dem":910,
    "gn:feature_class":"P",
    "gn:feature_code":"PPL",
    "gn:name":"Utinta",
    "gn:population":0,
    "gn:timezone":"Africa/Dar_es_Salaam",
    "iso:country":"TZ",
    "wof:name":"Utinta",
    "wof:placetype":"locality"
},
  "geometry": {"coordinates":[30.51667,-7.13333],"type":"Point"}
}