{
  "type": "Feature",
  "properties": {
    "gn:admin1_code":"11.0",
    "gn:admin2_code":"0903",
    "gn:admin3_code":"0903083",
    "gn:asciiname":"Chinmongwe",
    "gn:country_code":"TZ",
    "gn:dem":243,
    "gn:feature_class":"P",
    "gn:feature_code":"PPL",
    "gn:name":"Chinmongwe",
    "gn:population":0,
    "gn:timezone":"Africa/Dar_es_Salaam",
    "iso:country":"TZ",
    "wof:name":"Chinmongwe",
    "wof:placetype":"locality"
},
  "geometry": {"coordinates":[38.98333,-10.46667],"type":"Point"}
}