{
  "type": "Feature",
  "properties": {
    "gn:admin1_code":"2.0",
    "gn:admin2_code":"0607",
    "gn:admin3_code":"0607072",
    "gn:asciiname":"Chamangwe",
    "gn:country_code":"TZ",
    "gn:dem":61,
    "gn:feature_class":"P",
    "gn:feature_code":"PPL",
    "gn:name":"Chamangwe",
    "gn:population":0,
    "gn:timezone":"Africa/Dar_es_Salaam",
    "iso:country":"TZ",
    "wof:name":"Chamangwe",
    "wof:placetype":"locality"
},
  "geometry": {"coordinates":[38.96667,-6.56667],"type":"Point"}
}