{
  "type": "Feature",
  "properties": {
    "gn:admin1_code":"5.0",
    "gn:admin2_code":"1601",
    "gn:admin3_code":"1601051",
    "gn:asciiname":"Mpagwe",
    "gn:country_code":"TZ",
    "gn:dem":1193,
    "gn:feature_class":"P",
    "gn:feature_code":"PPL",
    "gn:name":"Mpagwe",
    "gn:population":0,
    "gn:timezone":"Africa/Dar_es_Salaam",
    "iso:country":"TZ",
    "wof:name":"Mpagwe",
    "wof:placetype":"locality"
},
  "geometry": {"coordinates":[31.02944,-4.72944],"type":"Point"}
}