{
  "type": "Feature",
  "properties": {
    "gn:admin1_code":"2.0",
    "gn:admin2_code":"0605",
    "gn:admin3_code":"0605181",
    "gn:asciiname":"Ndundu Tawa",
    "gn:country_code":"TZ",
    "gn:dem":12,
    "gn:feature_class":"P",
    "gn:feature_code":"PPL",
    "gn:name":"Ndundu Tawa",
    "gn:population":0,
    "gn:timezone":"Africa/Dar_es_Salaam",
    "iso:country":"TZ",
    "name:eng_x_preferred":[
        "Ndundu Tawa"
    ],
    "name:eng_x_variant":[
        "Ndundatawa"
    ],
    "wof:name":"Ndundu Tawa",
    "wof:placetype":"locality"
},
  "geometry": {"coordinates":[39.25612,-8.17065],"type":"Point"}
}