{
  "type": "Feature",
  "properties": {
    "gn:admin1_code":"10.0",
    "gn:admin2_code":"0503",
    "gn:admin3_code":"0503181",
    "gn:asciiname":"Taveta",
    "gn:country_code":"TZ",
    "gn:dem":515,
    "gn:feature_class":"P",
    "gn:feature_code":"PPL",
    "gn:name":"Taveta",
    "gn:population":0,
    "gn:timezone":"Africa/Dar_es_Salaam",
    "iso:country":"TZ",
    "name:deu_x_preferred":[
        "Taveta"
    ],
    "name:nld_x_preferred":[
        "Taveta"
    ],
    "name:spa_x_preferred":[
        "Taveta"
    ],
    "wof:name":"Taveta",
    "wof:placetype":"locality"
},
  "geometry": {"coordinates":[35.61667,-9.01667],"type":"Point"}
}