{
  "type": "Feature",
  "properties": {
    "gn:admin1_code":"17.0",
    "gn:admin2_code":"1406",
    "gn:admin3_code":"1406151",
    "gn:asciiname":"Igalula",
    "gn:country_code":"TZ",
    "gn:dem":1200,
    "gn:feature_class":"P",
    "gn:feature_code":"PPL",
    "gn:name":"Igalula",
    "gn:population":0,
    "gn:timezone":"Africa/Dar_es_Salaam",
    "iso:country":"TZ",
    "wof:name":"Igalula",
    "wof:placetype":"locality"
},
  "geometry": {"coordinates":[32.83333,-4.95],"type":"Point"}
}