{
  "type": "Feature",
  "properties": {
    "gn:admin1_code":"22.0",
    "gn:admin2_code":"5102",
    "gn:admin3_code":"5102141",
    "gn:asciiname":"Banda Maji",
    "gn:country_code":"TZ",
    "gn:dem":76,
    "gn:feature_class":"P",
    "gn:feature_code":"PPL",
    "gn:name":"Banda Maji",
    "gn:population":0,
    "gn:timezone":"Africa/Dar_es_Salaam",
    "iso:country":"TZ",
    "name:und_x_variant":[
        "Bandumadyi",
        "Banda Maji"
    ],
    "wof:name":"Banda Maji",
    "wof:placetype":"locality"
},
  "geometry": {"coordinates":[39.28333,-5.96667],"type":"Point"}
}