{
  "type": "Feature",
  "properties": {
    "gn:admin1_code":"10.0",
    "gn:admin2_code":"0501",
    "gn:admin3_code":"0501193",
    "gn:asciiname":"Mgunda",
    "gn:country_code":"TZ",
    "gn:dem":389,
    "gn:feature_class":"P",
    "gn:feature_code":"PPL",
    "gn:name":"Mgunda",
    "gn:population":0,
    "gn:timezone":"Africa/Dar_es_Salaam",
    "iso:country":"TZ",
    "wof:name":"Mgunda",
    "wof:placetype":"locality"
},
  "geometry": {"coordinates":[37.26667,-7.45],"type":"Point"}
}