{
  "type": "Feature",
  "properties": {
    "gn:admin1_code":"3.0",
    "gn:admin2_code":"0106",
    "gn:admin3_code":"0106151",
    "gn:asciiname":"Nondwa",
    "gn:country_code":"TZ",
    "gn:dem":890,
    "gn:feature_class":"P",
    "gn:feature_code":"PPL",
    "gn:name":"Nondwa",
    "gn:population":0,
    "gn:timezone":"Africa/Dar_es_Salaam",
    "iso:country":"TZ",
    "wof:name":"Nondwa",
    "wof:placetype":"locality"
},
  "geometry": {"coordinates":[35.33333,-6.43333],"type":"Point"}
}