{
  "type": "Feature",
  "properties": {
    "gn:admin1_code":"3.0",
    "gn:admin2_code":"0105",
    "gn:admin3_code":"0105131",
    "gn:asciiname":"Kisasa",
    "gn:country_code":"TZ",
    "gn:dem":1117,
    "gn:feature_class":"P",
    "gn:feature_code":"PPL",
    "gn:name":"Kisasa",
    "gn:population":10000,
    "gn:timezone":"Africa/Dar_es_Salaam",
    "iso:country":"TZ",
    "wof:name":"Kisasa",
    "wof:placetype":"locality",
    "wof:population":10000
},
  "geometry": {"coordinates":[35.79266,-6.17526],"type":"Point"}
}