{
  "type": "Feature",
  "properties": {
    "gn:admin1_code":"9.0",
    "gn:asciiname":"Ngomba",
    "gn:country_code":"TZ",
    "gn:dem":801,
    "gn:feature_class":"P",
    "gn:feature_code":"PPL",
    "gn:name":"Ngomba",
    "gn:population":0,
    "gn:timezone":"Africa/Dar_es_Salaam",
    "iso:country":"TZ",
    "wof:name":"Ngomba",
    "wof:placetype":"locality"
},
  "geometry": {"coordinates":[32.88333,-8.38333],"type":"Point"}
}