{
  "type": "Feature",
  "properties": {
    "gn:admin1_code":"18.0",
    "gn:admin2_code":"0402",
    "gn:admin3_code":"0402161",
    "gn:asciiname":"Mntindilo",
    "gn:country_code":"TZ",
    "gn:dem":434,
    "gn:feature_class":"P",
    "gn:feature_code":"PPL",
    "gn:name":"Mntindilo",
    "gn:population":0,
    "gn:timezone":"Africa/Dar_es_Salaam",
    "iso:country":"TZ",
    "name:und_x_variant":[
        "Mtindilo",
        "Mntindilo"
    ],
    "wof:name":"Mntindilo",
    "wof:placetype":"locality"
},
  "geometry": {"coordinates":[38.11667,-4.73333],"type":"Point"}
}