{
  "type": "Feature",
  "properties": {
    "iso:country":"TZ",
    "name:eng_x_preferred":[
        "Katumba"
    ],
    "name:fra_x_preferred":[
        "Katumba"
    ],
    "name:nld_x_preferred":[
        "Katumba"
    ],
    "name:pol_x_preferred":[
        "Katumba"
    ],
    "name:rus_x_preferred":[
        "\u041a\u0430\u0442\u0443\u043c\u0431\u0430"
    ],
    "name:swa_x_preferred":[
        "Katumba"
    ],
    "name:unk_x_variant":[
        "Kabumba"
    ],
    "qs:gn_country":"TZ",
    "qs:gn_fcode":"PPL",
    "qs:gn_pop":108558,
    "qs:name":"Katumba",
    "qs:name_adm0":"Tanzania",
    "qs:name_adm1":"Mbeya",
    "qs:photos":0,
    "qs:photos_1k":0,
    "qs:photos_9k":0,
    "qs:photos_9r":0,
    "qs:photos_all":0,
    "qs:photos_sr":0,
    "qs:placetype":"Town",
    "qs:pop_sr":"9",
    "qs:woe_adm0":23424973,
    "wd:wordcount":100,
    "wof:name":"Katumba",
    "wof:placetype":"locality",
    "wof:population":108558
},
  "geometry": {"coordinates":[33.61667,-9.23333],"type":"Point"}
}