{
  "type": "Feature",
  "properties": {
    "gn:admin1_code":"22.0",
    "gn:admin2_code":"5102",
    "gn:admin3_code":"5102131",
    "gn:asciiname":"Kinduni Mchonga",
    "gn:country_code":"TZ",
    "gn:dem":59,
    "gn:feature_class":"P",
    "gn:feature_code":"PPL",
    "gn:name":"Kinduni Mchonga",
    "gn:population":0,
    "gn:timezone":"Africa/Dar_es_Salaam",
    "iso:country":"TZ",
    "wof:name":"Kinduni Mchonga",
    "wof:placetype":"locality"
},
  "geometry": {"coordinates":[39.26667,-5.98333],"type":"Point"}
}