{
  "type": "Feature",
  "properties": {
    "gn:admin1_code":"7.0",
    "gn:admin2_code":"0802",
    "gn:admin3_code":"0802281",
    "gn:asciiname":"Nangaru",
    "gn:country_code":"TZ",
    "gn:dem":256,
    "gn:feature_class":"P",
    "gn:feature_code":"PPL",
    "gn:name":"Nangaru",
    "gn:population":0,
    "gn:timezone":"Africa/Dar_es_Salaam",
    "iso:country":"TZ",
    "wof:name":"Nangaru",
    "wof:placetype":"locality"
},
  "geometry": {"coordinates":[39.46667,-9.85],"type":"Point"}
}