{
  "type": "Feature",
  "properties": {
    "gn:admin1_code":"16.0",
    "gn:admin2_code":"1305",
    "gn:admin3_code":"1305181",
    "gn:asciiname":"Bungu",
    "gn:country_code":"TZ",
    "gn:dem":1234,
    "gn:feature_class":"P",
    "gn:feature_code":"PPL",
    "gn:name":"Bungu",
    "gn:population":0,
    "gn:timezone":"Africa/Dar_es_Salaam",
    "iso:country":"TZ",
    "wof:name":"Bungu",
    "wof:placetype":"locality"
},
  "geometry": {"coordinates":[34.41667,-4.93333],"type":"Point"}
}