{
  "type": "Feature",
  "properties": {
    "gn:admin1_code":"16.0",
    "gn:admin2_code":"1301",
    "gn:admin3_code":"1301011",
    "gn:asciiname":"Madalawa",
    "gn:country_code":"TZ",
    "gn:dem":1056,
    "gn:feature_class":"P",
    "gn:feature_code":"PPL",
    "gn:name":"Madalawa",
    "gn:population":0,
    "gn:timezone":"Africa/Dar_es_Salaam",
    "iso:country":"TZ",
    "wof:name":"Madalawa",
    "wof:placetype":"locality"
},
  "geometry": {"coordinates":[34.03333,-4.66667],"type":"Point"}
}