{
  "type": "Feature",
  "properties": {
    "gn:admin1_code":"6.0",
    "gn:admin2_code":"0302",
    "gn:admin3_code":"0302141",
    "gn:asciiname":"Kilomeni",
    "gn:country_code":"TZ",
    "gn:dem":1724,
    "gn:feature_class":"P",
    "gn:feature_code":"PPL",
    "gn:name":"Kilomeni",
    "gn:population":0,
    "gn:timezone":"Africa/Dar_es_Salaam",
    "iso:country":"TZ",
    "name:und_x_variant":[
        "Kilonchi",
        "Kilomeni"
    ],
    "wof:name":"Kilomeni",
    "wof:placetype":"locality"
},
  "geometry": {"coordinates":[37.65,-3.76667],"type":"Point"}
}