{
  "type": "Feature",
  "properties": {
    "gn:admin1_code":"12.0",
    "gn:admin2_code":"1905",
    "gn:admin3_code":"1905101",
    "gn:asciiname":"Ngoma",
    "gn:country_code":"TZ",
    "gn:dem":1172,
    "gn:feature_class":"P",
    "gn:feature_code":"PPL",
    "gn:name":"Ngoma",
    "gn:population":0,
    "gn:timezone":"Africa/Dar_es_Salaam",
    "iso:country":"TZ",
    "name:bar_x_preferred":[
        "Ngoma"
    ],
    "name:ceb_x_preferred":[
        "Ngoma"
    ],
    "name:deu_x_preferred":[
        "Ngoma"
    ],
    "name:est_x_preferred":[
        "Ngoma"
    ],
    "name:fra_x_preferred":[
        "Ngoma"
    ],
    "name:ita_x_preferred":[
        "Ngoma"
    ],
    "name:pol_x_preferred":[
        "Ngoma"
    ],
    "name:swa_x_preferred":[
        "Ngoma"
    ],
    "name:swe_x_preferred":[
        "Ngoma"
    ],
    "wof:name":"Ngoma",
    "wof:placetype":"locality"
},
  "geometry": {"coordinates":[32.6584,-2.91498],"type":"Point"}
}