{
  "type": "Feature",
  "properties": {
    "gn:admin1_code":"16.0",
    "gn:admin2_code":"1302",
    "gn:admin3_code":"1302181",
    "gn:asciiname":"Kijota",
    "gn:country_code":"TZ",
    "gn:dem":1620,
    "gn:feature_class":"P",
    "gn:feature_code":"PPL",
    "gn:name":"Kijota",
    "gn:population":0,
    "gn:timezone":"Africa/Dar_es_Salaam",
    "iso:country":"TZ",
    "name:und_x_variant":[
        "Kigota",
        "Kijota"
    ],
    "wof:name":"Kijota",
    "wof:placetype":"locality"
},
  "geometry": {"coordinates":[34.85,-4.58333],"type":"Point"}
}