{
  "type": "Feature",
  "properties": {
    "gn:admin1_code":"29.0",
    "gn:admin2_code":"2302",
    "gn:admin3_code":"2302041",
    "gn:asciiname":"Lusinde",
    "gn:country_code":"TZ",
    "gn:dem":1199,
    "gn:feature_class":"P",
    "gn:feature_code":"PPL",
    "gn:name":"Lusinde",
    "gn:population":0,
    "gn:timezone":"Africa/Dar_es_Salaam",
    "iso:country":"TZ",
    "name:eng_x_preferred":[
        "Lusinde"
    ],
    "wof:name":"Lusinde",
    "wof:placetype":"locality"
},
  "geometry": {"coordinates":[30.62263,-6.28165],"type":"Point"}
}