{
  "type": "Feature",
  "properties": {
    "gn:admin1_code":"18.0",
    "gn:admin2_code":"0401",
    "gn:admin3_code":"0401151",
    "gn:asciiname":"Kulasi",
    "gn:country_code":"TZ",
    "gn:dem":539,
    "gn:feature_class":"P",
    "gn:feature_code":"PPL",
    "gn:name":"Kulasi",
    "gn:population":0,
    "gn:timezone":"Africa/Dar_es_Salaam",
    "iso:country":"TZ",
    "wof:name":"Kulasi",
    "wof:placetype":"locality"
},
  "geometry": {"coordinates":[38.56667,-4.83333],"type":"Point"}
}