{
  "type": "Feature",
  "properties": {
    "gn:admin1_code":"3.0",
    "gn:admin2_code":"0101",
    "gn:admin3_code":"0101201",
    "gn:asciiname":"Chubi",
    "gn:country_code":"TZ",
    "gn:dem":1190,
    "gn:feature_class":"P",
    "gn:feature_code":"PPL",
    "gn:name":"Chubi",
    "gn:population":0,
    "gn:timezone":"Africa/Dar_es_Salaam",
    "iso:country":"TZ",
    "wof:name":"Chubi",
    "wof:placetype":"locality"
},
  "geometry": {"coordinates":[36.05,-4.53333],"type":"Point"}
}