{
  "type": "Feature",
  "properties": {
    "gn:admin1_code":"25.0",
    "gn:admin2_code":"5301",
    "gn:admin3_code":"5301333",
    "gn:asciiname":"Kikaangoni",
    "gn:cc2":"TZ",
    "gn:country_code":"TZ",
    "gn:dem":18,
    "gn:feature_class":"P",
    "gn:feature_code":"PPL",
    "gn:name":"Kikaangoni",
    "gn:population":0,
    "gn:timezone":"Africa/Dar_es_Salaam",
    "iso:country":"TZ",
    "name:und_x_variant":[
        "Kikaagoni",
        "Kikaangoni"
    ],
    "wof:name":"Kikaangoni",
    "wof:placetype":"locality"
},
  "geometry": {"coordinates":[39.21667,-6.08333],"type":"Point"}
}