{
  "type": "Feature",
  "properties": {
    "gn:admin1_code":"17.0",
    "gn:admin2_code":"1405",
    "gn:admin3_code":"1405121",
    "gn:asciiname":"Ipata",
    "gn:country_code":"TZ",
    "gn:dem":1096,
    "gn:feature_class":"P",
    "gn:feature_code":"PPL",
    "gn:name":"Ipata",
    "gn:population":0,
    "gn:timezone":"Africa/Dar_es_Salaam",
    "iso:country":"TZ",
    "wof:name":"Ipata",
    "wof:placetype":"locality"
},
  "geometry": {"coordinates":[32.38333,-6.03333],"type":"Point"}
}