{
  "type": "Feature",
  "properties": {
    "gn:admin1_code":"5.0",
    "gn:admin2_code":"1606",
    "gn:admin3_code":"1606151",
    "gn:asciiname":"Kisodji",
    "gn:country_code":"TZ",
    "gn:dem":1619,
    "gn:feature_class":"P",
    "gn:feature_code":"PPL",
    "gn:name":"Kisodji",
    "gn:population":0,
    "gn:timezone":"Africa/Dar_es_Salaam",
    "iso:country":"TZ",
    "wof:name":"Kisodji",
    "wof:placetype":"locality"
},
  "geometry": {"coordinates":[29.84417,-4.42944],"type":"Point"}
}