{
  "type": "Feature",
  "properties": {
    "gn:admin1_code":"14.0",
    "gn:admin2_code":"1005",
    "gn:admin3_code":"1005061",
    "gn:asciiname":"Mawa",
    "gn:country_code":"TZ",
    "gn:dem":1051,
    "gn:feature_class":"P",
    "gn:feature_code":"PPL",
    "gn:name":"Mawa",
    "gn:population":0,
    "gn:timezone":"Africa/Dar_es_Salaam",
    "iso:country":"TZ",
    "name:ceb_x_preferred":[
        "Mawa"
    ],
    "name:fra_x_preferred":[
        "Mawa"
    ],
    "name:swe_x_preferred":[
        "Mawa"
    ],
    "wof:name":"Mawa",
    "wof:placetype":"locality"
},
  "geometry": {"coordinates":[35.75,-10.51667],"type":"Point"}
}