{
  "type": "Feature",
  "properties": {
    "gn:admin1_code":"17.0",
    "gn:admin2_code":"1403",
    "gn:admin3_code":"1403081",
    "gn:asciiname":"Usungu",
    "gn:country_code":"TZ",
    "gn:dem":1187,
    "gn:feature_class":"P",
    "gn:feature_code":"PPL",
    "gn:name":"Usungu",
    "gn:population":0,
    "gn:timezone":"Africa/Dar_es_Salaam",
    "iso:country":"TZ",
    "wof:name":"Usungu",
    "wof:placetype":"locality"
},
  "geometry": {"coordinates":[32.45,-4.96667],"type":"Point"}
}