{
  "type": "Feature",
  "properties": {
    "gn:admin1_code":"29.0",
    "gn:admin2_code":"2303",
    "gn:admin3_code":"2303021",
    "gn:asciiname":"Ugalla",
    "gn:country_code":"TZ",
    "gn:dem":1129,
    "gn:feature_class":"P",
    "gn:feature_code":"PPL",
    "gn:name":"Ugalla",
    "gn:population":0,
    "gn:timezone":"Africa/Dar_es_Salaam",
    "iso:country":"TZ",
    "name:ara_x_preferred":[
        "\u0623\u0648\u063a\u0627\u0644\u0627"
    ],
    "name:ben_x_preferred":[
        "\u0989\u0997\u09be\u09b2\u09cd\u09b2\u09be"
    ],
    "name:deu_x_preferred":[
        "Ugalla River"
    ],
    "name:deu_x_variant":[
        "Ugalla"
    ],
    "name:ell_x_preferred":[
        "\u039f\u03c5\u03b3\u03ba\u03ac\u03bb\u03b1"
    ],
    "name:fas_x_preferred":[
        "\u0627\u0648\u06af\u0627\u0644\u0627"
    ],
    "name:fra_x_preferred":[
        "Ugalla"
    ],
    "name:heb_x_preferred":[
        "\u05d0\u05d5\u05d2\u05d0\u05dc\u05d4"
    ],
    "name:hin_x_preferred":[
        "\u0909\u0917\u093e\u0932\u093e"
    ],
    "name:hun_x_preferred":[
        "Ugalla"
    ],
    "name:ind_x_preferred":[
        "Ugalla"
    ],
    "name:ita_x_preferred":[
        "Ugalla"
    ],
    "name:jpn_x_preferred":[
        "\u30a6\u30ac\u30e9\u5ddd"
    ],
    "name:kor_x_preferred":[
        "\uc6b0\uac08\ub77c"
    ],
    "name:nld_x_preferred":[
        "Ugalla"
    ],
    "name:pol_x_preferred":[
        "Ugalla"
    ],
    "name:por_x_preferred":[
        "Ugalla"
    ],
    "name:rus_x_preferred":[
        "\u0440\u0435\u043a\u0430 \u0423\u0433\u0430\u043b\u043b\u0430"
    ],
    "name:spa_x_preferred":[
        "Ugalla"
    ],
    "name:swe_x_preferred":[
        "Ugalla"
    ],
    "name:tur_x_preferred":[
        "Ugalla"
    ],
    "name:ukr_x_preferred":[
        "\u0423\u0433\u0430\u043b\u043b\u0430"
    ],
    "name:urd_x_preferred":[
        "\u0627\u0648\u06af\u0627\u0644\u0627"
    ],
    "name:vie_x_preferred":[
        "S\u00f4ng Ugalla"
    ],
    "name:zho_cn_x_preferred":[
        "\u4e4c\u52a0\u62c9\u6cb3"
    ],
    "name:zho_tw_x_preferred":[
        "\u70cf\u52a0\u62c9\u6cb3"
    ],
    "wof:name":"Ugalla",
    "wof:placetype":"locality"
},
  "geometry": {"coordinates":[31.15,-5.78333],"type":"Point"}
}