{
  "type": "Feature",
  "properties": {
    "gn:admin1_code":"29.0",
    "gn:admin2_code":"2303",
    "gn:admin3_code":"2303021",
    "gn:asciiname":"Ugalla",
    "gn:country_code":"TZ",
    "gn:dem":1129,
    "gn:feature_class":"P",
    "gn:feature_code":"PPL",
    "gn:name":"Ugalla",
    "gn:population":0,
    "gn:timezone":"Africa/Dar_es_Salaam",
    "iso:country":"TZ",
    "wof:name":"Ugalla",
    "wof:placetype":"locality"
},
  "geometry": {"coordinates":[31.15,-5.78333],"type":"Point"}
}