{
  "type": "Feature",
  "properties": {
    "gn:admin1_code":"11.0",
    "gn:admin2_code":"0907",
    "gn:admin3_code":"0907063",
    "gn:asciiname":"Mumbaka",
    "gn:country_code":"TZ",
    "gn:dem":351,
    "gn:feature_class":"P",
    "gn:feature_code":"PPL",
    "gn:name":"Mumbaka",
    "gn:population":0,
    "gn:timezone":"Africa/Dar_es_Salaam",
    "iso:country":"TZ",
    "wof:name":"Mumbaka",
    "wof:placetype":"locality"
},
  "geometry": {"coordinates":[38.86667,-10.73333],"type":"Point"}
}