{
  "type": "Feature",
  "properties": {
    "gn:admin1_code":"25.0",
    "gn:admin2_code":"5301",
    "gn:admin3_code":"5301013",
    "gn:asciiname":"Mwera Kikokani",
    "gn:country_code":"TZ",
    "gn:dem":33,
    "gn:feature_class":"P",
    "gn:feature_code":"PPL",
    "gn:name":"Mwera Kikokani",
    "gn:population":0,
    "gn:timezone":"Africa/Dar_es_Salaam",
    "iso:country":"TZ",
    "wof:name":"Mwera Kikokani",
    "wof:placetype":"locality"
},
  "geometry": {"coordinates":[39.26667,-6.15],"type":"Point"}
}