{
  "type": "Feature",
  "properties": {
    "gn:admin1_code":"8.0",
    "gn:admin2_code":"2006",
    "gn:admin3_code":"2006211",
    "gn:asciiname":"Iringo",
    "gn:country_code":"TZ",
    "gn:dem":1180,
    "gn:feature_class":"P",
    "gn:feature_code":"PPL",
    "gn:name":"Iringo",
    "gn:population":0,
    "gn:timezone":"Africa/Dar_es_Salaam",
    "iso:country":"TZ",
    "wof:name":"Iringo",
    "wof:placetype":"locality"
},
  "geometry": {"coordinates":[33.96667,-1.35],"type":"Point"}
}