{
  "type": "Feature",
  "properties": {
    "gn:admin1_code":"28.0",
    "gn:admin2_code":"2502",
    "gn:admin3_code":"2502111",
    "gn:asciiname":"Nyankurukuru",
    "gn:country_code":"TZ",
    "gn:dem":1218,
    "gn:feature_class":"P",
    "gn:feature_code":"PPL",
    "gn:name":"Nyankurukuru",
    "gn:population":0,
    "gn:timezone":"Africa/Dar_es_Salaam",
    "iso:country":"TZ",
    "name:und_x_variant":[
        "Nyankukulu",
        "Nyankurukuru"
    ],
    "wof:name":"Nyankurukuru",
    "wof:placetype":"locality"
},
  "geometry": {"coordinates":[32.58333,-3.06667],"type":"Point"}
}