{
  "type": "Feature",
  "properties": {
    "gn:admin1_code":"10.0",
    "gn:admin2_code":"0506",
    "gn:admin3_code":"0506111",
    "gn:asciiname":"Sazima",
    "gn:country_code":"TZ",
    "gn:dem":1005,
    "gn:feature_class":"P",
    "gn:feature_code":"PPL",
    "gn:name":"Sazima",
    "gn:population":0,
    "gn:timezone":"Africa/Dar_es_Salaam",
    "iso:country":"TZ",
    "name:eng_x_preferred":[
        "Sazima"
    ],
    "wof:name":"Sazima",
    "wof:placetype":"locality"
},
  "geometry": {"coordinates":[37.52529000000001,-7.1165],"type":"Point"}
}