{
  "type": "Feature",
  "properties": {
    "gn:admin1_code":"31.0",
    "gn:admin2_code":"2404",
    "gn:admin3_code":"2404101",
    "gn:asciiname":"Kilolele",
    "gn:country_code":"TZ",
    "gn:dem":1186,
    "gn:feature_class":"P",
    "gn:feature_code":"PPL",
    "gn:name":"Kilolele",
    "gn:population":0,
    "gn:timezone":"Africa/Dar_es_Salaam",
    "iso:country":"TZ",
    "name:und_x_variant":[
        "Kiloleli",
        "Kilolele"
    ],
    "wof:name":"Kilolele",
    "wof:placetype":"locality"
},
  "geometry": {"coordinates":[33.83333,-3.45],"type":"Point"}
}