{
  "type": "Feature",
  "properties": {
    "gn:admin1_code":"18.0",
    "gn:admin2_code":"0406",
    "gn:admin3_code":"0406061",
    "gn:asciiname":"Mavumbi",
    "gn:country_code":"TZ",
    "gn:dem":533,
    "gn:feature_class":"P",
    "gn:feature_code":"PPL",
    "gn:name":"Mavumbi",
    "gn:population":0,
    "gn:timezone":"Africa/Dar_es_Salaam",
    "iso:country":"TZ",
    "wof:name":"Mavumbi",
    "wof:placetype":"locality"
},
  "geometry": {"coordinates":[38.15,-5.55],"type":"Point"}
}