{
  "type": "Feature",
  "properties": {
    "gn:admin1_code":"11.0",
    "gn:admin2_code":"0906",
    "gn:admin3_code":"0906071",
    "gn:asciiname":"Chitwangule",
    "gn:country_code":"TZ",
    "gn:dem":334,
    "gn:feature_class":"P",
    "gn:feature_code":"PPL",
    "gn:name":"Chitwangule",
    "gn:population":0,
    "gn:timezone":"Africa/Dar_es_Salaam",
    "iso:country":"TZ",
    "wof:name":"Chitwangule",
    "wof:placetype":"locality"
},
  "geometry": {"coordinates":[38.63333,-10.86667],"type":"Point"}
}