{
  "type": "Feature",
  "properties": {
    "gn:admin1_code":"21.0",
    "gn:admin2_code":"5202",
    "gn:admin3_code":"5202091",
    "gn:asciiname":"Usine",
    "gn:country_code":"TZ",
    "gn:dem":9,
    "gn:feature_class":"P",
    "gn:feature_code":"PPL",
    "gn:name":"Usine",
    "gn:population":0,
    "gn:timezone":"Africa/Dar_es_Salaam",
    "iso:country":"TZ",
    "name:und_x_variant":[
        "Usini",
        "Usine"
    ],
    "wof:name":"Usine",
    "wof:placetype":"locality"
},
  "geometry": {"coordinates":[39.49645,-6.47455],"type":"Point"}
}