{
  "type": "Feature",
  "properties": {
    "gn:admin1_code":"2.0",
    "gn:admin2_code":"0604",
    "gn:admin3_code":"0604051",
    "gn:asciiname":"Boza",
    "gn:country_code":"TZ",
    "gn:dem":10,
    "gn:feature_class":"P",
    "gn:feature_code":"PPL",
    "gn:name":"Boza",
    "gn:population":0,
    "gn:timezone":"Africa/Dar_es_Salaam",
    "iso:country":"TZ",
    "name:eng_x_preferred":[
        "Boza"
    ],
    "name:eng_x_variant":[
        "Bosa"
    ],
    "name:und_x_variant":[
        "Bosa"
    ],
    "wof:name":"Boza",
    "wof:placetype":"locality"
},
  "geometry": {"coordinates":[39.42906,-7.20084],"type":"Point"}
}