{
  "type": "Feature",
  "properties": {
    "gn:admin1_code":"2.0",
    "gn:admin2_code":"0604",
    "gn:admin3_code":"0604051",
    "gn:asciiname":"Boza",
    "gn:country_code":"TZ",
    "gn:dem":10,
    "gn:feature_class":"P",
    "gn:feature_code":"PPL",
    "gn:name":"Boza",
    "gn:population":0,
    "gn:timezone":"Africa/Dar_es_Salaam",
    "iso:country":"TZ",
    "name:ara_x_preferred":[
        "\u0628\u0648\u0638\u0629"
    ],
    "name:aze_x_preferred":[
        "Boza"
    ],
    "name:bak_x_preferred":[
        "\u0411\u0443\u0499\u0430"
    ],
    "name:bel_x_preferred":[
        "\u0411\u0443\u0437\u0430"
    ],
    "name:bos_x_preferred":[
        "Boza"
    ],
    "name:bul_x_preferred":[
        "\u0411\u043e\u0437\u0430"
    ],
    "name:cat_x_preferred":[
        "Boza"
    ],
    "name:ces_x_preferred":[
        "Boza"
    ],
    "name:deu_x_preferred":[
        "Boza"
    ],
    "name:eng_x_preferred":[
        "Boza"
    ],
    "name:eng_x_variant":[
        "Bosa"
    ],
    "name:fra_x_preferred":[
        "Boza"
    ],
    "name:heb_x_preferred":[
        "\u05d1\u05e8\u05d0\u05d2\u05d4"
    ],
    "name:hrv_x_preferred":[
        "Boza"
    ],
    "name:hun_x_preferred":[
        "Boza"
    ],
    "name:hye_x_preferred":[
        "\u0532\u0578\u0582\u0566\u0561"
    ],
    "name:ita_x_preferred":[
        "Boza"
    ],
    "name:kat_x_preferred":[
        "\u10d1\u10dd\u10d6\u10d0"
    ],
    "name:kaz_x_preferred":[
        "\u0411\u043e\u0437\u0430"
    ],
    "name:kir_x_preferred":[
        "\u0411\u043e\u0437\u043e"
    ],
    "name:kor_x_preferred":[
        "\ubcf4\uc790"
    ],
    "name:lbe_x_preferred":[
        "\u0414\u0443\u043a\u044c\u0440\u0430\u0445\u04c0\u0430\u043d"
    ],
    "name:mdf_x_preferred":[
        "\u041f\u043e\u0437\u0430"
    ],
    "name:mkd_x_preferred":[
        "\u0411\u043e\u0437\u0430"
    ],
    "name:nor_x_preferred":[
        "Boza"
    ],
    "name:pol_x_preferred":[
        "Boza"
    ],
    "name:por_x_preferred":[
        "Boza"
    ],
    "name:ron_x_preferred":[
        "Brag\u0103"
    ],
    "name:rus_x_preferred":[
        "\u0411\u0443\u0437\u0430"
    ],
    "name:spa_x_preferred":[
        "Boza"
    ],
    "name:sqi_x_preferred":[
        "Boza"
    ],
    "name:srp_x_preferred":[
        "\u0411\u043e\u0437\u0430"
    ],
    "name:tat_x_preferred":[
        "\u0411\u0443\u0437\u0430"
    ],
    "name:tur_x_preferred":[
        "Boza"
    ],
    "name:ukr_x_preferred":[
        "\u0411\u0443\u0437\u0430"
    ],
    "name:und_x_variant":[
        "Bosa"
    ],
    "name:uzb_x_preferred":[
        "Bo\u02bbza"
    ],
    "name:xmf_x_preferred":[
        "\u10d1\u10dd\u10d6\u10d0"
    ],
    "name:zho_x_preferred":[
        "\u535a\u85a9"
    ],
    "wof:name":"Boza",
    "wof:placetype":"locality"
},
  "geometry": {"coordinates":[39.42906,-7.20084],"type":"Point"}
}