{
  "type": "Feature",
  "properties": {
    "gn:admin1_code":"21.0",
    "gn:admin2_code":"5202",
    "gn:admin3_code":"5202081",
    "gn:asciiname":"Dimbani",
    "gn:country_code":"TZ",
    "gn:dem":15,
    "gn:feature_class":"P",
    "gn:feature_code":"PPL",
    "gn:name":"Dimbani",
    "gn:population":0,
    "gn:timezone":"Africa/Dar_es_Salaam",
    "iso:country":"TZ",
    "name:deu_x_preferred":[
        "Dimbani"
    ],
    "name:ukr_x_preferred":[
        "\u0414\u0456\u043c\u0431\u0430\u043d\u0456"
    ],
    "name:und_x_variant":[
        "Kizimkazi Dembani",
        "Dembani",
        "Dimbani"
    ],
    "wof:name":"Dimbani",
    "wof:placetype":"locality"
},
  "geometry": {"coordinates":[39.46667,-6.43333],"type":"Point"}
}