{
  "type": "Feature",
  "properties": {
    "gn:admin1_code":"6.0",
    "gn:admin2_code":"0304",
    "gn:admin3_code":"0304031",
    "gn:asciiname":"Kokirie",
    "gn:country_code":"TZ",
    "gn:dem":1814,
    "gn:feature_class":"P",
    "gn:feature_code":"PPL",
    "gn:name":"Kokirie",
    "gn:population":0,
    "gn:timezone":"Africa/Dar_es_Salaam",
    "iso:country":"TZ",
    "wof:name":"Kokirie",
    "wof:placetype":"locality"
},
  "geometry": {"coordinates":[37.53333,-3.25],"type":"Point"}
}