{
  "type": "Feature",
  "properties": {
    "gn:admin1_code":"10.0",
    "gn:admin2_code":"0502",
    "gn:admin3_code":"0502121",
    "gn:asciiname":"Lukosi",
    "gn:country_code":"TZ",
    "gn:dem":170,
    "gn:feature_class":"P",
    "gn:feature_code":"PPL",
    "gn:name":"Lukosi",
    "gn:population":0,
    "gn:timezone":"Africa/Dar_es_Salaam",
    "iso:country":"TZ",
    "wof:name":"Lukosi",
    "wof:placetype":"locality"
},
  "geometry": {"coordinates":[38.16667,-6.83333],"type":"Point"}
}