{
  "type": "Feature",
  "properties": {
    "gn:admin1_code":"8.0",
    "gn:admin2_code":"2001",
    "gn:admin3_code":"2001281",
    "gn:asciiname":"Nyamtiro",
    "gn:country_code":"TZ",
    "gn:dem":1782,
    "gn:feature_class":"P",
    "gn:feature_code":"PPL",
    "gn:name":"Nyamtiro",
    "gn:population":0,
    "gn:timezone":"Africa/Dar_es_Salaam",
    "iso:country":"TZ",
    "wof:name":"Nyamtiro",
    "wof:placetype":"locality"
},
  "geometry": {"coordinates":[34.58333,-1.31667],"type":"Point"}
}