{
  "type": "Feature",
  "properties": {
    "gn:admin1_code":"3.0",
    "gn:asciiname":"Gombwe",
    "gn:country_code":"TZ",
    "gn:dem":873,
    "gn:feature_class":"P",
    "gn:feature_code":"PPL",
    "gn:name":"Gombwe",
    "gn:population":0,
    "gn:timezone":"Africa/Dar_es_Salaam",
    "iso:country":"TZ",
    "wof:name":"Gombwe",
    "wof:placetype":"locality"
},
  "geometry": {"coordinates":[35.48333,-6.96667],"type":"Point"}
}