{
  "type": "Feature",
  "properties": {
    "gn:admin1_code":"19.0",
    "gn:admin2_code":"1801",
    "gn:admin3_code":"1801073",
    "gn:asciiname":"Omuruyanza",
    "gn:country_code":"TZ",
    "gn:dem":1614,
    "gn:feature_class":"P",
    "gn:feature_code":"PPL",
    "gn:name":"Omuruyanza",
    "gn:population":0,
    "gn:timezone":"Africa/Dar_es_Salaam",
    "iso:country":"TZ",
    "wof:name":"Omuruyanza",
    "wof:placetype":"locality"
},
  "geometry": {"coordinates":[31.13222,-1.58083],"type":"Point"}
}