{
  "type": "Feature",
  "properties": {
    "gn:admin1_code":"2.0",
    "gn:admin2_code":"0603",
    "gn:admin3_code":"0603041",
    "gn:asciiname":"Mtamba",
    "gn:country_code":"TZ",
    "gn:dem":272,
    "gn:feature_class":"P",
    "gn:feature_code":"PPL",
    "gn:name":"Mtamba",
    "gn:population":0,
    "gn:timezone":"Africa/Dar_es_Salaam",
    "iso:country":"TZ",
    "name:eng_x_preferred":[
        "Mtamba"
    ],
    "wof:name":"Mtamba",
    "wof:placetype":"locality"
},
  "geometry": {"coordinates":[38.90539,-7.0551],"type":"Point"}
}