{
  "type": "Feature",
  "properties": {
    "gn:admin1_code":"21.0",
    "gn:admin2_code":"5201",
    "gn:admin3_code":"5201361",
    "gn:asciiname":"Pingwe",
    "gn:country_code":"TZ",
    "gn:dem":13,
    "gn:feature_class":"P",
    "gn:feature_code":"PPL",
    "gn:name":"Pingwe",
    "gn:population":0,
    "gn:timezone":"Africa/Dar_es_Salaam",
    "iso:country":"TZ",
    "name:und_x_variant":[
        "Pingwi",
        "Pingwe"
    ],
    "wof:name":"Pingwe",
    "wof:placetype":"locality"
},
  "geometry": {"coordinates":[39.51667,-6.15],"type":"Point"}
}