{
  "type": "Feature",
  "properties": {
    "gn:admin1_code":"10.0",
    "gn:admin2_code":"0502",
    "gn:admin3_code":"0502091",
    "gn:asciiname":"Singiza",
    "gn:country_code":"TZ",
    "gn:dem":783,
    "gn:feature_class":"P",
    "gn:feature_code":"PPL",
    "gn:name":"Singiza",
    "gn:population":0,
    "gn:timezone":"Africa/Dar_es_Salaam",
    "iso:country":"TZ",
    "name:eng_x_preferred":[
        "Singiza"
    ],
    "wof:name":"Singiza",
    "wof:placetype":"locality"
},
  "geometry": {"coordinates":[37.68568,-7.25907],"type":"Point"}
}