{
  "type": "Feature",
  "properties": {
    "gn:admin1_code":"17.0",
    "gn:admin2_code":"1406",
    "gn:admin3_code":"1406171",
    "gn:asciiname":"Itulu",
    "gn:country_code":"TZ",
    "gn:dem":1180,
    "gn:feature_class":"P",
    "gn:feature_code":"PPL",
    "gn:name":"Itulu",
    "gn:population":0,
    "gn:timezone":"Africa/Dar_es_Salaam",
    "iso:country":"TZ",
    "wof:name":"Itulu",
    "wof:placetype":"locality"
},
  "geometry": {"coordinates":[32.86667,-5.13333],"type":"Point"}
}