{
  "type": "Feature",
  "properties": {
    "gn:admin1_code":"5.0",
    "gn:admin2_code":"1605",
    "gn:admin3_code":"1605061",
    "gn:asciiname":"Kabeba",
    "gn:cc2":"TZ",
    "gn:country_code":"TZ",
    "gn:dem":795,
    "gn:feature_class":"P",
    "gn:feature_code":"PPL",
    "gn:name":"Kabeba",
    "gn:population":0,
    "gn:timezone":"Africa/Dar_es_Salaam",
    "iso:country":"TZ",
    "name:und_x_variant":[
        "Kababa",
        "Kabeba"
    ],
    "wof:name":"Kabeba",
    "wof:placetype":"locality"
},
  "geometry": {"coordinates":[29.82833,-5.14472],"type":"Point"}
}