{
  "type": "Feature",
  "properties": {
    "gn:admin1_code":"19.0",
    "gn:admin2_code":"1804",
    "gn:admin3_code":"1804121",
    "gn:asciiname":"Nyamahuna",
    "gn:country_code":"TZ",
    "gn:dem":1356,
    "gn:feature_class":"P",
    "gn:feature_code":"PPL",
    "gn:name":"Nyamahuna",
    "gn:population":0,
    "gn:timezone":"Africa/Dar_es_Salaam",
    "iso:country":"TZ",
    "wof:name":"Nyamahuna",
    "wof:placetype":"locality"
},
  "geometry": {"coordinates":[31.20028,-2.90389],"type":"Point"}
}