{
  "type": "Feature",
  "properties": {
    "gn:admin1_code":"10.0",
    "gn:admin2_code":"0504",
    "gn:admin3_code":"0504181",
    "gn:asciiname":"Ifema",
    "gn:country_code":"TZ",
    "gn:dem":286,
    "gn:feature_class":"P",
    "gn:feature_code":"PPL",
    "gn:name":"Ifema",
    "gn:population":0,
    "gn:timezone":"Africa/Dar_es_Salaam",
    "iso:country":"TZ",
    "wof:name":"Ifema",
    "wof:placetype":"locality"
},
  "geometry": {"coordinates":[35.95,-8.91667],"type":"Point"}
}