{
  "type": "Feature",
  "properties": {
    "gn:admin1_code":"3.0",
    "gn:admin2_code":"0105",
    "gn:admin3_code":"0105241",
    "gn:asciiname":"Nzinge",
    "gn:country_code":"TZ",
    "gn:dem":1174,
    "gn:feature_class":"P",
    "gn:feature_code":"PPL",
    "gn:name":"Nzinge",
    "gn:population":0,
    "gn:timezone":"Africa/Dar_es_Salaam",
    "iso:country":"TZ",
    "wof:name":"Nzinge",
    "wof:placetype":"locality"
},
  "geometry": {"coordinates":[35.63333,-6.16667],"type":"Point"}
}