{
  "type": "Feature",
  "properties": {
    "gn:admin1_code":"7.0",
    "gn:admin2_code":"0804",
    "gn:admin3_code":"0804091",
    "gn:asciiname":"Nyera",
    "gn:country_code":"TZ",
    "gn:dem":386,
    "gn:feature_class":"P",
    "gn:feature_code":"PPL",
    "gn:name":"Nyera",
    "gn:population":0,
    "gn:timezone":"Africa/Dar_es_Salaam",
    "iso:country":"TZ",
    "wof:name":"Nyera",
    "wof:placetype":"locality"
},
  "geometry": {"coordinates":[38.08333,-9.63333],"type":"Point"}
}