{
  "type": "Feature",
  "properties": {
    "gn:admin1_code":"19.0",
    "gn:admin2_code":"1801",
    "gn:admin3_code":"1801063",
    "gn:asciiname":"Karaize",
    "gn:country_code":"TZ",
    "gn:dem":1542,
    "gn:feature_class":"P",
    "gn:feature_code":"PPL",
    "gn:name":"Karaize",
    "gn:population":0,
    "gn:timezone":"Africa/Dar_es_Salaam",
    "iso:country":"TZ",
    "wof:name":"Karaize",
    "wof:placetype":"locality"
},
  "geometry": {"coordinates":[31.1275,-1.51556],"type":"Point"}
}