{
  "type": "Feature",
  "properties": {
    "gn:admin1_code":"5.0",
    "gn:admin2_code":"1602",
    "gn:admin3_code":"1602061",
    "gn:asciiname":"Mbiria",
    "gn:cc2":"TZ",
    "gn:country_code":"TZ",
    "gn:dem":1504,
    "gn:feature_class":"P",
    "gn:feature_code":"PPL",
    "gn:name":"Mbiria",
    "gn:population":0,
    "gn:timezone":"Africa/Dar_es_Salaam",
    "iso:country":"TZ",
    "name:und_x_variant":[
        "Mbirira",
        "Mbiria"
    ],
    "wof:name":"Mbiria",
    "wof:placetype":"locality"
},
  "geometry": {"coordinates":[30.17083,-4.35333],"type":"Point"}
}