{
  "type": "Feature",
  "properties": {
    "gn:admin1_code":"16.0",
    "gn:admin2_code":"1306",
    "gn:admin3_code":"1306011",
    "gn:asciiname":"Igengu",
    "gn:country_code":"TZ",
    "gn:dem":1231,
    "gn:feature_class":"P",
    "gn:feature_code":"PPL",
    "gn:name":"Igengu",
    "gn:population":0,
    "gn:timezone":"Africa/Dar_es_Salaam",
    "iso:country":"TZ",
    "wof:name":"Igengu",
    "wof:placetype":"locality"
},
  "geometry": {"coordinates":[34.55,-4.13333],"type":"Point"}
}