{
  "type": "Feature",
  "properties": {
    "gn:admin1_code":"8.0",
    "gn:asciiname":"Shirati",
    "gn:country_code":"TZ",
    "gn:dem":1134,
    "gn:feature_class":"P",
    "gn:feature_code":"PPL",
    "gn:name":"Shirati",
    "gn:population":0,
    "gn:timezone":"Africa/Dar_es_Salaam",
    "iso:country":"TZ",
    "name:ell_x_preferred":[
        "\u03a3\u03b9\u03c1\u03ac\u03c4\u03b9"
    ],
    "wof:name":"Shirati",
    "wof:placetype":"locality"
},
  "geometry": {"coordinates":[33.98333,-1.13333],"type":"Point"}
}