{
  "type": "Feature",
  "properties": {
    "gn:admin1_code":"2.0",
    "gn:asciiname":"Komkomba",
    "gn:country_code":"TZ",
    "gn:dem":327,
    "gn:feature_class":"P",
    "gn:feature_code":"PPL",
    "gn:name":"Komkomba",
    "gn:population":0,
    "gn:timezone":"Africa/Dar_es_Salaam",
    "iso:country":"TZ",
    "wof:name":"Komkomba",
    "wof:placetype":"locality"
},
  "geometry": {"coordinates":[37.96667,-6.15],"type":"Point"}
}