{
  "type": "Feature",
  "properties": {
    "gn:admin1_code":"19.0",
    "gn:admin2_code":"1803",
    "gn:admin3_code":"1803231",
    "gn:asciiname":"Nyakakiri",
    "gn:country_code":"TZ",
    "gn:dem":1487,
    "gn:feature_class":"P",
    "gn:feature_code":"PPL",
    "gn:name":"Nyakakiri",
    "gn:population":0,
    "gn:timezone":"Africa/Dar_es_Salaam",
    "iso:country":"TZ",
    "wof:name":"Nyakakiri",
    "wof:placetype":"locality"
},
  "geometry": {"coordinates":[31.4775,-2.26028],"type":"Point"}
}