{
  "type": "Feature",
  "properties": {
    "gn:admin1_code":"18.0",
    "gn:admin2_code":"0401",
    "gn:admin3_code":"0401101",
    "gn:asciiname":"Nkelei",
    "gn:country_code":"TZ",
    "gn:dem":1034,
    "gn:feature_class":"P",
    "gn:feature_code":"PPL",
    "gn:name":"Nkelei",
    "gn:population":0,
    "gn:timezone":"Africa/Dar_es_Salaam",
    "iso:country":"TZ",
    "wof:name":"Nkelei",
    "wof:placetype":"locality"
},
  "geometry": {"coordinates":[38.48333,-4.91667],"type":"Point"}
}