{
  "type": "Feature",
  "properties": {
    "gn:admin1_code":"2.0",
    "gn:admin2_code":"0602",
    "gn:admin3_code":"0602041",
    "gn:asciiname":"Soga",
    "gn:country_code":"TZ",
    "gn:dem":163,
    "gn:feature_class":"P",
    "gn:feature_code":"PPL",
    "gn:name":"Soga",
    "gn:population":0,
    "gn:timezone":"Africa/Dar_es_Salaam",
    "iso:country":"TZ",
    "wof:name":"Soga",
    "wof:placetype":"locality"
},
  "geometry": {"coordinates":[38.86667,-6.83333],"type":"Point"}
}