{
  "type": "Feature",
  "properties": {
    "gn:admin1_code":"9.0",
    "gn:admin2_code":"1207",
    "gn:admin3_code":"1207081",
    "gn:asciiname":"Ruiwa",
    "gn:country_code":"TZ",
    "gn:dem":1168,
    "gn:feature_class":"P",
    "gn:feature_code":"PPL",
    "gn:name":"Ruiwa",
    "gn:population":0,
    "gn:timezone":"Africa/Dar_es_Salaam",
    "iso:country":"TZ",
    "name:swa_x_preferred":[
        "Ruiwa"
    ],
    "wof:name":"Ruiwa",
    "wof:placetype":"locality"
},
  "geometry": {"coordinates":[33.63333,-8.76667],"type":"Point"}
}