{
  "type": "Feature",
  "properties": {
    "gn:admin1_code":"5.0",
    "gn:asciiname":"Kapompogo",
    "gn:country_code":"TZ",
    "gn:dem":1142,
    "gn:feature_class":"P",
    "gn:feature_code":"PPL",
    "gn:name":"Kapompogo",
    "gn:population":0,
    "gn:timezone":"Africa/Dar_es_Salaam",
    "iso:country":"TZ",
    "name:eng_x_preferred":[
        "Kapompogo"
    ],
    "wof:name":"Kapompogo",
    "wof:placetype":"locality"
},
  "geometry": {"coordinates":[30.3512,-6.40789],"type":"Point"}
}