{
  "type": "Feature",
  "properties": {
    "gn:admin1_code":"15.0",
    "gn:admin2_code":"1702",
    "gn:admin3_code":"1702131",
    "gn:asciiname":"Bulegela",
    "gn:country_code":"TZ",
    "gn:dem":1070,
    "gn:feature_class":"P",
    "gn:feature_code":"PPL",
    "gn:name":"Bulegela",
    "gn:population":0,
    "gn:timezone":"Africa/Dar_es_Salaam",
    "iso:country":"TZ",
    "wof:name":"Bulegela",
    "wof:placetype":"locality"
},
  "geometry": {"coordinates":[34.02134,-3.94973],"type":"Point"}
}