{
  "type": "Feature",
  "properties": {
    "gn:admin1_code":"20.0",
    "gn:admin2_code":"5501",
    "gn:admin3_code":"5501051",
    "gn:asciiname":"Ndagoni",
    "gn:country_code":"TZ",
    "gn:dem":17,
    "gn:feature_class":"P",
    "gn:feature_code":"PPL",
    "gn:name":"Ndagoni",
    "gn:population":0,
    "gn:timezone":"Africa/Dar_es_Salaam",
    "iso:country":"TZ",
    "name:und_x_variant":[
        "Ndagone",
        "Ndagoni"
    ],
    "wof:name":"Ndagoni",
    "wof:placetype":"locality"
},
  "geometry": {"coordinates":[39.71667,-5.21667],"type":"Point"}
}