{
  "type": "Feature",
  "properties": {
    "gn:admin1_code":"19.0",
    "gn:admin2_code":"1808",
    "gn:admin3_code":"1808121",
    "gn:asciiname":"Kiraguju",
    "gn:country_code":"TZ",
    "gn:dem":1554,
    "gn:feature_class":"P",
    "gn:feature_code":"PPL",
    "gn:name":"Kiraguju",
    "gn:population":0,
    "gn:timezone":"Africa/Dar_es_Salaam",
    "iso:country":"TZ",
    "wof:name":"Kiraguju",
    "wof:placetype":"locality"
},
  "geometry": {"coordinates":[30.93333,-1.35],"type":"Point"}
}