{
  "type": "Feature",
  "properties": {
    "iso:country":"TZ",
    "name:ara_x_preferred":[
        "\u0645\u0628\u0648\u0627\u0628\u0648\u0627"
    ],
    "name:ceb_x_preferred":[
        "Mpwapwa"
    ],
    "name:eng_x_preferred":[
        "Mpwapwa"
    ],
    "name:ita_x_preferred":[
        "Distretto di Mpwapwa"
    ],
    "name:nld_x_preferred":[
        "Mpwapwa"
    ],
    "name:nob_x_preferred":[
        "Mpwapwa"
    ],
    "name:por_x_preferred":[
        "Mpwapwa"
    ],
    "name:swa_x_preferred":[
        "Wilaya ya Mpwapwa"
    ],
    "name:und_x_variant":[
        "Mpapwa"
    ],
    "ne:ADM0CAP":0.0,
    "ne:ADM0NAME":"Tanzania",
    "ne:ADM0_A3":"TZA",
    "ne:ADM1NAME":"Dodoma",
    "ne:ADMIN1_COD":0,
    "ne:CAPALT":0,
    "ne:CHANGED":4,
    "ne:CHECKME":0,
    "ne:COMPARE":0,
    "ne:DIFFASCII":0,
    "ne:DIFFNOTE":"Changed scale rank.",
    "ne:ELEVATION":0.0,
    "ne:FEATURECLA":"Populated place",
    "ne:FEATURE_CL":"P",
    "ne:FEATURE_CO":"PPL",
    "ne:GEONAMEID":153094,
    "ne:GEONAMESNO":"GeoNames match with ascii name + lat + long whole numbers.",
    "ne:GN_ASCII":"Mpwapwa",
    "ne:GN_POP":19806,
    "ne:GTOPO30":948.0,
    "ne:ISO_A2":"TZ",
    "ne:LABELRANK":5,
    "ne:LATITUDE":-6.349601,
    "ne:LONGITUDE":36.479985,
    "ne:LS_MATCH":1,
    "ne:LS_NAME":"Mpwapwa",
    "ne:MAX_AREAKM":3.0,
    "ne:MAX_AREAMI":1.0,
    "ne:MAX_BBXMAX":36.491667,
    "ne:MAX_BBXMIN":36.475,
    "ne:MAX_BBYMAX":-6.341667,
    "ne:MAX_BBYMIN":-6.358333,
    "ne:MAX_NATSCA":10.0,
    "ne:MAX_PERKM":7.0,
    "ne:MAX_PERMI":5.0,
    "ne:MAX_POP10":381,
    "ne:MAX_POP20":0,
    "ne:MAX_POP300":0,
    "ne:MAX_POP310":0,
    "ne:MAX_POP50":0,
    "ne:MEAN_BBXC":36.484722,
    "ne:MEAN_BBYC":-6.348611,
    "ne:MEGACITY":0,
    "ne:MIN_AREAKM":3.0,
    "ne:MIN_AREAMI":1.0,
    "ne:MIN_BBXMAX":36.491667,
    "ne:MIN_BBXMIN":36.475,
    "ne:MIN_BBYMAX":-6.341667,
    "ne:MIN_BBYMIN":-6.358333,
    "ne:MIN_PERKM":7.0,
    "ne:MIN_PERMI":5.0,
    "ne:NAME":"Mpwapwa",
    "ne:NAMEASCII":"Mpwapwa",
    "ne:NAMEDIFF":0,
    "ne:NATSCALE":20,
    "ne:POP1950":0,
    "ne:POP1955":0,
    "ne:POP1960":0,
    "ne:POP1965":0,
    "ne:POP1970":0,
    "ne:POP1975":0,
    "ne:POP1980":0,
    "ne:POP1985":0,
    "ne:POP1990":0,
    "ne:POP1995":0,
    "ne:POP2000":0,
    "ne:POP2005":0,
    "ne:POP2010":0,
    "ne:POP2015":0,
    "ne:POP2020":0,
    "ne:POP2025":0,
    "ne:POP2050":0,
    "ne:POP_MAX":19806,
    "ne:POP_MIN":381,
    "ne:POP_OTHER":381,
    "ne:RANK_MAX":6,
    "ne:RANK_MIN":2,
    "ne:SCALERANK":7,
    "ne:SOV0NAME":"United Republic of Tanzania",
    "ne:SOV_A3":"TZA",
    "ne:TIMEZONE":"Africa/Dar_es_Salaam",
    "ne:UN_FID":0,
    "ne:UN_LAT":0.0,
    "ne:UN_LONG":0.0,
    "ne:WORLDCITY":0,
    "qs:gn_country":"TZ",
    "qs:gn_fcode":"PPL",
    "qs:gn_pop":19806,
    "qs:name":"Mpwapwa",
    "qs:name_adm0":"Tanzania",
    "qs:name_adm1":"Dodoma",
    "qs:photos":0,
    "qs:photos_1k":0,
    "qs:photos_9k":1,
    "qs:photos_9r":1,
    "qs:photos_all":4,
    "qs:photos_sr":0,
    "qs:placetype":"Town",
    "qs:pop_sr":"6",
    "qs:woe_adm0":23424973,
    "wd:wordcount":614,
    "wof:name":"Mpwapwa",
    "wof:placetype":"locality",
    "wof:population":19806
},
  "geometry": {"coordinates":[36.48333,-6.35],"type":"Point"}
}