{
  "type": "Feature",
  "properties": {
    "gn:admin1_code":"20.0",
    "gn:admin2_code":"5502",
    "gn:admin3_code":"5502333",
    "gn:asciiname":"Msambe",
    "gn:country_code":"TZ",
    "gn:dem":15,
    "gn:feature_class":"P",
    "gn:feature_code":"PPL",
    "gn:name":"Msambe",
    "gn:population":0,
    "gn:timezone":"Africa/Dar_es_Salaam",
    "iso:country":"TZ",
    "wof:name":"Msambe",
    "wof:placetype":"locality"
},
  "geometry": {"coordinates":[39.68333,-5.36667],"type":"Point"}
}