{
  "type": "Feature",
  "properties": {
    "gn:admin1_code":"5.0",
    "gn:admin2_code":"1601",
    "gn:admin3_code":"1601051",
    "gn:asciiname":"Nyamondole",
    "gn:country_code":"TZ",
    "gn:dem":1113,
    "gn:feature_class":"P",
    "gn:feature_code":"PPL",
    "gn:name":"Nyamondole",
    "gn:population":0,
    "gn:timezone":"Africa/Dar_es_Salaam",
    "iso:country":"TZ",
    "wof:name":"Nyamondole",
    "wof:placetype":"locality"
},
  "geometry": {"coordinates":[30.80111,-4.65833],"type":"Point"}
}