{
  "type": "Feature",
  "properties": {
    "gn:admin1_code":"16.0",
    "gn:admin2_code":"1301",
    "gn:admin3_code":"1301151",
    "gn:asciiname":"Ussure",
    "gn:country_code":"TZ",
    "gn:dem":1415,
    "gn:feature_class":"P",
    "gn:feature_code":"PPL",
    "gn:name":"Ussure",
    "gn:population":0,
    "gn:timezone":"Africa/Dar_es_Salaam",
    "iso:country":"TZ",
    "name:und_x_variant":[
        "Usure",
        "Usule",
        "Ussure"
    ],
    "wof:name":"Ussure",
    "wof:placetype":"locality"
},
  "geometry": {"coordinates":[34.38333,-4.65],"type":"Point"}
}